Workbook

Sheet Global Inputs
A1: NivrāaCare — Global Unit Economics Inputs
A2: Change only blue numbers. Change any input and service profitability updates automatically. NC loyalty assumptions are controlled separately in the 'NC Credits' sheet.
A4: Input | B4: Value | C4: Unit | D4: Source / Note | F4: Governance
A5: Base customer charge per concierge hour | B5: ='MVP1 Pricing & SKU'!$B$7 -> 299 | C5: ₹ / hour | D5: Linked to Global Pricing Config — active master base hourly rate | F5: Founder Assumption
A6: Angel cost per hour | B6: 0 | C6: ₹ / Angel hour | D6: Founder working assumption: ₹700 ÷ 4 hours | E6: When we are keeping 3 Angels on payroll, then we do not have to pay them on per hour basis, so I have made per hour cost as ZERO.Angel payment 14K Per month | F6: Founder Assumption
A7: GST on care service | B7: ='Global Pricing Config'!$B$8 -> 0.18 | C7: % | D7: Illustrative assumption; confirm with CA | F7: Market Test / CA Confirmation
A8: Payment platform fee | B8: 0 | C8: % of customer collection | D8: Editable payment gateway assumption | F8: Market Test
A9: Payment platform fixed fee | B9: 0 | C9: ₹ / transaction | D9: Editable | F9: Founder Assumption
A10: Ops / support allocation | B10: 10 | C10: ₹ / journey | D10: Founder working assumption | F10: Founder Assumption
A11: Insurance / risk reserve | B11: 10 | C11: ₹ / journey | D11: Founder working assumption | F11: Founder Assumption
A12: WhatsApp / SMS / communication | B12: 0.5 | C12: ₹ / journey | D12: Founder working assumption | F12: Founder Assumption
A13: BGV + training allocation | B13: 0 | C13: ₹ / journey | D13: Founder working assumption | F13: Founder Assumption
A14: Refund / service recovery reserve | B14: 36 | C14: ₹ / journey | D14: Founder working assumption | F14: Founder Assumption
A15: Average third-party cab actual | B15: ='Global Pricing Config'!$B$10 -> 500 | C15: ₹ / journey | D15: Founder working assumption for Case 2 | F15: Founder Assumption
A16: Transport coordination fee | B16: ='Global Pricing Config'!$B$9 -> 149 | C16: ₹ / journey | D16: Founder working assumption for Case 2 | F16: Founder Assumption
A17: GST on transport coordination fee | B17: 0 | C17: % | D17: Set to applicable rate after CA confirmation | F17: Market Test / CA Confirmation
A18: Transport ops / booking support | B18: 10 | C18: ₹ / journey | D18: Founder working assumption | F18: Founder Assumption
A19: Legacy extended-hour price (inactive) | B19: ='MVP1 Pricing & SKU'!$B$8 -> 269 | C19: ₹ / hour | D19: Historical assumption only. Not used in current MVP pricing engine. | F19: Founder Assumption
A20: New customer acquisition cost (sensitivity only) | B20: 299 | C20: ₹ / new family | D20: Illustrative founder assumption for repeat-rate sensitivity | F20: Founder Assumption
A21: Base package hours (sensitivity only) | B21: 4 | C21: hours | D21: Used only in additional-hour sensitivity | F21: Founder Assumption
A22: Minimum booking hours (MVP1) | B22: ='Global Pricing Config'!$B$6 -> 2 | C22: hours | D22: Linked to MVP1 Pricing & SKU | F22: Founder Assumption
A24: PAYROLL ANGEL ECONOMICS
A25: Active payroll Angels | B25: 3 | C25: Angels | D25: Founder Assumption | E25: Initial payroll team assumption | F25: =D25 -> Founder Assumption
A26: Monthly salary / Angel | B26: 14000 | C26: ₹ / Angel / month | D26: Founder Assumption | E26: Based on founder working plan | F26: =D26 -> Founder Assumption
A27: Angel working days / month | B27: 26 | C27: days | D27: Founder Assumption | E27: Editable | F27: =D27 -> Founder Assumption
A28: Scheduled hours / Angel / day | B28: 8 | C28: hours | D28: Founder Assumption | E28: Editable | F28: =D28 -> Founder Assumption
A29: Target productive utilization | B29: 0.65 | C29: % | D29: Founder Assumption | E29: Planning utilization target | F29: =D29 -> Founder Assumption
A30: Monthly Angel payroll | B30: =B25*B26 -> 42000 | C30: ₹ / month | D30: Derived Formula | E30: Active payroll Angels × salary / Angel | F30: =D30 -> Derived Formula
A31: Available Angel hours / month | B31: =B25*B27*B28 -> 624 | C31: hours / month | D31: Derived Formula | E31: Angels × days × scheduled hours | F31: =D31 -> Derived Formula
A32: Target productive Angel hours / month | B32: =B31*B29 -> 405.6 | C32: hours / month | D32: Derived Formula | E32: Available hours × target utilization | F32: =D32 -> Derived Formula
A33: Target fully loaded Angel cost / productive hour | B33: =IF(B32=0,0,B30/B32) -> 103.5503 | C33: ₹ / productive hour | D33: Derived Formula | E33: Payroll ÷ target productive hours | F33: =D33 -> Derived Formula
A34: Current productive Angel hours / month | B34: =#REF!*#REF! -> #REF! | C34: hours / month | D34: Derived Formula | E34: Current completed journeys × weighted avg duration | F34: =D34 -> Derived Formula
A35: Current fully loaded Angel cost / productive hour | B35: =IF(B34=0,0,B30/B34) -> #REF! | C35: ₹ / productive hour | D35: Derived Formula | E35: Payroll ÷ current productive hours | F35: =D35 -> Derived Formula

Sheet Service Economics
A1: NivrāaCare — Dynamic Service Unit Economics | Incremental vs Fully Loaded Contribution
A2: Edit BLUE input cells (hours, service multiplier, fixed premium, Angel count, and optional overrides). MVP-1 pricing is controlled from 'MVP1 Pricing & SKU'; expected NC loyalty cost is controlled from 'NC Credits'. Overnight / very-long-duration rows are marked manual.
A4: Service | B4: Category | C4: Hours | D4: Rate Multiplier | E4: Fixed Premium / Fee | F4: No. of Angels | G4: Angel Cost/Hr Override | H4: Cab Cost Override | I4: Coord. Fee Override | J4: Effective Service Rate / Hr | K4: Customer Service Price (Incl GST; ₹299 × multiplier × billable hours + ₹199 fee) | L4: Net Service Revenue | M4: Effective Angel Cost/Hr | N4: Angel Cost | O4: Payment Platform Cost | P4: Other Variable Care Cost | Q4: CASE 1 Variable Delivery Cost | R4: CASE 1 Contribution Before Fixed Costs | S4: CASE 1 Contribution Margin | T4: Effective 3P Cab Cost | U4: Effective Coordination Fee | V4: Customer Transport Charge | W4: Transport Payment Cost | X4: Transport Ops Cost | Y4: Net Transport Coordination Contribution | Z4: CASE 2 Total Customer Outflow | AA4: CASE 2 Total Direct Cash Cost | AB4: CASE 2 Contribution Before Fixed Costs | AC4: CASE 2 Profit Uplift | AD4: CASE 2 Contribution Margin | AE4: Contribution / Service Hour C1 | AF4: Contribution / Service Hour C2 | AG4: Expected NC Loyalty Cost | AH4: Pricing Mode | AI4: Incremental Angel Cost / Hr | AJ4: Target Fully Loaded Angel Cost / Hr | AK4: Target Fully Loaded Angel Cost | AL4: CASE 1 Fully Loaded Contribution | AM4: CASE 1 Fully Loaded Margin | AN4: CASE 2 Fully Loaded Contribution | AO4: CASE 2 Fully Loaded Margin | AP4: Fully Loaded Contribution / Angel Hr | AQ4: Recurring / Strategic Potential | AR4: Multiplier Reason
A5: Hospital Visit | B5: Medical Visit | C5: 4 | D5: 1 | E5: 0 | F5: 1 | J5: ='MVP1 Pricing & SKU'!$B$7*D5 -> 299 | K5: 1395 | L5: =K5/(1+'Global Inputs'!$B$7) -> 1182.2034 | M5: =IF(G5="",'Global Inputs'!$B$6,G5) -> 0 | N5: =C5*F5*M5 -> 0 | O5: =K5*'Global Inputs'!$B$8+'Global Inputs'!$B$9 -> 0 | P5: =SUM('Global Inputs'!$B$10:$B$14) -> 56.5 | Q5: =SUM(N5:P5)+AG5 -> 105.325 | R5: =L5-Q5 -> 1076.8784 | S5: =IF(L5=0,0,R5/L5) -> 0.91090789 | T5: =IF(H5="",'Global Inputs'!$B$15,H5) -> 500 | U5: =IF(I5="",'Global Inputs'!$B$16,I5) -> 149 | V5: =T5+U5 -> 649 | W5: =V5*'Global Inputs'!$B$8 -> 0 | X5: ='Global Inputs'!$B$18 -> 10 | Y5: =U5/(1+'Global Inputs'!$B$17)-W5-X5 -> 139 | Z5: =K5+V5 -> 2044 | AA5: =Q5+T5+W5+X5 -> 615.325 | AB5: =R5+Y5 -> 1215.8784 | AC5: =AB5-R5 -> 139 | AD5: 0.91336786 | AE5: =IF(C5=0,0,R5/C5) -> 269.2196 | AF5: =IF(C5=0,0,AB5/C5) -> 303.9696 | AG5: =L5*'NC Credits'!$B$15 -> 48.825 | AH5: =IF(OR(ISNUMBER(SEARCH("Overnight",A5)),ISNUMBER(SEARCH("Multi-Day",A5)),ISNUMBER(SEARCH("Medical Tourism",A5))),"MANUAL","AUTO") -> AUTO | AI5: =M5 -> 0 | AJ5: ='Global Inputs'!$B$33 -> 103.5503 | AK5: =C5*F5*AJ5 -> 414.20118 | AL5: =R5+N5-AK5 -> 662.67721 | AM5: =IF(L5=0,0,AL5/L5) -> 0.56054416 | AN5: =AB5+N5-AK5 -> 801.67721 | AO5: =IF((L5+U5/(1+'Global Inputs'!$B$17))=0,0,AN5/(L5+U5/(1+'Global Inputs'!$B$17))) -> 0.60221993 | AP5: =IF(C5*F5=0,0,AL5/(C5*F5)) -> 165.6693 | AQ5: 5 | AR5: Full journey: home → facility → return / safe handover
A6: Hospital Visit — Concierge at Hospital | B6: Medical Visit | C6: 3 | D6: 0.8 | E6: 0 | F6: 1 | J6: ='MVP1 Pricing & SKU'!$B$7*D6 -> 239.2 | K6: 916.6 | L6: =K6/(1+'Global Inputs'!$B$7) -> 776.77966 | M6: =IF(G6="",'Global Inputs'!$B$6,G6) -> 0 | N6: =C6*F6*M6 -> 0 | O6: =K6*'Global Inputs'!$B$8+'Global Inputs'!$B$9 -> 0 | P6: =SUM('Global Inputs'!$B$10:$B$14) -> 56.5 | Q6: =SUM(N6:P6)+AG6 -> 88.581 | R6: =L6-Q6 -> 688.19866 | S6: =IF(L6=0,0,R6/L6) -> 0.8859638 | T6: =IF(H6="",'Global Inputs'!$B$15,H6) -> 500 | U6: =IF(I6="",'Global Inputs'!$B$16,I6) -> 149 | V6: =T6+U6 -> 649 | W6: =V6*'Global Inputs'!$B$8 -> 0 | X6: ='Global Inputs'!$B$18 -> 10 | Y6: =U6/(1+'Global Inputs'!$B$17)-W6-X6 -> 139 | Z6: =K6+V6 -> 1565.6 | AA6: =Q6+T6+W6+X6 -> 598.581 | AB6: =R6+Y6 -> 827.19866 | AC6: =AB6-R6 -> 139 | AD6: 0.8935157 | AE6: =IF(C6=0,0,R6/C6) -> 229.39955 | AF6: =IF(C6=0,0,AB6/C6) -> 275.73289 | AG6: =L6*'NC Credits'!$B$15 -> 32.081 | AH6: =IF(OR(ISNUMBER(SEARCH("Overnight",A6)),ISNUMBER(SEARCH("Multi-Day",A6)),ISNUMBER(SEARCH("Medical Tourism",A6))),"MANUAL","AUTO") -> AUTO | AI6: =M6 -> 0 | AJ6: ='Global Inputs'!$B$33 -> 103.5503 | AK6: =C6*F6*AJ6 -> 310.65089 | AL6: =R6+N6-AK6 -> 377.54777 | AM6: =IF(L6=0,0,AL6/L6) -> 0.4860423 | AN6: =AB6+N6-AK6 -> 516.54777 | AO6: =IF((L6+U6/(1+'Global Inputs'!$B$17))=0,0,AN6/(L6+U6/(1+'Global Inputs'!$B$17))) -> 0.55795973 | AP6: =IF(C6*F6=0,0,AL6/(C6*F6)) -> 125.84926 | AQ6: 4 | AR6: Hospital-only support; reduced travel and handover responsibility
A7: Clinic Visit | B7: Medical Visit | C7: 2 | D7: 0.9 | E7: 0 | F7: 1 | J7: ='MVP1 Pricing & SKU'!$B$7*D7 -> 269.1 | K7: 737.2 | L7: =K7/(1+'Global Inputs'!$B$7) -> 624.74576 | M7: =IF(G7="",'Global Inputs'!$B$6,G7) -> 0 | N7: =C7*F7*M7 -> 0 | O7: =K7*'Global Inputs'!$B$8+'Global Inputs'!$B$9 -> 0 | P7: =SUM('Global Inputs'!$B$10:$B$14) -> 56.5 | Q7: =SUM(N7:P7)+AG7 -> 82.302 | R7: =L7-Q7 -> 542.44376 | S7: =IF(L7=0,0,R7/L7) -> 0.86826321 | T7: =IF(H7="",'Global Inputs'!$B$15,H7) -> 500 | U7: =IF(I7="",'Global Inputs'!$B$16,I7) -> 149 | V7: =T7+U7 -> 649 | W7: =V7*'Global Inputs'!$B$8 -> 0 | X7: ='Global Inputs'!$B$18 -> 10 | Y7: =U7/(1+'Global Inputs'!$B$17)-W7-X7 -> 139 | Z7: =K7+V7 -> 1386.2 | AA7: =Q7+T7+W7+X7 -> 592.302 | AB7: =R7+Y7 -> 681.44376 | AC7: =AB7-R7 -> 139 | AD7: 0.88070759 | AE7: =IF(C7=0,0,R7/C7) -> 271.22188 | AF7: =IF(C7=0,0,AB7/C7) -> 340.72188 | AG7: =L7*'NC Credits'!$B$15 -> 25.802 | AH7: =IF(OR(ISNUMBER(SEARCH("Overnight",A7)),ISNUMBER(SEARCH("Multi-Day",A7)),ISNUMBER(SEARCH("Medical Tourism",A7))),"MANUAL","AUTO") -> AUTO | AI7: =M7 -> 0 | AJ7: ='Global Inputs'!$B$33 -> 103.5503 | AK7: =C7*F7*AJ7 -> 207.10059 | AL7: =R7+N7-AK7 -> 335.34317 | AM7: =IF(L7=0,0,AL7/L7) -> 0.53676742 | AN7: =AB7+N7-AK7 -> 474.34317 | AO7: =IF((L7+U7/(1+'Global Inputs'!$B$17))=0,0,AN7/(L7+U7/(1+'Global Inputs'!$B$17))) -> 0.61304784 | AP7: =IF(C7*F7=0,0,AL7/(C7*F7)) -> 167.67159 | AQ7: 4 | AR7: Shorter, lower-complexity outpatient journey
A8: Diagnostic Center Visit | B8: Medical Visit | C8: 3 | D8: 0.85 | E8: 0 | F8: 1 | J8: ='MVP1 Pricing & SKU'!$B$7*D8 -> 254.15 | K8: 961.45 | L8: =K8/(1+'Global Inputs'!$B$7) -> 814.78814 | M8: =IF(G8="",'Global Inputs'!$B$6,G8) -> 0 | N8: =C8*F8*M8 -> 0 | O8: =K8*'Global Inputs'!$B$8+'Global Inputs'!$B$9 -> 0 | P8: =SUM('Global Inputs'!$B$10:$B$14) -> 56.5 | Q8: =SUM(N8:P8)+AG8 -> 90.15075 | R8: =L8-Q8 -> 724.63739 | S8: =IF(L8=0,0,R8/L8) -> 0.88935682 | T8: =IF(H8="",'Global Inputs'!$B$15,H8) -> 500 | U8: =IF(I8="",'Global Inputs'!$B$16,I8) -> 149 | V8: =T8+U8 -> 649 | W8: =V8*'Global Inputs'!$B$8 -> 0 | X8: ='Global Inputs'!$B$18 -> 10 | Y8: =U8/(1+'Global Inputs'!$B$17)-W8-X8 -> 139 | Z8: =K8+V8 -> 1610.45 | AA8: =Q8+T8+W8+X8 -> 600.15075 | AB8: =R8+Y8 -> 863.63739 | AC8: =AB8-R8 -> 139 | AD8: 0.89608634 | AE8: =IF(C8=0,0,R8/C8) -> 241.5458 | AF8: =IF(C8=0,0,AB8/C8) -> 287.87913 | AG8: =L8*'NC Credits'!$B$15 -> 33.65075 | AH8: =IF(OR(ISNUMBER(SEARCH("Overnight",A8)),ISNUMBER(SEARCH("Multi-Day",A8)),ISNUMBER(SEARCH("Medical Tourism",A8))),"MANUAL","AUTO") -> AUTO | AI8: =M8 -> 0 | AJ8: ='Global Inputs'!$B$33 -> 103.5503 | AK8: =C8*F8*AJ8 -> 310.65089 | AL8: =R8+N8-AK8 -> 413.9865 | AM8: =IF(L8=0,0,AL8/L8) -> 0.50809097 | AN8: =AB8+N8-AK8 -> 552.9865 | AO8: =IF((L8+U8/(1+'Global Inputs'!$B$17))=0,0,AN8/(L8+U8/(1+'Global Inputs'!$B$17))) -> 0.57376355 | AP8: =IF(C8*F8=0,0,AL8/(C8*F8)) -> 137.9955 | AQ8: 4 | AR8: Generally simpler navigation / diagnostic-only workflow
A9: Health Check-up Concierge | B9: Medical Visit | C9: 5 | D9: 0.9 | E9: 0 | F9: 1 | J9: ='MVP1 Pricing & SKU'!$B$7*D9 -> 269.1 | K9: 1544.5 | L9: =K9/(1+'Global Inputs'!$B$7) -> 1308.8983 | M9: =IF(G9="",'Global Inputs'!$B$6,G9) -> 0 | N9: =C9*F9*M9 -> 0 | O9: =K9*'Global Inputs'!$B$8+'Global Inputs'!$B$9 -> 0 | P9: =SUM('Global Inputs'!$B$10:$B$14) -> 56.5 | Q9: =SUM(N9:P9)+AG9 -> 110.5575 | R9: =L9-Q9 -> 1198.3408 | S9: =IF(L9=0,0,R9/L9) -> 0.91553393 | T9: =IF(H9="",'Global Inputs'!$B$15,H9) -> 500 | U9: =IF(I9="",'Global Inputs'!$B$16,I9) -> 149 | V9: =T9+U9 -> 649 | W9: =V9*'Global Inputs'!$B$8 -> 0 | X9: ='Global Inputs'!$B$18 -> 10 | Y9: =U9/(1+'Global Inputs'!$B$17)-W9-X9 -> 139 | Z9: =K9+V9 -> 2193.5 | AA9: =Q9+T9+W9+X9 -> 620.5575 | AB9: =R9+Y9 -> 1337.3408 | AC9: =AB9-R9 -> 139 | AD9: 0.91730733 | AE9: =IF(C9=0,0,R9/C9) -> 239.66816 | AF9: =IF(C9=0,0,AB9/C9) -> 267.46816 | AG9: =L9*'NC Credits'!$B$15 -> 54.0575 | AH9: =IF(OR(ISNUMBER(SEARCH("Overnight",A9)),ISNUMBER(SEARCH("Multi-Day",A9)),ISNUMBER(SEARCH("Medical Tourism",A9))),"MANUAL","AUTO") -> AUTO | AI9: =M9 -> 0 | AJ9: ='Global Inputs'!$B$33 -> 103.5503 | AK9: =C9*F9*AJ9 -> 517.75148 | AL9: =R9+N9-AK9 -> 680.58933 | AM9: =IF(L9=0,0,AL9/L9) -> 0.51997113 | AN9: =AB9+N9-AK9 -> 819.58933 | AO9: =IF((L9+U9/(1+'Global Inputs'!$B$17))=0,0,AN9/(L9+U9/(1+'Global Inputs'!$B$17))) -> 0.56217181 | AP9: =IF(C9*F9=0,0,AL9/(C9*F9)) -> 136.11787 | AQ9: 3 | AR9: Structured preventive-care journey; moderate coordination
A10: Hospital Admission Concierge | B10: Hospital Support | C10: 4 | D10: 1.15 | E10: 0 | F10: 1 | J10: ='MVP1 Pricing & SKU'!$B$7*D10 -> 343.85 | K10: 1574.4 | L10: =K10/(1+'Global Inputs'!$B$7) -> 1334.2373 | M10: =IF(G10="",'Global Inputs'!$B$6,G10) -> 0 | N10: =C10*F10*M10 -> 0 | O10: =K10*'Global Inputs'!$B$8+'Global Inputs'!$B$9 -> 0 | P10: =SUM('Global Inputs'!$B$10:$B$14) -> 56.5 | Q10: =SUM(N10:P10)+AG10 -> 111.604 | R10: =L10-Q10 -> 1222.6333 | S10: =IF(L10=0,0,R10/L10) -> 0.91635371 | T10: =IF(H10="",'Global Inputs'!$B$15,H10) -> 500 | U10: =IF(I10="",'Global Inputs'!$B$16,I10) -> 149 | V10: =T10+U10 -> 649 | W10: =V10*'Global Inputs'!$B$8 -> 0 | X10: ='Global Inputs'!$B$18 -> 10 | Y10: =U10/(1+'Global Inputs'!$B$17)-W10-X10 -> 139 | Z10: =K10+V10 -> 2223.4 | AA10: =Q10+T10+W10+X10 -> 621.604 | AB10: =R10+Y10 -> 1361.6333 | AC10: =AB10-R10 -> 139 | AD10: 0.91801447 | AE10: =IF(C10=0,0,R10/C10) -> 305.65832 | AF10: =IF(C10=0,0,AB10/C10) -> 340.40832 | AG10: =L10*'NC Credits'!$B$15 -> 55.104 | AH10: =IF(OR(ISNUMBER(SEARCH("Overnight",A10)),ISNUMBER(SEARCH("Multi-Day",A10)),ISNUMBER(SEARCH("Medical Tourism",A10))),"MANUAL","AUTO") -> AUTO | AI10: =M10 -> 0 | AJ10: ='Global Inputs'!$B$33 -> 103.5503 | AK10: =C10*F10*AJ10 -> 414.20118 | AL10: =R10+N10-AK10 -> 808.4321 | AM10: =IF(L10=0,0,AL10/L10) -> 0.60591329 | AN10: =AB10+N10-AK10 -> 947.4321 | AO10: =IF((L10+U10/(1+'Global Inputs'!$B$17))=0,0,AN10/(L10+U10/(1+'Global Inputs'!$B$17))) -> 0.63875963 | AP10: =IF(C10*F10=0,0,AL10/(C10*F10)) -> 202.10803 | AQ10: 3 | AR10: Higher coordination, documentation and handoff complexity
A11: Hospital Discharge Concierge | B11: Hospital Support | C11: 4 | D11: 1.1 | E11: 0 | F11: 1 | J11: ='MVP1 Pricing & SKU'!$B$7*D11 -> 328.9 | K11: 1514.6 | L11: =K11/(1+'Global Inputs'!$B$7) -> 1283.5593 | M11: =IF(G11="",'Global Inputs'!$B$6,G11) -> 0 | N11: =C11*F11*M11 -> 0 | O11: =K11*'Global Inputs'!$B$8+'Global Inputs'!$B$9 -> 0 | P11: =SUM('Global Inputs'!$B$10:$B$14) -> 56.5 | Q11: =SUM(N11:P11)+AG11 -> 109.511 | R11: =L11-Q11 -> 1174.0483 | S11: =IF(L11=0,0,R11/L11) -> 0.91468178 | T11: =IF(H11="",'Global Inputs'!$B$15,H11) -> 500 | U11: =IF(I11="",'Global Inputs'!$B$16,I11) -> 149 | V11: =T11+U11 -> 649 | W11: =V11*'Global Inputs'!$B$8 -> 0 | X11: ='Global Inputs'!$B$18 -> 10 | Y11: =U11/(1+'Global Inputs'!$B$17)-W11-X11 -> 139 | Z11: =K11+V11 -> 2163.6 | AA11: =Q11+T11+W11+X11 -> 619.511 | AB11: =R11+Y11 -> 1313.0483 | AC11: =AB11-R11 -> 139 | AD11: 0.91657518 | AE11: =IF(C11=0,0,R11/C11) -> 293.51208 | AF11: =IF(C11=0,0,AB11/C11) -> 328.26208 | AG11: =L11*'NC Credits'!$B$15 -> 53.011 | AH11: =IF(OR(ISNUMBER(SEARCH("Overnight",A11)),ISNUMBER(SEARCH("Multi-Day",A11)),ISNUMBER(SEARCH("Medical Tourism",A11))),"MANUAL","AUTO") -> AUTO | AI11: =M11 -> 0 | AJ11: ='Global Inputs'!$B$33 -> 103.5503 | AK11: =C11*F11*AJ11 -> 414.20118 | AL11: =R11+N11-AK11 -> 759.84714 | AM11: =IF(L11=0,0,AL11/L11) -> 0.59198443 | AN11: =AB11+N11-AK11 -> 898.84714 | AO11: =IF((L11+U11/(1+'Global Inputs'!$B$17))=0,0,AN11/(L11+U11/(1+'Global Inputs'!$B$17))) -> 0.62744148 | AP11: =IF(C11*F11=0,0,AL11/(C11*F11)) -> 189.96178 | AQ11: 3 | AR11: Higher coordination and post-discharge handover responsibility
A12: Overnight Hospital Concierge | B12: Hospital Support | C12: 12 | D12: 0.85 | E12: 299 | F12: 1 | J12: ='MVP1 Pricing & SKU'!$B$7*D12 -> 254.15 | K12: 3547.8 | L12: =K12/(1+'Global Inputs'!$B$7) -> 3006.6102 | M12: =IF(G12="",'Global Inputs'!$B$6,G12) -> 0 | N12: =C12*F12*M12 -> 0 | O12: =K12*'Global Inputs'!$B$8+'Global Inputs'!$B$9 -> 0 | P12: =SUM('Global Inputs'!$B$10:$B$14) -> 56.5 | Q12: =SUM(N12:P12)+AG12 -> 180.673 | R12: =L12-Q12 -> 2825.9372 | S12: =IF(L12=0,0,R12/L12) -> 0.93990807 | T12: =IF(H12="",'Global Inputs'!$B$15,H12) -> 500 | U12: =IF(I12="",'Global Inputs'!$B$16,I12) -> 149 | V12: =T12+U12 -> 649 | W12: =V12*'Global Inputs'!$B$8 -> 0 | X12: ='Global Inputs'!$B$18 -> 10 | Y12: =U12/(1+'Global Inputs'!$B$17)-W12-X12 -> 139 | Z12: =K12+V12 -> 4196.8 | AA12: =Q12+T12+W12+X12 -> 690.673 | AB12: =R12+Y12 -> 2964.9372 | AC12: =AB12-R12 -> 139 | AD12: 0.9395765 | AE12: =IF(C12=0,0,R12/C12) -> 235.49476 | AF12: =IF(C12=0,0,AB12/C12) -> 247.0781 | AG12: =L12*'NC Credits'!$B$15 -> 124.173 | AH12: =IF(OR(ISNUMBER(SEARCH("Overnight",A12)),ISNUMBER(SEARCH("Multi-Day",A12)),ISNUMBER(SEARCH("Medical Tourism",A12))),"MANUAL","AUTO") -> MANUAL | AI12: =M12 -> 0 | AJ12: ='Global Inputs'!$B$33 -> 103.5503 | AK12: =C12*F12*AJ12 -> 1242.6036 | AL12: =R12+N12-AK12 -> 1583.3336 | AM12: =IF(L12=0,0,AL12/L12) -> 0.52661753 | AN12: =AB12+N12-AK12 -> 1722.3336 | AO12: =IF((L12+U12/(1+'Global Inputs'!$B$17))=0,0,AN12/(L12+U12/(1+'Global Inputs'!$B$17))) -> 0.5458005 | AP12: =IF(C12*F12=0,0,AL12/(C12*F12)) -> 131.94447 | AQ12: 2 | AR12: Long-duration service; manual pricing should supersede multiplier
A13: Multi-Day Hospital Concierge (per 12h shift) | B13: Hospital Support | C13: 12 | D13: 0.85 | E13: 299 | F13: 1 | J13: ='MVP1 Pricing & SKU'!$B$7*D13 -> 254.15 | K13: 3547.8 | L13: =K13/(1+'Global Inputs'!$B$7) -> 3006.6102 | M13: =IF(G13="",'Global Inputs'!$B$6,G13) -> 0 | N13: =C13*F13*M13 -> 0 | O13: =K13*'Global Inputs'!$B$8+'Global Inputs'!$B$9 -> 0 | P13: =SUM('Global Inputs'!$B$10:$B$14) -> 56.5 | Q13: =SUM(N13:P13)+AG13 -> 180.673 | R13: =L13-Q13 -> 2825.9372 | S13: =IF(L13=0,0,R13/L13) -> 0.93990807 | T13: =IF(H13="",'Global Inputs'!$B$15,H13) -> 500 | U13: =IF(I13="",'Global Inputs'!$B$16,I13) -> 149 | V13: =T13+U13 -> 649 | W13: =V13*'Global Inputs'!$B$8 -> 0 | X13: ='Global Inputs'!$B$18 -> 10 | Y13: =U13/(1+'Global Inputs'!$B$17)-W13-X13 -> 139 | Z13: =K13+V13 -> 4196.8 | AA13: =Q13+T13+W13+X13 -> 690.673 | AB13: =R13+Y13 -> 2964.9372 | AC13: =AB13-R13 -> 139 | AD13: 0.9395765 | AE13: =IF(C13=0,0,R13/C13) -> 235.49476 | AF13: =IF(C13=0,0,AB13/C13) -> 247.0781 | AG13: =L13*'NC Credits'!$B$15 -> 124.173 | AH13: =IF(OR(ISNUMBER(SEARCH("Overnight",A13)),ISNUMBER(SEARCH("Multi-Day",A13)),ISNUMBER(SEARCH("Medical Tourism",A13))),"MANUAL","AUTO") -> MANUAL | AI13: =M13 -> 0 | AJ13: ='Global Inputs'!$B$33 -> 103.5503 | AK13: =C13*F13*AJ13 -> 1242.6036 | AL13: =R13+N13-AK13 -> 1583.3336 | AM13: =IF(L13=0,0,AL13/L13) -> 0.52661753 | AN13: =AB13+N13-AK13 -> 1722.3336 | AO13: =IF((L13+U13/(1+'Global Inputs'!$B$17))=0,0,AN13/(L13+U13/(1+'Global Inputs'!$B$17))) -> 0.5458005 | AP13: =IF(C13*F13=0,0,AL13/(C13*F13)) -> 131.94447 | AQ13: 2 | AR13: Long-duration service; manual shift pricing
A14: Day Surgery / Procedure Concierge | B14: Procedure & Treatment | C14: 6 | D14: 1.2 | E14: 0 | F14: 1 | J14: ='MVP1 Pricing & SKU'!$B$7*D14 -> 358.8 | K14: 2351.8 | L14: =K14/(1+'Global Inputs'!$B$7) -> 1993.0508 | M14: =IF(G14="",'Global Inputs'!$B$6,G14) -> 0 | N14: =C14*F14*M14 -> 0 | O14: =K14*'Global Inputs'!$B$8+'Global Inputs'!$B$9 -> 0 | P14: =SUM('Global Inputs'!$B$10:$B$14) -> 56.5 | Q14: =SUM(N14:P14)+AG14 -> 138.813 | R14: =L14-Q14 -> 1854.2378 | S14: =IF(L14=0,0,R14/L14) -> 0.9303515 | T14: =IF(H14="",'Global Inputs'!$B$15,H14) -> 500 | U14: =IF(I14="",'Global Inputs'!$B$16,I14) -> 149 | V14: =T14+U14 -> 649 | W14: =V14*'Global Inputs'!$B$8 -> 0 | X14: ='Global Inputs'!$B$18 -> 10 | Y14: =U14/(1+'Global Inputs'!$B$17)-W14-X14 -> 139 | Z14: =K14+V14 -> 3000.8 | AA14: =Q14+T14+W14+X14 -> 648.813 | AB14: =R14+Y14 -> 1993.2378 | AC14: =AB14-R14 -> 139 | AD14: 0.93052779 | AE14: =IF(C14=0,0,R14/C14) -> 309.03964 | AF14: =IF(C14=0,0,AB14/C14) -> 332.20631 | AG14: =L14*'NC Credits'!$B$15 -> 82.313 | AH14: =IF(OR(ISNUMBER(SEARCH("Overnight",A14)),ISNUMBER(SEARCH("Multi-Day",A14)),ISNUMBER(SEARCH("Medical Tourism",A14))),"MANUAL","AUTO") -> AUTO | AI14: =M14 -> 0 | AJ14: ='Global Inputs'!$B$33 -> 103.5503 | AK14: =C14*F14*AJ14 -> 621.30178 | AL14: =R14+N14-AK14 -> 1232.9361 | AM14: =IF(L14=0,0,AL14/L14) -> 0.61861747 | AN14: =AB14+N14-AK14 -> 1371.9361 | AO14: =IF((L14+U14/(1+'Global Inputs'!$B$17))=0,0,AN14/(L14+U14/(1+'Global Inputs'!$B$17))) -> 0.64047783 | AP14: =IF(C14*F14=0,0,AL14/(C14*F14)) -> 205.48935 | AQ14: 3 | AR14: Procedure-day complexity and extended coordination
A15: Pre-Surgery Concierge | B15: Procedure & Treatment | C15: 4 | D15: 1.1 | E15: 0 | F15: 1 | J15: ='MVP1 Pricing & SKU'!$B$7*D15 -> 328.9 | K15: 1514.6 | L15: =K15/(1+'Global Inputs'!$B$7) -> 1283.5593 | M15: =IF(G15="",'Global Inputs'!$B$6,G15) -> 0 | N15: =C15*F15*M15 -> 0 | O15: =K15*'Global Inputs'!$B$8+'Global Inputs'!$B$9 -> 0 | P15: =SUM('Global Inputs'!$B$10:$B$14) -> 56.5 | Q15: =SUM(N15:P15)+AG15 -> 109.511 | R15: =L15-Q15 -> 1174.0483 | S15: =IF(L15=0,0,R15/L15) -> 0.91468178 | T15: =IF(H15="",'Global Inputs'!$B$15,H15) -> 500 | U15: =IF(I15="",'Global Inputs'!$B$16,I15) -> 149 | V15: =T15+U15 -> 649 | W15: =V15*'Global Inputs'!$B$8 -> 0 | X15: ='Global Inputs'!$B$18 -> 10 | Y15: =U15/(1+'Global Inputs'!$B$17)-W15-X15 -> 139 | Z15: =K15+V15 -> 2163.6 | AA15: =Q15+T15+W15+X15 -> 619.511 | AB15: =R15+Y15 -> 1313.0483 | AC15: =AB15-R15 -> 139 | AD15: 0.91657518 | AE15: =IF(C15=0,0,R15/C15) -> 293.51208 | AF15: =IF(C15=0,0,AB15/C15) -> 328.26208 | AG15: =L15*'NC Credits'!$B$15 -> 53.011 | AH15: =IF(OR(ISNUMBER(SEARCH("Overnight",A15)),ISNUMBER(SEARCH("Multi-Day",A15)),ISNUMBER(SEARCH("Medical Tourism",A15))),"MANUAL","AUTO") -> AUTO | AI15: =M15 -> 0 | AJ15: ='Global Inputs'!$B$33 -> 103.5503 | AK15: =C15*F15*AJ15 -> 414.20118 | AL15: =R15+N15-AK15 -> 759.84714 | AM15: =IF(L15=0,0,AL15/L15) -> 0.59198443 | AN15: =AB15+N15-AK15 -> 898.84714 | AO15: =IF((L15+U15/(1+'Global Inputs'!$B$17))=0,0,AN15/(L15+U15/(1+'Global Inputs'!$B$17))) -> 0.62744148 | AP15: =IF(C15*F15=0,0,AL15/(C15*F15)) -> 189.96178 | AQ15: 2 | AR15: Preparation, records and multi-party coordination
A16: Post-Surgery Follow-up | B16: Procedure & Treatment | C16: 3 | D16: 1 | E16: 0 | F16: 1 | J16: ='MVP1 Pricing & SKU'!$B$7*D16 -> 299 | K16: 1096 | L16: =K16/(1+'Global Inputs'!$B$7) -> 928.81356 | M16: =IF(G16="",'Global Inputs'!$B$6,G16) -> 0 | N16: =C16*F16*M16 -> 0 | O16: =K16*'Global Inputs'!$B$8+'Global Inputs'!$B$9 -> 0 | P16: =SUM('Global Inputs'!$B$10:$B$14) -> 56.5 | Q16: =SUM(N16:P16)+AG16 -> 94.86 | R16: =L16-Q16 -> 833.95356 | S16: =IF(L16=0,0,R16/L16) -> 0.89786971 | T16: =IF(H16="",'Global Inputs'!$B$15,H16) -> 500 | U16: =IF(I16="",'Global Inputs'!$B$16,I16) -> 149 | V16: =T16+U16 -> 649 | W16: =V16*'Global Inputs'!$B$8 -> 0 | X16: ='Global Inputs'!$B$18 -> 10 | Y16: =U16/(1+'Global Inputs'!$B$17)-W16-X16 -> 139 | Z16: =K16+V16 -> 1745 | AA16: =Q16+T16+W16+X16 -> 604.86 | AB16: =R16+Y16 -> 972.95356 | AC16: =AB16-R16 -> 139 | AD16: 0.90271045 | AE16: =IF(C16=0,0,R16/C16) -> 277.98452 | AF16: =IF(C16=0,0,AB16/C16) -> 324.31785 | AG16: =L16*'NC Credits'!$B$15 -> 38.36 | AH16: =IF(OR(ISNUMBER(SEARCH("Overnight",A16)),ISNUMBER(SEARCH("Multi-Day",A16)),ISNUMBER(SEARCH("Medical Tourism",A16))),"MANUAL","AUTO") -> AUTO | AI16: =M16 -> 0 | AJ16: ='Global Inputs'!$B$33 -> 103.5503 | AK16: =C16*F16*AJ16 -> 310.65089 | AL16: =R16+N16-AK16 -> 523.30267 | AM16: =IF(L16=0,0,AL16/L16) -> 0.56340981 | AN16: =AB16+N16-AK16 -> 662.30267 | AO16: =IF((L16+U16/(1+'Global Inputs'!$B$17))=0,0,AN16/(L16+U16/(1+'Global Inputs'!$B$17))) -> 0.61448723 | AP16: =IF(C16*F16=0,0,AL16/(C16*F16)) -> 174.43422 | AQ16: 3 | AR16: Standard follow-up journey with moderate coordination
... A34: Family Medical Update Concierge | B34: Continuing Care | C34: 3 | D34: 0.65 | E34: 0 | F34: 1 | J34: ='MVP1 Pricing & SKU'!$B$7*D34 -> 194.35 | K34: 782.05 | L34: =K34/(1+'Global Inputs'!$B$7) -> 662.75424 | M34: =IF(G34="",'Global Inputs'!$B$6,G34) -> 0 | N34: =C34*F34*M34 -> 0 | O34: =K34*'Global Inputs'!$B$8+'Global Inputs'!$B$9 -> 0 | P34: =SUM('Global Inputs'!$B$10:$B$14) -> 56.5 | Q34: =SUM(N34:P34)+AG34 -> 83.87175 | R34: =L34-Q34 -> 578.88249 | S34: =IF(L34=0,0,R34/L34) -> 0.8734497 | T34: =IF(H34="",'Global Inputs'!$B$15,H34) -> 500 | U34: =IF(I34="",'Global Inputs'!$B$16,I34) -> 149 | V34: =T34+U34 -> 649 | W34: =V34*'Global Inputs'!$B$8 -> 0 | X34: ='Global Inputs'!$B$18 -> 10 | Y34: =U34/(1+'Global Inputs'!$B$17)-W34-X34 -> 139 | Z34: =K34+V34 -> 1431.05 | AA34: =Q34+T34+W34+X34 -> 593.87175 | AB34: =R34+Y34 -> 717.88249 | AC34: =AB34-R34 -> 139 | AD34: 0.8843594 | AE34: =IF(C34=0,0,R34/C34) -> 192.96083 | AF34: =IF(C34=0,0,AB34/C34) -> 239.29416 | AG34: =L34*'NC Credits'!$B$15 -> 27.37175 | AH34: =IF(OR(ISNUMBER(SEARCH("Overnight",A34)),ISNUMBER(SEARCH("Multi-Day",A34)),ISNUMBER(SEARCH("Medical Tourism",A34))),"MANUAL","AUTO") -> AUTO | AI34: =M34 -> 0 | AJ34: ='Global Inputs'!$B$33 -> 103.5503 | AK34: =C34*F34*AJ34 -> 310.65089 | AL34: =R34+N34-AK34 -> 268.2316 | AM34: =IF(L34=0,0,AL34/L34) -> 0.40472257 | AN34: =AB34+N34-AK34 -> 407.2316 | AO34: =IF((L34+U34/(1+'Global Inputs'!$B$17))=0,0,AN34/(L34+U34/(1+'Global Inputs'!$B$17))) -> 0.50166859 | AP34: =IF(C34*F34=0,0,AL34/(C34*F34)) -> 89.410533 | AQ34: 5 | AR34: Communication-focused support; no full physical journey

Sheet Profit Maximizer
A1: NivrāaCare — Profit Maximizer & CFO Decision Support | Fully Loaded View
A2: Ranks modeled economics after payroll allocation while preserving recurring potential and operational complexity. Manual-priced overnight / 24h services are excluded from automatic 'highest' insights.
A4: CFO Insights — Dynamic
A5: Highest modeled eligible contribution / journey | B5: =INDEX($A$15:$A$44,MATCH(MAX($AL$15:$AL$44),$AL$15:$AL$44,0)) -> #REF! | C5: Fully loaded blended contribution | D5: =MAX($AL$15:$AL$44) -> #REF!
A6: Highest modeled eligible contribution / Angel hour | B6: =INDEX($A$15:$A$44,MATCH(MAX($AM$15:$AM$44),$AM$15:$AM$44,0)) -> Medical Tourism — Concierge Package (24 HR Basis) | C6: ₹ / Angel hour | D6: =MAX($AM$15:$AM$44) -> 488.20518
A7: Highest recurring strategic potential | B7: =INDEX($A$15:$A$44,MATCH(MAX($AJ$15:$AJ$44),$AJ$15:$AJ$44,0)) -> Hospital Visit | C7: Potential score | D7: =MAX($AJ$15:$AJ$44) -> 5
A8: Lowest fully loaded margin service | B8: =INDEX('Service Economics'!$A$5:$A$34,MATCH(MIN('Service Economics'!$AM$5:$AM$34),'Service Economics'!$AM$5:$AM$34,0)) -> Medical Records Concierge | C8: Fully loaded margin | D8: =MIN('Service Economics'!$AM$5:$AM$34) -> 0.40106519
A9: Recommended transport mix | B9: =IF(AVERAGE($G$15:$G$44)>AVERAGE($F$15:$F$44),"Case 2 primary / Case 1 fallback","Case 1 primary") -> Case 2 primary / Case 1 fallback | C9: Current break-even volume | D9: =#REF! -> #REF!
A10: Biggest profit lever | B10: =INDEX($A$51:$A$63,MATCH(MAX($I$51:$I$63),$I$51:$I$63,0)) -> #REF! | C10: Biggest unit-economics risk | D10: =IF(#REF!<#REF!*0.8,"Low Whitefield demand density / Angel under-utilization",IF(#REF!>4,"Long hospital waiting / journey duration","Transport/payment leakage")) -> #REF!
A11: ="Model insight: "&B6&" currently has the highest modeled contribution per Angel hour. Commercial priority must also consider repeat potential, operational complexity and manual-pricing status; do not treat the top modeled service as an automatic launch recommendation." -> Model insight: Medical Tourism — Concierge Package (24 HR Basis) currently has the highest modeled contribution per Angel hour. Commercial priority must also consider repeat potential, operational complexity and manual-pricing status; do not treat the top modeled service as an automatic launch recommendation.
A13: Service Profitability & Capacity Ranking — Incremental + Fully Loaded Views
A14: Service | B14: Category | C14: Hours | D14: Customer Price | E14: Revenue / Angel Hr | F14: Case 1 Contribution | G14: Case 2 Contribution | H14: Blended Contribution / Journey | I14: Contribution Margin | J14: Contribution / Angel Hr | K14: Repeat Potential (1-5) | L14: Operational Complexity (1-5) | M14: Transport Dependency (1-5) | N14: Strategic Weight (0.5-1.5) | O14: Capacity Efficiency Score | P14: Model Score | Q14: Recommended Priority | R14: Current Mix % | S14: Optimization Score | T14: Optimized Mix % | U14: Recurring Service? | V14: Rate Multiplier | W14: Fixed Premium | X14: Recurring Profit/Hr | Y14: Price Sensitivity Weight | Z14: Angel Hr Weight | AA14: Min Booking Test Price | AB14: Addl-Hour Test Price | AC14: Current Collection/Journey | AD14: Optimized Collection Weight | AE14: Optimized Contribution Weight | AF14: Optimized Hours Weight | AG14: Case 1 Fully Loaded Contribution | AH14: Case 2 Fully Loaded Contribution | AI14: Fully Loaded Contribution / Angel Hr | AJ14: Recurring / Strategic Potential | AK14: Portfolio | AL14: Auto-Rank Blended Contribution | AM14: Auto-Rank Contribution / Angel Hr
A15: ='Service Economics'!A5 -> Hospital Visit | B15: ='Service Economics'!B5 -> Medical Visit | C15: ='Service Economics'!C5 -> 4 | D15: ='Service Economics'!K5 -> 1395 | E15: =IF(C15=0,0,D15/C15) -> 348.75 | F15: ='Service Economics'!R5 -> 1076.8784 | G15: ='Service Economics'!AB5 -> 1215.8784 | H15: =#REF!*F15+#REF!*G15-#REF! -> #REF! | I15: =IF(('Service Economics'!L5+#REF!*'Service Economics'!U5/(1+'Global Inputs'!$B$17))=0,0,H15/('Service Economics'!L5+#REF!*'Service Economics'!U5/(1+'Global Inputs'!$B$17))) -> #REF! | J15: =IF(C15=0,0,H15/C15) -> #REF! | K15: 3 | L15: 3 | M15: 5 | N15: 1.2 | O15: =IF(MAX($J$15:$J$44)=0,0,J15/MAX($J$15:$J$44)*100) -> #REF! | P15: =(IF(MAX($J$15:$J$44)=0,0,J15/MAX($J$15:$J$44))*0.45+K15/5*0.2+(6-L15)/5*0.15+(6-M15)/5*0.1+N15/1.5*0.1)*100 -> #REF! | Q15: =IF(H15<=0,"REVIEW — Economics need improvement",IF(AND(J15>=AVERAGE($J$15:$J$44)*1.15,K15>=4,L15<=3),"CORE — Push aggressively",IF(J15>=AVERAGE($J$15:$J$44),"GROW — Attractive economics",IF(K15>=4,"STRATEGIC — Important but lower margin","REVIEW — Economics need improvement")))) -> #REF! | R15: =#REF! -> #REF! | S15: =MAX(J15,0)^3*(0.5+K15/10)*(0.5+(6-L15)/10)*N15 -> #REF! | T15: =IF(SUM($S$15:$S$44)=0,R15,0.2*R15+0.8*S15/SUM($S$15:$S$44)) -> #REF! | U15: No | V15: ='Service Economics'!D5 -> 1 | W15: ='Service Economics'!E5 -> 0 | X15: =IF(U15="Yes",J15,0) -> 0 | Y15: =R15*C15*V15 -> #REF! | Z15: =R15*C15*'Service Economics'!F5 -> #REF! | AA15: =MAX(C15,$C$53)*'Global Inputs'!$B$5*V15+W15 -> 1196 | AB15: =MAX(C15,'Global Inputs'!$B$22)*'Global Inputs'!$B$5*V15*$C$54+W15 -> 1076.4 | AC15: =D15+#REF!*'Service Economics'!V5 -> #REF! | AD15: =T15*AC15 -> #REF! | AE15: =T15*H15 -> #REF! | AF15: =T15*C15 -> #REF! | AG15: ='Service Economics'!AL5 -> 662.67721 | AH15: ='Service Economics'!AN5 -> 801.67721 | AI15: ='Service Economics'!AP5 -> 165.6693 | AJ15: ='Service Economics'!AQ5 -> 5 | AK15: =#REF! -> #REF! | AL15: =IF(ISNUMBER(SEARCH("Future",'Service Economics'!AH5)),-1000000000,AG15*(1-#REF!)+AH15*#REF!) -> #REF! | AM15: =IF(ISNUMBER(SEARCH("Future",'Service Economics'!AH5)),-1000000000,AI15) -> 165.6693
A16: ='Service Economics'!A6 -> Hospital Visit — Concierge at Hospital | B16: ='Service Economics'!B6 -> Medical Visit | C16: ='Service Economics'!C6 -> 3 | D16: ='Service Economics'!K6 -> 916.6 | E16: =IF(C16=0,0,D16/C16) -> 305.53333 | F16: ='Service Economics'!R6 -> 688.19866 | G16: ='Service Economics'!AB6 -> 827.19866 | H16: =#REF!*F16+#REF!*G16-#REF! -> #REF! | I16: =IF(('Service Economics'!L6+#REF!*'Service Economics'!U6/(1+'Global Inputs'!$B$17))=0,0,H16/('Service Economics'!L6+#REF!*'Service Economics'!U6/(1+'Global Inputs'!$B$17))) -> #REF! | J16: =IF(C16=0,0,H16/C16) -> #REF! | K16: 3 | L16: 2 | M16: 4 | N16: 1 | O16: =IF(MAX($J$15:$J$44)=0,0,J16/MAX($J$15:$J$44)*100) -> #REF! | P16: =(IF(MAX($J$15:$J$44)=0,0,J16/MAX($J$15:$J$44))*0.45+K16/5*0.2+(6-L16)/5*0.15+(6-M16)/5*0.1+N16/1.5*0.1)*100 -> #REF! | Q16: =IF(H16<=0,"REVIEW — Economics need improvement",IF(AND(J16>=AVERAGE($J$15:$J$44)*1.15,K16>=4,L16<=3),"CORE — Push aggressively",IF(J16>=AVERAGE($J$15:$J$44),"GROW — Attractive economics",IF(K16>=4,"STRATEGIC — Important but lower margin","REVIEW — Economics need improvement")))) -> #REF! | R16: =#REF! -> #REF! | S16: =MAX(J16,0)^3*(0.5+K16/10)*(0.5+(6-L16)/10)*N16 -> #REF! | T16: =IF(SUM($S$15:$S$44)=0,R16,0.2*R16+0.8*S16/SUM($S$15:$S$44)) -> #REF! | U16: No | V16: ='Service Economics'!D6 -> 0.8 | W16: ='Service Economics'!E6 -> 0 | X16: =IF(U16="Yes",J16,0) -> 0 | Y16: =R16*C16*V16 -> #REF! | Z16: =R16*C16*'Service Economics'!F6 -> #REF! | AA16: =MAX(C16,$C$53)*'Global Inputs'!$B$5*V16+W16 -> 717.6 | AB16: =MAX(C16,'Global Inputs'!$B$22)*'Global Inputs'!$B$5*V16*$C$54+W16 -> 645.84 | AC16: =D16+#REF!*'Service Economics'!V6 -> #REF! | AD16: =T16*AC16 -> #REF! | AE16: =T16*H16 -> #REF! | AF16: =T16*C16 -> #REF! | AG16: ='Service Economics'!AL6 -> 377.54777 | AH16: ='Service Economics'!AN6 -> 516.54777 | AI16: ='Service Economics'!AP6 -> 125.84926 | AJ16: ='Service Economics'!AQ6 -> 4 | AK16: =#REF! -> #REF! | AL16: =IF(ISNUMBER(SEARCH("Future",'Service Economics'!AH6)),-1000000000,AG16*(1-#REF!)+AH16*#REF!) -> #REF! | AM16: =IF(ISNUMBER(SEARCH("Future",'Service Economics'!AH6)),-1000000000,AI16) -> 125.84926
A17: ='Service Economics'!A7 -> Clinic Visit | B17: ='Service Economics'!B7 -> Medical Visit | C17: ='Service Economics'!C7 -> 2 | D17: ='Service Economics'!K7 -> 737.2 | E17: =IF(C17=0,0,D17/C17) -> 368.6 | F17: ='Service Economics'!R7 -> 542.44376 | G17: ='Service Economics'!AB7 -> 681.44376 | H17: =#REF!*F17+#REF!*G17-#REF! -> #REF! | I17: =IF(('Service Economics'!L7+#REF!*'Service Economics'!U7/(1+'Global Inputs'!$B$17))=0,0,H17/('Service Economics'!L7+#REF!*'Service Economics'!U7/(1+'Global Inputs'!$B$17))) -> #REF! | J17: =IF(C17=0,0,H17/C17) -> #REF! | K17: 3 | L17: 2 | M17: 4 | N17: 1 | O17: =IF(MAX($J$15:$J$44)=0,0,J17/MAX($J$15:$J$44)*100) -> #REF! | P17: =(IF(MAX($J$15:$J$44)=0,0,J17/MAX($J$15:$J$44))*0.45+K17/5*0.2+(6-L17)/5*0.15+(6-M17)/5*0.1+N17/1.5*0.1)*100 -> #REF! | Q17: =IF(H17<=0,"REVIEW — Economics need improvement",IF(AND(J17>=AVERAGE($J$15:$J$44)*1.15,K17>=4,L17<=3),"CORE — Push aggressively",IF(J17>=AVERAGE($J$15:$J$44),"GROW — Attractive economics",IF(K17>=4,"STRATEGIC — Important but lower margin","REVIEW — Economics need improvement")))) -> #REF! | R17: =#REF! -> #REF! | S17: =MAX(J17,0)^3*(0.5+K17/10)*(0.5+(6-L17)/10)*N17 -> #REF! | T17: =IF(SUM($S$15:$S$44)=0,R17,0.2*R17+0.8*S17/SUM($S$15:$S$44)) -> #REF! | U17: No | V17: ='Service Economics'!D7 -> 0.9 | W17: ='Service Economics'!E7 -> 0 | X17: =IF(U17="Yes",J17,0) -> 0 | Y17: =R17*C17*V17 -> #REF! | Z17: =R17*C17*'Service Economics'!F7 -> #REF! | AA17: =MAX(C17,$C$53)*'Global Inputs'!$B$5*V17+W17 -> 807.3 | AB17: =MAX(C17,'Global Inputs'!$B$22)*'Global Inputs'!$B$5*V17*$C$54+W17 -> 484.38 | AC17: =D17+#REF!*'Service Economics'!V7 -> #REF! | AD17: =T17*AC17 -> #REF! | AE17: =T17*H17 -> #REF! | AF17: =T17*C17 -> #REF! | AG17: ='Service Economics'!AL7 -> 335.34317 | AH17: ='Service Economics'!AN7 -> 474.34317 | AI17: ='Service Economics'!AP7 -> 167.67159 | AJ17: ='Service Economics'!AQ7 -> 4 | AK17: =#REF! -> #REF! | AL17: =IF(ISNUMBER(SEARCH("Future",'Service Economics'!AH7)),-1000000000,AG17*(1-#REF!)+AH17*#REF!) -> #REF! | AM17: =IF(ISNUMBER(SEARCH("Future",'Service Economics'!AH7)),-1000000000,AI17) -> 167.67159
A18: ='Service Economics'!A8 -> Diagnostic Center Visit | B18: ='Service Economics'!B8 -> Medical Visit | C18: ='Service Economics'!C8 -> 3 | D18: ='Service Economics'!K8 -> 961.45 | E18: =IF(C18=0,0,D18/C18) -> 320.48333 | F18: ='Service Economics'!R8 -> 724.63739 | G18: ='Service Economics'!AB8 -> 863.63739 | H18: =#REF!*F18+#REF!*G18-#REF! -> #REF! | I18: =IF(('Service Economics'!L8+#REF!*'Service Economics'!U8/(1+'Global Inputs'!$B$17))=0,0,H18/('Service Economics'!L8+#REF!*'Service Economics'!U8/(1+'Global Inputs'!$B$17))) -> #REF! | J18: =IF(C18=0,0,H18/C18) -> #REF! | K18: 3 | L18: 2 | M18: 4 | N18: 1 | O18: =IF(MAX($J$15:$J$44)=0,0,J18/MAX($J$15:$J$44)*100) -> #REF! | P18: =(IF(MAX($J$15:$J$44)=0,0,J18/MAX($J$15:$J$44))*0.45+K18/5*0.2+(6-L18)/5*0.15+(6-M18)/5*0.1+N18/1.5*0.1)*100 -> #REF! | Q18: =IF(H18<=0,"REVIEW — Economics need improvement",IF(AND(J18>=AVERAGE($J$15:$J$44)*1.15,K18>=4,L18<=3),"CORE — Push aggressively",IF(J18>=AVERAGE($J$15:$J$44),"GROW — Attractive economics",IF(K18>=4,"STRATEGIC — Important but lower margin","REVIEW — Economics need improvement")))) -> #REF! | R18: =#REF! -> #REF! | S18: =MAX(J18,0)^3*(0.5+K18/10)*(0.5+(6-L18)/10)*N18 -> #REF! | T18: =IF(SUM($S$15:$S$44)=0,R18,0.2*R18+0.8*S18/SUM($S$15:$S$44)) -> #REF! | U18: No | V18: ='Service Economics'!D8 -> 0.85 | W18: ='Service Economics'!E8 -> 0 | X18: =IF(U18="Yes",J18,0) -> 0 | Y18: =R18*C18*V18 -> #REF! | Z18: =R18*C18*'Service Economics'!F8 -> #REF! | AA18: =MAX(C18,$C$53)*'Global Inputs'!$B$5*V18+W18 -> 762.45 | AB18: =MAX(C18,'Global Inputs'!$B$22)*'Global Inputs'!$B$5*V18*$C$54+W18 -> 686.205 | AC18: =D18+#REF!*'Service Economics'!V8 -> #REF! | AD18: =T18*AC18 -> #REF! | AE18: =T18*H18 -> #REF! | AF18: =T18*C18 -> #REF! | AG18: ='Service Economics'!AL8 -> 413.9865 | AH18: ='Service Economics'!AN8 -> 552.9865 | AI18: ='Service Economics'!AP8 -> 137.9955 | AJ18: ='Service Economics'!AQ8 -> 4 | AK18: =#REF! -> #REF! | AL18: =IF(ISNUMBER(SEARCH("Future",'Service Economics'!AH8)),-1000000000,AG18*(1-#REF!)+AH18*#REF!) -> #REF! | AM18: =IF(ISNUMBER(SEARCH("Future",'Service Economics'!AH8)),-1000000000,AI18) -> 137.9955
A19: ='Service Economics'!A9 -> Health Check-up Concierge | B19: ='Service Economics'!B9 -> Medical Visit | C19: ='Service Economics'!C9 -> 5 | D19: ='Service Economics'!K9 -> 1544.5 | E19: =IF(C19=0,0,D19/C19) -> 308.9 | F19: ='Service Economics'!R9 -> 1198.3408 | G19: ='Service Economics'!AB9 -> 1337.3408 | H19: =#REF!*F19+#REF!*G19-#REF! -> #REF! | I19: =IF(('Service Economics'!L9+#REF!*'Service Economics'!U9/(1+'Global Inputs'!$B$17))=0,0,H19/('Service Economics'!L9+#REF!*'Service Economics'!U9/(1+'Global Inputs'!$B$17))) -> #REF! | J19: =IF(C19=0,0,H19/C19) -> #REF! | K19: 2 | L19: 3 | M19: 4 | N19: 0.9 | O19: =IF(MAX($J$15:$J$44)=0,0,J19/MAX($J$15:$J$44)*100) -> #REF! | P19: =(IF(MAX($J$15:$J$44)=0,0,J19/MAX($J$15:$J$44))*0.45+K19/5*0.2+(6-L19)/5*0.15+(6-M19)/5*0.1+N19/1.5*0.1)*100 -> #REF! | Q19: =IF(H19<=0,"REVIEW — Economics need improvement",IF(AND(J19>=AVERAGE($J$15:$J$44)*1.15,K19>=4,L19<=3),"CORE — Push aggressively",IF(J19>=AVERAGE($J$15:$J$44),"GROW — Attractive economics",IF(K19>=4,"STRATEGIC — Important but lower margin","REVIEW — Economics need improvement")))) -> #REF! | R19: =#REF! -> #REF! | S19: =MAX(J19,0)^3*(0.5+K19/10)*(0.5+(6-L19)/10)*N19 -> #REF! | T19: =IF(SUM($S$15:$S$44)=0,R19,0.2*R19+0.8*S19/SUM($S$15:$S$44)) -> #REF! | U19: No | V19: ='Service Economics'!D9 -> 0.9 | W19: ='Service Economics'!E9 -> 0 | X19: =IF(U19="Yes",J19,0) -> 0 | Y19: =R19*C19*V19 -> #REF! | Z19: =R19*C19*'Service Economics'!F9 -> #REF! | AA19: =MAX(C19,$C$53)*'Global Inputs'!$B$5*V19+W19 -> 1345.5 | AB19: =MAX(C19,'Global Inputs'!$B$22)*'Global Inputs'!$B$5*V19*$C$54+W19 -> 1210.95 | AC19: =D19+#REF!*'Service Economics'!V9 -> #REF! | AD19: =T19*AC19 -> #REF! | AE19: =T19*H19 -> #REF! | AF19: =T19*C19 -> #REF! | AG19: ='Service Economics'!AL9 -> 680.58933 | AH19: ='Service Economics'!AN9 -> 819.58933 | AI19: ='Service Economics'!AP9 -> 136.11787 | AJ19: ='Service Economics'!AQ9 -> 3 | AK19: =#REF! -> #REF! | AL19: =IF(ISNUMBER(SEARCH("Future",'Service Economics'!AH9)),-1000000000,AG19*(1-#REF!)+AH19*#REF!) -> #REF! | AM19: =IF(ISNUMBER(SEARCH("Future",'Service Economics'!AH9)),-1000000000,AI19) -> 136.11787
A20: ='Service Economics'!A10 -> Hospital Admission Concierge | B20: ='Service Economics'!B10 -> Hospital Support | C20: ='Service Economics'!C10 -> 4 | D20: ='Service Economics'!K10 -> 1574.4 | E20: =IF(C20=0,0,D20/C20) -> 393.6 | F20: ='Service Economics'!R10 -> 1222.6333 | G20: ='Service Economics'!AB10 -> 1361.6333 | H20: =#REF!*F20+#REF!*G20-#REF! -> #REF! | I20: =IF(('Service Economics'!L10+#REF!*'Service Economics'!U10/(1+'Global Inputs'!$B$17))=0,0,H20/('Service Economics'!L10+#REF!*'Service Economics'!U10/(1+'Global Inputs'!$B$17))) -> #REF! | J20: =IF(C20=0,0,H20/C20) -> #REF! | K20: 2 | L20: 4 | M20: 4 | N20: 1.1 | O20: =IF(MAX($J$15:$J$44)=0,0,J20/MAX($J$15:$J$44)*100) -> #REF! | P20: =(IF(MAX($J$15:$J$44)=0,0,J20/MAX($J$15:$J$44))*0.45+K20/5*0.2+(6-L20)/5*0.15+(6-M20)/5*0.1+N20/1.5*0.1)*100 -> #REF! | Q20: =IF(H20<=0,"REVIEW — Economics need improvement",IF(AND(J20>=AVERAGE($J$15:$J$44)*1.15,K20>=4,L20<=3),"CORE — Push aggressively",IF(J20>=AVERAGE($J$15:$J$44),"GROW — Attractive economics",IF(K20>=4,"STRATEGIC — Important but lower margin","REVIEW — Economics need improvement")))) -> #REF! | R20: =#REF! -> #REF! | S20: =MAX(J20,0)^3*(0.5+K20/10)*(0.5+(6-L20)/10)*N20 -> #REF! | T20: =IF(SUM($S$15:$S$44)=0,R20,0.2*R20+0.8*S20/SUM($S$15:$S$44)) -> #REF! | U20: No | V20: ='Service Economics'!D10 -> 1.15 | W20: ='Service Economics'!E10 -> 0 | X20: =IF(U20="Yes",J20,0) -> 0 | Y20: =R20*C20*V20 -> #REF! | Z20: =R20*C20*'Service Economics'!F10 -> #REF! | AA20: =MAX(C20,$C$53)*'Global Inputs'!$B$5*V20+W20 -> 1375.4 | AB20: =MAX(C20,'Global Inputs'!$B$22)*'Global Inputs'!$B$5*V20*$C$54+W20 -> 1237.86 | AC20: =D20+#REF!*'Service Economics'!V10 -> #REF! | AD20: =T20*AC20 -> #REF! | AE20: =T20*H20 -> #REF! | AF20: =T20*C20 -> #REF! | AG20: ='Service Economics'!AL10 -> 808.4321 | AH20: ='Service Economics'!AN10 -> 947.4321 | AI20: ='Service Economics'!AP10 -> 202.10803 | AJ20: ='Service Economics'!AQ10 -> 3 | AK20: =#REF! -> #REF! | AL20: =IF(ISNUMBER(SEARCH("Future",'Service Economics'!AH10)),-1000000000,AG20*(1-#REF!)+AH20*#REF!) -> #REF! | AM20: =IF(ISNUMBER(SEARCH("Future",'Service Economics'!AH10)),-1000000000,AI20) -> 202.10803
A21: ='Service Economics'!A11 -> Hospital Discharge Concierge | B21: ='Service Economics'!B11 -> Hospital Support | C21: ='Service Economics'!C11 -> 4 | D21: ='Service Economics'!K11 -> 1514.6 | E21: =IF(C21=0,0,D21/C21) -> 378.65 | F21: ='Service Economics'!R11 -> 1174.0483 | G21: ='Service Economics'!AB11 -> 1313.0483 | H21: =#REF!*F21+#REF!*G21-#REF! -> #REF! | I21: =IF(('Service Economics'!L11+#REF!*'Service Economics'!U11/(1+'Global Inputs'!$B$17))=0,0,H21/('Service Economics'!L11+#REF!*'Service Economics'!U11/(1+'Global Inputs'!$B$17))) -> #REF! | J21: =IF(C21=0,0,H21/C21) -> #REF! | K21: 2 | L21: 4 | M21: 4 | N21: 1.1 | O21: =IF(MAX($J$15:$J$44)=0,0,J21/MAX($J$15:$J$44)*100) -> #REF! | P21: =(IF(MAX($J$15:$J$44)=0,0,J21/MAX($J$15:$J$44))*0.45+K21/5*0.2+(6-L21)/5*0.15+(6-M21)/5*0.1+N21/1.5*0.1)*100 -> #REF! | Q21: =IF(H21<=0,"REVIEW — Economics need improvement",IF(AND(J21>=AVERAGE($J$15:$J$44)*1.15,K21>=4,L21<=3),"CORE — Push aggressively",IF(J21>=AVERAGE($J$15:$J$44),"GROW — Attractive economics",IF(K21>=4,"STRATEGIC — Important but lower margin","REVIEW — Economics need improvement")))) -> #REF! | R21: =#REF! -> #REF! | S21: =MAX(J21,0)^3*(0.5+K21/10)*(0.5+(6-L21)/10)*N21 -> #REF! | T21: =IF(SUM($S$15:$S$44)=0,R21,0.2*R21+0.8*S21/SUM($S$15:$S$44)) -> #REF! | U21: No | V21: ='Service Economics'!D11 -> 1.1 | W21: ='Service Economics'!E11 -> 0 | X21: =IF(U21="Yes",J21,0) -> 0 | Y21: =R21*C21*V21 -> #REF! | Z21: =R21*C21*'Service Economics'!F11 -> #REF! | AA21: =MAX(C21,$C$53)*'Global Inputs'!$B$5*V21+W21 -> 1315.6 | AB21: =MAX(C21,'Global Inputs'!$B$22)*'Global Inputs'!$B$5*V21*$C$54+W21 -> 1184.04 | AC21: =D21+#REF!*'Service Economics'!V11 -> #REF! | AD21: =T21*AC21 -> #REF! | AE21: =T21*H21 -> #REF! | AF21: =T21*C21 -> #REF! | AG21: ='Service Economics'!AL11 -> 759.84714 | AH21: ='Service Economics'!AN11 -> 898.84714 | AI21: ='Service Economics'!AP11 -> 189.96178 | AJ21: ='Service Economics'!AQ11 -> 3 | AK21: =#REF! -> #REF! | AL21: =IF(ISNUMBER(SEARCH("Future",'Service Economics'!AH11)),-1000000000,AG21*(1-#REF!)+AH21*#REF!) -> #REF! | AM21: =IF(ISNUMBER(SEARCH("Future",'Service Economics'!AH11)),-1000000000,AI21) -> 189.96178
A22: ='Service Economics'!A12 -> Overnight Hospital Concierge | B22: ='Service Economics'!B12 -> Hospital Support | C22: ='Service Economics'!C12 -> 12 | D22: ='Service Economics'!K12 -> 3547.8 | E22: =IF(C22=0,0,D22/C22) -> 295.65 | F22: ='Service Economics'!R12 -> 2825.9372 | G22: ='Service Economics'!AB12 -> 2964.9372 | H22: =#REF!*F22+#REF!*G22-#REF! -> #REF! | I22: =IF(('Service Economics'!L12+#REF!*'Service Economics'!U12/(1+'Global Inputs'!$B$17))=0,0,H22/('Service Economics'!L12+#REF!*'Service Economics'!U12/(1+'Global Inputs'!$B$17))) -> #REF! | J22: =IF(C22=0,0,H22/C22) -> #REF! | K22: 2 | L22: 4 | M22: 2 | N22: 0.9 | O22: =IF(MAX($J$15:$J$44)=0,0,J22/MAX($J$15:$J$44)*100) -> #REF! | P22: =(IF(MAX($J$15:$J$44)=0,0,J22/MAX($J$15:$J$44))*0.45+K22/5*0.2+(6-L22)/5*0.15+(6-M22)/5*0.1+N22/1.5*0.1)*100 -> #REF! | Q22: =IF(H22<=0,"REVIEW — Economics need improvement",IF(AND(J22>=AVERAGE($J$15:$J$44)*1.15,K22>=4,L22<=3),"CORE — Push aggressively",IF(J22>=AVERAGE($J$15:$J$44),"GROW — Attractive economics",IF(K22>=4,"STRATEGIC — Important but lower margin","REVIEW — Economics need improvement")))) -> #REF! | R22: =#REF! -> #REF! | S22: =MAX(J22,0)^3*(0.5+K22/10)*(0.5+(6-L22)/10)*N22 -> #REF! | T22: =IF(SUM($S$15:$S$44)=0,R22,0.2*R22+0.8*S22/SUM($S$15:$S$44)) -> #REF! | U22: No | V22: ='Service Economics'!D12 -> 0.85 | W22: ='Service Economics'!E12 -> 299 | X22: =IF(U22="Yes",J22,0) -> 0 | Y22: =R22*C22*V22 -> #REF! | Z22: =R22*C22*'Service Economics'!F12 -> #REF! | AA22: =MAX(C22,$C$53)*'Global Inputs'!$B$5*V22+W22 -> 3348.8 | AB22: =MAX(C22,'Global Inputs'!$B$22)*'Global Inputs'!$B$5*V22*$C$54+W22 -> 3043.82 | AC22: =D22+#REF!*'Service Economics'!V12 -> #REF! | AD22: =T22*AC22 -> #REF! | AE22: =T22*H22 -> #REF! | AF22: =T22*C22 -> #REF! | AG22: ='Service Economics'!AL12 -> 1583.3336 | AH22: ='Service Economics'!AN12 -> 1722.3336 | AI22: ='Service Economics'!AP12 -> 131.94447 | AJ22: ='Service Economics'!AQ12 -> 2 | AK22: =#REF! -> #REF! | AL22: =IF(ISNUMBER(SEARCH("Future",'Service Economics'!AH12)),-1000000000,AG22*(1-#REF!)+AH22*#REF!) -> #REF! | AM22: =IF(ISNUMBER(SEARCH("Future",'Service Economics'!AH12)),-1000000000,AI22) -> 131.94447
A23: ='Service Economics'!A13 -> Multi-Day Hospital Concierge (per 12h shift) | B23: ='Service Economics'!B13 -> Hospital Support | C23: ='Service Economics'!C13 -> 12 | D23: ='Service Economics'!K13 -> 3547.8 | E23: =IF(C23=0,0,D23/C23) -> 295.65 | F23: ='Service Economics'!R13 -> 2825.9372 | G23: ='Service Economics'!AB13 -> 2964.9372 | H23: =#REF!*F23+#REF!*G23-#REF! -> #REF! | I23: =IF(('Service Economics'!L13+#REF!*'Service Economics'!U13/(1+'Global Inputs'!$B$17))=0,0,H23/('Service Economics'!L13+#REF!*'Service Economics'!U13/(1+'Global Inputs'!$B$17))) -> #REF! | J23: =IF(C23=0,0,H23/C23) -> #REF! | K23: 3 | L23: 5 | M23: 1 | N23: 0.8 | O23: =IF(MAX($J$15:$J$44)=0,0,J23/MAX($J$15:$J$44)*100) -> #REF! | P23: =(IF(MAX($J$15:$J$44)=0,0,J23/MAX($J$15:$J$44))*0.45+K23/5*0.2+(6-L23)/5*0.15+(6-M23)/5*0.1+N23/1.5*0.1)*100 -> #REF! | Q23: =IF(H23<=0,"REVIEW — Economics need improvement",IF(AND(J23>=AVERAGE($J$15:$J$44)*1.15,K23>=4,L23<=3),"CORE — Push aggressively",IF(J23>=AVERAGE($J$15:$J$44),"GROW — Attractive economics",IF(K23>=4,"STRATEGIC — Important but lower margin","REVIEW — Economics need improvement")))) -> #REF! | R23: =#REF! -> #REF! | S23: =MAX(J23,0)^3*(0.5+K23/10)*(0.5+(6-L23)/10)*N23 -> #REF! | T23: =IF(SUM($S$15:$S$44)=0,R23,0.2*R23+0.8*S23/SUM($S$15:$S$44)) -> #REF! | U23: Yes | V23: ='Service Economics'!D13 -> 0.85 | W23: ='Service Economics'!E13 -> 299 | X23: =IF(U23="Yes",J23,0) -> #REF! | Y23: =R23*C23*V23 -> #REF! | Z23: =R23*C23*'Service Economics'!F13 -> #REF! | AA23: =MAX(C23,$C$53)*'Global Inputs'!$B$5*V23+W23 -> 3348.8 | AB23: =MAX(C23,'Global Inputs'!$B$22)*'Global Inputs'!$B$5*V23*$C$54+W23 -> 3043.82 | AC23: =D23+#REF!*'Service Economics'!V13 -> #REF! | AD23: =T23*AC23 -> #REF! | AE23: =T23*H23 -> #REF! | AF23: =T23*C23 -> #REF! | AG23: ='Service Economics'!AL13 -> 1583.3336 | AH23: ='Service Economics'!AN13 -> 1722.3336 | AI23: ='Service Economics'!AP13 -> 131.94447 | AJ23: ='Service Economics'!AQ13 -> 2 | AK23: =#REF! -> #REF! | AL23: =IF(ISNUMBER(SEARCH("Future",'Service Economics'!AH13)),-1000000000,AG23*(1-#REF!)+AH23*#REF!) -> #REF! | AM23: =IF(ISNUMBER(SEARCH("Future",'Service Economics'!AH13)),-1000000000,AI23) -> 131.94447
A24: ='Service Economics'!A14 -> Day Surgery / Procedure Concierge | B24: ='Service Economics'!B14 -> Procedure & Treatment | C24: ='Service Economics'!C14 -> 6 | D24: ='Service Economics'!K14 -> 2351.8 | E24: =IF(C24=0,0,D24/C24) -> 391.96667 | F24: ='Service Economics'!R14 -> 1854.2378 | G24: ='Service Economics'!AB14 -> 1993.2378 | H24: =#REF!*F24+#REF!*G24-#REF! -> #REF! | I24: =IF(('Service Economics'!L14+#REF!*'Service Economics'!U14/(1+'Global Inputs'!$B$17))=0,0,H24/('Service Economics'!L14+#REF!*'Service Economics'!U14/(1+'Global Inputs'!$B$17))) -> #REF! | J24: =IF(C24=0,0,H24/C24) -> #REF! | K24: 2 | L24: 4 | M24: 4 | N24: 1.1 | O24: =IF(MAX($J$15:$J$44)=0,0,J24/MAX($J$15:$J$44)*100) -> #REF! | P24: =(IF(MAX($J$15:$J$44)=0,0,J24/MAX($J$15:$J$44))*0.45+K24/5*0.2+(6-L24)/5*0.15+(6-M24)/5*0.1+N24/1.5*0.1)*100 -> #REF! | Q24: =IF(H24<=0,"REVIEW — Economics need improvement",IF(AND(J24>=AVERAGE($J$15:$J$44)*1.15,K24>=4,L24<=3),"CORE — Push aggressively",IF(J24>=AVERAGE($J$15:$J$44),"GROW — Attractive economics",IF(K24>=4,"STRATEGIC — Important but lower margin","REVIEW — Economics need improvement")))) -> #REF! | R24: =#REF! -> #REF! | S24: =MAX(J24,0)^3*(0.5+K24/10)*(0.5+(6-L24)/10)*N24 -> #REF! | T24: =IF(SUM($S$15:$S$44)=0,R24,0.2*R24+0.8*S24/SUM($S$15:$S$44)) -> #REF! | U24: No | V24: ='Service Economics'!D14 -> 1.2 | W24: ='Service Economics'!E14 -> 0 | X24: =IF(U24="Yes",J24,0) -> 0 | Y24: =R24*C24*V24 -> #REF! | Z24: =R24*C24*'Service Economics'!F14 -> #REF! | AA24: =MAX(C24,$C$53)*'Global Inputs'!$B$5*V24+W24 -> 2152.8 | AB24: =MAX(C24,'Global Inputs'!$B$22)*'Global Inputs'!$B$5*V24*$C$54+W24 -> 1937.52 | AC24: =D24+#REF!*'Service Economics'!V14 -> #REF! | AD24: =T24*AC24 -> #REF! | AE24: =T24*H24 -> #REF! | AF24: =T24*C24 -> #REF! | AG24: ='Service Economics'!AL14 -> 1232.9361 | AH24: ='Service Economics'!AN14 -> 1371.9361 | AI24: ='Service Economics'!AP14 -> 205.48935 | AJ24: ='Service Economics'!AQ14 -> 3 | AK24: =#REF! -> #REF! | AL24: =IF(ISNUMBER(SEARCH("Future",'Service Economics'!AH14)),-1000000000,AG24*(1-#REF!)+AH24*#REF!) -> #REF! | AM24: =IF(ISNUMBER(SEARCH("Future",'Service Economics'!AH14)),-1000000000,AI24) -> 205.48935
A25: ='Service Economics'!A15 -> Pre-Surgery Concierge | B25: ='Service Economics'!B15 -> Procedure & Treatment | C25: ='Service Economics'!C15 -> 4 | D25: ='Service Economics'!K15 -> 1514.6 | E25: =IF(C25=0,0,D25/C25) -> 378.65 | F25: ='Service Economics'!R15 -> 1174.0483 | G25: ='Service Economics'!AB15 -> 1313.0483 | H25: =#REF!*F25+#REF!*G25-#REF! -> #REF! | I25: =IF(('Service Economics'!L15+#REF!*'Service Economics'!U15/(1+'Global Inputs'!$B$17))=0,0,H25/('Service Economics'!L15+#REF!*'Service Economics'!U15/(1+'Global Inputs'!$B$17))) -> #REF! | J25: =IF(C25=0,0,H25/C25) -> #REF! | K25: 2 | L25: 3 | M25: 4 | N25: 1 | O25: =IF(MAX($J$15:$J$44)=0,0,J25/MAX($J$15:$J$44)*100) -> #REF! | P25: =(IF(MAX($J$15:$J$44)=0,0,J25/MAX($J$15:$J$44))*0.45+K25/5*0.2+(6-L25)/5*0.15+(6-M25)/5*0.1+N25/1.5*0.1)*100 -> #REF! | Q25: =IF(H25<=0,"REVIEW — Economics need improvement",IF(AND(J25>=AVERAGE($J$15:$J$44)*1.15,K25>=4,L25<=3),"CORE — Push aggressively",IF(J25>=AVERAGE($J$15:$J$44),"GROW — Attractive economics",IF(K25>=4,"STRATEGIC — Important but lower margin","REVIEW — Economics need improvement")))) -> #REF! | R25: =#REF! -> #REF! | S25: =MAX(J25,0)^3*(0.5+K25/10)*(0.5+(6-L25)/10)*N25 -> #REF! | T25: =IF(SUM($S$15:$S$44)=0,R25,0.2*R25+0.8*S25/SUM($S$15:$S$44)) -> #REF! | U25: No | V25: ='Service Economics'!D15 -> 1.1 | W25: ='Service Economics'!E15 -> 0 | X25: =IF(U25="Yes",J25,0) -> 0 | Y25: =R25*C25*V25 -> #REF! | Z25: =R25*C25*'Service Economics'!F15 -> #REF! | AA25: =MAX(C25,$C$53)*'Global Inputs'!$B$5*V25+W25 -> 1315.6 | AB25: =MAX(C25,'Global Inputs'!$B$22)*'Global Inputs'!$B$5*V25*$C$54+W25 -> 1184.04 | AC25: =D25+#REF!*'Service Economics'!V15 -> #REF! | AD25: =T25*AC25 -> #REF! | AE25: =T25*H25 -> #REF! | AF25: =T25*C25 -> #REF! | AG25: ='Service Economics'!AL15 -> 759.84714 | AH25: ='Service Economics'!AN15 -> 898.84714 | AI25: ='Service Economics'!AP15 -> 189.96178 | AJ25: ='Service Economics'!AQ15 -> 2 | AK25: =#REF! -> #REF! | AL25: =IF(ISNUMBER(SEARCH("Future",'Service Economics'!AH15)),-1000000000,AG25*(1-#REF!)+AH25*#REF!) -> #REF! | AM25: =IF(ISNUMBER(SEARCH("Future",'Service Economics'!AH15)),-1000000000,AI25) -> 189.96178
A26: ='Service Economics'!A16 -> Post-Surgery Follow-up | B26: ='Service Economics'!B16 -> Procedure & Treatment | C26: ='Service Economics'!C16 -> 3 | D26: ='Service Economics'!K16 -> 1096 | E26: =IF(C26=0,0,D26/C26) -> 365.33333 | F26: ='Service Economics'!R16 -> 833.95356 | G26: ='Service Economics'!AB16 -> 972.95356 | H26: =#REF!*F26+#REF!*G26-#REF! -> #REF! | I26: =IF(('Service Economics'!L16+#REF!*'Service Economics'!U16/(1+'Global Inputs'!$B$17))=0,0,H26/('Service Economics'!L16+#REF!*'Service Economics'!U16/(1+'Global Inputs'!$B$17))) -> #REF! | J26: =IF(C26=0,0,H26/C26) -> #REF! | K26: 3 | L26: 3 | M26: 4 | N26: 1 | O26: =IF(MAX($J$15:$J$44)=0,0,J26/MAX($J$15:$J$44)*100) -> #REF! | P26: =(IF(MAX($J$15:$J$44)=0,0,J26/MAX($J$15:$J$44))*0.45+K26/5*0.2+(6-L26)/5*0.15+(6-M26)/5*0.1+N26/1.5*0.1)*100 -> #REF! | Q26: =IF(H26<=0,"REVIEW — Economics need improvement",IF(AND(J26>=AVERAGE($J$15:$J$44)*1.15,K26>=4,L26<=3),"CORE — Push aggressively",IF(J26>=AVERAGE($J$15:$J$44),"GROW — Attractive economics",IF(K26>=4,"STRATEGIC — Important but lower margin","REVIEW — Economics need improvement")))) -> #REF! | R26: =#REF! -> #REF! | S26: =MAX(J26,0)^3*(0.5+K26/10)*(0.5+(6-L26)/10)*N26 -> #REF! | T26: =IF(SUM($S$15:$S$44)=0,R26,0.2*R26+0.8*S26/SUM($S$15:$S$44)) -> #REF! | U26: Yes | V26: ='Service Economics'!D16 -> 1 | W26: ='Service Economics'!E16 -> 0 | X26: =IF(U26="Yes",J26,0) -> #REF! | Y26: =R26*C26*V26 -> #REF! | Z26: =R26*C26*'Service Economics'!F16 -> #REF! | AA26: =MAX(C26,$C$53)*'Global Inputs'!$B$5*V26+W26 -> 897 | AB26: =MAX(C26,'Global Inputs'!$B$22)*'Global Inputs'!$B$5*V26*$C$54+W26 -> 807.3 | AC26: =D26+#REF!*'Service Economics'!V16 -> #REF! | AD26: =T26*AC26 -> #REF! | AE26: =T26*H26 -> #REF! | AF26: =T26*C26 -> #REF! | AG26: ='Service Economics'!AL16 -> 523.30267 | AH26: ='Service Economics'!AN16 -> 662.30267 | AI26: ='Service Economics'!AP16 -> 174.43422 | AJ26: ='Service Economics'!AQ16 -> 3 | AK26: =#REF! -> #REF! | AL26: =IF(ISNUMBER(SEARCH("Future",'Service Economics'!AH16)),-1000000000,AG26*(1-#REF!)+AH26*#REF!) -> #REF! | AM26: =IF(ISNUMBER(SEARCH("Future",'Service Economics'!AH16)),-1000000000,AI26) -> 174.43422
... A44: ='Service Economics'!A34 -> Family Medical Update Concierge | B44: ='Service Economics'!B34 -> Continuing Care | C44: ='Service Economics'!C34 -> 3 | D44: ='Service Economics'!K34 -> 782.05 | E44: =IF(C44=0,0,D44/C44) -> 260.68333 | F44: ='Service Economics'!R34 -> 578.88249 | G44: ='Service Economics'!AB34 -> 717.88249 | H44: =#REF!*F44+#REF!*G44-#REF! -> #REF! | I44: =IF(('Service Economics'!L34+#REF!*'Service Economics'!U34/(1+'Global Inputs'!$B$17))=0,0,H44/('Service Economics'!L34+#REF!*'Service Economics'!U34/(1+'Global Inputs'!$B$17))) -> #REF! | J44: =IF(C44=0,0,H44/C44) -> #REF! | K44: 5 | L44: 1 | M44: 1 | N44: 1.2 | O44: =IF(MAX($J$15:$J$44)=0,0,J44/MAX($J$15:$J$44)*100) -> #REF! | P44: =(IF(MAX($J$15:$J$44)=0,0,J44/MAX($J$15:$J$44))*0.45+K44/5*0.2+(6-L44)/5*0.15+(6-M44)/5*0.1+N44/1.5*0.1)*100 -> #REF! | Q44: =IF(H44<=0,"REVIEW — Economics need improvement",IF(AND(J44>=AVERAGE($J$15:$J$44)*1.15,K44>=4,L44<=3),"CORE — Push aggressively",IF(J44>=AVERAGE($J$15:$J$44),"GROW — Attractive economics",IF(K44>=4,"STRATEGIC — Important but lower margin","REVIEW — Economics need improvement")))) -> #REF! | R44: =#REF! -> #REF! | S44: =MAX(J44,0)^3*(0.5+K44/10)*(0.5+(6-L44)/10)*N44 -> #REF! | T44: =IF(SUM($S$15:$S$44)=0,R44,0.2*R44+0.8*S44/SUM($S$15:$S$44)) -> #REF! | U44: Yes | V44: ='Service Economics'!D34 -> 0.65 | W44: ='Service Economics'!E34 -> 0 | X44: =IF(U44="Yes",J44,0) -> #REF! | Y44: =R44*C44*V44 -> #REF! | Z44: =R44*C44*'Service Economics'!F34 -> #REF! | AA44: =MAX(C44,$C$53)*'Global Inputs'!$B$5*V44+W44 -> 583.05 | AB44: =MAX(C44,'Global Inputs'!$B$22)*'Global Inputs'!$B$5*V44*$C$54+W44 -> 524.745 | AC44: =D44+#REF!*'Service Economics'!V34 -> #REF! | AD44: =T44*AC44 -> #REF! | AE44: =T44*H44 -> #REF! | AF44: =T44*C44 -> #REF! | AG44: ='Service Economics'!AL34 -> 268.2316 | AH44: ='Service Economics'!AN34 -> 407.2316 | AI44: ='Service Economics'!AP34 -> 89.410533 | AJ44: ='Service Economics'!AQ34 -> 5 | AK44: =#REF! -> #REF! | AL44: =IF(ISNUMBER(SEARCH("Future",'Service Economics'!AH34)),-1000000000,AG44*(1-#REF!)+AH44*#REF!) -> #REF! | AM44: =IF(ISNUMBER(SEARCH("Future",'Service Economics'!AH34)),-1000000000,AI44) -> 89.410533
A49: Profit Optimization Levers — One-Variable Sensitivity (All Else Equal)
A50: Lever | B50: Current Value | C50: Test Value | D50: Monthly Revenue | E50: Contribution | F50: Operating Profit | G50: Profit / Angel | H50: Break-even Journeys | I50: Δ Operating Profit
A51: Base price / hour | B51: ='Global Inputs'!$B$5 -> 299 | C51: 499 | D51: =#REF!+#REF!*(SUM($Y$15:$Y$44)*(C51-B51)) -> #REF! | E51: =#REF!+#REF!*((SUM($Y$15:$Y$44)*(C51-B51))/(1+'Global Inputs'!$B$7)*(1-'NC Credits'!$B$15)-(SUM($Y$15:$Y$44)*(C51-B51))*'Global Inputs'!$B$8) -> #REF! | F51: =#REF!+#REF!*((SUM($Y$15:$Y$44)*(C51-B51))/(1+'Global Inputs'!$B$7)*(1-'NC Credits'!$B$15)-(SUM($Y$15:$Y$44)*(C51-B51))*'Global Inputs'!$B$8) -> #REF! | G51: =IF(#REF!=0,0,F51/#REF!) -> #REF! | H51: =IF(E51/#REF!<=0,0,#REF!/(E51/#REF!)) -> #REF! | I51: =F51-#REF! -> #REF!
A52: Angel cost / hour | B52: ='Global Inputs'!$B$6 -> 0 | C52: 160 | D52: =#REF! -> #REF! | E52: =#REF!-#REF!*(SUM($Z$15:$Z$44)*(C52-B52)) -> #REF! | F52: =#REF!-#REF!*(SUM($Z$15:$Z$44)*(C52-B52)) -> #REF! | G52: =IF(#REF!=0,0,F52/#REF!) -> #REF! | H52: =IF(E52/#REF!<=0,0,#REF!/(E52/#REF!)) -> #REF! | I52: =F52-#REF! -> #REF!
A53: Minimum booking hours | B53: ='Global Inputs'!$B$22 -> 2 | C53: 3 | D53: =#REF!+#REF!*(SUMPRODUCT($R$15:$R$44,$AA$15:$AA$44-$D$15:$D$44)) -> #REF! | E53: =#REF!+#REF!*((SUMPRODUCT($R$15:$R$44,$AA$15:$AA$44-$D$15:$D$44))/(1+'Global Inputs'!$B$7)*(1-'NC Credits'!$B$15)-(SUMPRODUCT($R$15:$R$44,$AA$15:$AA$44-$D$15:$D$44))*'Global Inputs'!$B$8) -> #REF! | F53: =#REF!+#REF!*((SUMPRODUCT($R$15:$R$44,$AA$15:$AA$44-$D$15:$D$44))/(1+'Global Inputs'!$B$7)*(1-'NC Credits'!$B$15)-(SUMPRODUCT($R$15:$R$44,$AA$15:$AA$44-$D$15:$D$44))*'Global Inputs'!$B$8) -> #REF! | G53: =IF(#REF!=0,0,F53/#REF!) -> #REF! | H53: =IF(E53/#REF!<=0,0,#REF!/(E53/#REF!)) -> #REF! | I53: =F53-#REF! -> #REF!
A54: Portfolio multiplier factor | B54: 1 | C54: 0.9 | D54: =#REF!+#REF!*(SUMPRODUCT($R$15:$R$44,$AB$15:$AB$44-$D$15:$D$44)) -> #REF! | E54: =#REF!+#REF!*((SUMPRODUCT($R$15:$R$44,$AB$15:$AB$44-$D$15:$D$44))/(1+'Global Inputs'!$B$7)*(1-'NC Credits'!$B$15)-(SUMPRODUCT($R$15:$R$44,$AB$15:$AB$44-$D$15:$D$44))*'Global Inputs'!$B$8) -> #REF! | F54: =#REF!+#REF!*((SUMPRODUCT($R$15:$R$44,$AB$15:$AB$44-$D$15:$D$44))/(1+'Global Inputs'!$B$7)*(1-'NC Credits'!$B$15)-(SUMPRODUCT($R$15:$R$44,$AB$15:$AB$44-$D$15:$D$44))*'Global Inputs'!$B$8) -> #REF! | G54: =IF(#REF!=0,0,F54/#REF!) -> #REF! | H54: =IF(E54/#REF!<=0,0,#REF!/(E54/#REF!)) -> #REF! | I54: =F54-#REF! -> #REF!
A55: Transport coordination fee | B55: ='Global Inputs'!$B$16 -> 149 | C55: 199 | D55: =#REF!+#REF!*#REF!*(C55-B55) -> #REF! | E55: =#REF!+#REF!*(#REF!*((C55-B55)/(1+'Global Inputs'!$B$17)-(C55-B55)*'Global Inputs'!$B$8)) -> #REF! | F55: =#REF!+#REF!*(#REF!*((C55-B55)/(1+'Global Inputs'!$B$17)-(C55-B55)*'Global Inputs'!$B$8)) -> #REF! | G55: =IF(#REF!=0,0,F55/#REF!) -> #REF! | H55: =IF(E55/#REF!<=0,0,#REF!/(E55/#REF!)) -> #REF! | I55: =F55-#REF! -> #REF!
A56: Cab cost | B56: ='Global Inputs'!$B$15 -> 500 | C56: 450 | D56: =#REF!+#REF!*#REF!*(C56-B56) -> #REF! | E56: =#REF!+#REF!*(-#REF!*(C56-B56)*'Global Inputs'!$B$8) -> #REF! | F56: =#REF!+#REF!*(-#REF!*(C56-B56)*'Global Inputs'!$B$8) -> #REF! | G56: =IF(#REF!=0,0,F56/#REF!) -> #REF! | H56: =IF(E56/#REF!<=0,0,#REF!/(E56/#REF!)) -> #REF! | I56: =F56-#REF! -> #REF!
A57: Payment platform fee | B57: ='Global Inputs'!$B$8 -> 0 | C57: 0.015 | D57: =#REF! -> #REF! | E57: =#REF!-(#REF!*(C57-B57)) -> #REF! | F57: =#REF!-(#REF!*(C57-B57)) -> #REF! | G57: =IF(#REF!=0,0,F57/#REF!) -> #REF! | H57: =IF(E57/#REF!<=0,0,#REF!/(E57/#REF!)) -> #REF! | I57: =F57-#REF! -> #REF!
A58: Angel utilization | B58: =#REF! -> #REF! | C58: 0.75 | D58: =MIN(#REF!,#REF!*#REF!*#REF!*C58/#REF!,#REF!*#REF!*#REF!)*#REF! -> #REF! | E58: =MIN(#REF!,#REF!*#REF!*#REF!*C58/#REF!,#REF!*#REF!*#REF!)*#REF! -> #REF! | F58: =E58-#REF! -> #REF! | G58: =IF(#REF!=0,0,F58/#REF!) -> #REF! | H58: =IF(E58/#REF!<=0,0,#REF!/(E58/#REF!)) -> #REF! | I58: =F58-#REF! -> #REF!
A59: Service mix | B59: Current Mix | C59: Optimized Mix | D59: =MIN(#REF!,#REF!*#REF!*#REF!*#REF!/SUM($AF$15:$AF$44),#REF!*#REF!*#REF!)*SUM($AD$15:$AD$44) -> #REF! | E59: =MIN(#REF!,#REF!*#REF!*#REF!*#REF!/SUM($AF$15:$AF$44),#REF!*#REF!*#REF!)*SUM($AE$15:$AE$44) -> #REF! | F59: =E59-#REF! -> #REF! | G59: =IF(#REF!=0,0,F59/#REF!) -> #REF! | H59: =IF(E59/#REF!<=0,0,#REF!/(E59/#REF!)) -> #REF! | I59: =F59-#REF! -> #REF!
A60: Repeat booking rate | B60: =#REF! -> #REF! | C60: 0.4 | D60: =#REF! -> #REF! | E60: =#REF!+(#REF!*(C60-B60)*'Global Inputs'!$B$20) -> #REF! | F60: =#REF!+(#REF!*(C60-B60)*'Global Inputs'!$B$20) -> #REF! | G60: =IF(#REF!=0,0,F60/#REF!) -> #REF! | H60: =IF(E60/#REF!<=0,0,#REF!/(E60/#REF!)) -> #REF! | I60: =F60-#REF! -> #REF!
A61: Cancellation rate | B61: =#REF! -> #REF! | C61: 0.05 | D61: =MIN((#REF!*(1-C61)*(1-#REF!)),#REF!*#REF!*#REF!*#REF!/#REF!,#REF!*#REF!*#REF!)*#REF! -> #REF! | E61: =MIN((#REF!*(1-C61)*(1-#REF!)),#REF!*#REF!*#REF!*#REF!/#REF!,#REF!*#REF!*#REF!)*#REF! -> #REF! | F61: =E61-#REF! -> #REF! | G61: =IF(#REF!=0,0,F61/#REF!) -> #REF! | H61: =IF(E61/#REF!<=0,0,#REF!/(E61/#REF!)) -> #REF! | I61: =F61-#REF! -> #REF!
A62: Customer leads / day | B62: =#REF! -> #REF! | C62: 20 | D62: =MIN((C62*#REF!*#REF!*(1-#REF!)*(1-#REF!)),#REF!*#REF!*#REF!*#REF!/#REF!,#REF!*#REF!*#REF!)*#REF! -> #REF! | E62: =MIN((C62*#REF!*#REF!*(1-#REF!)*(1-#REF!)),#REF!*#REF!*#REF!*#REF!/#REF!,#REF!*#REF!*#REF!)*#REF! -> #REF! | F62: =E62-#REF! -> #REF! | G62: =F62/#REF! -> #REF! | H62: =#REF!/#REF! -> #REF! | I62: =F62-#REF! -> #REF!
A63: Fixed monthly cost | B63: =#REF! -> #REF! | C63: 150000 | D63: =#REF! -> #REF! | E63: =#REF! -> #REF! | F63: =E63-C63 -> #REF! | G63: =F63/#REF! -> #REF! | H63: =C63/#REF! -> #REF! | I63: =F63-#REF! -> #REF!
A67: Whitefield Portfolio — Current Mix vs Profit-Optimized Mix
A68: Metric | B68: Current / Default Mix | C68: Profit-Optimized Mix | D68: Improvement
A69: Weighted avg service hours | B69: =SUMPRODUCT($R$15:$R$44,$C$15:$C$44) -> #REF! | C69: =SUM($AF$15:$AF$44) -> #REF! | D69: =C69-B69 -> #REF!
A70: Monthly journeys | B70: =#REF! -> #REF! | C70: =MIN(#REF!,#REF!*#REF!*#REF!*#REF!/SUM($AF$15:$AF$44),#REF!*#REF!*#REF!) -> #REF! | D70: =C70-B70 -> #REF!
A71: Customer collections | B71: =#REF! -> #REF! | C71: =MIN(#REF!,#REF!*#REF!*#REF!*#REF!/SUM($AF$15:$AF$44),#REF!*#REF!*#REF!)*SUM($AD$15:$AD$44) -> #REF! | D71: =C71-B71 -> #REF!
A72: Monthly contribution | B72: =#REF! -> #REF! | C72: =MIN(#REF!,#REF!*#REF!*#REF!*#REF!/SUM($AF$15:$AF$44),#REF!*#REF!*#REF!)*SUM($AE$15:$AE$44) -> #REF! | D72: =C72-B72 -> #REF!
A73: Contribution / Angel hour | B73: =#REF! -> #REF! | C73: =IF(C70*C69=0,0,C72/(C70*C69)) -> #REF! | D73: =C73-B73 -> #REF!
A74: Monthly operating profit | B74: =#REF! -> #REF! | C74: =C72-#REF! -> #REF! | D74: =C74-B74 -> #REF!
A76: Profit Maximizer note: the optimized mix is intentionally weighted heavily toward contribution per Angel hour, while retaining 20% of the current portfolio mix so the model does not collapse into a single service. Founder judgement inputs remain editable.

Sheet Growth & Pricing Strategy
A1: NivrāaCare — Growth, Pricing & Profitability Strategy | Founder CFO Decision Engine
A2: Objective: optimize Price → Conversion → Customers → Repeat Usage → Monthly Journeys → Angel Utilization → Contribution → Fixed-Cost Coverage → EBITDA → Cash Runway. | AO2: Hourly Price | AP2: Monthly Profit | AR2: Hourly Price | AS2: Conversion | AU2: Journeys / Day | AV2: Monthly Profit | AX2: Angel Utilization | AY2: Monthly Profit
AO3: 249 | AP3: =H64 -> #REF! | AR3: 249 | AS3: =B64 -> 0.5 | AU3: 3 | AV3: =AU3*$B$7*$AB$11-$B$27 -> #REF! | AX3: 0.3 | AY3: =H95 -> #REF!
A4: FOUNDER INPUT / SELECTOR | B4: VALUE | C4: NOTE | E4: FOUNDER DASHBOARD — CURRENT SELECTED GROWTH STRATEGY | AA4: SELECTED PRICING HELPER | AB4: VALUE | AO4: 299 | AP4: =H65 -> #REF! | AR4: 299 | AS4: =B65 -> 0.45 | AU4: 5 | AV4: =AU4*$B$7*$AB$11-$B$27 -> #REF! | AX4: 0.4 | AY4: =H96 -> #REF!
A5: Target monthly operating profit | B5: 0 | C5: Select break-even through ₹1Cr/month | E5: Selected base hourly rate | F5: =$B$16 -> 299 | H5: TARGET-PROFIT REQUIREMENT | I5: VALUE | AA5: Avg care bill | AB5: =$B$17+MAX($B$11,$B$18)*$B$16+$B$20 -> #REF! | AO5: 349 | AP5: =H66 -> #REF! | AR5: 349 | AS5: =B66 -> 0.4 | AU5: 8 | AV5: =AU5*$B$7*$AB$11-$B$27 -> #REF! | AX5: 0.5 | AY5: =H97 -> #REF!
A6: Leads per day | B6: 10 | C6: Founder planning assumption | E6: Legacy extended-hour price (inactive) | F6: =$B$19 -> 269 | H6: Target operating profit | I6: =$B$5 -> 0 | AA6: Net care revenue | AB6: =AB5/(1+$B$23) -> #REF! | AO6: 399 | AP6: =H67 -> #REF! | AR6: 399 | AS6: =B67 -> 0.37 | AU6: 10 | AV6: =AU6*$B$7*$AB$11-$B$27 -> #REF! | AX6: 0.6 | AY6: =H98 -> #REF!
A7: Operating days / month | B7: 26 | C7: Whitefield operating assumption | E7: Minimum booking hours | F7: =$B$18 -> 2 | H7: Required monthly contribution | I7: =$B$27+$B$5 -> #REF! | AA7: Angel cost / journey | AB7: =$B$11*$B$21 -> #REF! | AO7: 449 | AP7: =H68 -> #REF! | AR7: 449 | AS7: =B68 -> 0.35 | AU7: 12 | AV7: =AU7*$B$7*$AB$11-$B$27 -> #REF! | AX7: 0.7 | AY7: =H99 -> #REF!
A8: Active Angels | B8: 5 | C8: Current planning assumption | E8: Journey / coordination fee | F8: =$B$17 -> 199 | H8: Required journeys / month | I8: =IF($AB$11<=0,0,I7/$AB$11) -> #REF! | AA8: Other variable cost / journey | AB8: =$B$22+AB5*$B$24+AB6*'NC Credits'!$B$15 -> #REF! | AU8: 15 | AV8: =AU8*$B$7*$AB$11-$B$27 -> #REF! | AX8: 0.8 | AY8: =H100 -> #REF!
A9: Working hours / Angel / day | B9: 8 | C9: Capacity assumption | E9: Average customer bill | F9: =$AB$23 -> #REF! | H9: Required journeys / day | I9: =I8/$B$7 -> #REF! | AA9: Care contribution / journey | AB9: =AB6-AB7-AB8 -> #REF! | AU9: 20 | AV9: =AU9*$B$7*$AB$11-$B$27 -> #REF! | AX9: 0.9 | AY9: =H101 -> #REF!
A10: Target Angel utilization | B10: 0.65 | C10: Productive service + required journey capacity | E10: Contribution / journey | F10: =$AB$11 -> #REF! | H10: Required Angels | I10: =I8*$B$11/($B$7*$B$9*$B$10) -> #REF! | AA10: Blended transport contribution | AB10: =$B$25*$B$26 -> 83.4
A11: Average actual journey duration | B11: =#REF! -> #REF! | C11: Linked to current Whitefield service mix | E11: Contribution / Angel hour | F11: =$AB$12 -> #REF! | H11: Required leads / day | I11: =IF($AB$13*$B$14*(1-$B$12)*(1-$B$13)=0,0,I8/($B$7*$AB$13*$B$14*(1-$B$12)*(1-$B$13))) -> #REF! | AA11: Total blended contribution / journey | AB11: =AB9+AB10 -> #REF!
A12: Cancellation rate | B12: 0.08 | C12: Founder planning assumption | E12: True CAC | F12: =$AB$22 -> 300 | H12: Sustainable fixed-cost ceiling | I12: =$AB$18-$B$5 -> #REF! | AA12: Contribution / Angel hour | AB12: =IF($B$11=0,0,AB11/$B$11) -> #REF! | AO12: Monthly Fixed Cost | AP12: Monthly Profit | AR12: Lifetime Journeys | AS12: Safe CAC | AT12: Cumulative Contribution | AU12: Recurring Service | AV12: Monthly Revenue | AX12: Service | AY12: Contribution / Journey
A13: No-show / refund rate | B13: 0.03 | C13: Founder planning assumption | E13: Repeat journey share | F13: =$B$15 -> 0.3 | H13: Profit gap at current selected pricing | I13: =MAX($B$5-$AB$19,0) -> #REF! | AA13: Current selected conversion | AB13: =INDEX($B$64:$B$68,MATCH($B$16,$A$64:$A$68,0)) -> 0.45 | AO13: 68000 | AP13: =$AB$18-AO13 -> #REF! | AR13: 1 | AS13: =D125 -> #REF! | AT13: =B125 -> #REF! | AU13: Dialysis Visit Concierge | AV13: =H144 -> 23416 | AX13: =A177 -> Hospital Visit | AY13: =E177 -> 1111.5309
A14: Average journeys / customer / month | B14: 1.3 | C14: Includes repeat behavior; editable | E14: Angel utilization | F14: =IF($B$8*$B$7*$B$9=0,0,$AB$16*$B$11/($B$8*$B$7*$B$9)) -> #REF! | AA14: Demand journeys / month | AB14: =$B$6*$B$7*AB13*$B$14*(1-$B$12)*(1-$B$13) -> 135.73404 | AO14: 100000 | AP14: =$AB$18-AO14 -> #REF! | AR14: 2 | AS14: =D126 -> #REF! | AT14: =B126 -> #REF! | AU14: Chemotherapy Visit Concierge | AV14: =H145 -> 7492 | AX14: =A178 -> Hospital Visit — Concierge at Hospital | AY14: =E178 -> 752.09968
A15: Repeat journey share | B15: 0.3 | C15: Founder planning assumption | E15: Journeys / day | F15: =$AB$17 -> #REF! | AA15: Capacity journeys / month | AB15: =$B$8*$B$7*$B$9*$B$10/$B$11 -> #REF! | AO15: 140000 | AP15: =$AB$18-AO15 -> #REF! | AR15: 4 | AS15: =D127 -> #REF! | AT15: =B127 -> #REF! | AU15: Radiation Therapy Concierge | AV15: =H146 -> 10226.5 | AX15: =A179 -> Clinic Visit | AY15: =E179 -> 625.84376
A16: Selected base hourly rate | B16: ='MVP1 Pricing & SKU'!$B$7 -> 299 | C16: MVP-1 first 4 hours; central pricing input | E16: Selected fixed cost | F16: =$B$27 -> #REF! | AA16: Completed journeys / month | AB16: =MIN(AB14,AB15) -> #REF! | AO16: 180000 | AP16: =$AB$18-AO16 -> #REF! | AR16: 8 | AS16: =D128 -> #REF! | AT16: =B128 -> #REF! | AU16: Physiotherapy / Rehab Visit | AV16: =H147 -> 8487.6 | AX16: =A180 -> Diagnostic Center Visit | AY16: =E180 -> 787.31972
A17: Journey / coordination fee | B17: ='MVP1 Pricing & SKU'!$B$9 -> 199 | C17: Care journey activation / coordination fee | E17: Monthly contribution | F17: =$AB$18 -> #REF! | AA17: Completed journeys / day | AB17: =AB16/$B$7 -> #REF! | AO17: 200000 | AP17: =$AB$18-AO17 -> #REF! | AR17: 12 | AS17: =D129 -> #REF! | AT17: =B129 -> #REF! | AU17: Chronic Care Follow-up | AV17: =H148 -> 2937.9 | AX17: =A181 -> Health Check-up Concierge | AY17: =E181 -> 1215.9317
A18: Minimum billable hours | B18: ='MVP1 Pricing & SKU'!$B$5 -> 2 | C18: Customer billing minimum | E18: Monthly operating profit | F18: =$AB$19 -> #REF! | AA18: Monthly contribution | AB18: =AB16*AB11 -> #REF! | AO18: 240000 | AP18: =$AB$18-AO18 -> #REF! | AU18: NRI Parent Medical Concierge | AV18: =H149 -> 9373.2 | AX18: =A182 -> Hospital Admission Concierge | AY18: =E182 -> 1249.9737
A19: Legacy extended-hour price (inactive) | B19: ='MVP1 Pricing & SKU'!$B$8 -> 269 | C19: Legacy reference only; not used in active pricing. | E19: Break-even journeys / day | F19: =$AB$21 -> #REF! | AA19: Monthly operating profit | AB19: =AB18-$B$27 -> #REF! | AO19: 300000 | AP19: =$AB$18-AO19 -> #REF! | AU19: Post-Surgery Follow-up | AV19: =H150 -> 2132 | AX19: =A183 -> Hospital Discharge Concierge | AY19: =E183 -> 1203.8261
A20: Average service premium | B20: 0 | C20: Urgent / overnight / premium mix allowance | E20: Cash runway | F20: =IF(COUNTIF($H$287:$H$298,"CASH OUT")=0,">12 months",MATCH("CASH OUT",$H$287:$H$298,0)-1) -> >12 months | AA20: Break-even journeys / month | AB20: =IF(AB11<=0,0,$B$27/AB11) -> #REF! | AX20: =A184 -> Overnight Hospital Concierge | AY20: =E184 -> 2702.1605
A21: Angel payout / service hour | B21: ='Global Inputs'!$B$6 -> 0 | C21: Linked to current Global Inputs | E21: Profitability status | F21: =IF($AB$11<=0,"RED — economics unsustainable",IF($AB$19>=0,"GREEN — profitable and scalable","AMBER — contribution positive but insufficient scale")) -> #REF! | AA21: Break-even journeys / day | AB21: =AB20/$B$7 -> #REF! | AX21: =A185 -> Multi-Day Hospital Concierge (per 12h shift) | AY21: =E185 -> 2702.1605
A22: Per-journey non-Angel variable cost | B22: =SUM('Global Inputs'!$B$10:$B$14) -> 56.5 | C22: Ops + risk + comms + BGV/training + recovery reserve | E22: Recommended operating model | F22: =IF($AB$16<=50,"Ultra-Lean Pilot",IF($AB$16<=150,"Lean MVP","Scale / Full Team")) -> #REF! | AA22: True CAC | AB22: =$B$28+$B$29+$B$30+$B$120+$B$121 -> 300 | AO22: Service | AP22: Contribution / Angel Hr | AR22: Month | AS22: Ending Cash | AU22: Month | AV22: Monthly Journeys | AX22: =A186 -> Day Surgery / Procedure Concierge | AY22: =E186 -> 1820.6439
A23: GST on care service | B23: ='Global Inputs'!$B$7 -> 0.18 | C23: Illustrative; confirm with CA | E23: NivrāaCredit earn rate | F23: ='NC Credits'!$B$6 -> 0.05 | AA23: Average total customer outflow | AB23: =AB5+$B$25*('Global Inputs'!$B$15+'Global Inputs'!$B$16) -> #REF! | AO23: =A177 -> Hospital Visit | AP23: =G177 -> 277.88273 | AR23: Month 1 | AS23: =G287 -> #REF! | AU23: Month 1 | AV23: =B287 -> #REF! | AX23: =A187 -> Pre-Surgery Concierge | AY23: =E187 -> 1203.8261
A24: Payment platform fee | B24: ='Global Inputs'!$B$8 -> 0 | C24: Current gateway assumption | E24: Expected NC cost / journey | F24: ='NC Credits'!$B$23 -> #REF! | AA24: Angels required for demand | AB24: =AB16*$B$11/($B$7*$B$9*$B$10) -> #REF! | AO24: =A178 -> Hospital Visit — Concierge at Hospital | AP24: =G178 -> 250.69989 | AR24: Month 2 | AS24: =G288 -> #REF! | AU24: Month 2 | AV24: =B288 -> #REF! | AX24: =A188 -> Post-Surgery Follow-up | AY24: =E188 -> 892.97983
A25: Case 2 transport mix | B25: 0.6 | C25: % of journeys where NivrāaCare coordinates transport | E25: Monthly expected NC cost | F25: ='NC Credits'!$B$26 -> #REF! | AA25: Excess Angel equivalents | AB25: =MAX($B$8-AB24,0) -> #REF! | AO25: =A179 -> Clinic Visit | AP25: =G179 -> 312.92188 | AR25: Month 3 | AS25: =G289 -> #REF! | AU25: Month 3 | AV25: =B289 -> #REF!
A26: Transport contribution / Case 2 journey | B26: ='Global Inputs'!$B$16/(1+'Global Inputs'!$B$17)-('Global Inputs'!$B$15+'Global Inputs'!$B$16)*'Global Inputs'!$B$8-'Global Inputs'!$B$18 -> 139 | C26: Derived from current transport assumptions | E26: NC face value issued / month | F26: ='NC Credits'!$B$27 -> #REF! | AO26: =A180 -> Diagnostic Center Visit | AP26: =G180 -> 262.43991 | AR26: Month 4 | AS26: =G290 -> #REF! | AU26: Month 4 | AV26: =B290 -> #REF!
A27: Selected monthly fixed cost | B27: =#REF! -> #REF! | C27: Lean MVP fixed cost incl. payroll Angel salaries | E27: Legacy 4-hour threshold | F27: =$B$36 -> 4 | AO27: =A181 -> Health Check-up Concierge | AP27: =G181 -> 243.18635 | AR27: Month 5 | AS27: =G291 -> #REF! | AU27: Month 5 | AV27: =B291 -> #REF! | AX27: Operating Model | AY27: Break-even Journeys / Day
A28: Paid marketing CAC | B28: 300 | C28: Planning assumption per new family | AO28: =A182 -> Hospital Admission Concierge | AP28: =G182 -> 312.49343 | AR28: Month 6 | AS28: =G292 -> #REF! | AU28: Month 6 | AV28: =B292 -> #REF! | AX28: Ultra-Lean Pilot | AY28: =E107 -> #REF!
A29: First-journey subsidy / discount | B29: 0 | C29: Treat as CAC | AO29: =A183 -> Hospital Discharge Concierge | AP29: =G183 -> 300.95653 | AR29: Month 7 | AS29: =G293 -> #REF! | AU29: Month 7 | AV29: =B293 -> #REF! | AX29: Lean MVP | AY29: =E108 -> #REF!
A30: Referral reward | B30: 0 | C30: Treat as CAC | AO30: =A184 -> Overnight Hospital Concierge | AP30: =G184 -> 225.18004 | AR30: Month 8 | AS30: =G294 -> #REF! | AU30: Month 8 | AV30: =B294 -> #REF! | AX30: Scale / Full Team | AY30: =E109 -> #REF!
A31: Safe CAC as % of expected LTV | B31: 0.3 | C31: Founder risk-control assumption | AO31: =A185 -> Multi-Day Hospital Concierge (per 12h shift) | AP31: =G185 -> 225.18004 | AR31: Month 9 | AS31: =G295 -> #REF! | AU31: Month 9 | AV31: =B295 -> #REF!
A32: Opening cash available | B32: 1000000 | C32: Runway input | AO32: =A186 -> Day Surgery / Procedure Concierge | AP32: =G186 -> 303.44066 | AR32: Month 10 | AS32: =G296 -> #REF! | AU32: Month 10 | AV32: =B296 -> #REF!
A33: Additional founder capital | B33: 500000 | C33: Runway input | AO33: =A187 -> Pre-Surgery Concierge | AP33: =G187 -> 300.95653 | AR33: Month 11 | AS33: =G297 -> #REF! | AU33: Month 11 | AV33: =B297 -> #REF!
A34: One-time launch / setup costs | B34: 200000 | C34: Runway input | AO34: =A188 -> Post-Surgery Follow-up | AP34: =G188 -> 297.65994 | AR34: Month 12 | AS34: =G298 -> #REF! | AU34: Month 12 | AV34: =B298 -> #REF!
A35: Monthly journey growth | B35: 0.12 | C35: Runway assumption
A36: Legacy 4-hour threshold | B36: ='MVP1 Pricing & SKU'!$B$6 -> 4 | C36: Reference threshold only; all hours use the same base hourly rate × service multiplier.
A38: 1–2. MVP-1 Base Hourly Pricing + Duration Economics
A39: Actual Journey Duration (hrs) | B39: Customer Care Bill | C39: Net Care Revenue | D39: Angel Cost | E39: Other Variable Cost | F39: Blended Contribution | G39: Contribution % | H39: Contribution / Angel Hour | J39: TRUE COST / PRICE FLOOR | K39: VALUE
A40: 2 | B40: =$B$17+MAX(A40,$B$18)*$B$16+$B$20 -> 797 | C40: =B40/(1+$B$23) -> 675.42373 | D40: =A40*$B$21 -> 0 | E40: 84.395 | F40: =C40-D40-E40+$B$25*$B$26 -> 674.42873 | G40: 0.88180937 | H40: =IF(A40=0,0,F40/A40) -> 337.21436 | J40: First-hour delivery cost | K40: =$B$21+$B$22+($B$17+$B$16)*$B$24+(($B$17+$B$16)/(1+$B$23))*'NC Credits'!$B$15 -> 73.93
A41: 3 | B41: =$B$17+MAX(A41,$B$18)*$B$16+$B$20 -> 1096 | C41: =B41/(1+$B$23) -> 928.81356 | D41: =A41*$B$21 -> 0 | E41: 94.86 | F41: =C41-D41-E41+$B$25*$B$26 -> 917.35356 | G41: 0.90094416 | H41: =IF(A41=0,0,F41/A41) -> 305.78452 | J41: Incremental additional-hour delivery cost | K41: =$B$21+$B$19*$B$24+($B$19/(1+$B$23))*'NC Credits'!$B$15 -> 9.415
A42: 4 | B42: =$B$17+MAX(A42,$B$18)*$B$16+$B$20 -> 1395 | C42: =B42/(1+$B$23) -> 1182.2034 | D42: =A42*$B$21 -> 0 | E42: 105.325 | F42: =C42-D42-E42+$B$25*$B$26 -> 1160.2784 | G42: 0.91245305 | H42: =IF(A42=0,0,F42/A42) -> 290.0696 | J42: Avg delivery cost / hour at selected duration | K42: =IF($B$11=0,0,($B$11*$B$21+$B$22+$AB$5*$B$24+$AB$6*'NC Credits'!$B$15)/$B$11) -> #REF!
A43: 5 | B43: =$B$17+MAX(A43,$B$18)*$B$16+$B$20 -> 1694 | C43: =B43/(1+$B$23) -> 1435.5932 | D43: =A43*$B$21 -> 0 | E43: 115.79 | F43: =C43-D43-E43+$B$25*$B$26 -> 1403.2032 | G43: 0.92013735 | H43: =IF(A43=0,0,F43/A43) -> 280.64064 | J43: Absolute customer price floor / hr (no contribution) | K43: =IF($B$11=0,0,(($B$11*$B$21+$B$22+$AB$5*$B$24+$AB$6*'NC Credits'!$B$15)-$B$17*(1/(1+$B$23)-$B$24-'NC Credits'!$B$15/(1+$B$23)))/((1/(1+$B$23)-$B$24-'NC Credits'!$B$15/(1+$B$23))*$B$11)) -> #REF!
A44: 6 | B44: =$B$17+MAX(A44,$B$18)*$B$16+$B$20 -> 1993 | C44: =B44/(1+$B$23) -> 1688.9831 | D44: =A44*$B$21 -> 0 | E44: 126.255 | F44: =C44-D44-E44+$B$25*$B$26 -> 1646.1281 | G44: 0.92563188 | H44: =IF(A44=0,0,F44/A44) -> 274.35468 | J44: Recommended safe contribution / Angel hr | K44: 150
A45: 7 | B45: =$B$17+MAX(A45,$B$18)*$B$16+$B$20 -> 2292 | C45: =B45/(1+$B$23) -> 1942.3729 | D45: =A45*$B$21 -> 0 | E45: 136.72 | F45: =C45-D45-E45+$B$25*$B$26 -> 1889.0529 | G45: 0.92975593 | H45: =IF(A45=0,0,F45/A45) -> 269.8647 | J45: Sustainable hourly price at safe contribution | K45: =IF($B$11=0,0,(($B$11*$B$21+$B$22+$K$44*$B$11-$B$25*$B$26)-$B$17*(1/(1+$B$23)-$B$24-'NC Credits'!$B$15/(1+$B$23)))/((1/(1+$B$23)-$B$24-'NC Credits'!$B$15/(1+$B$23))*$B$11)) -> #REF!
A46: 8 | B46: =$B$17+MAX(A46,$B$18)*$B$16+$B$20 -> 2591 | C46: =B46/(1+$B$23) -> 2195.7627 | D46: =A46*$B$21 -> 0 | E46: 147.185 | F46: =C46-D46-E46+$B$25*$B$26 -> 2131.9777 | G46: 0.93296539 | H46: =IF(A46=0,0,F46/A46) -> 266.49721 | J46: Minimum economically viable duration | K46: =IFERROR(INDEX($A$40:$A$48,MATCH(TRUE,$F$40:$F$48>0,0)),">12 hrs") -> >12 hrs
A47: 10 | B47: =$B$17+MAX(A47,$B$18)*$B$16+$B$20 -> 3189 | C47: =B47/(1+$B$23) -> 2702.5424 | D47: =A47*$B$21 -> 0 | E47: 168.115 | F47: =C47-D47-E47+$B$25*$B$26 -> 2617.8274 | G47: 0.93763661 | H47: =IF(A47=0,0,F47/A47) -> 261.78274
A48: 12 | B48: =$B$17+MAX(A48,$B$18)*$B$16+$B$20 -> 3787 | C48: =B48/(1+$B$23) -> 3209.322 | D48: =A48*$B$21 -> 0 | E48: 189.045 | F48: =C48-D48-E48+$B$25*$B$26 -> 3103.677 | G48: 0.94087256 | H48: =IF(A48=0,0,F48/A48) -> 258.63975
A51: 3. MVP-1 Pricing Comparison — Planning Sensitivity
A52: Scenario | B52: Base Hourly Rate | C52: Additional-Hour Base Rate | D52: Journey Fee | E52: Conversion Assumption | F52: Avg Customer Care Bill | G52: Contribution / Journey | H52: Contribution / Angel Hr | I52: Break-even Journeys / Month | J52: Break-even / Day | K52: Expected Monthly Profit / (Loss) | L52: MVP1 SELECTED SUMMARY | M52: VALUE
A53: ₹249 all hours | B53: 249 | C53: 249 | D53: =C53+$B$18*B53+MAX($B$11-$B$18,0)*B53+$B$20 -> #REF! | E53: 1163.837 | F53: =$D53+MAX($B$11,$B$18)*$B53+$B$20 -> #REF! | G53: 2098.472 | H53: =IF($B$11=0,0,G53/$B$11) -> #REF! | I53: =IF(G53<=0,0,$B$27/G53) -> #REF! | J53: =IF($B$7=0,0,I53/$B$7) -> #REF! | K53: =MIN($B$6*$B$7*E53*$B$14*(1-$B$12)*(1-$B$13),$B$8*$B$7*$B$9*$B$10/$B$11)*G53-$B$27 -> #REF! | L53: Base hourly rate | M53: =$B$16 -> 299
A54: ₹299 all hours — CURRENT | B54: 299 | C54: 299 | D54: =C54+$B$18*B54+MAX($B$11-$B$18,0)*B54+$B$20 -> #REF! | E54: 0.45 | F54: =$D54+MAX($B$11,$B$18)*$B54+$B$20 -> #REF! | G54: 1310.8918 | H54: =IF($B$11=0,0,G54/$B$11) -> #REF! | I54: =IF(G54<=0,0,$B$27/G54) -> #REF! | J54: =IF($B$7=0,0,I54/$B$7) -> #REF! | K54: =MIN($B$6*$B$7*E54*$B$14*(1-$B$12)*(1-$B$13),$B$8*$B$7*$B$9*$B$10/$B$11)*G54-$B$27 -> #REF! | L54: Base hourly rate — all hours | M54: =$B$16 -> 299
A55: ₹349 all hours | B55: 349 | C55: 349 | D55: =C55+$B$18*B55+MAX($B$11-$B$18,0)*B55+$B$20 -> #REF! | E55: 0.4 | F55: =$D55+MAX($B$11,$B$18)*$B55+$B$20 -> #REF! | G55: 1498.5695 | H55: =IF($B$11=0,0,G55/$B$11) -> #REF! | I55: =IF(G55<=0,0,$B$27/G55) -> #REF! | J55: =IF($B$7=0,0,I55/$B$7) -> #REF! | K55: =MIN($B$6*$B$7*E55*$B$14*(1-$B$12)*(1-$B$13),$B$8*$B$7*$B$9*$B$10/$B$11)*G55-$B$27 -> #REF! | L55: Journey fee | M55: =$B$17 -> 199
A56: ₹399 all hours | B56: 399 | C56: 399 | D56: =C56+$B$18*B56+MAX($B$11-$B$18,0)*B56+$B$20 -> #REF! | E56: 0.37 | F56: =$D56+MAX($B$11,$B$18)*$B56+$B$20 -> #REF! | G56: 1686.2472 | H56: =IF($B$11=0,0,G56/$B$11) -> #REF! | I56: =IF(G56<=0,0,$B$27/G56) -> #REF! | J56: =IF($B$7=0,0,I56/$B$7) -> #REF! | K56: =MIN($B$6*$B$7*E56*$B$14*(1-$B$12)*(1-$B$13),$B$8*$B$7*$B$9*$B$10/$B$11)*G56-$B$27 -> #REF! | L56: Legacy 4-hour threshold | M56: =$B$36 -> 4
A57: ₹449 all hours | B57: 449 | C57: 449 | D57: =C57+$B$18*B57+MAX($B$11-$B$18,0)*B57+$B$20 -> #REF! | E57: 0.35 | F57: =$D57+MAX($B$11,$B$18)*$B57+$B$20 -> #REF! | G57: 1873.9249 | H57: =IF($B$11=0,0,G57/$B$11) -> #REF! | I57: =IF(G57<=0,0,$B$27/G57) -> #REF! | J57: =IF($B$7=0,0,I57/$B$7) -> #REF! | K57: =MIN($B$6*$B$7*E57*$B$14*(1-$B$12)*(1-$B$13),$B$8*$B$7*$B$9*$B$10/$B$11)*G57-$B$27 -> #REF! | L57: Contribution / journey | M57: =$AB$11 -> #REF!
D58: =C58+$B$18*B58+MAX($B$11-$B$18,0)*B58+$B$20 -> #REF! | F58: =$D58+MAX($B$11,$B$18)*$B58+$B$20 -> #REF! | H58: =IF($B$11=0,0,G58/$B$11) -> #REF! | I58: =IF(G58<=0,0,$B$27/G58) -> 0 | J58: =IF($B$7=0,0,I58/$B$7) -> 0
D59: =C59+$B$18*B59+MAX($B$11-$B$18,0)*B59+$B$20 -> #REF! | F59: =$D59+MAX($B$11,$B$18)*$B59+$B$20 -> #REF! | H59: =IF($B$11=0,0,G59/$B$11) -> #REF! | I59: =IF(G59<=0,0,$B$27/G59) -> 0 | J59: =IF($B$7=0,0,I59/$B$7) -> 0
A62: 4. Price vs Conversion — Base Hourly Rate Sensitivity
A63: Hourly Rate | B63: Conversion Assumption | C63: Demand Journeys | D63: Capacity Journeys | E63: Completed Journeys | F63: Contribution / Journey | G63: Monthly Contribution | H63: Operating Profit | I63: Profit Rank | K63: PRICE DECISION | L63: VALUE | M63: INTERPRETATION
A64: 249 | B64: 0.5 | C64: =$B$6*$B$7*B64*$B$14*(1-$B$12)*(1-$B$13) -> 150.8156 | D64: =$AB$15 -> #REF! | E64: =MIN(C64,D64) -> #REF! | F64: =($B$17+MAX($B$11,$B$18)*A64+$B$20)/(1+$B$23)-$B$11*$B$21-($B$22+($B$17+MAX($B$11,$B$18)*A64+$B$20)*$B$24+(($B$17+MAX($B$11,$B$18)*A64+$B$20)/(1+$B$23))*'NC Credits'!$B$15)+$B$25*$B$26 -> #REF! | G64: =E64*F64 -> #REF! | H64: =G64-$B$27 -> #REF! | I64: =RANK(H64,$H$64:$H$68,0) -> #REF! | K64: MVP1 selected base hourly rate | L64: =$B$16 -> 299
A65: 299 | B65: 0.45 | C65: =$B$6*$B$7*B65*$B$14*(1-$B$12)*(1-$B$13) -> 135.73404 | D65: =$AB$15 -> #REF! | E65: =MIN(C65,D65) -> #REF! | F65: =($B$17+MAX($B$11,$B$18)*A65+$B$20)/(1+$B$23)-$B$11*$B$21-($B$22+($B$17+MAX($B$11,$B$18)*A65+$B$20)*$B$24+(($B$17+MAX($B$11,$B$18)*A65+$B$20)/(1+$B$23))*'NC Credits'!$B$15)+$B$25*$B$26 -> #REF! | G65: =E65*F65 -> #REF! | H65: =G65-$B$27 -> #REF! | I65: =RANK(H65,$H$64:$H$68,0) -> #REF! | K65: MVP1 additional-hour base rate | L65: =$B$16 -> 299
A66: 349 | B66: 0.4 | C66: =$B$6*$B$7*B66*$B$14*(1-$B$12)*(1-$B$13) -> 120.65248 | D66: =$AB$15 -> #REF! | E66: =MIN(C66,D66) -> #REF! | F66: =($B$17+MAX($B$11,$B$18)*A66+$B$20)/(1+$B$23)-$B$11*$B$21-($B$22+($B$17+MAX($B$11,$B$18)*A66+$B$20)*$B$24+(($B$17+MAX($B$11,$B$18)*A66+$B$20)/(1+$B$23))*'NC Credits'!$B$15)+$B$25*$B$26 -> #REF! | G66: =E66*F66 -> #REF! | H66: =G66-$B$27 -> #REF! | I66: =RANK(H66,$H$64:$H$68,0) -> #REF! | K66: MVP1 journey fee | L66: =$B$17 -> 199
A67: 399 | B67: 0.37 | C67: =$B$6*$B$7*B67*$B$14*(1-$B$12)*(1-$B$13) -> 111.60354 | D67: =$AB$15 -> #REF! | E67: =MIN(C67,D67) -> #REF! | F67: =($B$17+MAX($B$11,$B$18)*A67+$B$20)/(1+$B$23)-$B$11*$B$21-($B$22+($B$17+MAX($B$11,$B$18)*A67+$B$20)*$B$24+(($B$17+MAX($B$11,$B$18)*A67+$B$20)/(1+$B$23))*'NC Credits'!$B$15)+$B$25*$B$26 -> #REF! | G67: =E67*F67 -> #REF! | H67: =G67-$B$27 -> #REF! | I67: =RANK(H67,$H$64:$H$68,0) -> #REF! | K67: Modeled best base hourly rate under current assumptions | L67: =INDEX($A$64:$A$68,MATCH(1,$I$64:$I$68,0)) -> #N/A
A68: 449 | B68: 0.35 | C68: =$B$6*$B$7*B68*$B$14*(1-$B$12)*(1-$B$13) -> 105.57092 | D68: =$AB$15 -> #REF! | E68: =MIN(C68,D68) -> #REF! | F68: =($B$17+MAX($B$11,$B$18)*A68+$B$20)/(1+$B$23)-$B$11*$B$21-($B$22+($B$17+MAX($B$11,$B$18)*A68+$B$20)*$B$24+(($B$17+MAX($B$11,$B$18)*A68+$B$20)/(1+$B$23))*'NC Credits'!$B$15)+$B$25*$B$26 -> #REF! | G68: =E68*F68 -> #REF! | H68: =G68-$B$27 -> #REF! | I68: =RANK(H68,$H$64:$H$68,0) -> #REF! | K68: Interpretation | L68: Sensitivity only — do not change MVP-1 pricing until real conversion and repeat data is available.
A72: 5. Price Elasticity Decision Table — Monthly Operating Profit Heatmap
A73: Hourly Price / Conversion | B73: 0.1 | C73: 0.15 | D73: 0.2 | E73: 0.25 | F73: 0.3 | G73: 0.4 | H73: 0.5
A74: 249 | B74: =MIN($B$6*$B$7*B$73*$B$14*(1-$B$12)*(1-$B$13),$AB$15)*(($B$17+$B$18*$A74+MAX($B$11-$B$18,0)*$A74+$B$20)/(1+$B$23)-$B$11*$B$21-$B$22-($B$17+$B$18*$A74+MAX($B$11-$B$18,0)*$A74+$B$20)*$B$24-(($B$17+$B$18*$A74+MAX($B$11-$B$18,0)*$A74+$B$20)/(1+$B$23))*'NC Credits'!$B$15+$B$25*$B$26)-$B$27 -> #REF! | C74: =MIN($B$6*$B$7*C$73*$B$14*(1-$B$12)*(1-$B$13),$AB$15)*(($B$17+$B$18*$A74+MAX($B$11-$B$18,0)*$A74+$B$20)/(1+$B$23)-$B$11*$B$21-$B$22-($B$17+$B$18*$A74+MAX($B$11-$B$18,0)*$A74+$B$20)*$B$24-(($B$17+$B$18*$A74+MAX($B$11-$B$18,0)*$A74+$B$20)/(1+$B$23))*'NC Credits'!$B$15+$B$25*$B$26)-$B$27 -> #REF! | D74: =MIN($B$6*$B$7*D$73*$B$14*(1-$B$12)*(1-$B$13),$AB$15)*(($B$17+$B$18*$A74+MAX($B$11-$B$18,0)*$A74+$B$20)/(1+$B$23)-$B$11*$B$21-$B$22-($B$17+$B$18*$A74+MAX($B$11-$B$18,0)*$A74+$B$20)*$B$24-(($B$17+$B$18*$A74+MAX($B$11-$B$18,0)*$A74+$B$20)/(1+$B$23))*'NC Credits'!$B$15+$B$25*$B$26)-$B$27 -> #REF! | E74: =MIN($B$6*$B$7*E$73*$B$14*(1-$B$12)*(1-$B$13),$AB$15)*(($B$17+$B$18*$A74+MAX($B$11-$B$18,0)*$A74+$B$20)/(1+$B$23)-$B$11*$B$21-$B$22-($B$17+$B$18*$A74+MAX($B$11-$B$18,0)*$A74+$B$20)*$B$24-(($B$17+$B$18*$A74+MAX($B$11-$B$18,0)*$A74+$B$20)/(1+$B$23))*'NC Credits'!$B$15+$B$25*$B$26)-$B$27 -> #REF! | F74: =MIN($B$6*$B$7*F$73*$B$14*(1-$B$12)*(1-$B$13),$AB$15)*(($B$17+$B$18*$A74+MAX($B$11-$B$18,0)*$A74+$B$20)/(1+$B$23)-$B$11*$B$21-$B$22-($B$17+$B$18*$A74+MAX($B$11-$B$18,0)*$A74+$B$20)*$B$24-(($B$17+$B$18*$A74+MAX($B$11-$B$18,0)*$A74+$B$20)/(1+$B$23))*'NC Credits'!$B$15+$B$25*$B$26)-$B$27 -> #REF! | G74: =MIN($B$6*$B$7*G$73*$B$14*(1-$B$12)*(1-$B$13),$AB$15)*(($B$17+$B$18*$A74+MAX($B$11-$B$18,0)*$A74+$B$20)/(1+$B$23)-$B$11*$B$21-$B$22-($B$17+$B$18*$A74+MAX($B$11-$B$18,0)*$A74+$B$20)*$B$24-(($B$17+$B$18*$A74+MAX($B$11-$B$18,0)*$A74+$B$20)/(1+$B$23))*'NC Credits'!$B$15+$B$25*$B$26)-$B$27 -> #REF! | H74: =MIN($B$6*$B$7*H$73*$B$14*(1-$B$12)*(1-$B$13),$AB$15)*(($B$17+$B$18*$A74+MAX($B$11-$B$18,0)*$A74+$B$20)/(1+$B$23)-$B$11*$B$21-$B$22-($B$17+$B$18*$A74+MAX($B$11-$B$18,0)*$A74+$B$20)*$B$24-(($B$17+$B$18*$A74+MAX($B$11-$B$18,0)*$A74+$B$20)/(1+$B$23))*'NC Credits'!$B$15+$B$25*$B$26)-$B$27 -> #REF!
A75: 299 | B75: =MIN($B$6*$B$7*B$73*$B$14*(1-$B$12)*(1-$B$13),$AB$15)*(($B$17+$B$18*$A75+MAX($B$11-$B$18,0)*$A75+$B$20)/(1+$B$23)-$B$11*$B$21-$B$22-($B$17+$B$18*$A75+MAX($B$11-$B$18,0)*$A75+$B$20)*$B$24-(($B$17+$B$18*$A75+MAX($B$11-$B$18,0)*$A75+$B$20)/(1+$B$23))*'NC Credits'!$B$15+$B$25*$B$26)-$B$27 -> #REF! | C75: =MIN($B$6*$B$7*C$73*$B$14*(1-$B$12)*(1-$B$13),$AB$15)*(($B$17+$B$18*$A75+MAX($B$11-$B$18,0)*$A75+$B$20)/(1+$B$23)-$B$11*$B$21-$B$22-($B$17+$B$18*$A75+MAX($B$11-$B$18,0)*$A75+$B$20)*$B$24-(($B$17+$B$18*$A75+MAX($B$11-$B$18,0)*$A75+$B$20)/(1+$B$23))*'NC Credits'!$B$15+$B$25*$B$26)-$B$27 -> #REF! | D75: =MIN($B$6*$B$7*D$73*$B$14*(1-$B$12)*(1-$B$13),$AB$15)*(($B$17+$B$18*$A75+MAX($B$11-$B$18,0)*$A75+$B$20)/(1+$B$23)-$B$11*$B$21-$B$22-($B$17+$B$18*$A75+MAX($B$11-$B$18,0)*$A75+$B$20)*$B$24-(($B$17+$B$18*$A75+MAX($B$11-$B$18,0)*$A75+$B$20)/(1+$B$23))*'NC Credits'!$B$15+$B$25*$B$26)-$B$27 -> #REF! | E75: =MIN($B$6*$B$7*E$73*$B$14*(1-$B$12)*(1-$B$13),$AB$15)*(($B$17+$B$18*$A75+MAX($B$11-$B$18,0)*$A75+$B$20)/(1+$B$23)-$B$11*$B$21-$B$22-($B$17+$B$18*$A75+MAX($B$11-$B$18,0)*$A75+$B$20)*$B$24-(($B$17+$B$18*$A75+MAX($B$11-$B$18,0)*$A75+$B$20)/(1+$B$23))*'NC Credits'!$B$15+$B$25*$B$26)-$B$27 -> #REF! | F75: =MIN($B$6*$B$7*F$73*$B$14*(1-$B$12)*(1-$B$13),$AB$15)*(($B$17+$B$18*$A75+MAX($B$11-$B$18,0)*$A75+$B$20)/(1+$B$23)-$B$11*$B$21-$B$22-($B$17+$B$18*$A75+MAX($B$11-$B$18,0)*$A75+$B$20)*$B$24-(($B$17+$B$18*$A75+MAX($B$11-$B$18,0)*$A75+$B$20)/(1+$B$23))*'NC Credits'!$B$15+$B$25*$B$26)-$B$27 -> #REF! | G75: =MIN($B$6*$B$7*G$73*$B$14*(1-$B$12)*(1-$B$13),$AB$15)*(($B$17+$B$18*$A75+MAX($B$11-$B$18,0)*$A75+$B$20)/(1+$B$23)-$B$11*$B$21-$B$22-($B$17+$B$18*$A75+MAX($B$11-$B$18,0)*$A75+$B$20)*$B$24-(($B$17+$B$18*$A75+MAX($B$11-$B$18,0)*$A75+$B$20)/(1+$B$23))*'NC Credits'!$B$15+$B$25*$B$26)-$B$27 -> #REF! | H75: =MIN($B$6*$B$7*H$73*$B$14*(1-$B$12)*(1-$B$13),$AB$15)*(($B$17+$B$18*$A75+MAX($B$11-$B$18,0)*$A75+$B$20)/(1+$B$23)-$B$11*$B$21-$B$22-($B$17+$B$18*$A75+MAX($B$11-$B$18,0)*$A75+$B$20)*$B$24-(($B$17+$B$18*$A75+MAX($B$11-$B$18,0)*$A75+$B$20)/(1+$B$23))*'NC Credits'!$B$15+$B$25*$B$26)-$B$27 -> #REF!
A76: 349 | B76: =MIN($B$6*$B$7*B$73*$B$14*(1-$B$12)*(1-$B$13),$AB$15)*(($B$17+$B$18*$A76+MAX($B$11-$B$18,0)*$A76+$B$20)/(1+$B$23)-$B$11*$B$21-$B$22-($B$17+$B$18*$A76+MAX($B$11-$B$18,0)*$A76+$B$20)*$B$24-(($B$17+$B$18*$A76+MAX($B$11-$B$18,0)*$A76+$B$20)/(1+$B$23))*'NC Credits'!$B$15+$B$25*$B$26)-$B$27 -> #REF! | C76: =MIN($B$6*$B$7*C$73*$B$14*(1-$B$12)*(1-$B$13),$AB$15)*(($B$17+$B$18*$A76+MAX($B$11-$B$18,0)*$A76+$B$20)/(1+$B$23)-$B$11*$B$21-$B$22-($B$17+$B$18*$A76+MAX($B$11-$B$18,0)*$A76+$B$20)*$B$24-(($B$17+$B$18*$A76+MAX($B$11-$B$18,0)*$A76+$B$20)/(1+$B$23))*'NC Credits'!$B$15+$B$25*$B$26)-$B$27 -> #REF! | D76: =MIN($B$6*$B$7*D$73*$B$14*(1-$B$12)*(1-$B$13),$AB$15)*(($B$17+$B$18*$A76+MAX($B$11-$B$18,0)*$A76+$B$20)/(1+$B$23)-$B$11*$B$21-$B$22-($B$17+$B$18*$A76+MAX($B$11-$B$18,0)*$A76+$B$20)*$B$24-(($B$17+$B$18*$A76+MAX($B$11-$B$18,0)*$A76+$B$20)/(1+$B$23))*'NC Credits'!$B$15+$B$25*$B$26)-$B$27 -> #REF! | E76: =MIN($B$6*$B$7*E$73*$B$14*(1-$B$12)*(1-$B$13),$AB$15)*(($B$17+$B$18*$A76+MAX($B$11-$B$18,0)*$A76+$B$20)/(1+$B$23)-$B$11*$B$21-$B$22-($B$17+$B$18*$A76+MAX($B$11-$B$18,0)*$A76+$B$20)*$B$24-(($B$17+$B$18*$A76+MAX($B$11-$B$18,0)*$A76+$B$20)/(1+$B$23))*'NC Credits'!$B$15+$B$25*$B$26)-$B$27 -> #REF! | F76: =MIN($B$6*$B$7*F$73*$B$14*(1-$B$12)*(1-$B$13),$AB$15)*(($B$17+$B$18*$A76+MAX($B$11-$B$18,0)*$A76+$B$20)/(1+$B$23)-$B$11*$B$21-$B$22-($B$17+$B$18*$A76+MAX($B$11-$B$18,0)*$A76+$B$20)*$B$24-(($B$17+$B$18*$A76+MAX($B$11-$B$18,0)*$A76+$B$20)/(1+$B$23))*'NC Credits'!$B$15+$B$25*$B$26)-$B$27 -> #REF! | G76: =MIN($B$6*$B$7*G$73*$B$14*(1-$B$12)*(1-$B$13),$AB$15)*(($B$17+$B$18*$A76+MAX($B$11-$B$18,0)*$A76+$B$20)/(1+$B$23)-$B$11*$B$21-$B$22-($B$17+$B$18*$A76+MAX($B$11-$B$18,0)*$A76+$B$20)*$B$24-(($B$17+$B$18*$A76+MAX($B$11-$B$18,0)*$A76+$B$20)/(1+$B$23))*'NC Credits'!$B$15+$B$25*$B$26)-$B$27 -> #REF! | H76: =MIN($B$6*$B$7*H$73*$B$14*(1-$B$12)*(1-$B$13),$AB$15)*(($B$17+$B$18*$A76+MAX($B$11-$B$18,0)*$A76+$B$20)/(1+$B$23)-$B$11*$B$21-$B$22-($B$17+$B$18*$A76+MAX($B$11-$B$18,0)*$A76+$B$20)*$B$24-(($B$17+$B$18*$A76+MAX($B$11-$B$18,0)*$A76+$B$20)/(1+$B$23))*'NC Credits'!$B$15+$B$25*$B$26)-$B$27 -> #REF!
A77: 399 | B77: =MIN($B$6*$B$7*B$73*$B$14*(1-$B$12)*(1-$B$13),$AB$15)*(($B$17+$B$18*$A77+MAX($B$11-$B$18,0)*$A77+$B$20)/(1+$B$23)-$B$11*$B$21-$B$22-($B$17+$B$18*$A77+MAX($B$11-$B$18,0)*$A77+$B$20)*$B$24-(($B$17+$B$18*$A77+MAX($B$11-$B$18,0)*$A77+$B$20)/(1+$B$23))*'NC Credits'!$B$15+$B$25*$B$26)-$B$27 -> #REF! | C77: =MIN($B$6*$B$7*C$73*$B$14*(1-$B$12)*(1-$B$13),$AB$15)*(($B$17+$B$18*$A77+MAX($B$11-$B$18,0)*$A77+$B$20)/(1+$B$23)-$B$11*$B$21-$B$22-($B$17+$B$18*$A77+MAX($B$11-$B$18,0)*$A77+$B$20)*$B$24-(($B$17+$B$18*$A77+MAX($B$11-$B$18,0)*$A77+$B$20)/(1+$B$23))*'NC Credits'!$B$15+$B$25*$B$26)-$B$27 -> #REF! | D77: =MIN($B$6*$B$7*D$73*$B$14*(1-$B$12)*(1-$B$13),$AB$15)*(($B$17+$B$18*$A77+MAX($B$11-$B$18,0)*$A77+$B$20)/(1+$B$23)-$B$11*$B$21-$B$22-($B$17+$B$18*$A77+MAX($B$11-$B$18,0)*$A77+$B$20)*$B$24-(($B$17+$B$18*$A77+MAX($B$11-$B$18,0)*$A77+$B$20)/(1+$B$23))*'NC Credits'!$B$15+$B$25*$B$26)-$B$27 -> #REF! | E77: =MIN($B$6*$B$7*E$73*$B$14*(1-$B$12)*(1-$B$13),$AB$15)*(($B$17+$B$18*$A77+MAX($B$11-$B$18,0)*$A77+$B$20)/(1+$B$23)-$B$11*$B$21-$B$22-($B$17+$B$18*$A77+MAX($B$11-$B$18,0)*$A77+$B$20)*$B$24-(($B$17+$B$18*$A77+MAX($B$11-$B$18,0)*$A77+$B$20)/(1+$B$23))*'NC Credits'!$B$15+$B$25*$B$26)-$B$27 -> #REF! | F77: =MIN($B$6*$B$7*F$73*$B$14*(1-$B$12)*(1-$B$13),$AB$15)*(($B$17+$B$18*$A77+MAX($B$11-$B$18,0)*$A77+$B$20)/(1+$B$23)-$B$11*$B$21-$B$22-($B$17+$B$18*$A77+MAX($B$11-$B$18,0)*$A77+$B$20)*$B$24-(($B$17+$B$18*$A77+MAX($B$11-$B$18,0)*$A77+$B$20)/(1+$B$23))*'NC Credits'!$B$15+$B$25*$B$26)-$B$27 -> #REF! | G77: =MIN($B$6*$B$7*G$73*$B$14*(1-$B$12)*(1-$B$13),$AB$15)*(($B$17+$B$18*$A77+MAX($B$11-$B$18,0)*$A77+$B$20)/(1+$B$23)-$B$11*$B$21-$B$22-($B$17+$B$18*$A77+MAX($B$11-$B$18,0)*$A77+$B$20)*$B$24-(($B$17+$B$18*$A77+MAX($B$11-$B$18,0)*$A77+$B$20)/(1+$B$23))*'NC Credits'!$B$15+$B$25*$B$26)-$B$27 -> #REF! | H77: =MIN($B$6*$B$7*H$73*$B$14*(1-$B$12)*(1-$B$13),$AB$15)*(($B$17+$B$18*$A77+MAX($B$11-$B$18,0)*$A77+$B$20)/(1+$B$23)-$B$11*$B$21-$B$22-($B$17+$B$18*$A77+MAX($B$11-$B$18,0)*$A77+$B$20)*$B$24-(($B$17+$B$18*$A77+MAX($B$11-$B$18,0)*$A77+$B$20)/(1+$B$23))*'NC Credits'!$B$15+$B$25*$B$26)-$B$27 -> #REF!
A78: 449 | B78: =MIN($B$6*$B$7*B$73*$B$14*(1-$B$12)*(1-$B$13),$AB$15)*(($B$17+$B$18*$A78+MAX($B$11-$B$18,0)*$A78+$B$20)/(1+$B$23)-$B$11*$B$21-$B$22-($B$17+$B$18*$A78+MAX($B$11-$B$18,0)*$A78+$B$20)*$B$24-(($B$17+$B$18*$A78+MAX($B$11-$B$18,0)*$A78+$B$20)/(1+$B$23))*'NC Credits'!$B$15+$B$25*$B$26)-$B$27 -> #REF! | C78: =MIN($B$6*$B$7*C$73*$B$14*(1-$B$12)*(1-$B$13),$AB$15)*(($B$17+$B$18*$A78+MAX($B$11-$B$18,0)*$A78+$B$20)/(1+$B$23)-$B$11*$B$21-$B$22-($B$17+$B$18*$A78+MAX($B$11-$B$18,0)*$A78+$B$20)*$B$24-(($B$17+$B$18*$A78+MAX($B$11-$B$18,0)*$A78+$B$20)/(1+$B$23))*'NC Credits'!$B$15+$B$25*$B$26)-$B$27 -> #REF! | D78: =MIN($B$6*$B$7*D$73*$B$14*(1-$B$12)*(1-$B$13),$AB$15)*(($B$17+$B$18*$A78+MAX($B$11-$B$18,0)*$A78+$B$20)/(1+$B$23)-$B$11*$B$21-$B$22-($B$17+$B$18*$A78+MAX($B$11-$B$18,0)*$A78+$B$20)*$B$24-(($B$17+$B$18*$A78+MAX($B$11-$B$18,0)*$A78+$B$20)/(1+$B$23))*'NC Credits'!$B$15+$B$25*$B$26)-$B$27 -> #REF! | E78: =MIN($B$6*$B$7*E$73*$B$14*(1-$B$12)*(1-$B$13),$AB$15)*(($B$17+$B$18*$A78+MAX($B$11-$B$18,0)*$A78+$B$20)/(1+$B$23)-$B$11*$B$21-$B$22-($B$17+$B$18*$A78+MAX($B$11-$B$18,0)*$A78+$B$20)*$B$24-(($B$17+$B$18*$A78+MAX($B$11-$B$18,0)*$A78+$B$20)/(1+$B$23))*'NC Credits'!$B$15+$B$25*$B$26)-$B$27 -> #REF! | F78: =MIN($B$6*$B$7*F$73*$B$14*(1-$B$12)*(1-$B$13),$AB$15)*(($B$17+$B$18*$A78+MAX($B$11-$B$18,0)*$A78+$B$20)/(1+$B$23)-$B$11*$B$21-$B$22-($B$17+$B$18*$A78+MAX($B$11-$B$18,0)*$A78+$B$20)*$B$24-(($B$17+$B$18*$A78+MAX($B$11-$B$18,0)*$A78+$B$20)/(1+$B$23))*'NC Credits'!$B$15+$B$25*$B$26)-$B$27 -> #REF! | G78: =MIN($B$6*$B$7*G$73*$B$14*(1-$B$12)*(1-$B$13),$AB$15)*(($B$17+$B$18*$A78+MAX($B$11-$B$18,0)*$A78+$B$20)/(1+$B$23)-$B$11*$B$21-$B$22-($B$17+$B$18*$A78+MAX($B$11-$B$18,0)*$A78+$B$20)*$B$24-(($B$17+$B$18*$A78+MAX($B$11-$B$18,0)*$A78+$B$20)/(1+$B$23))*'NC Credits'!$B$15+$B$25*$B$26)-$B$27 -> #REF! | H78: =MIN($B$6*$B$7*H$73*$B$14*(1-$B$12)*(1-$B$13),$AB$15)*(($B$17+$B$18*$A78+MAX($B$11-$B$18,0)*$A78+$B$20)/(1+$B$23)-$B$11*$B$21-$B$22-($B$17+$B$18*$A78+MAX($B$11-$B$18,0)*$A78+$B$20)*$B$24-(($B$17+$B$18*$A78+MAX($B$11-$B$18,0)*$A78+$B$20)/(1+$B$23))*'NC Credits'!$B$15+$B$25*$B$26)-$B$27 -> #REF!
A82: 7. Angel Pay Strategy — Protect Quality, Improve Effective Cost Through Utilization
A83: Angel Payout / Service Hr | B83: Contribution / Journey | C83: Contribution / Angel Hr | D83: Hourly Price Needed for ₹150 Contrib / Angel Hr | E83: Break-even Journeys / Month | F83: Break-even / Day | G83: Monthly Profit at Current Demand | I83: Payout Model | J83: Base Commitment | K83: Utilization Assumption | L83: Effective Cost / Productive Hr | M83: Founder Note
A84: 125 | B84: 733.39178 | C84: =IF($B$11=0,0,B84/$B$11) -> #REF! | D84: 288.23906 | E84: =IF(B84<=0,0,$B$27/B84) -> #REF! | F84: =E84/$B$7 -> #REF! | G84: =$AB$16*B84-$B$27 -> #REF! | I84: Pure hourly gig | J84: 175 | K84: 1 | L84: =J84 -> 175 | M84: Pay only productive service hours
A85: 140 | B85: 664.09178 | C85: =IF($B$11=0,0,B85/$B$11) -> #REF! | D85: 306.70156 | E85: =IF(B85<=0,0,$B$27/B85) -> #REF! | F85: =E85/$B$7 -> #REF! | G85: =$AB$16*B85-$B$27 -> #REF! | I85: Guaranteed 4-hour block | J85: 700 | K85: 0.7 | L85: =J85/(4*K85) -> 250 | M85: Reliability higher; effective cost rises if block underused
A86: 150 | B86: 617.89178 | C86: =IF($B$11=0,0,B86/$B$11) -> #REF! | D86: 319.00989 | E86: =IF(B86<=0,0,$B$27/B86) -> #REF! | F86: =E86/$B$7 -> #REF! | G86: =$AB$16*B86-$B$27 -> #REF! | I86: Recurring-customer assignment | J86: 600 | K86: 0.85 | L86: =J86/(4*K86) -> 176.47059 | M86: Illustrative recurring block economics
A87: 160 | B87: 571.69178 | C87: =IF($B$11=0,0,B87/$B$11) -> #REF! | D87: 331.31823 | E87: =IF(B87<=0,0,$B$27/B87) -> #REF! | F87: =E87/$B$7 -> #REF! | G87: =$AB$16*B87-$B$27 -> #REF! | I87: Half-day shift | J87: 650 | K87: 0.75 | L87: =J87/(4*K87) -> 216.66667 | M87: 4-hour shift; utilization is critical
A88: 175 | B88: 502.39178 | C88: =IF($B$11=0,0,B88/$B$11) -> #REF! | D88: 349.78073 | E88: =IF(B88<=0,0,$B$27/B88) -> #REF! | F88: =E88/$B$7 -> #REF! | G88: =$AB$16*B88-$B$27 -> #REF! | I88: Full-day shift | J88: 1200 | K88: 0.7 | L88: =J88/(8*K88) -> 214.28571 | M88: 8-hour shift; only for proven density
A89: 200 | B89: 386.89178 | C89: =IF($B$11=0,0,B89/$B$11) -> #REF! | D89: 380.55156 | E89: =IF(B89<=0,0,$B$27/B89) -> #REF! | F89: =E89/$B$7 -> #REF! | G89: =$AB$16*B89-$B$27 -> #REF!
A93: 8. Angel Utilization Engine — Capacity, Idle Time & Overstaffing
A94: Utilization | B94: Available Angel Hrs | C94: Productive Hrs | D94: Idle Hrs | E94: Capacity Journeys | F94: Completed Journeys | G94: Contribution | H94: Operating Profit | J94: OVERSTAFFING DETECTOR | K94: VALUE
A95: 0.3 | B95: =$B$8*$B$7*$B$9 -> 1040 | C95: =B95*A95 -> 312 | D95: =B95-C95 -> 728 | E95: =IF($B$11=0,0,C95/$B$11) -> #REF! | F95: =MIN(E95,$AB$14) -> #REF! | G95: =F95*$AB$11 -> #REF! | H95: =G95-$B$27 -> #REF! | J95: Angels currently planned | K95: =$B$8 -> 5
A96: 0.4 | B96: =$B$8*$B$7*$B$9 -> 1040 | C96: =B96*A96 -> 416 | D96: =B96-C96 -> 624 | E96: =IF($B$11=0,0,C96/$B$11) -> #REF! | F96: =MIN(E96,$AB$14) -> #REF! | G96: =F96*$AB$11 -> #REF! | H96: =G96-$B$27 -> #REF! | J96: Angels required at current selected demand | K96: =$AB$24 -> #REF!
A97: 0.5 | B97: =$B$8*$B$7*$B$9 -> 1040 | C97: =B97*A97 -> 520 | D97: =B97-C97 -> 520 | E97: =IF($B$11=0,0,C97/$B$11) -> #REF! | F97: =MIN(E97,$AB$14) -> #REF! | G97: =F97*$AB$11 -> #REF! | H97: =G97-$B$27 -> #REF! | J97: Excess Angel equivalents | K97: =$AB$25 -> #REF!
A98: 0.6 | B98: =$B$8*$B$7*$B$9 -> 1040 | C98: =B98*A98 -> 624 | D98: =B98-C98 -> 416 | E98: =IF($B$11=0,0,C98/$B$11) -> #REF! | F98: =MIN(E98,$AB$14) -> #REF! | G98: =F98*$AB$11 -> #REF! | H98: =G98-$B$27 -> #REF! | J98: Current utilization | K98: =$F$14 -> #REF!
A99: 0.7 | B99: =$B$8*$B$7*$B$9 -> 1040 | C99: =B99*A99 -> 728 | D99: =B99-C99 -> 312 | E99: =IF($B$11=0,0,C99/$B$11) -> #REF! | F99: =MIN(E99,$AB$14) -> #REF! | G99: =F99*$AB$11 -> #REF! | H99: =G99-$B$27 -> #REF! | J99: Current journeys / Angel / day | K99: =IF($B$8*$B$7=0,0,$AB$16/($B$8*$B$7)) -> #REF!
A100: 0.8 | B100: =$B$8*$B$7*$B$9 -> 1040 | C100: =B100*A100 -> 832 | D100: =B100-C100 -> 208 | E100: =IF($B$11=0,0,C100/$B$11) -> #REF! | F100: =MIN(E100,$AB$14) -> #REF! | G100: =F100*$AB$11 -> #REF! | H100: =G100-$B$27 -> #REF! | J100: Capacity warning | K100: =IF(K96>1,"Overstaffed relative to current demand","Capacity aligned / tight") -> #REF!
A101: 0.9 | B101: =$B$8*$B$7*$B$9 -> 1040 | C101: =B101*A101 -> 936 | D101: =B101-C101 -> 104 | E101: =IF($B$11=0,0,C101/$B$11) -> #REF! | F101: =MIN(E101,$AB$14) -> #REF! | G101: =F101*$AB$11 -> #REF! | H101: =G101-$B$27 -> #REF!
A105: 9. Fixed Cost Strategy — Ultra-Lean → Lean MVP → Scale / Full Team
A106: Operating Model | B106: Journey Range | C106: Fixed Cost / Month | D106: Break-even Journeys | E106: Break-even / Day | F106: Profit @ 5/day | G106: Profit @ 10/day | H106: Profit @ 15/day | J106: FIXED-COST CEILING | K106: CURRENT / RESULT | L106: GAP | M106: ACTION
A107: Ultra-Lean Pilot | B107: 0–50 | C107: =#REF! -> #REF! | D107: =IF($AB$11<=0,0,C107/$AB$11) -> #REF! | E107: =D107/$B$7 -> #REF! | F107: =5*$B$7*$AB$11-C107 -> #REF! | G107: =10*$B$7*$AB$11-C107 -> #REF! | H107: =15*$B$7*$AB$11-C107 -> #REF! | J107: Current selected fixed cost | K107: =$B$27 -> #REF! | M107: Current operating assumption
A108: Lean MVP | B108: 51–150 | C108: =#REF! -> #REF! | D108: =IF($AB$11<=0,0,C108/$AB$11) -> #REF! | E108: =D108/$B$7 -> #REF! | F108: =5*$B$7*$AB$11-C108 -> #REF! | G108: =10*$B$7*$AB$11-C108 -> #REF! | H108: =15*$B$7*$AB$11-C108 -> #REF! | J108: Sustainable fixed cost at current demand | K108: =$AB$18 -> #REF! | L108: =$B$27-K108 -> #REF! | M108: Maximum at break-even
A109: Scale / Full Team | B109: 151+ | C109: =#REF! -> #REF! | D109: =IF($AB$11<=0,0,C109/$AB$11) -> #REF! | E109: =D109/$B$7 -> #REF! | F109: =5*$B$7*$AB$11-C109 -> #REF! | G109: =10*$B$7*$AB$11-C109 -> #REF! | H109: =15*$B$7*$AB$11-C109 -> #REF! | J109: Sustainable fixed cost at selected target | K109: =$AB$18-$B$5 -> #REF! | L109: =$B$27-K109 -> #REF! | M109: Must be ≤ this to hit target without more volume
J110: Excess overhead vs break-even | K110: =MAX($B$27-$AB$18,0) -> #REF! | M110: Reduce cost or grow contribution
A114: 11. Customer Acquisition Engine — Treat Discounts as CAC, Not Invisible Loss
A115: CAC Component | B115: Amount | C115: Classification | D115: Included in True CAC? | E115: Current Result | F115: Founder Note | H115: Lead Funnel KPI | I115: Value | J115: Formula Driver | K115: Target / Comment
A116: Paid marketing CAC | B116: =$B$28 -> 300 | C116: Marketing | D116: Yes | E116: =$B$28 -> 300 | F116: Editable | H116: Monthly leads | I116: =$B$6*$B$7 -> 260 | J116: Leads/day × operating days | K116: Grow density before geography
A117: First-journey subsidy | B117: =$B$29 -> 0 | C117: Acquisition subsidy | D117: Yes | E117: =$B$29 -> 0 | F117: A discount is still acquisition spend | H117: Selected conversion | I117: =$AB$13 -> 0.45 | J117: Linked to price-conversion curve | K117: Editable assumptions determine this
A118: Referral reward | B118: =$B$30 -> 0 | C118: Referral CAC | D118: Yes | E118: =$B$30 -> 0 | F118: Editable | H118: New paying customers / month | I118: =I116*I117 -> 117 | J118: Leads × conversion | K118: Before repeat frequency
A119: TRUE CAC | B119: =$AB$22 -> 300 | C119: Total | D119: Yes | E119: =$AB$22 -> 300 | F119: Paid CAC + subsidy + referral + NC promotional credits | H119: Monthly completed journeys | I119: =$AB$16 -> #REF! | J119: Demand capped by Angel capacity | K119: Core scale metric
A120: Welcome NC promotional value | B120: ='NC Credits'!$B$11*'NC Credits'!$B$7 -> 0 | C120: Loyalty acquisition | D120: Yes | E120: =B120 -> 0 | F120: Future; 0 at MVP launch | H120: Average journeys / customer | I120: =$B$14 -> 1.3 | J120: Repeat behavior | K120: Increase with trust / recurring care
...

Sheet NC Credits
A1: NivrāaCare — NivrāaCredits Loyalty Economics
A2: Founder-configurable loyalty model. Credits are earned on eligible NivrāaCare care-service spend, exclude transport/pass-through charges, and are issued only after successful journey completion.
A4: NC CREDIT PROGRAM ASSUMPTIONS — EDIT BLUE INPUTS
A5: Program enabled (1=ON, 0=OFF) | B5: ='Global Pricing Config'!$B$11 -> 1 | C5: toggle | D5: Set to 0 to switch NC economics off without deleting formulas.
A6: NivrāaCredit earn rate | B6: ='Global Pricing Config'!$B$12 -> 0.05 | C6: % of eligible spend | D6: ="Founder-configurable. Current setting = "&ROUND(B6*100/B7,2)&" NivrāaCredits per ₹100 eligible spend." -> Founder-configurable. Current setting = 5 NivrāaCredits per ₹100 eligible spend.
A7: ₹ value per 1 NivrāaCredit | B7: ='Global Pricing Config'!$B$13 -> 1 | C7: ₹ / NC | D7: Current planning rule: 1 NivrāaCredit = ₹1 redemption value.
A8: Expected redemption rate | B8: ='Global Pricing Config'!$B$16 -> 0.7 | C8: % of issued value | D8: Planning assumption for expected economic cost / breakage.
A9: Maximum redemption per booking | B9: ='Global Pricing Config'!$B$14 -> 0.2 | C9: % of eligible service value | D9: Protects contribution; customer cannot fully pay a journey with NC.
A10: Credit expiry | B10: ='Global Pricing Config'!$B$15 -> 180 | C10: days | D10: Planning policy; legal/accounting wording to be finalized before launch.
A11: Welcome NC (future) | B11: 0 | C11: NC / new family | D11: Default 0 for MVP. If activated, treated as CAC.
A12: Referral NC reward (future) | B12: 0 | C12: NC / successful referral | D12: Default 0 for MVP. If activated, treated as CAC.
A13: Eligible spend factor | B13: 1 | C13: % of eligible care-service spend | D13: 100% of eligible care-service amount; transport, cab reimbursement and third-party pass-through excluded.
A14: Earn trigger | B14: Completed journey only | C14: policy | D14: Issue NC only after successful journey completion / closure.
A15: Expected loyalty cost rate | B15: =B5*B6*B8*B13*(1+'Global Inputs'!$B$7) -> 0.0413 | C15: ₹ expected cost / ₹ eligible net revenue | D15: Equivalent expected loyalty cost rate applied to net care revenue. Gross eligible spend × Earn Rate × Expected Redemption.
A16: Face-value issuance rate | B16: =B5*B6*B13*(1+'Global Inputs'!$B$7) -> 0.059 | C16: ₹ face value / ₹ eligible net revenue | D16: Equivalent face-value issuance rate applied to net care revenue. Gross eligible spend × Earn Rate.
A18: CURRENT SELECTED MODEL IMPACT — LINKED TO GROWTH & PRICING STRATEGY
A19: Average customer care bill (incl. GST) | B19: ='Growth & Pricing Strategy'!$AB$5 -> #REF! | C19: ₹ / journey | D19: Selected pricing engine gross care bill.
A20: Eligible care-service spend (customer billing basis) | B20: =$B$19*$B$13 -> #REF! | C20: ₹ / journey | D20: Care-service customer billing amount used for Credit earning; transport/pass-through excluded.
A21: NC earned / journey | B21: =IF($B$7=0,0,$B$5*$B$20*$B$6/$B$7) -> #REF! | C21: NC | D21: Face-value credits issued after completed journey.
A22: Face value issued / journey | B22: =$B$21*$B$7 -> #REF! | C22: ₹ / journey | D22: NC earned × ₹ value per NC.
A23: Expected redeemed NC cost / journey | B23: =$B$22*$B$8 -> #REF! | C23: ₹ / journey | D23: Face value × expected redemption rate.
A24: Pre-NC blended contribution / journey | B24: ='Growth & Pricing Strategy'!$AB$11+$B$23 -> #REF! | C24: ₹ / journey | D24: Contribution before loyalty cost.
A25: Post-NC blended contribution / journey | B25: ='Growth & Pricing Strategy'!$AB$11 -> #REF! | C25: ₹ / journey | D25: Contribution after expected NC cost.
A26: Monthly expected NC cost | B26: ='Growth & Pricing Strategy'!$AB$16*$B$23 -> #REF! | C26: ₹ / month | D26: Expected redemption cost at current completed journeys.
A27: Monthly NC face value issued | B27: ='Growth & Pricing Strategy'!$AB$16*$B$22 -> #REF! | C27: ₹ / month | D27: Nominal NC issued at current completed journeys.
A28: Monthly operating profit after NC | B28: ='Growth & Pricing Strategy'!$AB$19 -> #REF! | C28: ₹ / month | D28: Linked to the NC-adjusted growth model.
A29: Break-even journeys / day after NC | B29: ='Growth & Pricing Strategy'!$AB$21 -> #REF! | C29: journeys / day | D29: NC-adjusted break-even.
A30: Contribution reduction from NC | B30: =IF($B$24=0,0,$B$23/$B$24) -> #REF! | C30: % | D30: Expected NC cost ÷ pre-NC contribution.
A33: CUSTOMER-FACING EXAMPLE — CURRENT CONFIGURATION
A34: Example eligible care-service spend | B34: 1694 | C34: ₹ | D34: Illustrative Hospital Visit care charge; transport excluded.
A35: NivrāaCredits earned | B35: =FLOOR(IF($B$7=0,0,$B$34*$B$6/$B$7),1) -> 84 | C35: NC | D35: Whole Credits only; round down.
A36: Maximum NivrāaCredits redeemable on a future eligible booking | B36: =FLOOR(IF($B$7=0,0,$B$34*$B$9/$B$7),1) -> 338 | C36: NC | D36: Based on max-redemption cap.
A37: Expected model cost of Credits earned | B37: =$B$35*$B$7*$B$8 -> 58.8 | C37: ₹ | D37: Expected redemption value used in economics.
A38: Suggested customer message | B38: ="Earn "&ROUND($B$6*100/$B$7,2)&" NivrāaCredits per ₹100 eligible care-service spend • 1 NivrāaCredit = ₹"&ROUND($B$7,2)&" • redeem up to "&TEXT($B$9,"0%")&" of an eligible booking." -> Earn 5 NivrāaCredits per ₹100 eligible care-service spend • 1 NivrāaCredit = ₹1 • redeem up to 20% of an eligible booking. | D38: Earn NC on completed NivrāaCare journeys and use them on future eligible services.
A41: NIVRĀACREDIT EARN-RATE SENSITIVITY — CURRENT VOLUME & PRICING
A42: Earn Rate | B42: Credits / ₹100 | C42: Expected Cost / Journey | D42: Adj. Contribution / Journey | E42: Monthly Credit Cost | F42: Monthly Operating Profit | G42: Break-even / Day
A43: 0.03 | B43: =A43*100/$B$7 -> 3 | C43: =$B$20*A43*$B$8*$B$5 -> #REF! | D43: =$B$24-C43 -> #REF! | E43: ='Growth & Pricing Strategy'!$AB$16*C43 -> #REF! | F43: ='Growth & Pricing Strategy'!$AB$16*D43-'Growth & Pricing Strategy'!$B$27 -> #REF! | G43: =IF(D43<=0,0,'Growth & Pricing Strategy'!$B$27/D43/'Growth & Pricing Strategy'!$B$7) -> #REF!
A44: 0.05 | B44: =A44*100/$B$7 -> 5 | C44: =$B$20*A44*$B$8*$B$5 -> #REF! | D44: =$B$24-C44 -> #REF! | E44: ='Growth & Pricing Strategy'!$AB$16*C44 -> #REF! | F44: ='Growth & Pricing Strategy'!$AB$16*D44-'Growth & Pricing Strategy'!$B$27 -> #REF! | G44: =IF(D44<=0,0,'Growth & Pricing Strategy'!$B$27/D44/'Growth & Pricing Strategy'!$B$7) -> #REF!
A45: 0.07 | B45: =A45*100/$B$7 -> 7 | C45: =$B$20*A45*$B$8*$B$5 -> #REF! | D45: =$B$24-C45 -> #REF! | E45: ='Growth & Pricing Strategy'!$AB$16*C45 -> #REF! | F45: ='Growth & Pricing Strategy'!$AB$16*D45-'Growth & Pricing Strategy'!$B$27 -> #REF! | G45: =IF(D45<=0,0,'Growth & Pricing Strategy'!$B$27/D45/'Growth & Pricing Strategy'!$B$7) -> #REF!
A46: 0.1 | B46: =A46*100/$B$7 -> 10 | C46: =$B$20*A46*$B$8*$B$5 -> #REF! | D46: =$B$24-C46 -> #REF! | E46: ='Growth & Pricing Strategy'!$AB$16*C46 -> #REF! | F46: ='Growth & Pricing Strategy'!$AB$16*D46-'Growth & Pricing Strategy'!$B$27 -> #REF! | G46: =IF(D46<=0,0,'Growth & Pricing Strategy'!$B$27/D46/'Growth & Pricing Strategy'!$B$7) -> #REF!
A47: 0.12 | B47: =A47*100/$B$7 -> 12 | C47: =$B$20*A47*$B$8*$B$5 -> #REF! | D47: =$B$24-C47 -> #REF! | E47: ='Growth & Pricing Strategy'!$AB$16*C47 -> #REF! | F47: ='Growth & Pricing Strategy'!$AB$16*D47-'Growth & Pricing Strategy'!$B$27 -> #REF! | G47: =IF(D47<=0,0,'Growth & Pricing Strategy'!$B$27/D47/'Growth & Pricing Strategy'!$B$7) -> #REF!
A48: 0.15 | B48: =A48*100/$B$7 -> 15 | C48: =$B$20*A48*$B$8*$B$5 -> #REF! | D48: =$B$24-C48 -> #REF! | E48: ='Growth & Pricing Strategy'!$AB$16*C48 -> #REF! | F48: ='Growth & Pricing Strategy'!$AB$16*D48-'Growth & Pricing Strategy'!$B$27 -> #REF! | G48: =IF(D48<=0,0,'Growth & Pricing Strategy'!$B$27/D48/'Growth & Pricing Strategy'!$B$7) -> #REF!
A49: Model note: this is an expected-cost planning model, not an accounting opinion. Confirm loyalty-credit revenue recognition, expiry, GST treatment and liability presentation with the company's CA before launch.

Sheet MVP1 Pricing & SKU
A1: NivrāaCare — MVP-1 Duration Pricing, SKU & Unit Economics
A2: Founder pricing engine: ₹299/hour × service-specific multiplier × billable hours + ₹199 Care Coordination Fee; 2-hour minimum. Transport is separate. ₹269 is retained only as a legacy/inactive reference.
A4: MVP-1 PRICING & ECONOMIC ASSUMPTIONS — EDIT BLUE INPUTS | F4: CFO CHECK — PAYROLL ANGELS | U4: CUSTOMER-FACING MVP-1 PRICING
A5: Minimum booking hours | B5: ='Global Pricing Config'!$B$6 -> 2 | C5: hours | D5: Founder MVP-1 pricing decision | F5: =IF(B10=0,"Angel cost/hour is currently ₹0. Ensure all Angel payroll salaries are included in monthly fixed costs; otherwise profitability will be overstated.","Angel cost/hour is variable in the current model.") -> Angel cost/hour is currently ₹0. Ensure all Angel payroll salaries are included in monthly fixed costs; otherwise profitability will be overstated. | U5: Simple hourly pricing Base rate: ₹299/hour × service-specific rate adjustment Minimum booking: 2 hours ₹199 Care Coordination Fee Transport charged separately Additional hours continue at the same effective service rate.
A6: Legacy 4-hour threshold (inactive) | B6: 4 | C6: hours | D6: Historical reference only. Current pricing uses one effective service rate across all billable hours.
A7: Base hourly rate | B7: ='Global Pricing Config'!$B$5 -> 299 | C7: ₹ / hour | D7: Founder MVP-1 pricing decision
A8: Legacy extended-hour price (inactive) | B8: 269 | C8: ₹ / hour | D8: Historical ₹269 assumption. Not used in current MVP pricing engine.
A9: Journey / Care Coordination Fee | B9: ='Global Pricing Config'!$B$7 -> 199 | C9: ₹ / journey | D9: Separate booking-level fee
A10: Angel cost / hour | B10: ='Global Inputs'!$B$6 -> 0 | C10: ₹ / Angel hour | D10: Linked to Global Inputs
A11: GST on care service | B11: ='Global Pricing Config'!$B$8 -> 0.18 | C11: % | D11: Linked to Global Inputs; illustrative until CA confirms
A12: Payment gateway fee | B12: ='Global Inputs'!$B$8 -> 0 | C12: % of collection | D12: Linked to Global Inputs | U12: PRICING COMPARISON — EDIT CONVERSION ASSUMPTIONS
A13: Other variable cost / journey | B13: =SUM('Global Inputs'!$B$10:$B$14) -> 56.5 | C13: ₹ / journey | D13: Ops + insurance + communication + BGV/training + recovery reserve | U13: Scenario | V13: Base Hourly Rate | W13: Additional-Hour Base Rate | X13: Journey Fee | Y13: Conversion Assumption | Z13: Avg Customer Price | AA13: Contribution / Journey | AB13: Contribution / Angel Hr | AC13: Break-even / Month | AD13: Break-even / Day | AE13: Expected Monthly Profit / (Loss)
A14: NivrāaCredit earn rate | B14: ='NC Credits'!$B$6 -> 0.05 | C14: % | D14: Linked to NC Credits | U14: ₹249 all hours | V14: 249 | W14: 249 | X14: 199 | Y14: 0.5 | Z14: =$X14+MIN(MAX('Growth & Pricing Strategy'!$B$11,$B$5),$B$6)*$V14+MAX(MAX('Growth & Pricing Strategy'!$B$11,$B$5)-$B$6,0)*$W14 -> #REF! | AA14: =Z14/(1+$B$11)-'Growth & Pricing Strategy'!$B$11*$B$10-($B$13+Z14*$B$12+(Z14/(1+$B$11))*$B$18)+$B$16*$B$17 -> #REF! | AB14: =IF('Growth & Pricing Strategy'!$B$11=0,0,AA14/'Growth & Pricing Strategy'!$B$11) -> #REF! | AC14: =IF(AA14<=0,0,'Growth & Pricing Strategy'!$B$27/AA14) -> #REF! | AD14: =IF($B$19=0,0,AC14/$B$19) -> #REF! | AE14: =MIN('Growth & Pricing Strategy'!$B$6*'Growth & Pricing Strategy'!$B$7*$Y14*'Growth & Pricing Strategy'!$B$14*(1-'Growth & Pricing Strategy'!$B$12)*(1-'Growth & Pricing Strategy'!$B$13),'Growth & Pricing Strategy'!$B$8*'Growth & Pricing Strategy'!$B$7*'Growth & Pricing Strategy'!$B$9*'Growth & Pricing Strategy'!$B$10/'Growth & Pricing Strategy'!$B$11)*AA14-'Growth & Pricing Strategy'!$B$27 -> #REF!
A15: Expected NC redemption | B15: ='NC Credits'!$B$8 -> 0.7 | C15: % | D15: Linked to NC Credits | U15: ₹299 all hours — CURRENT | V15: 299 | W15: 299 | X15: 199 | Y15: 0.45 | Z15: =$X15+MIN(MAX('Growth & Pricing Strategy'!$B$11,$B$5),$B$6)*$V15+MAX(MAX('Growth & Pricing Strategy'!$B$11,$B$5)-$B$6,0)*$W15 -> #REF! | AA15: =Z15/(1+$B$11)-'Growth & Pricing Strategy'!$B$11*$B$10-($B$13+Z15*$B$12+(Z15/(1+$B$11))*$B$18)+$B$16*$B$17 -> #REF! | AB15: =IF('Growth & Pricing Strategy'!$B$11=0,0,AA15/'Growth & Pricing Strategy'!$B$11) -> #REF! | AC15: =IF(AA15<=0,0,'Growth & Pricing Strategy'!$B$27/AA15) -> #REF! | AD15: =IF($B$19=0,0,AC15/$B$19) -> #REF! | AE15: =MIN('Growth & Pricing Strategy'!$B$6*'Growth & Pricing Strategy'!$B$7*$Y15*'Growth & Pricing Strategy'!$B$14*(1-'Growth & Pricing Strategy'!$B$12)*(1-'Growth & Pricing Strategy'!$B$13),'Growth & Pricing Strategy'!$B$8*'Growth & Pricing Strategy'!$B$7*'Growth & Pricing Strategy'!$B$9*'Growth & Pricing Strategy'!$B$10/'Growth & Pricing Strategy'!$B$11)*AA15-'Growth & Pricing Strategy'!$B$27 -> #REF!
A16: Case 2 transport mix | B16: ='Growth & Pricing Strategy'!$B$25 -> 0.6 | C16: % of journeys | D16: Linked to Growth & Pricing Strategy | U16: ₹349 all hours | V16: 349 | W16: 349 | X16: 199 | Y16: 0.4 | Z16: =$X16+MIN(MAX('Growth & Pricing Strategy'!$B$11,$B$5),$B$6)*$V16+MAX(MAX('Growth & Pricing Strategy'!$B$11,$B$5)-$B$6,0)*$W16 -> #REF! | AA16: =Z16/(1+$B$11)-'Growth & Pricing Strategy'!$B$11*$B$10-($B$13+Z16*$B$12+(Z16/(1+$B$11))*$B$18)+$B$16*$B$17 -> #REF! | AB16: =IF('Growth & Pricing Strategy'!$B$11=0,0,AA16/'Growth & Pricing Strategy'!$B$11) -> #REF! | AC16: =IF(AA16<=0,0,'Growth & Pricing Strategy'!$B$27/AA16) -> #REF! | AD16: =IF($B$19=0,0,AC16/$B$19) -> #REF! | AE16: =MIN('Growth & Pricing Strategy'!$B$6*'Growth & Pricing Strategy'!$B$7*$Y16*'Growth & Pricing Strategy'!$B$14*(1-'Growth & Pricing Strategy'!$B$12)*(1-'Growth & Pricing Strategy'!$B$13),'Growth & Pricing Strategy'!$B$8*'Growth & Pricing Strategy'!$B$7*'Growth & Pricing Strategy'!$B$9*'Growth & Pricing Strategy'!$B$10/'Growth & Pricing Strategy'!$B$11)*AA16-'Growth & Pricing Strategy'!$B$27 -> #REF!
A17: Transport contribution / Case 2 journey | B17: ='Growth & Pricing Strategy'!$B$26 -> 139 | C17: ₹ / Case 2 journey | D17: Linked to Growth & Pricing Strategy | U17: ₹399 all hours | V17: 399 | W17: 399 | X17: 199 | Y17: 0.37 | Z17: =$X17+MIN(MAX('Growth & Pricing Strategy'!$B$11,$B$5),$B$6)*$V17+MAX(MAX('Growth & Pricing Strategy'!$B$11,$B$5)-$B$6,0)*$W17 -> #REF! | AA17: =Z17/(1+$B$11)-'Growth & Pricing Strategy'!$B$11*$B$10-($B$13+Z17*$B$12+(Z17/(1+$B$11))*$B$18)+$B$16*$B$17 -> #REF! | AB17: =IF('Growth & Pricing Strategy'!$B$11=0,0,AA17/'Growth & Pricing Strategy'!$B$11) -> #REF! | AC17: =IF(AA17<=0,0,'Growth & Pricing Strategy'!$B$27/AA17) -> #REF! | AD17: =IF($B$19=0,0,AC17/$B$19) -> #REF! | AE17: =MIN('Growth & Pricing Strategy'!$B$6*'Growth & Pricing Strategy'!$B$7*$Y17*'Growth & Pricing Strategy'!$B$14*(1-'Growth & Pricing Strategy'!$B$12)*(1-'Growth & Pricing Strategy'!$B$13),'Growth & Pricing Strategy'!$B$8*'Growth & Pricing Strategy'!$B$7*'Growth & Pricing Strategy'!$B$9*'Growth & Pricing Strategy'!$B$10/'Growth & Pricing Strategy'!$B$11)*AA17-'Growth & Pricing Strategy'!$B$27 -> #REF!
A18: Expected NC loyalty cost rate | B18: ='NC Credits'!$B$15 -> 0.0413 | C18: % of eligible net service revenue | D18: Linked to NC Credits | U18: ₹449 all hours | V18: 449 | W18: 449 | X18: 199 | Y18: 0.35 | Z18: =$X18+MIN(MAX('Growth & Pricing Strategy'!$B$11,$B$5),$B$6)*$V18+MAX(MAX('Growth & Pricing Strategy'!$B$11,$B$5)-$B$6,0)*$W18 -> #REF! | AA18: =Z18/(1+$B$11)-'Growth & Pricing Strategy'!$B$11*$B$10-($B$13+Z18*$B$12+(Z18/(1+$B$11))*$B$18)+$B$16*$B$17 -> #REF! | AB18: =IF('Growth & Pricing Strategy'!$B$11=0,0,AA18/'Growth & Pricing Strategy'!$B$11) -> #REF! | AC18: =IF(AA18<=0,0,'Growth & Pricing Strategy'!$B$27/AA18) -> #REF! | AD18: =IF($B$19=0,0,AC18/$B$19) -> #REF! | AE18: =MIN('Growth & Pricing Strategy'!$B$6*'Growth & Pricing Strategy'!$B$7*$Y18*'Growth & Pricing Strategy'!$B$14*(1-'Growth & Pricing Strategy'!$B$12)*(1-'Growth & Pricing Strategy'!$B$13),'Growth & Pricing Strategy'!$B$8*'Growth & Pricing Strategy'!$B$7*'Growth & Pricing Strategy'!$B$9*'Growth & Pricing Strategy'!$B$10/'Growth & Pricing Strategy'!$B$11)*AA18-'Growth & Pricing Strategy'!$B$27 -> #REF!
A19: Operating days / month | B19: ='Growth & Pricing Strategy'!$B$7 -> 26 | C19: days | D19: Linked to Growth & Pricing Strategy
U21: BASE HOURLY ECONOMIC SAFETY CHECK — 1.00x SERVICE
A22: LEGACY SKU LABELS — NOT USED BY PRICING API | U22: Base gross revenue / hour | V22: =$B$7 -> 299
A23: SKU | B23: Customer Label | C23: Duration | D23: Pricing Rule | E23: Status | U23: Base net revenue / hour | V23: =V22/(1+$B$11) -> 253.38983
A24: NC-C2 | B24: Standard Care | C24: 2–4 hours | D24: ₹299/hour × service multiplier + ₹199 journey fee | E24: LEGACY | U24: Incremental Angel cost / hour | V24: =$B$10 -> 0
A25: NC-C4+ | B25: Extended Care | C25: >4 hours | D25: Same effective hourly rate after hour 4: ₹299 × service multiplier; + ₹199 fee | E25: LEGACY | U25: Target fully loaded Angel cost / hour | V25: ='Global Inputs'!$B$33 -> 103.5503
A26: NC-OD | B26: Overnight / Long Duration | C26: Overnight / very long | D26: Separate manual pricing — current hourly formula is not auto-quoted to customers | E26: Future / Manual Pricing | U26: Gateway cost / hour | V26: =V22*$B$12 -> 0
U27: NC expected cost / hour | V27: =V23*$B$18 -> 10.465
U28: Other incremental operating cost / hour | V28: 0
A29: LEGACY DURATION BREAKOUT — HISTORICAL REFERENCE ONLY | U29: Incremental Base-Hour Contribution | V29: =V23-V24-V26-V27-V28 -> 242.92483
A30: Actual Duration (hrs) | B30: Billable Hours | C30: Legacy First 4h Ref | D30: Legacy Additional Hours Ref | E30: Hourly Service Revenue | F30: Journey Fee | G30: Gross Customer Service Price | H30: GST Embedded | I30: Net Service Revenue | J30: Angel Cost | K30: Gateway Cost | L30: Other Variable Cost | M30: NC Expected Cost | N30: Total Variable Cost | O30: Contribution Before Transport | P30: Transport Contribution | Q30: Blended Contribution | R30: Contribution % | S30: Contribution / Angel Hour | U30: Fully Loaded Base-Hour Contribution | V30: =V23-V25-V26-V27-V28 -> 139.37453
A31: 2 | B31: =MAX(A31,$B$5) -> 2 | C31: =MIN(B31,$B$6) -> 2 | D31: =MAX(B31-$B$6,0) -> 0 | E31: =(C31+D31)*$B$7 -> 598 | F31: =$B$9 -> 199 | G31: =E31+F31 -> 797 | H31: =G31-G31/(1+$B$11) -> 121.57627 | I31: =G31/(1+$B$11) -> 675.42373 | J31: =A31*$B$10 -> 0 | K31: =G31*$B$12 -> 0 | L31: =$B$13 -> 56.5 | M31: =I31*$B$18 -> 27.895 | N31: =SUM(J31:M31) -> 84.395 | O31: =I31-N31 -> 591.02873 | P31: =$B$16*$B$17 -> 83.4 | Q31: =O31+P31 -> 674.42873 | R31: =IF((I31+$B$16*('Global Inputs'!$B$16/(1+'Global Inputs'!$B$17)))=0,0,Q31/(I31+$B$16*('Global Inputs'!$B$16/(1+'Global Inputs'!$B$17)))) -> 0.88180937 | S31: =IF(A31=0,0,Q31/A31) -> 337.21436 | U31: Economic status — fully loaded | V31: =IF(V30>0,"GREEN — economically positive",IF(V30=0,"AMBER — break-even","RED — uneconomic")) -> GREEN — economically positive
A32: 3 | B32: =MAX(A32,$B$5) -> 3 | C32: =MIN(B32,$B$6) -> 3 | D32: =MAX(B32-$B$6,0) -> 0 | E32: =(C32+D32)*$B$7 -> 897 | F32: =$B$9 -> 199 | G32: =E32+F32 -> 1096 | H32: =G32-G32/(1+$B$11) -> 167.18644 | I32: =G32/(1+$B$11) -> 928.81356 | J32: =A32*$B$10 -> 0 | K32: =G32*$B$12 -> 0 | L32: =$B$13 -> 56.5 | M32: =I32*$B$18 -> 38.36 | N32: =SUM(J32:M32) -> 94.86 | O32: =I32-N32 -> 833.95356 | P32: =$B$16*$B$17 -> 83.4 | Q32: =O32+P32 -> 917.35356 | R32: =IF((I32+$B$16*('Global Inputs'!$B$16/(1+'Global Inputs'!$B$17)))=0,0,Q32/(I32+$B$16*('Global Inputs'!$B$16/(1+'Global Inputs'!$B$17)))) -> 0.90094416 | S32: =IF(A32=0,0,Q32/A32) -> 305.78452 | U32: CFO note | V32: ₹299 is the master hourly rate. Service-specific economics depend on the multiplier; use the Pricing Engine multiplier safety table for low/high-multiplier services.
A33: 4 | B33: =MAX(A33,$B$5) -> 4 | C33: =MIN(B33,$B$6) -> 4 | D33: =MAX(B33-$B$6,0) -> 0 | E33: =(C33+D33)*$B$7 -> 1196 | F33: =$B$9 -> 199 | G33: =E33+F33 -> 1395 | H33: =G33-G33/(1+$B$11) -> 212.79661 | I33: =G33/(1+$B$11) -> 1182.2034 | J33: =A33*$B$10 -> 0 | K33: =G33*$B$12 -> 0 | L33: =$B$13 -> 56.5 | M33: =I33*$B$18 -> 48.825 | N33: =SUM(J33:M33) -> 105.325 | O33: =I33-N33 -> 1076.8784 | P33: =$B$16*$B$17 -> 83.4 | Q33: =O33+P33 -> 1160.2784 | R33: =IF((I33+$B$16*('Global Inputs'!$B$16/(1+'Global Inputs'!$B$17)))=0,0,Q33/(I33+$B$16*('Global Inputs'!$B$16/(1+'Global Inputs'!$B$17)))) -> 0.91245305 | S33: =IF(A33=0,0,Q33/A33) -> 290.0696 | U33: 4-hour price | V33: =G33 -> 1395 | W33: 1395 | X33: =IF(V33=W33,"PASS","CHECK") -> PASS
A34: 5 | B34: =MAX(A34,$B$5) -> 5 | C34: =MIN(B34,$B$6) -> 4 | D34: =MAX(B34-$B$6,0) -> 1 | E34: =(C34+D34)*$B$7 -> 1495 | F34: =$B$9 -> 199 | G34: =E34+F34 -> 1694 | H34: =G34-G34/(1+$B$11) -> 258.40678 | I34: =G34/(1+$B$11) -> 1435.5932 | J34: =A34*$B$10 -> 0 | K34: =G34*$B$12 -> 0 | L34: =$B$13 -> 56.5 | M34: =I34*$B$18 -> 59.29 | N34: =SUM(J34:M34) -> 115.79 | O34: =I34-N34 -> 1319.8032 | P34: =$B$16*$B$17 -> 83.4 | Q34: =O34+P34 -> 1403.2032 | R34: =IF((I34+$B$16*('Global Inputs'!$B$16/(1+'Global Inputs'!$B$17)))=0,0,Q34/(I34+$B$16*('Global Inputs'!$B$16/(1+'Global Inputs'!$B$17)))) -> 0.92013735 | S34: =IF(A34=0,0,Q34/A34) -> 280.64064 | U34: 5-hour price | V34: =G34 -> 1694 | W34: 1694 | X34: =IF(V34=W34,"PASS","CHECK") -> PASS
A35: 6 | B35: =MAX(A35,$B$5) -> 6 | C35: =MIN(B35,$B$6) -> 4 | D35: =MAX(B35-$B$6,0) -> 2 | E35: =(C35+D35)*$B$7 -> 1794 | F35: =$B$9 -> 199 | G35: =E35+F35 -> 1993 | H35: =G35-G35/(1+$B$11) -> 304.01695 | I35: =G35/(1+$B$11) -> 1688.9831 | J35: =A35*$B$10 -> 0 | K35: =G35*$B$12 -> 0 | L35: =$B$13 -> 56.5 | M35: =I35*$B$18 -> 69.755 | N35: =SUM(J35:M35) -> 126.255 | O35: =I35-N35 -> 1562.7281 | P35: =$B$16*$B$17 -> 83.4 | Q35: =O35+P35 -> 1646.1281 | R35: =IF((I35+$B$16*('Global Inputs'!$B$16/(1+'Global Inputs'!$B$17)))=0,0,Q35/(I35+$B$16*('Global Inputs'!$B$16/(1+'Global Inputs'!$B$17)))) -> 0.92563188 | S35: =IF(A35=0,0,Q35/A35) -> 274.35468 | U35: 6-hour price | V35: =G35 -> 1993 | W35: 1993 | X35: =IF(V35=W35,"PASS","CHECK") -> PASS
A36: 7 | B36: =MAX(A36,$B$5) -> 7 | C36: =MIN(B36,$B$6) -> 4 | D36: =MAX(B36-$B$6,0) -> 3 | E36: =(C36+D36)*$B$7 -> 2093 | F36: =$B$9 -> 199 | G36: =E36+F36 -> 2292 | H36: =G36-G36/(1+$B$11) -> 349.62712 | I36: =G36/(1+$B$11) -> 1942.3729 | J36: =A36*$B$10 -> 0 | K36: =G36*$B$12 -> 0 | L36: =$B$13 -> 56.5 | M36: =I36*$B$18 -> 80.22 | N36: =SUM(J36:M36) -> 136.72 | O36: =I36-N36 -> 1805.6529 | P36: =$B$16*$B$17 -> 83.4 | Q36: =O36+P36 -> 1889.0529 | R36: =IF((I36+$B$16*('Global Inputs'!$B$16/(1+'Global Inputs'!$B$17)))=0,0,Q36/(I36+$B$16*('Global Inputs'!$B$16/(1+'Global Inputs'!$B$17)))) -> 0.92975593 | S36: =IF(A36=0,0,Q36/A36) -> 269.8647 | U36: 8-hour price | V36: =G37 -> 2591 | W36: 2591 | X36: =IF(V36=W36,"PASS","CHECK") -> PASS
A37: 8 | B37: =MAX(A37,$B$5) -> 8 | C37: =MIN(B37,$B$6) -> 4 | D37: =MAX(B37-$B$6,0) -> 4 | E37: =(C37+D37)*$B$7 -> 2392 | F37: =$B$9 -> 199 | G37: =E37+F37 -> 2591 | H37: =G37-G37/(1+$B$11) -> 395.23729 | I37: =G37/(1+$B$11) -> 2195.7627 | J37: =A37*$B$10 -> 0 | K37: =G37*$B$12 -> 0 | L37: =$B$13 -> 56.5 | M37: =I37*$B$18 -> 90.685 | N37: =SUM(J37:M37) -> 147.185 | O37: =I37-N37 -> 2048.5777 | P37: =$B$16*$B$17 -> 83.4 | Q37: =O37+P37 -> 2131.9777 | R37: =IF((I37+$B$16*('Global Inputs'!$B$16/(1+'Global Inputs'!$B$17)))=0,0,Q37/(I37+$B$16*('Global Inputs'!$B$16/(1+'Global Inputs'!$B$17)))) -> 0.93296539 | S37: =IF(A37=0,0,Q37/A37) -> 266.49721
A38: 10 | B38: =MAX(A38,$B$5) -> 10 | C38: =MIN(B38,$B$6) -> 4 | D38: =MAX(B38-$B$6,0) -> 6 | E38: =(C38+D38)*$B$7 -> 2990 | F38: =$B$9 -> 199 | G38: =E38+F38 -> 3189 | H38: =G38-G38/(1+$B$11) -> 486.45763 | I38: =G38/(1+$B$11) -> 2702.5424 | J38: =A38*$B$10 -> 0 | K38: =G38*$B$12 -> 0 | L38: =$B$13 -> 56.5 | M38: =I38*$B$18 -> 111.615 | N38: =SUM(J38:M38) -> 168.115 | O38: =I38-N38 -> 2534.4274 | P38: =$B$16*$B$17 -> 83.4 | Q38: =O38+P38 -> 2617.8274 | R38: =IF((I38+$B$16*('Global Inputs'!$B$16/(1+'Global Inputs'!$B$17)))=0,0,Q38/(I38+$B$16*('Global Inputs'!$B$16/(1+'Global Inputs'!$B$17)))) -> 0.93763661 | S38: =IF(A38=0,0,Q38/A38) -> 261.78274
A39: 12 | B39: =MAX(A39,$B$5) -> 12 | C39: =MIN(B39,$B$6) -> 4 | D39: =MAX(B39-$B$6,0) -> 8 | E39: =(C39+D39)*$B$7 -> 3588 | F39: =$B$9 -> 199 | G39: =E39+F39 -> 3787 | H39: =G39-G39/(1+$B$11) -> 577.67797 | I39: =G39/(1+$B$11) -> 3209.322 | J39: =A39*$B$10 -> 0 | K39: =G39*$B$12 -> 0 | L39: =$B$13 -> 56.5 | M39: =I39*$B$18 -> 132.545 | N39: =SUM(J39:M39) -> 189.045 | O39: =I39-N39 -> 3020.277 | P39: =$B$16*$B$17 -> 83.4 | Q39: =O39+P39 -> 3103.677 | R39: =IF((I39+$B$16*('Global Inputs'!$B$16/(1+'Global Inputs'!$B$17)))=0,0,Q39/(I39+$B$16*('Global Inputs'!$B$16/(1+'Global Inputs'!$B$17)))) -> 0.94087256 | S39: =IF(A39=0,0,Q39/A39) -> 258.63975

Sheet Pricing Engine
A1: NivrāaCare — Dynamic Pricing Engine | P1: Service Selector Source | Q1: Hour Options
A2: Select service, hours and transport. The engine calculates the customer quote, detailed price build-up and internal CFO economics from the master model. | P2: ='Service Master'!B5 -> Hospital Visit | Q2: 1
P3: ='Service Master'!B6 -> Hospital Visit — Concierge at Hospital | Q3: 1.5
A4: INPUT — QUOTE SETUP | F4: AUTOMATIC SERVICE & PRICING LOOKUP | J4: MODEL LEGEND | P4: ='Service Master'!B7 -> Clinic Visit | Q4: 2
A5: Quote ID | B5: NC-Q-0001 | C5: Optional / editable | F5: Service Category | G5: =INDEX('Service Economics'!$B$5:$B$34,MATCH($B$10,'Service Economics'!$A$5:$A$34,0)) -> Medical Visit | J5: Blue text / yellow fill | M5: Editable input | P5: ='Service Master'!B8 -> Diagnostic Center Visit | Q5: 2.5
A6: Quote Date | B6: =TODAY() -> 46297 | C6: Auto-filled; editable if needed | F6: Default Duration | G6: =INDEX('Service Economics'!$C$5:$C$34,MATCH($B$10,'Service Economics'!$A$5:$A$34,0)) -> 4 | J6: Green text | M6: Cross-sheet link | P6: ='Service Master'!B9 -> Health Check-up Concierge | Q6: 3
A7: Customer Name | C7: Optional | F7: Service Multiplier | G7: =INDEX('Service Economics'!$D$5:$D$34,MATCH($B$10,'Service Economics'!$A$5:$A$34,0)) -> 1 | J7: Black text | M7: Same-sheet formula | P7: ='Service Master'!B10 -> Hospital Admission Concierge | Q7: 3.5
A8: Patient Name | C8: Optional | F8: No. of Angels | G8: =INDEX('Service Economics'!$F$5:$F$34,MATCH($B$10,'Service Economics'!$A$5:$A$34,0)) -> 1 | J8: Default Cab Cost | M8: ='Global Inputs'!$B$15 -> 500 | P8: ='Service Master'!B11 -> Hospital Discharge Concierge | Q8: 4
A9: Created By | C9: Optional | F9: Pricing Mode / SKU | G9: =INDEX('Service Economics'!$AH$5:$AH$34,MATCH($B$10,'Service Economics'!$A$5:$A$34,0)) -> AUTO | J9: Expected NC Loyalty Cost Rate | M9: ='NC Credits'!$B$15 -> 0.0413 | P9: ='Service Master'!B12 -> Overnight Hospital Concierge | Q9: 4.5
A10: Select Service | B10: Hospital Visit | C10: Choose from active service catalogue | F10: Recurring Potential | G10: =INDEX('Service Economics'!$AQ$5:$AQ$34,MATCH($B$10,'Service Economics'!$A$5:$A$34,0)) -> 5 | P10: ='Service Master'!B13 -> Multi-Day Hospital Concierge (per 12h shift) | Q10: 5
A11: Selected Hours | B11: 5 | C11: 1.0 to 24.0 hours in 0.5-hour increments | F11: Multiplier Reason | G11: =INDEX('Service Economics'!$AR$5:$AR$34,MATCH($B$10,'Service Economics'!$A$5:$A$34,0)) -> Full journey: home → facility → return / safe handover | P11: ='Service Master'!B14 -> Day Surgery / Procedure Concierge | Q11: 5.5
A12: Transport Required? | B12: Patient Arranges Transport | C12: Choose who arranges transport | F12: Minimum Booking Hours | G12: ='MVP1 Pricing & SKU'!$B$5 -> 2 | P12: ='Service Master'!B15 -> Pre-Surgery Concierge | Q12: 6
A13: Estimated Cab Fare | B13: ='Global Pricing Config'!$B$10 -> 500 | C13: Defaults to Global Inputs; can be overwritten | F13: Base Hourly Rate | G13: ='Global Pricing Config'!$B$5 -> 299 | P13: ='Service Master'!B16 -> Post-Surgery Follow-up | Q13: 6.5
A14: Founder Price Override (₹) | C14: Leave blank to use calculated price | F14: Effective Service Rate | G14: ='Global Pricing Config'!$B$5*$G$7 -> 299 | P14: ='Service Master'!B17 -> Dialysis Visit Concierge | Q14: 7
A15: Override Reason | C15: Launch offer / corporate agreement / service recovery / founder-approved discount | F15: Care Coordination Fee | G15: ='Global Pricing Config'!$B$7 -> 199 | P15: ='Service Master'!B18 -> Chemotherapy Visit Concierge | Q15: 7.5
A16: NivrāaCredit Discount (₹) | B16: - | C16: Rupee discount supplied by the app/backend after converting redeemed NivrāaCredits. 1 NivrāaCredit = current configured ₹ value. | F16: Care GST | G16: ='Global Pricing Config'!$B$8 -> 0.18 | P16: ='Service Master'!B19 -> Radiation Therapy Concierge | Q16: 8
A17: =IF(IFERROR(ISNUMBER(SEARCH("Manual",$G$9)),FALSE),"MANUAL PRICING REQUIRED","AUTO PRICING ACTIVE") -> AUTO PRICING ACTIVE | F17: Transport Coordination Fee | G17: ='Global Pricing Config'!$B$9 -> 149 | P17: ='Service Master'!B20 -> Physiotherapy / Rehab Visit | Q17: 8.5
F18: Default Cab Estimate | G18: ='Global Pricing Config'!$B$10 -> 500 | P18: ='Service Master'!B21 -> Chronic Care Follow-up | Q18: 9
F19: Service Code | G19: =INDEX('Service Master'!$A$5:$A$34,MATCH($B$10,'Service Master'!$B$5:$B$34,0)) -> HOSPITAL_VISIT | P19: ='Service Master'!B22 -> NRI Parent Medical Concierge | Q19: 9.5
A20: NIVRĀACARE JOURNEY ESTIMATE | J20: PRINTABLE CUSTOMER QUOTE | K20: PRINTABLE CUSTOMER QUOTE | L20: PRINTABLE CUSTOMER QUOTE | M20: PRINTABLE CUSTOMER QUOTE | N20: PRINTABLE CUSTOMER QUOTE | P20: ='Service Master'!B23 -> Second Opinion Concierge | Q20: 10
A21: Service | D21: =$B$10 -> Hospital Visit | J21: Quote ID | L21: =$B$5 -> NC-Q-0001 | P21: ='Service Master'!B24 -> Teleconsultation Concierge | Q21: 10.5
A22: Duration | D22: =TEXT($B$11,"0.0")&" hrs" -> 5.0 hrs | J22: Quote Date | L22: =TEXT($B$6,"dd-mmm-yyyy") -> 02-Oct-2026 | P22: ='Service Master'!B25 -> Medical Records Concierge | Q22: 11
A23: NivrāaCare Service Charge | D23: =$B$39 -> 1495 | J23: Customer | L23: =IF($B$7="","—",$B$7) -> — | P23: ='Service Master'!B26 -> Insurance / TPA Desk Concierge | Q23: 11.5
A24: Care Coordination Fee | D24: =$B$40 -> 199 | J24: Patient | L24: =IF($B$8="","—",$B$8) -> — | P24: ='Service Master'!B27 -> Hospital Transfer Concierge | Q24: 12
A25: Care Charge Before Credits | D25: =$B$42 -> 1694 | J25: Created By | L25: =IF($B$9="","—",$B$9) -> — | P25: ='Service Master'!B28 -> Rehab / Nursing Facility Transfer | Q25: 12.5
A26: NivrāaCredit Discount | D26: =IF(ISNUMBER($B$47),-$B$47,"") -> 0 | J26: Service | L26: =$B$10 -> Hospital Visit | P26: ='Service Master'!B29 -> 24×7 Urgent Care Coordination | Q26: 13
A27: Care Charge After Credits | D27: =$B$48 -> 1694 | J27: Estimated Duration | L27: =TEXT($B$11,"0.0")&" hours" -> 5.0 hours | P27: ='Service Master'!B30 -> Doctor-at-Home Coordination | Q27: 13.5
A28: Third-Party Cab Estimate | D28: =IF($B$12="NivrāaCare Arranges Transport",$B$13,0) -> 0 | P28: ='Service Master'!B31 -> Nurse-at-Home Coordination | Q28: 14
A29: Transport Coordination Fee | D29: =IF($B$12="NivrāaCare Arranges Transport",'Global Pricing Config'!$B$9,0) -> 0 | J29: PRICE SUMMARY | P29: ='Service Master'!B32 -> Medical Tourism — Concierge Package (24 HR Basis) | Q29: 14.5
A30: Transport Total | D30: =D28+D29 -> 0 | J30: Care Service Before Credits | M30: =$B$42 -> 1694 | P30: ='Service Master'!B33 -> Pharmacy / Prescription Coordination | Q30: 15
A31: Total Customer Payable | D31: =D27+D30 -> 1694 | J31: NivrāaCredit Discount Applied | M31: =IF(ISNUMBER($B$47),-$B$47,"") -> 0 | P31: ='Service Master'!B34 -> Family Medical Update Concierge | Q31: 15.5
A32: NIVRĀACREDITS EARNED | D32: =$M$49 -> 84 | J32: Care Charge After Credits | M32: =$B$48 -> 1694 | Q32: 16
A33: ="Earn "&ROUND('NC Credits'!$B$6*100/'NC Credits'!$B$7,2)&" NivrāaCredits per ₹100 of eligible NivrāaCare care-service spend. Credits are added after successful journey completion." -> Earn 5 NivrāaCredits per ₹100 of eligible NivrāaCare care-service spend. Credits are added after successful journey completion. | J33: Estimated Third-Party Cab | M33: =IF($B$12="NivrāaCare Arranges Transport",$B$13,0) -> 0 | Q33: 16.5
J34: Transport Coordination | M34: =IF($B$12="NivrāaCare Arranges Transport",'Global Pricing Config'!$B$9,0) -> 0 | Q34: 17
J35: Transport Total | M35: =$B$51 -> 0 | Q35: 17.5
A36: INTERNAL PRICING CALCULATION — NOT CUSTOMER FACING | J36: TOTAL PAYABLE | M36: =$B$52 -> 1694 | Q36: 18
A37: Pricing Component | B37: Value | C37: Calculation | D37: Internal Explanation | F37: FOUNDER FORMULA | J37: NivrāaCredits Earned | M37: =$M$49 -> 84 | Q37: 18.5
A38: Selected Hours | B38: =$B$11 -> 5 | C38: Booking input | D38: Actual requested journey duration. | F38: Billable Hours | G38: =MAX($B$11,'Global Pricing Config'!$B$6) -> 5 | Q38: 19
A39: NivrāaCare Service Charge | B39: =$G$38*$G$41 -> 1495 | C39: Billable Hours × Effective Service Rate | D39: Hourly service charge before the fixed coordination fee. | F39: Base Hourly Rate | G39: ='Global Pricing Config'!$B$5 -> 299 | J39: ="Transport charges are estimates and may vary based on actual third-party cab fare. " &"Additional service time is billed at the selected effective service rate. " &"Credits are added after successful journey completion. Current earn rate: " &ROUND('NC Credits'!$B$6*100/'NC Credits'!$B$7,2) & " NivrāaCredits per ₹100 eligible care-service spend." -> Transport charges are estimates and may vary based on actual third-party cab fare. Additional service time is billed at the selected effective service rate. Credits are added after successful journey completion. Current earn rate: 5 NivrāaCredits per ₹100 eligible care-service spend. | Q39: 19.5
A40: Care Coordination Fee | B40: ='Global Pricing Config'!$B$7 -> 199 | C40: Master pricing configuration | D40: Fixed once per journey. | F40: Service Multiplier | G40: =$G$7 -> 1 | Q40: 20
A41: Standard Calculated Care Price | B41: =IF(IFERROR(ISNUMBER(SEARCH("Manual",$G$42)),FALSE),"",B39+B40) -> 1694 | C41: Service Charge + Coordination Fee | D41: Standard price before override or Credit redemption. | F41: Effective Service Rate | G41: =G39*G40 -> 299 | J41: =IF(IFERROR(ISNUMBER(SEARCH("Manual",$G$9)),FALSE),"MANUAL PRICING REQUIRED — customer total will appear only after an approved override is entered.","Quote generated from the current NivrāaCare master pricing model.") -> Quote generated from the current NivrāaCare master pricing model. | Q41: 20.5
A42: Care Charge Before Credits | B42: =IF(ISNUMBER($B$14),$B$14,B41) -> 1694 | C42: Approved override if present; otherwise standard price | D42: Price used before redeemed NivrāaCredits. | F42: Pricing Mode | G42: =$G$9 -> AUTO | Q42: 21
A43: Requested NivrāaCredit Discount | B43: =IF(NOT(ISNUMBER(B42)),"",$B$16) -> - | C43: Input from app/backend | D43: Requested rupee discount after app converts Credits to ₹. | F43: Pricing Status | G43: =IF(IFERROR(ISNUMBER(SEARCH("Manual",G42)),FALSE),"MANUAL PRICING REQUIRED","AUTO PRICING") -> AUTO PRICING | Q43: 21.5
A44: Maximum Allowed Credit Discount | B44: =IF(NOT(ISNUMBER(B42)),"",B42*'Global Pricing Config'!$B$14) -> 338.8 | C44: Care Price × Max Redemption % | D44: Founder-configurable redemption cap. | J44: NIVRĀACREDITS — CURRENT BILL | K44: NIVRĀACREDITS — CURRENT BILL | L44: NIVRĀACREDITS — CURRENT BILL | M44: NIVRĀACREDITS — CURRENT BILL | N44: NIVRĀACREDITS — CURRENT BILL | Q44: 22
A45: NivrāaCredit Discount Applied | B45: =IF(NOT(ISNUMBER(B42)),"",MIN(MAX(B43,0),MAX(B44,0),MAX(B42,0))) -> 0 | C45: MIN(Requested, Max Allowed, Care Price) | D45: Actual Credit discount used in billing. | F45: ="Care Price = "&TEXT($G$38,"0.0")&" hrs × ₹"&TEXT($G$39,"#,##0")&" × "&TEXT($G$40,"0.00")&"x + ₹"&TEXT($B$40,"#,##0")&" = ₹"&TEXT($B$41,"#,##0") -> Care Price = 5.0 hrs × ₹299 × 1.00x + ₹199 = ₹1,694 | J45: Eligible Credit-Earning Spend | M45: =IF(NOT(ISNUMBER($B$48)),"",$B$48) -> 1694 | Q45: 22.5
A46: Final Care Charge After Credits | B46: =IF(NOT(ISNUMBER(B42)),"",MAX(B42-B45,0)) -> 1694 | C46: Care Price Before Credits − Discount Applied | D46: Eligible care-service amount actually paid. | J46: Current NivrāaCredit Earn Rate | M46: ='NC Credits'!$B$6 -> 0.05 | Q46: 23
A47: Credit Discount Applied — API Output | B47: =B45 -> 0 | C47: API response field | D47: Explicit API output. | J47: Credits Earned per ₹100 | M47: =100*'NC Credits'!$B$6/'NC Credits'!$B$7 -> 5 | Q47: 23.5
A48: Final Care Charge — API Output | B48: =B46 -> 1694 | C48: API response field | D48: Final customer care amount after Credits. | J48: Raw Credits Earned | M48: =IF(NOT(ISNUMBER($B$48)),"",$B$48*'NC Credits'!$B$6/'NC Credits'!$B$7*'NC Credits'!$B$5) -> 84.7 | Q48: 24
A49: GST Embedded in Final Care Charge | B49: =IF(NOT(ISNUMBER(B48)),"",B48-B50) -> 258.40678 | C49: Final Care Charge − Net Care Revenue | D49: Internal tax view. | J49: NivrāaCredits Earned on This Bill | M49: =IF(NOT(ISNUMBER(M48)),"",FLOOR(M48,1)) -> 84
A50: Net Care Revenue | B50: =IF(NOT(ISNUMBER(B48)),"",B48/(1+'Global Pricing Config'!$B$8)) -> 1435.5932 | C50: Final Care Charge ÷ (1 + GST) | D50: Internal revenue view. | J50: Loyalty Status | M50: =IF('NC Credits'!$B$5=0,"CREDIT EARNING OFF",IF(NOT(ISNUMBER($B$48)),"PENDING FINAL PRICE",IF($B$48<=0,"NO ELIGIBLE SPEND","CREDIT EARNING ACTIVE"))) -> CREDIT EARNING ACTIVE
A51: Transport Total | B51: =IF($B$12="NivrāaCare Arranges Transport",$B$13+'Global Pricing Config'!$B$9,0) -> 0 | C51: Cab Estimate + Transport Coordination Fee | D51: Transport is separate from care pricing.
A52: Total Customer Payable | B52: =IF(NOT(ISNUMBER(B48)),"",B48+B51) -> 1694 | C52: Final Care Charge + Transport Total | D52: Final customer amount. | J52: INTERNAL LOYALTY ECONOMICS — NOT CUSTOMER FACING
A53: INTERNAL CFO VIEW — NOT CUSTOMER FACING | J53: Face Value of Credits Issued | M53: =IF(NOT(ISNUMBER(M49)),"",M49*'NC Credits'!$B$7) -> 84
A54: CFO Metric | B54: Amount / Rate | C54: Formula / Interpretation | E54: PRICE OVERRIDE & DISCOUNT SAFETY | J54: Expected Redemption Rate | M54: ='NC Credits'!$B$8 -> 0.7
A55: Gross Customer Billings | B55: =IF(NOT(ISNUMBER($B$52)),"",$B$52) -> 1694 | C55: Final care charge after Credits + transport customer collection. | E55: Standard Calculated Price | H55: =$B$41 -> 1694 | J55: Expected Loyalty Cost | M55: =IF(NOT(ISNUMBER(M53)),"",M53*M54) -> 58.8
A56: GST — Final Care Service | B56: =IF(NOT(ISNUMBER($B$49)),"",$B$49) -> 258.40678 | C56: GST embedded in final care charge after NivrāaCredit redemption. | E56: Override Price | H56: =IF(ISNUMBER($B$14),$B$14,"") | J56: Loyalty Cost % of Net Care Revenue | M56: =IFERROR(M55/($B$50),0) -> 0.040958678
A57: Net Care Revenue After Credits | B57: =IF(NOT(ISNUMBER($B$50)),"",$B$50) -> 1435.5932 | C57: Care revenue after NivrāaCredit discount and GST removal. | E57: Discount / Premium | H57: =IF(ISNUMBER($B$14),$B$14-$B$41,0) -> 0 | J57: Redemption Status | M57: =IF(NOT(ISNUMBER($B$42)),"PENDING FINAL PRICE",IF($B$43<=0,"NO CREDIT REDEMPTION",IF($B$43>$B$45,"CREDIT DISCOUNT CAPPED","DISCOUNT APPLIED AS REQUESTED"))) -> CREDIT DISCOUNT CAPPED
A58: Transport Coordination Revenue | B58: =IF($B$12="NivrāaCare Arranges Transport",'Global Inputs'!$B$16/(1+'Global Inputs'!$B$17),0) -> 0 | C58: Coordination fee net of any applicable coordination-fee GST. | E58: Discount / Premium % | H58: =IF(OR(NOT(ISNUMBER($B$14)),$B$41=0),0,$B$14/$B$41-1) -> 0
A59: Pass-through Cab Amount | B59: =IF($B$12="NivrāaCare Arranges Transport",$B$13,0) -> 0 | C59: Third-party cab reimbursement; not operating revenue. | E59: Contribution Before Override | H59: =IF(NOT(ISNUMBER($B$41)),"",($B$41/(1+$G$16)+IF($B$12="NivrāaCare Arranges Transport",'Global Inputs'!$B$16/(1+'Global Inputs'!$B$17),0))-(($B$41+IF($B$12="NivrāaCare Arranges Transport",$B$13+'Global Inputs'!$B$16,0))*'Global Inputs'!$B$8+'Global Inputs'!$B$9+'Global Inputs'!$B$10+'Global Inputs'!$B$11+'Global Inputs'!$B$12+'Global Inputs'!$B$13+'Global Inputs'!$B$14+FLOOR($B$41*'NC Credits'!$B$6/'NC Credits'!$B$7,1)*'NC Credits'!$B$7*'NC Credits'!$B$8+IFERROR($B$11*$G$8*INDEX('Service Economics'!$AI$5:$AI$34,MATCH($B$10,'Service Economics'!$A$5:$A$34,0)),0)+IF($B$12="NivrāaCare Arranges Transport",'Global Inputs'!$B$18,0))) -> 1320.2932 | J59: =IF(M49="","Credits will be calculated after a valid final care price is available.","You will earn "&TEXT(M49,"0")&" NivrāaCredits on this journey. Credits are added after successful journey completion.") -> You will earn 84 NivrāaCredits on this journey. Credits are added after successful journey completion.
A60: Net Operating Revenue | B60: =B57+B58 -> 1435.5932 | C60: Net care revenue + net transport coordination revenue. | E60: Contribution After Override + Credits | H60: =$B$71 -> 1320.2932
A61: Payment Gateway Cost | B61: =IF(B55="","",B55*'Global Inputs'!$B$8+'Global Inputs'!$B$9) -> 0 | C61: Gateway fee on collected customer billings + fixed transaction fee. | E61: Contribution Impact vs Standard | H61: =H60-H59 -> 0
A62: Ops / Support Allocation | B62: ='Global Inputs'!$B$10 -> 10 | C62: Per-journey operating/support allocation. | E62: Margin Before Override | H62: =IFERROR(H59/($B$41/(1+$G$16)+IF($B$12="NivrāaCare Arranges Transport",'Global Inputs'!$B$16/(1+'Global Inputs'!$B$17),0)),0) -> 0.91968477
A63: Insurance / Risk Reserve | B63: ='Global Inputs'!$B$11 -> 10 | C63: Per-journey risk reserve. | E63: Margin After Override + Credits | H63: =$B$72 -> 0.91968477
A64: Communication Cost | B64: ='Global Inputs'!$B$12 -> 0.5 | C64: WhatsApp/SMS/communication allocation. | E64: Margin Impact vs Standard | H64: =H63-H62 -> 0
A65: BGV + Training Allocation | B65: ='Global Inputs'!$B$13 -> 0 | C65: Per-journey BGV/training allocation. | E65: Discount Safety | H65: =IF(IFERROR(ISNUMBER(SEARCH("Manual",$G$42)),FALSE),"MANUAL",IF(NOT(ISNUMBER($B$14)),"STANDARD",IF($B$75<0,"RED",IF($B$76<20%,"AMBER","GREEN")))) -> STANDARD
A66: Refund / Recovery Reserve | B66: ='Global Inputs'!$B$14 -> 36 | C66: Expected service recovery reserve.
A67: Expected Future NivrāaCredit Cost | B67: =$M$55 -> 58.8 | C67: Credits earned on this bill × ₹ value per Credit × expected redemption rate. | E67: PRICING HEALTH CHECK
A68: Incremental Angel Cost | B68: =IFERROR($B$11*$G$8*INDEX('Service Economics'!$AI$5:$AI$34,MATCH($B$10,'Service Economics'!$A$5:$A$34,0)),0) -> 0 | C68: Selected hours × Angels × incremental Angel cost/hour. | E68: Service Multiplier | H68: =$G$40 -> 1
A69: Transport Ops Cost | B69: =IF($B$12="NivrāaCare Arranges Transport",'Global Inputs'!$B$18,0) -> 0 | C69: Additional booking/coordination operations cost. | E69: Incremental Contribution / Hour | H69: =IFERROR($B$71/$B$11,0) -> 264.05864
A70: Total Variable Delivery Cost | B70: =SUM(B61:B69) -> 115.3 | C70: Sum of all variable delivery costs. | E70: Fully Loaded Contribution / Hour | H70: =IFERROR($B$75/$B$11,0) -> 264.05864
A71: Contribution Before Fixed Costs | B71: =IF(B60="","",B60-B70) -> 1320.2932 | C71: Net operating revenue − variable delivery cost. | E71: Contribution Margin | H71: =$B$72 -> 0.91968477
A72: Contribution Margin | B72: =IFERROR(B71/B60,0) -> 0.91968477 | C72: Contribution before fixed costs ÷ net operating revenue. | E72: NC Credits Cost | H72: =$B$67 -> 58.8
A73: Contribution / Service Hour | B73: =IFERROR(B71/$B$11,0) -> 264.05864 | C73: Contribution before fixed costs ÷ selected hours. | E73: Fully Loaded Angel Cost | H73: =$B$74 -> 0
A74: Fully Loaded Angel Payroll | B74: =IFERROR($B$11*$G$8*#REF!,0) -> 0 | C74: Selected hours × Angels × current payroll cost/productive hour. | E74: Transport Uplift | H74: =IF($B$12="NivrāaCare Arranges Transport",$B$58-$B$69-($B$51*'Global Inputs'!$B$8),0) -> 0
A75: Fully Loaded Contribution | B75: =B71-B74 -> 1320.2932 | C75: Contribution before fixed costs − fully loaded Angel payroll allocation. | E75: Pricing Status | H75: =IF(IFERROR(ISNUMBER(SEARCH("Manual",$G$42)),FALSE),"MANUAL",IF($B$75<0,"RED",IF(OR($B$76<20%,IFERROR($B$75/$B$11,0)<50),"AMBER","GREEN"))) -> GREEN
A76: Fully Loaded Contribution Margin | B76: =IFERROR(B75/B60,0) -> 0.91968477 | C76: Fully loaded contribution ÷ net operating revenue.
A78: SERVICE MULTIPLIER SAFETY ANALYSIS — 5-HOUR REFERENCE JOURNEY
A79: Shows how service multipliers change the effective customer rate and unit economics. Reference economics use a 5-hour patient-arranged-transport journey, 1 Angel, current variable-cost assumptions and current fully loaded Angel payroll cost.
A80: Multiplier | B80: Effective Hourly Rate | C80: 4h Care Price | D80: 5h Care Price | E80: 6h Care Price | F80: 5h Contribution / Hr | G80: 5h Fully Loaded Contribution / Hr | H80: Contribution Margin | I80: Financial Status
A81: 0.6 | B81: =$G$14*A81 -> 179.4 | C81: =$G$16+4*$G$14*A81 -> 717.78 | D81: =$G$16+5*$G$14*A81 -> 897.18 | E81: =$G$16+6*$G$14*A81 -> 1076.58 | F81: =((D81/(1+$G$17))-(D81*'Global Inputs'!$B$8+'Global Inputs'!$B$9+SUM('Global Inputs'!$B$10:$B$14)+(D81/(1+$G$17))*$M$9+5*$G$8*INDEX('Service Economics'!$AI$5:$AI$34,MATCH($B$10,'Service Economics'!$A$5:$A$34,0))))/5 -> -10.153165 | G81: =F81-(#REF!*$G$8) -> #REF! | H81: =IFERROR((F81*5)/(D81/(1+$G$17)),0) -> -8.487565 | I81: =IF(G81<0,"RED",IF(OR(G81<50,H81<20%),"AMBER","GREEN")) -> #REF!
A82: 0.65 | B82: =$G$14*A82 -> 194.35 | C82: =$G$16+4*$G$14*A82 -> 777.58 | D82: =$G$16+5*$G$14*A82 -> 971.93 | E82: =$G$16+6*$G$14*A82 -> 1166.28 | F82: =((D82/(1+$G$17))-(D82*'Global Inputs'!$B$8+'Global Inputs'!$B$9+SUM('Global Inputs'!$B$10:$B$14)+(D82/(1+$G$17))*$M$9+5*$G$8*INDEX('Service Economics'!$AI$5:$AI$34,MATCH($B$10,'Service Economics'!$A$5:$A$34,0))))/5 -> -10.057614 | G82: =F82-(#REF!*$G$8) -> #REF! | H82: =IFERROR((F82*5)/(D82/(1+$G$17)),0) -> -7.7610638 | I82: =IF(G82<0,"RED",IF(OR(G82<50,H82<20%),"AMBER","GREEN")) -> #REF!
A83: 0.7 | B83: =$G$14*A83 -> 209.3 | C83: =$G$16+4*$G$14*A83 -> 837.38 | D83: =$G$16+5*$G$14*A83 -> 1046.68 | E83: =$G$16+6*$G$14*A83 -> 1255.98 | F83: =((D83/(1+$G$17))-(D83*'Global Inputs'!$B$8+'Global Inputs'!$B$9+SUM('Global Inputs'!$B$10:$B$14)+(D83/(1+$G$17))*$M$9+5*$G$8*INDEX('Service Economics'!$AI$5:$AI$34,MATCH($B$10,'Service Economics'!$A$5:$A$34,0))))/5 -> -9.9620638 | G83: =F83-(#REF!*$G$8) -> #REF! | H83: =IFERROR((F83*5)/(D83/(1+$G$17)),0) -> -7.1383306 | I83: =IF(G83<0,"RED",IF(OR(G83<50,H83<20%),"AMBER","GREEN")) -> #REF!
A84: 0.75 | B84: =$G$14*A84 -> 224.25 | C84: =$G$16+4*$G$14*A84 -> 897.18 | D84: =$G$16+5*$G$14*A84 -> 1121.43 | E84: =$G$16+6*$G$14*A84 -> 1345.68 | F84: =((D84/(1+$G$17))-(D84*'Global Inputs'!$B$8+'Global Inputs'!$B$9+SUM('Global Inputs'!$B$10:$B$14)+(D84/(1+$G$17))*$M$9+5*$G$8*INDEX('Service Economics'!$AI$5:$AI$34,MATCH($B$10,'Service Economics'!$A$5:$A$34,0))))/5 -> -9.8665134 | G84: =F84-(#REF!*$G$8) -> #REF! | H84: =IFERROR((F84*5)/(D84/(1+$G$17)),0) -> -6.5986152 | I84: =IF(G84<0,"RED",IF(OR(G84<50,H84<20%),"AMBER","GREEN")) -> #REF!
A85: 0.8 | B85: =$G$14*A85 -> 239.2 | C85: =$G$16+4*$G$14*A85 -> 956.98 | D85: =$G$16+5*$G$14*A85 -> 1196.18 | E85: =$G$16+6*$G$14*A85 -> 1435.38 | F85: =((D85/(1+$G$17))-(D85*'Global Inputs'!$B$8+'Global Inputs'!$B$9+SUM('Global Inputs'!$B$10:$B$14)+(D85/(1+$G$17))*$M$9+5*$G$8*INDEX('Service Economics'!$AI$5:$AI$34,MATCH($B$10,'Service Economics'!$A$5:$A$34,0))))/5 -> -9.770963 | G85: =F85-(#REF!*$G$8) -> #REF! | H85: =IFERROR((F85*5)/(D85/(1+$G$17)),0) -> -6.1263541 | I85: =IF(G85<0,"RED",IF(OR(G85<50,H85<20%),"AMBER","GREEN")) -> #REF!
A86: 0.85 | B86: =$G$14*A86 -> 254.15 | C86: =$G$16+4*$G$14*A86 -> 1016.78 | D86: =$G$16+5*$G$14*A86 -> 1270.93 | E86: =$G$16+6*$G$14*A86 -> 1525.08 | F86: =((D86/(1+$G$17))-(D86*'Global Inputs'!$B$8+'Global Inputs'!$B$9+SUM('Global Inputs'!$B$10:$B$14)+(D86/(1+$G$17))*$M$9+5*$G$8*INDEX('Service Economics'!$AI$5:$AI$34,MATCH($B$10,'Service Economics'!$A$5:$A$34,0))))/5 -> -9.6754125 | G86: =F86-(#REF!*$G$8) -> #REF! | H86: =IFERROR((F86*5)/(D86/(1+$G$17)),0) -> -5.7096452 | I86: =IF(G86<0,"RED",IF(OR(G86<50,H86<20%),"AMBER","GREEN")) -> #REF!
A87: 0.9 | B87: =$G$14*A87 -> 269.1 | C87: =$G$16+4*$G$14*A87 -> 1076.58 | D87: =$G$16+5*$G$14*A87 -> 1345.68 | E87: =$G$16+6*$G$14*A87 -> 1614.78 | F87: =((D87/(1+$G$17))-(D87*'Global Inputs'!$B$8+'Global Inputs'!$B$9+SUM('Global Inputs'!$B$10:$B$14)+(D87/(1+$G$17))*$M$9+5*$G$8*INDEX('Service Economics'!$AI$5:$AI$34,MATCH($B$10,'Service Economics'!$A$5:$A$34,0))))/5 -> -9.5798621 | G87: =F87-(#REF!*$G$8) -> #REF! | H87: =IFERROR((F87*5)/(D87/(1+$G$17)),0) -> -5.3392312 | I87: =IF(G87<0,"RED",IF(OR(G87<50,H87<20%),"AMBER","GREEN")) -> #REF!
A88: 1 | B88: =$G$14*A88 -> 299 | C88: =$G$16+4*$G$14*A88 -> 1196.18 | D88: =$G$16+5*$G$14*A88 -> 1495.18 | E88: =$G$16+6*$G$14*A88 -> 1794.18 | F88: =((D88/(1+$G$17))-(D88*'Global Inputs'!$B$8+'Global Inputs'!$B$9+SUM('Global Inputs'!$B$10:$B$14)+(D88/(1+$G$17))*$M$9+5*$G$8*INDEX('Service Economics'!$AI$5:$AI$34,MATCH($B$10,'Service Economics'!$A$5:$A$34,0))))/5 -> -9.3887612 | G88: =F88-(#REF!*$G$8) -> #REF! | H88: =IFERROR((F88*5)/(D88/(1+$G$17)),0) -> -4.7095139 | I88: =IF(G88<0,"RED",IF(OR(G88<50,H88<20%),"AMBER","GREEN")) -> #REF!
A89: 1.1 | B89: =$G$14*A89 -> 328.9 | C89: =$G$16+4*$G$14*A89 -> 1315.78 | D89: =$G$16+5*$G$14*A89 -> 1644.68 | E89: =$G$16+6*$G$14*A89 -> 1973.58 | F89: =((D89/(1+$G$17))-(D89*'Global Inputs'!$B$8+'Global Inputs'!$B$9+SUM('Global Inputs'!$B$10:$B$14)+(D89/(1+$G$17))*$M$9+5*$G$8*INDEX('Service Economics'!$AI$5:$AI$34,MATCH($B$10,'Service Economics'!$A$5:$A$34,0))))/5 -> -9.1976604 | G89: =F89-(#REF!*$G$8) -> #REF! | H89: =IFERROR((F89*5)/(D89/(1+$G$17)),0) -> -4.1942781 | I89: =IF(G89<0,"RED",IF(OR(G89<50,H89<20%),"AMBER","GREEN")) -> #REF!
A90: 1.2 | B90: =$G$14*A90 -> 358.8 | C90: =$G$16+4*$G$14*A90 -> 1435.38 | D90: =$G$16+5*$G$14*A90 -> 1794.18 | E90: =$G$16+6*$G$14*A90 -> 2152.98 | F90: =((D90/(1+$G$17))-(D90*'Global Inputs'!$B$8+'Global Inputs'!$B$9+SUM('Global Inputs'!$B$10:$B$14)+(D90/(1+$G$17))*$M$9+5*$G$8*INDEX('Service Economics'!$AI$5:$AI$34,MATCH($B$10,'Service Economics'!$A$5:$A$34,0))))/5 -> -9.0065595 | G90: =F90-(#REF!*$G$8) -> #REF! | H90: =IFERROR((F90*5)/(D90/(1+$G$17)),0) -> -3.7649063 | I90: =IF(G90<0,"RED",IF(OR(G90<50,H90<20%),"AMBER","GREEN")) -> #REF!
A91: 1.3 | B91: =$G$14*A91 -> 388.7 | C91: =$G$16+4*$G$14*A91 -> 1554.98 | D91: =$G$16+5*$G$14*A91 -> 1943.68 | E91: =$G$16+6*$G$14*A91 -> 2332.38 | F91: =((D91/(1+$G$17))-(D91*'Global Inputs'!$B$8+'Global Inputs'!$B$9+SUM('Global Inputs'!$B$10:$B$14)+(D91/(1+$G$17))*$M$9+5*$G$8*INDEX('Service Economics'!$AI$5:$AI$34,MATCH($B$10,'Service Economics'!$A$5:$A$34,0))))/5 -> -8.8154586 | G91: =F91-(#REF!*$G$8) -> #REF! | H91: =IFERROR((F91*5)/(D91/(1+$G$17)),0) -> -3.4015856 | I91: =IF(G91<0,"RED",IF(OR(G91<50,H91<20%),"AMBER","GREEN")) -> #REF!

Sheet Global Pricing Config
A1: NivrāaCare — Global Pricing Config
A2: Canonical business configuration for the Pricing API. Change blue inputs here; operational pricing sheets link back to this source.
A4: Config Key | B4: Value | C4: Unit | D4: Customer/Internal | E4: Current Purpose | F4: Governance
A5: base_hourly_rate | B5: 299 | C5: ₹ / hour | D5: Internal | E5: Base rate before service multiplier | F5: Founder
A6: minimum_billable_hours | B6: 2 | C6: hours | D6: Internal | E6: Minimum chargeable journey duration | F6: Founder
A7: care_coordination_fee | B7: 199 | C7: ₹ / journey | D7: Customer-safe output | E7: Fixed journey coordination fee | F7: Founder
A8: care_gst_rate | B8: 0.18 | C8: % | D8: Internal | E8: Care-service GST assumption; confirm with CA | F8: CA / Founder
A9: transport_coordination_fee | B9: 149 | C9: ₹ / journey | D9: Customer-safe output | E9: Transport booking/coordination fee | F9: Founder
A10: default_cab_estimate | B10: 500 | C10: ₹ / journey | D10: Internal default | E10: Editable quote default only | F10: Founder
A11: credit_program_enabled | B11: 1 | C11: 1/0 | D11: Internal | E11: Master NivrāaCredits switch | F11: Founder
A12: credit_earn_rate | B12: 0.05 | C12: % of eligible spend | D12: Internal config | E12: Founder-configurable loyalty earn rate | F12: Founder
A13: credit_value_rupees | B13: 1 | C13: ₹ / Credit | D13: Internal config | E13: 1 Credit redemption value | F13: Founder
A14: credit_max_redemption_percentage | B14: 0.2 | C14: % of eligible care price | D14: Internal config | E14: Maximum Credits usable on one booking | F14: Founder
A15: credit_expiry_days | B15: 180 | C15: days | D15: Internal config | E15: Current planning expiry | F15: Founder / Legal
A16: credit_expected_redemption_rate | B16: 0.7 | C16: % of issued value | D16: Internal CFO | E16: Expected loyalty redemption / breakage | F16: CFO

Sheet Service Master
A1: NivrāaCare — Service Master
A2: Stable API-facing service identifiers mapped to the existing Service Economics model. Human-readable service names may change; service_code should remain stable.
A4: service_code | B4: service_name | C4: category | D4: service_multiplier | E4: pricing_mode | F4: number_of_angels | G4: active_flag | H4: multiplier_reason
A5: HOSPITAL_VISIT | B5: ='Service Economics'!A5 -> Hospital Visit | C5: ='Service Economics'!B5 -> Medical Visit | D5: ='Service Economics'!D5 -> 1 | E5: ='Service Economics'!AH5 -> AUTO | F5: ='Service Economics'!F5 -> 1 | G5: TRUE | H5: ='Service Economics'!AR5 -> Full journey: home → facility → return / safe handover
A6: HOSPITAL_ONLY | B6: ='Service Economics'!A6 -> Hospital Visit — Concierge at Hospital | C6: ='Service Economics'!B6 -> Medical Visit | D6: ='Service Economics'!D6 -> 0.8 | E6: ='Service Economics'!AH6 -> AUTO | F6: ='Service Economics'!F6 -> 1 | G6: TRUE | H6: ='Service Economics'!AR6 -> Hospital-only support; reduced travel and handover responsibility
A7: CLINIC_VISIT | B7: ='Service Economics'!A7 -> Clinic Visit | C7: ='Service Economics'!B7 -> Medical Visit | D7: ='Service Economics'!D7 -> 0.9 | E7: ='Service Economics'!AH7 -> AUTO | F7: ='Service Economics'!F7 -> 1 | G7: TRUE | H7: ='Service Economics'!AR7 -> Shorter, lower-complexity outpatient journey
A8: DIAGNOSTIC | B8: ='Service Economics'!A8 -> Diagnostic Center Visit | C8: ='Service Economics'!B8 -> Medical Visit | D8: ='Service Economics'!D8 -> 0.85 | E8: ='Service Economics'!AH8 -> AUTO | F8: ='Service Economics'!F8 -> 1 | G8: TRUE | H8: ='Service Economics'!AR8 -> Generally simpler navigation / diagnostic-only workflow
A9: HEALTH_CHECKUP | B9: ='Service Economics'!A9 -> Health Check-up Concierge | C9: ='Service Economics'!B9 -> Medical Visit | D9: ='Service Economics'!D9 -> 0.9 | E9: ='Service Economics'!AH9 -> AUTO | F9: ='Service Economics'!F9 -> 1 | G9: TRUE | H9: ='Service Economics'!AR9 -> Structured preventive-care journey; moderate coordination
A10: ADMISSION | B10: ='Service Economics'!A10 -> Hospital Admission Concierge | C10: ='Service Economics'!B10 -> Hospital Support | D10: ='Service Economics'!D10 -> 1.15 | E10: ='Service Economics'!AH10 -> AUTO | F10: ='Service Economics'!F10 -> 1 | G10: TRUE | H10: ='Service Economics'!AR10 -> Higher coordination, documentation and handoff complexity
A11: DISCHARGE | B11: ='Service Economics'!A11 -> Hospital Discharge Concierge | C11: ='Service Economics'!B11 -> Hospital Support | D11: ='Service Economics'!D11 -> 1.1 | E11: ='Service Economics'!AH11 -> AUTO | F11: ='Service Economics'!F11 -> 1 | G11: TRUE | H11: ='Service Economics'!AR11 -> Higher coordination and post-discharge handover responsibility
A12: OVERNIGHT | B12: ='Service Economics'!A12 -> Overnight Hospital Concierge | C12: ='Service Economics'!B12 -> Hospital Support | D12: ='Service Economics'!D12 -> 0.85 | E12: ='Service Economics'!AH12 -> MANUAL | F12: ='Service Economics'!F12 -> 1 | G12: TRUE | H12: ='Service Economics'!AR12 -> Long-duration service; manual pricing should supersede multiplier
A13: MULTI_DAY_12H | B13: ='Service Economics'!A13 -> Multi-Day Hospital Concierge (per 12h shift) | C13: ='Service Economics'!B13 -> Hospital Support | D13: ='Service Economics'!D13 -> 0.85 | E13: ='Service Economics'!AH13 -> MANUAL | F13: ='Service Economics'!F13 -> 1 | G13: TRUE | H13: ='Service Economics'!AR13 -> Long-duration service; manual shift pricing
A14: DAY_PROCEDURE | B14: ='Service Economics'!A14 -> Day Surgery / Procedure Concierge | C14: ='Service Economics'!B14 -> Procedure & Treatment | D14: ='Service Economics'!D14 -> 1.2 | E14: ='Service Economics'!AH14 -> AUTO | F14: ='Service Economics'!F14 -> 1 | G14: TRUE | H14: ='Service Economics'!AR14 -> Procedure-day complexity and extended coordination
A15: PRE_SURGERY | B15: ='Service Economics'!A15 -> Pre-Surgery Concierge | C15: ='Service Economics'!B15 -> Procedure & Treatment | D15: ='Service Economics'!D15 -> 1.1 | E15: ='Service Economics'!AH15 -> AUTO | F15: ='Service Economics'!F15 -> 1 | G15: TRUE | H15: ='Service Economics'!AR15 -> Preparation, records and multi-party coordination
A16: POST_SURGERY | B16: ='Service Economics'!A16 -> Post-Surgery Follow-up | C16: ='Service Economics'!B16 -> Procedure & Treatment | D16: ='Service Economics'!D16 -> 1 | E16: ='Service Economics'!AH16 -> AUTO | F16: ='Service Economics'!F16 -> 1 | G16: TRUE | H16: ='Service Economics'!AR16 -> Standard follow-up journey with moderate coordination
... A34: FAMILY_UPDATE | B34: ='Service Economics'!A34 -> Family Medical Update Concierge | C34: ='Service Economics'!B34 -> Continuing Care | D34: ='Service Economics'!D34 -> 0.65 | E34: ='Service Economics'!AH34 -> AUTO | F34: ='Service Economics'!F34 -> 1 | G34: TRUE | H34: ='Service Economics'!AR34 -> Communication-focused support; no full physical journey

Sheet API Mapping
A1: NivrāaCare — Pricing API Mapping
A2: Developer-facing contract for a Google-Sheets-backed pricing API. Booking facts come from the app; business configuration is retrieved centrally.
A4: Field Name | B4: Type | C4: Required? | D4: Source | E4: Example | F4: Customer/Internal | G4: Description
A5: service_code | B5: string | C5: Yes | D5: API Request | E5: HOSPITAL_VISIT | F5: Customer-safe | G5: Stable service identifier.
A6: selected_hours | B6: decimal | C6: Yes | D6: API Request | E6: 5 | F6: Customer-safe | G6: Requested journey duration.
A7: transport_required | B7: boolean / enum | C7: Yes | D7: API Request | E7: true | F7: Customer-safe | G7: Whether NivrāaCare coordinates third-party transport.
A8: estimated_cab_fare | B8: decimal | C8: Conditional | D8: API Request | E8: 500 | F8: Customer-safe | G8: Required when transport is arranged; third-party estimate.
A9: nivraa_credit_discount_rupees | B9: decimal | C9: Yes | D9: API Request | E9: 20 | F9: Customer-safe | G9: ₹ value of Credits selected for redemption by the app.
A10: price_override_rupees | B10: decimal | C10: No | D10: Admin Request | E10: 1500 | F10: Internal | G10: Founder/admin approved override.
A11: override_reason | B11: string | C11: No | D11: Admin Request | E11: Launch offer | F11: Internal | G11: Reason for override.
A12: quote_id | B12: string | C12: No | D12: Metadata | E12: NC-Q-0001 | F12: Customer-safe | G12: Quote identifier.
A13: customer_id | B13: string | C13: No | D13: Metadata | E13: CUST-001 | F13: Internal | G13: Application customer ID.
A14: patient_id | B14: string | C14: No | D14: Metadata | E14: PAT-001 | F14: Internal | G14: Patient profile ID.
A15: created_by | B15: string | C15: No | D15: Metadata | E15: OPS-01 | F15: Internal | G15: Creator / system identifier.
... A52: fully_loaded_contribution | B52: decimal | C52: Internal Output | D52: Calculation | E52: - | F52: Internal | G52: Contribution after fully loaded Angel payroll.
A56: PRICING API — CORE CALCULATION LOGIC
A57: service = lookup(service_code)
A58: billable_hours = MAX(selected_hours, minimum_billable_hours)
A59: effective_hourly_rate = base_hourly_rate × service_multiplier
A60: service_time_charge = billable_hours × effective_hourly_rate
A61: standard_care_charge = service_time_charge + care_coordination_fee
A62: care_charge_before_credits = approved price_override if present else standard_care_charge
A63: credit_discount_max_allowed = care_charge_before_credits × credit_max_redemption_percentage
A64: credit_discount_applied = MIN(requested_credit_discount, max_allowed, care_charge_before_credits)
A65: final_care_charge = MAX(care_charge_before_credits − credit_discount_applied, 0)
A66: transport_total = transport_required ? estimated_cab_fare + transport_coordination_fee : 0
A67: total_customer_payable = final_care_charge + transport_total
... A72: SAMPLE REQUEST — HOSPITAL VISIT, 5 HOURS, ₹20 CREDIT REDEMPTION
A73: service_code | B73: HOSPITAL_VISIT | D73: SAMPLE RESPONSE
A74: selected_hours | B74: 5 | D74: service_code | E74: HOSPITAL_VISIT
A75: transport_required | B75: TRUE | D75: service_name | E75: Hospital Visit
A76: estimated_cab_fare | B76: 500 | D76: selected_hours | E76: 5
A77: nivraa_credit_discount_rupees | B77: 20 | D77: billable_hours | E77: 5
D78: effective_hourly_rate | E78: 299
D79: service_time_charge | E79: 1495
D80: care_coordination_fee | E80: 199
D81: care_charge_before_credits | E81: 1694
D82: credit_discount_requested | E82: 20
D83: credit_discount_max_allowed | E83: 338.8
D84: credit_discount_applied | E84: 20
D85: final_care_charge | E85: 1674
D86: cab_fare | E86: 500
D87: transport_coordination_fee | E87: 149
D88: transport_total | E88: 649
D89: total_customer_payable | E89: 2323
... D92: nivraa_credits_earned | E92: 83
D93: pricing_status | E93: VALID

Sheet Pricing API Test Cases
A1: NivrāaCare — Pricing API Test Cases
A2: Reference tests for developer implementation. Actual values calculate from Global Pricing Config + Service Master, so pricing changes automatically flow through the test suite.
A4: Case | B4: Service Code | C4: Selected Hours | D4: Transport Required | E4: Cab Fare | F4: Credit Discount Requested | G4: Price Override | H4: Expected Final Care | I4: Expected Transport | J4: Expected Total | K4: Expected Credits | L4: Pricing Mode | M4: Multiplier | N4: Billable Hours | O4: Actual Care | P4: Actual Transport | Q4: Actual Total | R4: Actual Credits | S4: Credit Max Allowed | T4: Credit Applied | U4: Pricing Status | V4: Test Result
A5: Case 1 | B5: HOSPITAL_VISIT | C5: 5 | D5: NO | E5: 0 | F5: 0 | H5: 1694 | I5: 0 | J5: 1694 | K5: 84 | L5: =INDEX('Service Master'!$E$5:$E$34,MATCH(B5,'Service Master'!$A$5:$A$34,0)) -> AUTO | M5: =INDEX('Service Master'!$D$5:$D$34,MATCH(B5,'Service Master'!$A$5:$A$34,0)) -> 1 | N5: =MAX(C5,'Global Pricing Config'!$B$6) -> 5 | O5: =IF(L5="MANUAL","",MAX((IF(ISNUMBER(G5),G5,(N5*'Global Pricing Config'!$B$5*M5+'Global Pricing Config'!$B$7)))-(MIN(MAX(F5,0),MAX((IF(ISNUMBER(G5),G5,(N5*'Global Pricing Config'!$B$5*M5+'Global Pricing Config'!$B$7)))*'Global Pricing Config'!$B$14,0),MAX(IF(ISNUMBER(G5),G5,(N5*'Global Pricing Config'!$B$5*M5+'Global Pricing Config'!$B$7)),0))),0)) -> 1694 | P5: =IF(D5="YES",E5+'Global Pricing Config'!$B$9,0) -> 0 | Q5: =IF(L5="MANUAL","",O5+P5) -> 1694 | R5: =IF(L5="MANUAL","",FLOOR((MAX((IF(ISNUMBER(G5),G5,(N5*'Global Pricing Config'!$B$5*M5+'Global Pricing Config'!$B$7)))-(MIN(MAX(F5,0),MAX((IF(ISNUMBER(G5),G5,(N5*'Global Pricing Config'!$B$5*M5+'Global Pricing Config'!$B$7)))*'Global Pricing Config'!$B$14,0),MAX(IF(ISNUMBER(G5),G5,(N5*'Global Pricing Config'!$B$5*M5+'Global Pricing Config'!$B$7)),0))),0))*'Global Pricing Config'!$B$12/'Global Pricing Config'!$B$13,1)) -> 84 | S5: =IF(L5="MANUAL","",((IF(ISNUMBER(G5),G5,(N5*'Global Pricing Config'!$B$5*M5+'Global Pricing Config'!$B$7)))*'Global Pricing Config'!$B$14)) -> 338.8 | T5: =IF(L5="MANUAL","",(MIN(MAX(F5,0),MAX((IF(ISNUMBER(G5),G5,(N5*'Global Pricing Config'!$B$5*M5+'Global Pricing Config'!$B$7)))*'Global Pricing Config'!$B$14,0),MAX(IF(ISNUMBER(G5),G5,(N5*'Global Pricing Config'!$B$5*M5+'Global Pricing Config'!$B$7)),0)))) -> 0 | U5: =IF(L5="MANUAL","MANUAL PRICING REQUIRED",IF(F5>T5,"CREDIT DISCOUNT CAPPED","VALID")) -> VALID | V5: =IF(AND(ABS(O5-H5)<0.01,ABS(P5-I5)<0.01,ABS(Q5-J5)<0.01,R5=K5),"PASS","CHECK") -> PASS
A6: Case 2 | B6: HOSPITAL_VISIT | C6: 5 | D6: YES | E6: 500 | F6: 0 | H6: 1694 | I6: 649 | J6: 2343 | K6: 84 | L6: =INDEX('Service Master'!$E$5:$E$34,MATCH(B6,'Service Master'!$A$5:$A$34,0)) -> AUTO | M6: =INDEX('Service Master'!$D$5:$D$34,MATCH(B6,'Service Master'!$A$5:$A$34,0)) -> 1 | N6: =MAX(C6,'Global Pricing Config'!$B$6) -> 5 | O6: =IF(L6="MANUAL","",MAX((IF(ISNUMBER(G6),G6,(N6*'Global Pricing Config'!$B$5*M6+'Global Pricing Config'!$B$7)))-(MIN(MAX(F6,0),MAX((IF(ISNUMBER(G6),G6,(N6*'Global Pricing Config'!$B$5*M6+'Global Pricing Config'!$B$7)))*'Global Pricing Config'!$B$14,0),MAX(IF(ISNUMBER(G6),G6,(N6*'Global Pricing Config'!$B$5*M6+'Global Pricing Config'!$B$7)),0))),0)) -> 1694 | P6: =IF(D6="YES",E6+'Global Pricing Config'!$B$9,0) -> 649 | Q6: =IF(L6="MANUAL","",O6+P6) -> 2343 | R6: =IF(L6="MANUAL","",FLOOR((MAX((IF(ISNUMBER(G6),G6,(N6*'Global Pricing Config'!$B$5*M6+'Global Pricing Config'!$B$7)))-(MIN(MAX(F6,0),MAX((IF(ISNUMBER(G6),G6,(N6*'Global Pricing Config'!$B$5*M6+'Global Pricing Config'!$B$7)))*'Global Pricing Config'!$B$14,0),MAX(IF(ISNUMBER(G6),G6,(N6*'Global Pricing Config'!$B$5*M6+'Global Pricing Config'!$B$7)),0))),0))*'Global Pricing Config'!$B$12/'Global Pricing Config'!$B$13,1)) -> 84 | S6: =IF(L6="MANUAL","",((IF(ISNUMBER(G6),G6,(N6*'Global Pricing Config'!$B$5*M6+'Global Pricing Config'!$B$7)))*'Global Pricing Config'!$B$14)) -> 338.8 | T6: =IF(L6="MANUAL","",(MIN(MAX(F6,0),MAX((IF(ISNUMBER(G6),G6,(N6*'Global Pricing Config'!$B$5*M6+'Global Pricing Config'!$B$7)))*'Global Pricing Config'!$B$14,0),MAX(IF(ISNUMBER(G6),G6,(N6*'Global Pricing Config'!$B$5*M6+'Global Pricing Config'!$B$7)),0)))) -> 0 | U6: =IF(L6="MANUAL","MANUAL PRICING REQUIRED",IF(F6>T6,"CREDIT DISCOUNT CAPPED","VALID")) -> VALID | V6: =IF(AND(ABS(O6-H6)<0.01,ABS(P6-I6)<0.01,ABS(Q6-J6)<0.01,R6=K6),"PASS","CHECK") -> PASS
A7: Case 3 | B7: HOSPITAL_VISIT | C7: 5 | D7: YES | E7: 500 | F7: 20 | H7: 1674 | I7: 649 | J7: 2323 | K7: 83 | L7: =INDEX('Service Master'!$E$5:$E$34,MATCH(B7,'Service Master'!$A$5:$A$34,0)) -> AUTO | M7: =INDEX('Service Master'!$D$5:$D$34,MATCH(B7,'Service Master'!$A$5:$A$34,0)) -> 1 | N7: =MAX(C7,'Global Pricing Config'!$B$6) -> 5 | O7: =IF(L7="MANUAL","",MAX((IF(ISNUMBER(G7),G7,(N7*'Global Pricing Config'!$B$5*M7+'Global Pricing Config'!$B$7)))-(MIN(MAX(F7,0),MAX((IF(ISNUMBER(G7),G7,(N7*'Global Pricing Config'!$B$5*M7+'Global Pricing Config'!$B$7)))*'Global Pricing Config'!$B$14,0),MAX(IF(ISNUMBER(G7),G7,(N7*'Global Pricing Config'!$B$5*M7+'Global Pricing Config'!$B$7)),0))),0)) -> 1674 | P7: =IF(D7="YES",E7+'Global Pricing Config'!$B$9,0) -> 649 | Q7: =IF(L7="MANUAL","",O7+P7) -> 2323 | R7: =IF(L7="MANUAL","",FLOOR((MAX((IF(ISNUMBER(G7),G7,(N7*'Global Pricing Config'!$B$5*M7+'Global Pricing Config'!$B$7)))-(MIN(MAX(F7,0),MAX((IF(ISNUMBER(G7),G7,(N7*'Global Pricing Config'!$B$5*M7+'Global Pricing Config'!$B$7)))*'Global Pricing Config'!$B$14,0),MAX(IF(ISNUMBER(G7),G7,(N7*'Global Pricing Config'!$B$5*M7+'Global Pricing Config'!$B$7)),0))),0))*'Global Pricing Config'!$B$12/'Global Pricing Config'!$B$13,1)) -> 83 | S7: =IF(L7="MANUAL","",((IF(ISNUMBER(G7),G7,(N7*'Global Pricing Config'!$B$5*M7+'Global Pricing Config'!$B$7)))*'Global Pricing Config'!$B$14)) -> 338.8 | T7: =IF(L7="MANUAL","",(MIN(MAX(F7,0),MAX((IF(ISNUMBER(G7),G7,(N7*'Global Pricing Config'!$B$5*M7+'Global Pricing Config'!$B$7)))*'Global Pricing Config'!$B$14,0),MAX(IF(ISNUMBER(G7),G7,(N7*'Global Pricing Config'!$B$5*M7+'Global Pricing Config'!$B$7)),0)))) -> 20 | U7: =IF(L7="MANUAL","MANUAL PRICING REQUIRED",IF(F7>T7,"CREDIT DISCOUNT CAPPED","VALID")) -> VALID | V7: =IF(AND(ABS(O7-H7)<0.01,ABS(P7-I7)<0.01,ABS(Q7-J7)<0.01,R7=K7),"PASS","CHECK") -> PASS
A8: Case 4 | B8: HOSPITAL_ONLY | C8: 5 | D8: NO | E8: 0 | F8: 0 | H8: 1395 | I8: 0 | J8: 1395 | K8: 69 | L8: =INDEX('Service Master'!$E$5:$E$34,MATCH(B8,'Service Master'!$A$5:$A$34,0)) -> AUTO | M8: =INDEX('Service Master'!$D$5:$D$34,MATCH(B8,'Service Master'!$A$5:$A$34,0)) -> 0.8 | N8: =MAX(C8,'Global Pricing Config'!$B$6) -> 5 | O8: =IF(L8="MANUAL","",MAX((IF(ISNUMBER(G8),G8,(N8*'Global Pricing Config'!$B$5*M8+'Global Pricing Config'!$B$7)))-(MIN(MAX(F8,0),MAX((IF(ISNUMBER(G8),G8,(N8*'Global Pricing Config'!$B$5*M8+'Global Pricing Config'!$B$7)))*'Global Pricing Config'!$B$14,0),MAX(IF(ISNUMBER(G8),G8,(N8*'Global Pricing Config'!$B$5*M8+'Global Pricing Config'!$B$7)),0))),0)) -> 1395 | P8: =IF(D8="YES",E8+'Global Pricing Config'!$B$9,0) -> 0 | Q8: =IF(L8="MANUAL","",O8+P8) -> 1395 | R8: =IF(L8="MANUAL","",FLOOR((MAX((IF(ISNUMBER(G8),G8,(N8*'Global Pricing Config'!$B$5*M8+'Global Pricing Config'!$B$7)))-(MIN(MAX(F8,0),MAX((IF(ISNUMBER(G8),G8,(N8*'Global Pricing Config'!$B$5*M8+'Global Pricing Config'!$B$7)))*'Global Pricing Config'!$B$14,0),MAX(IF(ISNUMBER(G8),G8,(N8*'Global Pricing Config'!$B$5*M8+'Global Pricing Config'!$B$7)),0))),0))*'Global Pricing Config'!$B$12/'Global Pricing Config'!$B$13,1)) -> 69 | S8: =IF(L8="MANUAL","",((IF(ISNUMBER(G8),G8,(N8*'Global Pricing Config'!$B$5*M8+'Global Pricing Config'!$B$7)))*'Global Pricing Config'!$B$14)) -> 279 | T8: =IF(L8="MANUAL","",(MIN(MAX(F8,0),MAX((IF(ISNUMBER(G8),G8,(N8*'Global Pricing Config'!$B$5*M8+'Global Pricing Config'!$B$7)))*'Global Pricing Config'!$B$14,0),MAX(IF(ISNUMBER(G8),G8,(N8*'Global Pricing Config'!$B$5*M8+'Global Pricing Config'!$B$7)),0)))) -> 0 | U8: =IF(L8="MANUAL","MANUAL PRICING REQUIRED",IF(F8>T8,"CREDIT DISCOUNT CAPPED","VALID")) -> VALID | V8: =IF(AND(ABS(O8-H8)<0.01,ABS(P8-I8)<0.01,ABS(Q8-J8)<0.01,R8=K8),"PASS","CHECK") -> PASS
A9: Case 5 | B9: HOSPITAL_ONLY | C9: 5 | D9: NO | E9: 0 | F9: 100 | H9: 1295 | I9: 0 | J9: 1295 | K9: 64 | L9: =INDEX('Service Master'!$E$5:$E$34,MATCH(B9,'Service Master'!$A$5:$A$34,0)) -> AUTO | M9: =INDEX('Service Master'!$D$5:$D$34,MATCH(B9,'Service Master'!$A$5:$A$34,0)) -> 0.8 | N9: =MAX(C9,'Global Pricing Config'!$B$6) -> 5 | O9: =IF(L9="MANUAL","",MAX((IF(ISNUMBER(G9),G9,(N9*'Global Pricing Config'!$B$5*M9+'Global Pricing Config'!$B$7)))-(MIN(MAX(F9,0),MAX((IF(ISNUMBER(G9),G9,(N9*'Global Pricing Config'!$B$5*M9+'Global Pricing Config'!$B$7)))*'Global Pricing Config'!$B$14,0),MAX(IF(ISNUMBER(G9),G9,(N9*'Global Pricing Config'!$B$5*M9+'Global Pricing Config'!$B$7)),0))),0)) -> 1295 | P9: =IF(D9="YES",E9+'Global Pricing Config'!$B$9,0) -> 0 | Q9: =IF(L9="MANUAL","",O9+P9) -> 1295 | R9: =IF(L9="MANUAL","",FLOOR((MAX((IF(ISNUMBER(G9),G9,(N9*'Global Pricing Config'!$B$5*M9+'Global Pricing Config'!$B$7)))-(MIN(MAX(F9,0),MAX((IF(ISNUMBER(G9),G9,(N9*'Global Pricing Config'!$B$5*M9+'Global Pricing Config'!$B$7)))*'Global Pricing Config'!$B$14,0),MAX(IF(ISNUMBER(G9),G9,(N9*'Global Pricing Config'!$B$5*M9+'Global Pricing Config'!$B$7)),0))),0))*'Global Pricing Config'!$B$12/'Global Pricing Config'!$B$13,1)) -> 64 | S9: =IF(L9="MANUAL","",((IF(ISNUMBER(G9),G9,(N9*'Global Pricing Config'!$B$5*M9+'Global Pricing Config'!$B$7)))*'Global Pricing Config'!$B$14)) -> 279 | T9: =IF(L9="MANUAL","",(MIN(MAX(F9,0),MAX((IF(ISNUMBER(G9),G9,(N9*'Global Pricing Config'!$B$5*M9+'Global Pricing Config'!$B$7)))*'Global Pricing Config'!$B$14,0),MAX(IF(ISNUMBER(G9),G9,(N9*'Global Pricing Config'!$B$5*M9+'Global Pricing Config'!$B$7)),0)))) -> 100 | U9: =IF(L9="MANUAL","MANUAL PRICING REQUIRED",IF(F9>T9,"CREDIT DISCOUNT CAPPED","VALID")) -> VALID | V9: =IF(AND(ABS(O9-H9)<0.01,ABS(P9-I9)<0.01,ABS(Q9-J9)<0.01,R9=K9),"PASS","CHECK") -> PASS
A10: Case 6 | B10: HOSPITAL_VISIT | C10: 5 | D10: NO | E10: 0 | F10: 500 | H10: 1355.2 | I10: 0 | J10: 1355.2 | K10: 67 | L10: =INDEX('Service Master'!$E$5:$E$34,MATCH(B10,'Service Master'!$A$5:$A$34,0)) -> AUTO | M10: =INDEX('Service Master'!$D$5:$D$34,MATCH(B10,'Service Master'!$A$5:$A$34,0)) -> 1 | N10: =MAX(C10,'Global Pricing Config'!$B$6) -> 5 | O10: =IF(L10="MANUAL","",MAX((IF(ISNUMBER(G10),G10,(N10*'Global Pricing Config'!$B$5*M10+'Global Pricing Config'!$B$7)))-(MIN(MAX(F10,0),MAX((IF(ISNUMBER(G10),G10,(N10*'Global Pricing Config'!$B$5*M10+'Global Pricing Config'!$B$7)))*'Global Pricing Config'!$B$14,0),MAX(IF(ISNUMBER(G10),G10,(N10*'Global Pricing Config'!$B$5*M10+'Global Pricing Config'!$B$7)),0))),0)) -> 1355.2 | P10: =IF(D10="YES",E10+'Global Pricing Config'!$B$9,0) -> 0 | Q10: =IF(L10="MANUAL","",O10+P10) -> 1355.2 | R10: =IF(L10="MANUAL","",FLOOR((MAX((IF(ISNUMBER(G10),G10,(N10*'Global Pricing Config'!$B$5*M10+'Global Pricing Config'!$B$7)))-(MIN(MAX(F10,0),MAX((IF(ISNUMBER(G10),G10,(N10*'Global Pricing Config'!$B$5*M10+'Global Pricing Config'!$B$7)))*'Global Pricing Config'!$B$14,0),MAX(IF(ISNUMBER(G10),G10,(N10*'Global Pricing Config'!$B$5*M10+'Global Pricing Config'!$B$7)),0))),0))*'Global Pricing Config'!$B$12/'Global Pricing Config'!$B$13,1)) -> 67 | S10: =IF(L10="MANUAL","",((IF(ISNUMBER(G10),G10,(N10*'Global Pricing Config'!$B$5*M10+'Global Pricing Config'!$B$7)))*'Global Pricing Config'!$B$14)) -> 338.8 | T10: =IF(L10="MANUAL","",(MIN(MAX(F10,0),MAX((IF(ISNUMBER(G10),G10,(N10*'Global Pricing Config'!$B$5*M10+'Global Pricing Config'!$B$7)))*'Global Pricing Config'!$B$14,0),MAX(IF(ISNUMBER(G10),G10,(N10*'Global Pricing Config'!$B$5*M10+'Global Pricing Config'!$B$7)),0)))) -> 338.8 | U10: =IF(L10="MANUAL","MANUAL PRICING REQUIRED",IF(F10>T10,"CREDIT DISCOUNT CAPPED","VALID")) -> CREDIT DISCOUNT CAPPED | V10: =IF(AND(ABS(O10-H10)<0.01,ABS(P10-I10)<0.01,ABS(Q10-J10)<0.01,R10=K10),"PASS","CHECK") -> PASS
A11: Case 7 | B11: HOSPITAL_VISIT | C11: 1 | D11: NO | E11: 0 | F11: 0 | H11: 797 | I11: 0 | J11: 797 | K11: 39 | L11: =INDEX('Service Master'!$E$5:$E$34,MATCH(B11,'Service Master'!$A$5:$A$34,0)) -> AUTO | M11: =INDEX('Service Master'!$D$5:$D$34,MATCH(B11,'Service Master'!$A$5:$A$34,0)) -> 1 | N11: =MAX(C11,'Global Pricing Config'!$B$6) -> 2 | O11: =IF(L11="MANUAL","",MAX((IF(ISNUMBER(G11),G11,(N11*'Global Pricing Config'!$B$5*M11+'Global Pricing Config'!$B$7)))-(MIN(MAX(F11,0),MAX((IF(ISNUMBER(G11),G11,(N11*'Global Pricing Config'!$B$5*M11+'Global Pricing Config'!$B$7)))*'Global Pricing Config'!$B$14,0),MAX(IF(ISNUMBER(G11),G11,(N11*'Global Pricing Config'!$B$5*M11+'Global Pricing Config'!$B$7)),0))),0)) -> 797 | P11: =IF(D11="YES",E11+'Global Pricing Config'!$B$9,0) -> 0 | Q11: =IF(L11="MANUAL","",O11+P11) -> 797 | R11: =IF(L11="MANUAL","",FLOOR((MAX((IF(ISNUMBER(G11),G11,(N11*'Global Pricing Config'!$B$5*M11+'Global Pricing Config'!$B$7)))-(MIN(MAX(F11,0),MAX((IF(ISNUMBER(G11),G11,(N11*'Global Pricing Config'!$B$5*M11+'Global Pricing Config'!$B$7)))*'Global Pricing Config'!$B$14,0),MAX(IF(ISNUMBER(G11),G11,(N11*'Global Pricing Config'!$B$5*M11+'Global Pricing Config'!$B$7)),0))),0))*'Global Pricing Config'!$B$12/'Global Pricing Config'!$B$13,1)) -> 39 | S11: =IF(L11="MANUAL","",((IF(ISNUMBER(G11),G11,(N11*'Global Pricing Config'!$B$5*M11+'Global Pricing Config'!$B$7)))*'Global Pricing Config'!$B$14)) -> 159.4 | T11: =IF(L11="MANUAL","",(MIN(MAX(F11,0),MAX((IF(ISNUMBER(G11),G11,(N11*'Global Pricing Config'!$B$5*M11+'Global Pricing Config'!$B$7)))*'Global Pricing Config'!$B$14,0),MAX(IF(ISNUMBER(G11),G11,(N11*'Global Pricing Config'!$B$5*M11+'Global Pricing Config'!$B$7)),0)))) -> 0 | U11: =IF(L11="MANUAL","MANUAL PRICING REQUIRED",IF(F11>T11,"CREDIT DISCOUNT CAPPED","VALID")) -> VALID | V11: =IF(AND(ABS(O11-H11)<0.01,ABS(P11-I11)<0.01,ABS(Q11-J11)<0.01,R11=K11),"PASS","CHECK") -> PASS
A12: Case 8 | B12: OVERNIGHT | C12: 8 | D12: NO | E12: 0 | F12: 0 | I12: 0 | L12: =INDEX('Service Master'!$E$5:$E$34,MATCH(B12,'Service Master'!$A$5:$A$34,0)) -> MANUAL | M12: =INDEX('Service Master'!$D$5:$D$34,MATCH(B12,'Service Master'!$A$5:$A$34,0)) -> 0.85 | N12: =MAX(C12,'Global Pricing Config'!$B$6) -> 8 | O12: =IF(L12="MANUAL","",MAX((IF(ISNUMBER(G12),G12,(N12*'Global Pricing Config'!$B$5*M12+'Global Pricing Config'!$B$7)))-(MIN(MAX(F12,0),MAX((IF(ISNUMBER(G12),G12,(N12*'Global Pricing Config'!$B$5*M12+'Global Pricing Config'!$B$7)))*'Global Pricing Config'!$B$14,0),MAX(IF(ISNUMBER(G12),G12,(N12*'Global Pricing Config'!$B$5*M12+'Global Pricing Config'!$B$7)),0))),0)) | P12: =IF(D12="YES",E12+'Global Pricing Config'!$B$9,0) -> 0 | Q12: =IF(L12="MANUAL","",O12+P12) | R12: =IF(L12="MANUAL","",FLOOR((MAX((IF(ISNUMBER(G12),G12,(N12*'Global Pricing Config'!$B$5*M12+'Global Pricing Config'!$B$7)))-(MIN(MAX(F12,0),MAX((IF(ISNUMBER(G12),G12,(N12*'Global Pricing Config'!$B$5*M12+'Global Pricing Config'!$B$7)))*'Global Pricing Config'!$B$14,0),MAX(IF(ISNUMBER(G12),G12,(N12*'Global Pricing Config'!$B$5*M12+'Global Pricing Config'!$B$7)),0))),0))*'Global Pricing Config'!$B$12/'Global Pricing Config'!$B$13,1)) | S12: =IF(L12="MANUAL","",((IF(ISNUMBER(G12),G12,(N12*'Global Pricing Config'!$B$5*M12+'Global Pricing Config'!$B$7)))*'Global Pricing Config'!$B$14)) | T12: =IF(L12="MANUAL","",(MIN(MAX(F12,0),MAX((IF(ISNUMBER(G12),G12,(N12*'Global Pricing Config'!$B$5*M12+'Global Pricing Config'!$B$7)))*'Global Pricing Config'!$B$14,0),MAX(IF(ISNUMBER(G12),G12,(N12*'Global Pricing Config'!$B$5*M12+'Global Pricing Config'!$B$7)),0)))) | U12: =IF(L12="MANUAL","MANUAL PRICING REQUIRED",IF(F12>T12,"CREDIT DISCOUNT CAPPED","VALID")) -> MANUAL PRICING REQUIRED | V12: =IF(U12="MANUAL PRICING REQUIRED","PASS","CHECK") -> PASS
