Workbook

Sheet Dashboard
A1: NivrāaCare — Dynamic Unit Economics Dashboard | CFO View | J1: Service Selector Source | K1: Hour Options
A2: Select service + hours. Case 1 = patient arranges transport. Case 2 = NivrāaCare coordinates a third-party cab. Contribution is before fixed costs. | J2: Hospital Visit | K2: 1
J3: Hospital Visit — Concierge at Hospital | K3: 1.5
A4: Selected Service | B4: Hospital Visit | C4: Selected Hours | D4: 5 | J4: Clinic Visit | K4: 2
E5: Model | F5: Contribution Before Fixed Costs | J5: Diagnostic Center Visit | K5: 2.5
A6: Metric | B6: Case 1 — Patient Transport | C6: Case 2 — NivrāaCare 3P Cab | E6: Case 1 | F6: =B16 -> 1319.8032 | J6: Health Check-up Concierge | K6: 3
A7: Service Hours | B7: =$D$4 -> 5 | C7: =$D$4 -> 5 | E7: Case 2 | F7: =C16 -> 1458.8032 | J7: Hospital Admission Concierge | K7: 3.5
A8: Service Pricing Multiplier | B8: =SUMIF('Service Economics'!$A$5:$A$34,$B$4,'Service Economics'!$D$5:$D$34) -> 1 | C8: =B8 -> 1 | E8: Uplift | F8: =C19 -> 139 | J8: Hospital Discharge Concierge | K8: 4
A9: Customer Care Price (incl. GST) | B9: ='MVP1 Pricing & SKU'!$B$9+MAX($D$4,'MVP1 Pricing & SKU'!$B$5)*'MVP1 Pricing & SKU'!$B$7*$B$8+SUMIF('Service Economics'!$A$5:$A$34,$B$4,'Service Economics'!$E$5:$E$34) -> 1694 | C9: =B9 -> 1694 | J9: Overnight Hospital Concierge | K9: 4.5
A10: Net Care Revenue | B10: =B9/(1+'Global Inputs'!$B$7) -> 1435.5932 | C10: =B10 -> 1435.5932 | J10: Multi-Day Hospital Concierge (per 12h shift) | K10: 5
A11: Transport Customer Collection | B11: 0 | C11: =IF(SUMIF('Service Economics'!$A$5:$A$34,$B$4,'Service Economics'!$H$5:$H$34)=0,'Global Inputs'!$B$15,SUMIF('Service Economics'!$A$5:$A$34,$B$4,'Service Economics'!$H$5:$H$34))+IF(SUMIF('Service Economics'!$A$5:$A$34,$B$4,'Service Economics'!$I$5:$I$34)=0,'Global Inputs'!$B$16,SUMIF('Service Economics'!$A$5:$A$34,$B$4,'Service Economics'!$I$5:$I$34)) -> 649 | J11: Day Surgery / Procedure Concierge | K11: 5.5
A12: Pass-through Cab Amount | B12: 0 | C12: =IF(SUMIF('Service Economics'!$A$5:$A$34,$B$4,'Service Economics'!$H$5:$H$34)=0,'Global Inputs'!$B$15,SUMIF('Service Economics'!$A$5:$A$34,$B$4,'Service Economics'!$H$5:$H$34)) -> 500 | J12: Pre-Surgery Concierge | K12: 6
A13: Total Customer Outflow | B13: =B9+B11 -> 1694 | C13: =C9+C11 -> 2343 | J13: Post-Surgery Follow-up | K13: 6.5
A14: Net Operating Revenue | B14: =B10 -> 1435.5932 | C14: =C10+IF(SUMIF('Service Economics'!$A$5:$A$34,$B$4,'Service Economics'!$I$5:$I$34)=0,'Global Inputs'!$B$16,SUMIF('Service Economics'!$A$5:$A$34,$B$4,'Service Economics'!$I$5:$I$34))/(1+'Global Inputs'!$B$17) -> 1584.5932 | J14: Dialysis Visit Concierge | K14: 7
A15: Variable Delivery Cost | B15: =($D$4*SUMIF('Service Economics'!$A$5:$A$34,$B$4,'Service Economics'!$F$5:$F$34)*IF(SUMIF('Service Economics'!$A$5:$A$34,$B$4,'Service Economics'!$G$5:$G$34)=0,'Global Inputs'!$B$6,SUMIF('Service Economics'!$A$5:$A$34,$B$4,'Service Economics'!$G$5:$G$34)))+(B9*'Global Inputs'!$B$8+'Global Inputs'!$B$9)+SUM('Global Inputs'!$B$10:$B$14)+((B9/(1+'Global Inputs'!$B$7))*'NC Credits'!$B$15) -> 115.79 | C15: =B15+C11*'Global Inputs'!$B$8+'Global Inputs'!$B$18 -> 125.79 | J15: Chemotherapy Visit Concierge | K15: 7.5
A16: Contribution Before Fixed Costs | B16: =B14-B15 -> 1319.8032 | C16: =C14-C15 -> 1458.8032 | J16: Radiation Therapy Concierge | K16: 8
A17: Contribution Margin | B17: =IF(B14=0,0,B16/B14) -> 0.91934345 | C17: =IF(C14=0,0,C16/C14) -> 0.92061685 | J17: Physiotherapy / Rehab Visit | K17: 8.5
A18: Contribution / Service Hour | B18: =IF($D$4=0,0,B16/$D$4) -> 263.96064 | C18: =IF($D$4=0,0,C16/$D$4) -> 291.76064 | J18: Chronic Care Follow-up | K18: 9
A19: Contribution Uplift vs Case 1 | B19: 0 | C19: =C16-B16 -> 139 | J19: NRI Parent Medical Concierge | K19: 9.5
J20: Second Opinion Concierge | K20: 10
A21: Selected Hours is a dashboard-only scenario override. Minimum billing remains 2 hours. Service multipliers reflect effort/value and remain editable in Service Economics. | J21: Teleconsultation Concierge | K21: 10.5
J22: Medical Records Concierge | K22: 11
J23: Insurance / TPA Desk Concierge | K23: 11.5
A24: Selected Journey — Detailed CFO Breakup | J24: Hospital Transfer Concierge | K24: 12
A25: ="Live calculation for "&$B$4&" | "&TEXT($D$4,"0.0")&" hours | Pricing, loyalty, transport and Angel economics" -> Live calculation for Hospital Visit | 5.0 hours | Pricing, loyalty, transport and Angel economics | J25: Rehab / Nursing Facility Transfer | K25: 12.5
A26: Metric | B26: Case 1 — Patient Transport | C26: Case 2 — NivrāaCare 3P Cab | D26: CFO Formula / Meaning | F26: CFO Lens — What the Journey Really Earns | J26: 24×7 Urgent Care Coordination | K26: 13
A27: Customer Care Price (incl. GST) | B27: =B9 -> 1694 | C27: =C9 -> 1694 | D27: See Customer Care Price Build-Up below for the complete tier-by-tier calculation. | F27: Current Angel Utilization | G27: ='Angel Economics'!$G$9 -> 0.18104625 | J27: Doctor-at-Home Coordination | K27: 13.5
A28: Less: Embedded GST | B28: =B27-B29 -> 258.40678 | C28: =C27-C29 -> 258.40678 | D28: Customer care price less net care revenue; reflects embedded GST. | F28: Target Angel Utilization | G28: ='Angel Economics'!$H$9 -> 0.65 | J28: Nurse-at-Home Coordination | K28: 14
A29: Net Care Revenue | B29: =B10 -> 1435.5932 | C29: =C10 -> 1435.5932 | D29: Care revenue after removing GST. | F29: Current Fully Loaded Angel Cost / Hr | G29: ='Angel Economics'!$G$10 -> 241.65096 | J29: Medical Tourism — Concierge Package (24 HR Basis) | K29: 14.5
A30: Transport Customer Collection | B30: =B11 -> 0 | C30: =C11 -> 649 | D30: Case 2 = cab reimbursement + transport coordination fee. | F30: Target Fully Loaded Angel Cost / Hr | G30: ='Angel Economics'!$H$10 -> 103.5503 | J30: Pharmacy / Prescription Coordination | K30: 15
A31: Less: Pass-through Cab Amount | B31: =B12 -> 0 | C31: =C12 -> 500 | D31: Cab reimbursement collected and paid onward; not operating revenue. | F31: Case 1 Incremental Contribution / Hr | G31: =B44/$D$4 -> 263.96064 | J31: Family Medical Update Concierge | K31: 15.5
A32: Transport Coordination Fee | B32: =MAX(0,B30-B31) -> 0 | C32: =MAX(0,C30-C31) -> 149 | D32: Transport collection less pass-through cab amount. | F32: Case 2 Incremental Contribution / Hr | G32: =C44/$D$4 -> 291.76064 | K32: 16
A33: Net Operating Revenue | B33: =B14 -> 1435.5932 | C33: =C14 -> 1584.5932 | D33: Net care revenue + net transport coordination revenue. | F33: Case 1 Fully Loaded Contribution — Current | G33: =B46 -> 111.54842 | K33: 16.5
A34: Payment Platform Cost | B34: =$B$27*'Global Inputs'!$B$8+'Global Inputs'!$B$9 -> 0 | C34: =$C$27*'Global Inputs'!$B$8+'Global Inputs'!$B$9+$C$30*'Global Inputs'!$B$8 -> 0 | D34: Care gateway fee + fixed gateway fee + transport gateway fee where applicable. | F34: Case 2 Fully Loaded Contribution — Current | G34: =C46 -> 250.54842 | K34: 17
A35: Ops / Support Allocation | B35: ='Global Inputs'!$B$10 -> 10 | C35: ='Global Inputs'!$B$10 -> 10 | D35: Per-journey operating/support variable allocation. | F35: Case 1 Fully Loaded Contribution — Target | G35: =B47 -> 802.05174 | K35: 17.5
A36: Insurance / Risk Reserve | B36: ='Global Inputs'!$B$11 -> 10 | C36: ='Global Inputs'!$B$11 -> 10 | D36: Per-journey insurance / risk reserve. | F36: Case 2 Fully Loaded Contribution — Target | G36: =C47 -> 941.05174 | K36: 18
A37: WhatsApp / SMS / Communication | B37: ='Global Inputs'!$B$12 -> 0.5 | C37: ='Global Inputs'!$B$12 -> 0.5 | D37: Per-journey messaging / communication cost. | F37: Case 2 Transport Uplift | G37: =C44-B44 -> 139 | K37: 18.5
A38: BGV + Training Allocation | B38: ='Global Inputs'!$B$13 -> 0 | C38: ='Global Inputs'!$B$13 -> 0 | D38: Per-journey BGV/training allocation. | F38: Current Density Status | G38: =IF(G27<40%,"RED — payroll density too low",IF(G27<60%,"AMBER — improve utilization","GREEN — healthy utilization")) -> RED — payroll density too low | K38: 19
A39: Refund / Service Recovery Reserve | B39: ='Global Inputs'!$B$14 -> 36 | C39: ='Global Inputs'!$B$14 -> 36 | D39: Expected refund / service recovery reserve. | K39: 19.5
A40: Expected NC Credits Cost | B40: =$B$29*'NC Credits'!$B$15 -> 59.29 | C40: =$C$29*'NC Credits'!$B$15 -> 59.29 | D40: Net care revenue × expected NC loyalty cost rate. | F40: CFO interpretation: Contribution Before Fixed Costs is the marginal journey economics. Fully Loaded Contribution additionally allocates salaried Angel payroll. When utilization is low, the same payroll is spread across too few productive hours, so a journey can look highly profitable incrementally while producing much less fully loaded contribution. | K40: 20
A41: Incremental Angel Cost | B41: =IFERROR($D$4*INDEX('Service Economics'!$F$5:$F$34,MATCH($B$4,'Service Economics'!$A$5:$A$34,0))*INDEX('Service Economics'!$M$5:$M$34,MATCH($B$4,'Service Economics'!$A$5:$A$34,0)),0) -> 0 | C41: =IFERROR($D$4*INDEX('Service Economics'!$F$5:$F$34,MATCH($B$4,'Service Economics'!$A$5:$A$34,0))*INDEX('Service Economics'!$M$5:$M$34,MATCH($B$4,'Service Economics'!$A$5:$A$34,0)),0) -> 0 | D41: Selected hours × no. of Angels × incremental Angel cost/hour. | K41: 20.5
A42: Transport Ops / Booking Support | B42: =0 -> 0 | C42: ='Global Inputs'!$B$18 -> 10 | D42: Additional booking / coordination ops cost for Case 2 only. | K42: 21
A43: Total Variable Delivery Cost | B43: =SUM(B34:B42) -> 115.79 | C43: =SUM(C34:C42) -> 125.79 | D43: Sum of all variable delivery costs above. | K43: 21.5
A44: Contribution Before Fixed Costs | B44: =B33-B43 -> 1319.8032 | C44: =C33-C43 -> 1458.8032 | D44: Net operating revenue − total variable delivery cost. | K44: 22
A45: Fully Loaded Angel Payroll — Current Utilization | B45: =IFERROR($D$4*INDEX('Service Economics'!$F$5:$F$34,MATCH($B$4,'Service Economics'!$A$5:$A$34,0))*'Angel Economics'!$G$10,0) -> 1208.2548 | C45: =IFERROR($D$4*INDEX('Service Economics'!$F$5:$F$34,MATCH($B$4,'Service Economics'!$A$5:$A$34,0))*'Angel Economics'!$G$10,0) -> 1208.2548 | D45: Selected hours × no. of Angels × current payroll cost/productive hour. | F45: Key operating lever: increase journey density and Angel utilization before adding fixed payroll. At target utilization, fully loaded cost/hour falls materially and more of the journey contribution becomes available to cover central fixed costs and EBITDA. | K45: 22.5
A46: Fully Loaded Contribution — Current Utilization | B46: =B44-B45 -> 111.54842 | C46: =C44-C45 -> 250.54842 | D46: Incremental contribution less current fully loaded Angel payroll allocation. | K46: 23
A47: Fully Loaded Contribution — Target Utilization | B47: =B44-IFERROR($D$4*INDEX('Service Economics'!$F$5:$F$34,MATCH($B$4,'Service Economics'!$A$5:$A$34,0))*'Angel Economics'!$H$10,0) -> 802.05174 | C47: =C44-IFERROR($D$4*INDEX('Service Economics'!$F$5:$F$34,MATCH($B$4,'Service Economics'!$A$5:$A$34,0))*'Angel Economics'!$H$10,0) -> 941.05174 | D47: Incremental contribution less Angel payroll allocation at target utilization. | K47: 23.5
K48: 24
A50: LEGACY PRICE BREAKOUT — HISTORICAL REFERENCE ONLY
A51: ="Live price bridge for "&$B$4&" | "&TEXT($D$4,"0.0")&" hours | Multiplier "&TEXT(INDEX('Service Economics'!$D$5:$D$34,MATCH($B$4,'Service Economics'!$A$5:$A$34,0)),"0.00x") -> Live price bridge for Hospital Visit | 5.0 hours | Multiplier 1.00x
A52: Price Component | B52: Value | C52: Calculation | D52: Why It Exists | F52: Live Founder Formula
A53: Selected Actual Hours | B53: =D4 -> 5 | C53: Dashboard scenario input | D53: Actual journey duration selected by founder. | F53: ="₹"&TEXT(B66,"#,##0")&" + ("&TEXT(B57,"0.0")&" × ₹"&TEXT(B58,"#,##0")&" × "&TEXT(B64,"0.00")&"x) + ("&TEXT(B60,"0.0")&" × ₹"&TEXT(B58,"#,##0")&" × "&TEXT(B64,"0.00")&"x) = ₹"&TEXT(B67,"#,##0") -> ₹199 + (4.0 × ₹299 × 1.00x) + (1.0 × ₹299 × 1.00x) = ₹1,694
A54: Minimum Billable Hours | B54: ='MVP1 Pricing & SKU'!B5 -> 2 | C54: MVP-1 assumption | D54: Protects minimum journey economics.
A55: Billable Hours | B55: =MAX(B53,B54) -> 5 | C55: MAX(Actual Hours, Minimum Hours) | D55: Customer is billed at least the minimum.
A56: Legacy 4-hour threshold | B56: ='MVP1 Pricing & SKU'!B6 -> 4 | C56: MVP-1 assumption | D56: Hours up to this threshold use the base rate.
A57: Legacy First 4h Hours | B57: =MIN(B55,B56) -> 4 | C57: Historical split only; not used in active Pricing Engine | D57: Number of hours charged at ₹299/hour.
A58: Base Hourly Rate | B58: ='MVP1 Pricing & SKU'!B7 -> 299 | C58: MVP-1 assumption | D58: Customer-facing rate for the first tier. | F58: Pricing rule: every billable hour uses the same effective service rate = ₹299 × service multiplier. The ₹199 Care Coordination Fee is added once and is never multiplied.
A59: Legacy First 4h Service Value | B59: =B57*B58*B64 -> 1196 | C59: Historical split only | D59: Value of the first 4 billable hours after applying the service-specific rate adjustment.
A60: Extended Billable Hours | B60: =MAX(B55-B56,0) -> 1 | C60: Historical additional-hours split only | D60: Only hours above 4 get the lower extended rate.
A61: Additional-Hour Effective Rate | B61: =B58*B64 -> 299 | C61: Base Hourly Rate × Service Multiplier | D61: Additional hours continue at the same effective service rate.
A62: Additional-Hour Service Value | B62: =B60*B61 -> 299 | C62: Additional Hours × Effective Rate | D62: Value of time beyond hour 4; no separate ₹269 discount is applied. | F62: ="Simplified formula: ₹"&TEXT(B66,"#,##0")&" + ("&TEXT(B55,"0.0")&" billable hours × ₹"&TEXT(B58,"#,##0")&" × "&TEXT(B64,"0.00")&"x) = ₹"&TEXT(B67,"#,##0") -> Simplified formula: ₹199 + (5.0 billable hours × ₹299 × 1.00x) = ₹1,694
A63: Total Adjusted Hourly Service Value | B63: =B59+B62 -> 1495 | C63: Historical first-4h + additional-hours reference | D63: Total hourly service value after the service adjustment.
A64: Service Pricing Multiplier | B64: =INDEX('Service Economics'!$D$5:$D$34,MATCH($B$4,'Service Economics'!$A$5:$A$34,0)) -> 1 | C64: Selected service multiplier | D64: Adjusts price for effort, complexity and service scope.
A65: Effective Service Rate / Hour | B65: =B58*B64 -> 299 | C65: Base Rate × Service Multiplier | D65: Same effective rate applies to all billable hours.
A66: Care Coordination Fee | B66: ='MVP1 Pricing & SKU'!B9 -> 199 | C66: Fixed fee per journey | D66: Booking, coordination and journey-level operating overhead.
A67: Customer Care Price (incl. GST) | B67: =B63+B66 -> 1694 | C67: Adjusted Hourly Service Value + Coordination Fee | D67: Final customer-facing care price before transport.
A68: Embedded GST | B68: =B67-B69 -> 258.40678 | C68: Customer Price − Net Care Revenue | D68: GST embedded inside the customer-facing care price.
A69: Net Care Revenue | B69: =B67/(1+'MVP1 Pricing & SKU'!B11) -> 1435.5932 | C69: Customer Price ÷ (1 + GST %) | D69: Revenue retained for operating economics before variable costs.

Sheet Global Inputs
A1: NivrāaCare — Global Unit Economics Inputs
A2: Change only blue numbers. Change any input and service profitability updates automatically. NC loyalty assumptions are controlled separately in the 'NC Credits' sheet.
A4: Input | B4: Value | C4: Unit | D4: Source / Note | F4: Governance
A5: Base customer charge per concierge hour | B5: ='MVP1 Pricing & SKU'!$B$7 -> 299 | C5: ₹ / hour | D5: Linked to Global Pricing Config — active master base hourly rate | F5: Founder Assumption
A6: Angel cost per hour | B6: 0 | C6: ₹ / Angel hour | D6: Founder working assumption: ₹700 ÷ 4 hours | E6: When we are keeping 3 Angels on payroll, then we do not have to pay them on per hour basis, so I have made per hour cost as ZERO.Angel payment 14K Per month | F6: Founder Assumption
A7: GST on care service | B7: ='Global Pricing Config'!$B$8 -> 0.18 | C7: % | D7: Illustrative assumption; confirm with CA | F7: Market Test / CA Confirmation
A8: Payment platform fee | B8: 0 | C8: % of customer collection | D8: Editable payment gateway assumption | F8: Market Test
A9: Payment platform fixed fee | B9: 0 | C9: ₹ / transaction | D9: Editable | F9: Founder Assumption
A10: Ops / support allocation | B10: 10 | C10: ₹ / journey | D10: Founder working assumption | F10: Founder Assumption
A11: Insurance / risk reserve | B11: 10 | C11: ₹ / journey | D11: Founder working assumption | F11: Founder Assumption
A12: WhatsApp / SMS / communication | B12: 0.5 | C12: ₹ / journey | D12: Founder working assumption | F12: Founder Assumption
A13: BGV + training allocation | B13: 0 | C13: ₹ / journey | D13: Founder working assumption | F13: Founder Assumption
A14: Refund / service recovery reserve | B14: 36 | C14: ₹ / journey | D14: Founder working assumption | F14: Founder Assumption
A15: Average third-party cab actual | B15: ='Global Pricing Config'!$B$10 -> 500 | C15: ₹ / journey | D15: Founder working assumption for Case 2 | F15: Founder Assumption
A16: Transport coordination fee | B16: ='Global Pricing Config'!$B$9 -> 149 | C16: ₹ / journey | D16: Founder working assumption for Case 2 | F16: Founder Assumption
A17: GST on transport coordination fee | B17: 0 | C17: % | D17: Set to applicable rate after CA confirmation | F17: Market Test / CA Confirmation
A18: Transport ops / booking support | B18: 10 | C18: ₹ / journey | D18: Founder working assumption | F18: Founder Assumption
A19: Legacy extended-hour price (inactive) | B19: ='MVP1 Pricing & SKU'!$B$8 -> 269 | C19: ₹ / hour | D19: Historical assumption only. Not used in current MVP pricing engine. | F19: Founder Assumption
A20: New customer acquisition cost (sensitivity only) | B20: 299 | C20: ₹ / new family | D20: Illustrative founder assumption for repeat-rate sensitivity | F20: Founder Assumption
A21: Base package hours (sensitivity only) | B21: 4 | C21: hours | D21: Used only in additional-hour sensitivity | F21: Founder Assumption
A22: Minimum booking hours (MVP1) | B22: ='Global Pricing Config'!$B$6 -> 2 | C22: hours | D22: Linked to MVP1 Pricing & SKU | F22: Founder Assumption
A24: PAYROLL ANGEL ECONOMICS
A25: Active payroll Angels | B25: 3 | C25: Angels | D25: Founder Assumption | E25: Initial payroll team assumption | F25: =D25 -> Founder Assumption
A26: Monthly salary / Angel | B26: 14000 | C26: ₹ / Angel / month | D26: Founder Assumption | E26: Based on founder working plan | F26: =D26 -> Founder Assumption
A27: Angel working days / month | B27: 26 | C27: days | D27: Founder Assumption | E27: Editable | F27: =D27 -> Founder Assumption
A28: Scheduled hours / Angel / day | B28: 8 | C28: hours | D28: Founder Assumption | E28: Editable | F28: =D28 -> Founder Assumption
A29: Target productive utilization | B29: 0.65 | C29: % | D29: Founder Assumption | E29: Planning utilization target | F29: =D29 -> Founder Assumption
A30: Monthly Angel payroll | B30: =B25*B26 -> 42000 | C30: ₹ / month | D30: Derived Formula | E30: Active payroll Angels × salary / Angel | F30: =D30 -> Derived Formula
A31: Available Angel hours / month | B31: =B25*B27*B28 -> 624 | C31: hours / month | D31: Derived Formula | E31: Angels × days × scheduled hours | F31: =D31 -> Derived Formula
A32: Target productive Angel hours / month | B32: =B31*B29 -> 405.6 | C32: hours / month | D32: Derived Formula | E32: Available hours × target utilization | F32: =D32 -> Derived Formula
A33: Target fully loaded Angel cost / productive hour | B33: =IF(B32=0,0,B30/B32) -> 103.5503 | C33: ₹ / productive hour | D33: Derived Formula | E33: Payroll ÷ target productive hours | F33: =D33 -> Derived Formula
A34: Current productive Angel hours / month | B34: ='Whitefield Monthly Projection'!$Q$19*'Whitefield Monthly Projection'!$Q$15 -> 173.8044 | C34: hours / month | D34: Derived Formula | E34: Current completed journeys × weighted avg duration | F34: =D34 -> Derived Formula
A35: Current fully loaded Angel cost / productive hour | B35: =IF(B34=0,0,B30/B34) -> 241.65096 | C35: ₹ / productive hour | D35: Derived Formula | E35: Payroll ÷ current productive hours | F35: =D35 -> Derived Formula

Sheet Service Economics
A1: NivrāaCare — Dynamic Service Unit Economics | Incremental vs Fully Loaded Contribution
A2: Edit BLUE input cells (hours, service multiplier, fixed premium, Angel count, and optional overrides). MVP-1 pricing is controlled from 'MVP1 Pricing & SKU'; expected NC loyalty cost is controlled from 'NC Credits'. Overnight / very-long-duration rows are marked manual.
A4: Service | B4: Category | C4: Hours | D4: Rate Multiplier | E4: Fixed Premium / Fee | F4: No. of Angels | G4: Angel Cost/Hr Override | H4: Cab Cost Override | I4: Coord. Fee Override | J4: Effective Service Rate / Hr | K4: Customer Service Price (Incl GST; ₹299 × multiplier × billable hours + ₹199 fee) | L4: Net Service Revenue | M4: Effective Angel Cost/Hr | N4: Angel Cost | O4: Payment Platform Cost | P4: Other Variable Care Cost | Q4: CASE 1 Variable Delivery Cost | R4: CASE 1 Contribution Before Fixed Costs | S4: CASE 1 Contribution Margin | T4: Effective 3P Cab Cost | U4: Effective Coordination Fee | V4: Customer Transport Charge | W4: Transport Payment Cost | X4: Transport Ops Cost | Y4: Net Transport Coordination Contribution | Z4: CASE 2 Total Customer Outflow | AA4: CASE 2 Total Direct Cash Cost | AB4: CASE 2 Contribution Before Fixed Costs | AC4: CASE 2 Profit Uplift | AD4: CASE 2 Contribution Margin | AE4: Contribution / Service Hour C1 | AF4: Contribution / Service Hour C2 | AG4: Expected NC Loyalty Cost | AH4: Pricing Mode | AI4: Incremental Angel Cost / Hr | AJ4: Target Fully Loaded Angel Cost / Hr | AK4: Target Fully Loaded Angel Cost | AL4: CASE 1 Fully Loaded Contribution | AM4: CASE 1 Fully Loaded Margin | AN4: CASE 2 Fully Loaded Contribution | AO4: CASE 2 Fully Loaded Margin | AP4: Fully Loaded Contribution / Angel Hr | AQ4: Recurring / Strategic Potential | AR4: Multiplier Reason
A5: Hospital Visit | B5: Medical Visit | C5: 4 | D5: 1 | E5: 0 | F5: 1 | J5: ='MVP1 Pricing & SKU'!$B$7*D5 -> 299 | K5: 1395 | L5: =K5/(1+'Global Inputs'!$B$7) -> 1182.2034 | M5: =IF(G5="",'Global Inputs'!$B$6,G5) -> 0 | N5: =C5*F5*M5 -> 0 | O5: =K5*'Global Inputs'!$B$8+'Global Inputs'!$B$9 -> 0 | P5: =SUM('Global Inputs'!$B$10:$B$14) -> 56.5 | Q5: =SUM(N5:P5)+AG5 -> 105.325 | R5: =L5-Q5 -> 1076.8784 | S5: =IF(L5=0,0,R5/L5) -> 0.91090789 | T5: =IF(H5="",'Global Inputs'!$B$15,H5) -> 500 | U5: =IF(I5="",'Global Inputs'!$B$16,I5) -> 149 | V5: =T5+U5 -> 649 | W5: =V5*'Global Inputs'!$B$8 -> 0 | X5: ='Global Inputs'!$B$18 -> 10 | Y5: =U5/(1+'Global Inputs'!$B$17)-W5-X5 -> 139 | Z5: =K5+V5 -> 2044 | AA5: =Q5+T5+W5+X5 -> 615.325 | AB5: =R5+Y5 -> 1215.8784 | AC5: =AB5-R5 -> 139 | AD5: 0.91336786 | AE5: =IF(C5=0,0,R5/C5) -> 269.2196 | AF5: =IF(C5=0,0,AB5/C5) -> 303.9696 | AG5: =L5*'NC Credits'!$B$15 -> 48.825 | AH5: =IF(OR(ISNUMBER(SEARCH("Overnight",A5)),ISNUMBER(SEARCH("Multi-Day",A5)),ISNUMBER(SEARCH("Medical Tourism",A5))),"MANUAL","AUTO") -> AUTO | AI5: =M5 -> 0 | AJ5: ='Global Inputs'!$B$33 -> 103.5503 | AK5: =C5*F5*AJ5 -> 414.20118 | AL5: =R5+N5-AK5 -> 662.67721 | AM5: =IF(L5=0,0,AL5/L5) -> 0.56054416 | AN5: =AB5+N5-AK5 -> 801.67721 | AO5: =IF((L5+U5/(1+'Global Inputs'!$B$17))=0,0,AN5/(L5+U5/(1+'Global Inputs'!$B$17))) -> 0.60221993 | AP5: =IF(C5*F5=0,0,AL5/(C5*F5)) -> 165.6693 | AQ5: 5 | AR5: Full journey: home → facility → return / safe handover
A6: Hospital Visit — Concierge at Hospital | B6: Medical Visit | C6: 3 | D6: 0.8 | E6: 0 | F6: 1 | J6: ='MVP1 Pricing & SKU'!$B$7*D6 -> 239.2 | K6: 916.6 | L6: =K6/(1+'Global Inputs'!$B$7) -> 776.77966 | M6: =IF(G6="",'Global Inputs'!$B$6,G6) -> 0 | N6: =C6*F6*M6 -> 0 | O6: =K6*'Global Inputs'!$B$8+'Global Inputs'!$B$9 -> 0 | P6: =SUM('Global Inputs'!$B$10:$B$14) -> 56.5 | Q6: =SUM(N6:P6)+AG6 -> 88.581 | R6: =L6-Q6 -> 688.19866 | S6: =IF(L6=0,0,R6/L6) -> 0.8859638 | T6: =IF(H6="",'Global Inputs'!$B$15,H6) -> 500 | U6: =IF(I6="",'Global Inputs'!$B$16,I6) -> 149 | V6: =T6+U6 -> 649 | W6: =V6*'Global Inputs'!$B$8 -> 0 | X6: ='Global Inputs'!$B$18 -> 10 | Y6: =U6/(1+'Global Inputs'!$B$17)-W6-X6 -> 139 | Z6: =K6+V6 -> 1565.6 | AA6: =Q6+T6+W6+X6 -> 598.581 | AB6: =R6+Y6 -> 827.19866 | AC6: =AB6-R6 -> 139 | AD6: 0.8935157 | AE6: =IF(C6=0,0,R6/C6) -> 229.39955 | AF6: =IF(C6=0,0,AB6/C6) -> 275.73289 | AG6: =L6*'NC Credits'!$B$15 -> 32.081 | AH6: =IF(OR(ISNUMBER(SEARCH("Overnight",A6)),ISNUMBER(SEARCH("Multi-Day",A6)),ISNUMBER(SEARCH("Medical Tourism",A6))),"MANUAL","AUTO") -> AUTO | AI6: =M6 -> 0 | AJ6: ='Global Inputs'!$B$33 -> 103.5503 | AK6: =C6*F6*AJ6 -> 310.65089 | AL6: =R6+N6-AK6 -> 377.54777 | AM6: =IF(L6=0,0,AL6/L6) -> 0.4860423 | AN6: =AB6+N6-AK6 -> 516.54777 | AO6: =IF((L6+U6/(1+'Global Inputs'!$B$17))=0,0,AN6/(L6+U6/(1+'Global Inputs'!$B$17))) -> 0.55795973 | AP6: =IF(C6*F6=0,0,AL6/(C6*F6)) -> 125.84926 | AQ6: 4 | AR6: Hospital-only support; reduced travel and handover responsibility
A7: Clinic Visit | B7: Medical Visit | C7: 2 | D7: 0.9 | E7: 0 | F7: 1 | J7: ='MVP1 Pricing & SKU'!$B$7*D7 -> 269.1 | K7: 737.2 | L7: =K7/(1+'Global Inputs'!$B$7) -> 624.74576 | M7: =IF(G7="",'Global Inputs'!$B$6,G7) -> 0 | N7: =C7*F7*M7 -> 0 | O7: =K7*'Global Inputs'!$B$8+'Global Inputs'!$B$9 -> 0 | P7: =SUM('Global Inputs'!$B$10:$B$14) -> 56.5 | Q7: =SUM(N7:P7)+AG7 -> 82.302 | R7: =L7-Q7 -> 542.44376 | S7: =IF(L7=0,0,R7/L7) -> 0.86826321 | T7: =IF(H7="",'Global Inputs'!$B$15,H7) -> 500 | U7: =IF(I7="",'Global Inputs'!$B$16,I7) -> 149 | V7: =T7+U7 -> 649 | W7: =V7*'Global Inputs'!$B$8 -> 0 | X7: ='Global Inputs'!$B$18 -> 10 | Y7: =U7/(1+'Global Inputs'!$B$17)-W7-X7 -> 139 | Z7: =K7+V7 -> 1386.2 | AA7: =Q7+T7+W7+X7 -> 592.302 | AB7: =R7+Y7 -> 681.44376 | AC7: =AB7-R7 -> 139 | AD7: 0.88070759 | AE7: =IF(C7=0,0,R7/C7) -> 271.22188 | AF7: =IF(C7=0,0,AB7/C7) -> 340.72188 | AG7: =L7*'NC Credits'!$B$15 -> 25.802 | AH7: =IF(OR(ISNUMBER(SEARCH("Overnight",A7)),ISNUMBER(SEARCH("Multi-Day",A7)),ISNUMBER(SEARCH("Medical Tourism",A7))),"MANUAL","AUTO") -> AUTO | AI7: =M7 -> 0 | AJ7: ='Global Inputs'!$B$33 -> 103.5503 | AK7: =C7*F7*AJ7 -> 207.10059 | AL7: =R7+N7-AK7 -> 335.34317 | AM7: =IF(L7=0,0,AL7/L7) -> 0.53676742 | AN7: =AB7+N7-AK7 -> 474.34317 | AO7: =IF((L7+U7/(1+'Global Inputs'!$B$17))=0,0,AN7/(L7+U7/(1+'Global Inputs'!$B$17))) -> 0.61304784 | AP7: =IF(C7*F7=0,0,AL7/(C7*F7)) -> 167.67159 | AQ7: 4 | AR7: Shorter, lower-complexity outpatient journey
A8: Diagnostic Center Visit | B8: Medical Visit | C8: 3 | D8: 0.85 | E8: 0 | F8: 1 | J8: ='MVP1 Pricing & SKU'!$B$7*D8 -> 254.15 | K8: 961.45 | L8: =K8/(1+'Global Inputs'!$B$7) -> 814.78814 | M8: =IF(G8="",'Global Inputs'!$B$6,G8) -> 0 | N8: =C8*F8*M8 -> 0 | O8: =K8*'Global Inputs'!$B$8+'Global Inputs'!$B$9 -> 0 | P8: =SUM('Global Inputs'!$B$10:$B$14) -> 56.5 | Q8: =SUM(N8:P8)+AG8 -> 90.15075 | R8: =L8-Q8 -> 724.63739 | S8: =IF(L8=0,0,R8/L8) -> 0.88935682 | T8: =IF(H8="",'Global Inputs'!$B$15,H8) -> 500 | U8: =IF(I8="",'Global Inputs'!$B$16,I8) -> 149 | V8: =T8+U8 -> 649 | W8: =V8*'Global Inputs'!$B$8 -> 0 | X8: ='Global Inputs'!$B$18 -> 10 | Y8: =U8/(1+'Global Inputs'!$B$17)-W8-X8 -> 139 | Z8: =K8+V8 -> 1610.45 | AA8: =Q8+T8+W8+X8 -> 600.15075 | AB8: =R8+Y8 -> 863.63739 | AC8: =AB8-R8 -> 139 | AD8: 0.89608634 | AE8: =IF(C8=0,0,R8/C8) -> 241.5458 | AF8: =IF(C8=0,0,AB8/C8) -> 287.87913 | AG8: =L8*'NC Credits'!$B$15 -> 33.65075 | AH8: =IF(OR(ISNUMBER(SEARCH("Overnight",A8)),ISNUMBER(SEARCH("Multi-Day",A8)),ISNUMBER(SEARCH("Medical Tourism",A8))),"MANUAL","AUTO") -> AUTO | AI8: =M8 -> 0 | AJ8: ='Global Inputs'!$B$33 -> 103.5503 | AK8: =C8*F8*AJ8 -> 310.65089 | AL8: =R8+N8-AK8 -> 413.9865 | AM8: =IF(L8=0,0,AL8/L8) -> 0.50809097 | AN8: =AB8+N8-AK8 -> 552.9865 | AO8: =IF((L8+U8/(1+'Global Inputs'!$B$17))=0,0,AN8/(L8+U8/(1+'Global Inputs'!$B$17))) -> 0.57376355 | AP8: =IF(C8*F8=0,0,AL8/(C8*F8)) -> 137.9955 | AQ8: 4 | AR8: Generally simpler navigation / diagnostic-only workflow
A9: Health Check-up Concierge | B9: Medical Visit | C9: 5 | D9: 0.9 | E9: 0 | F9: 1 | J9: ='MVP1 Pricing & SKU'!$B$7*D9 -> 269.1 | K9: 1544.5 | L9: =K9/(1+'Global Inputs'!$B$7) -> 1308.8983 | M9: =IF(G9="",'Global Inputs'!$B$6,G9) -> 0 | N9: =C9*F9*M9 -> 0 | O9: =K9*'Global Inputs'!$B$8+'Global Inputs'!$B$9 -> 0 | P9: =SUM('Global Inputs'!$B$10:$B$14) -> 56.5 | Q9: =SUM(N9:P9)+AG9 -> 110.5575 | R9: =L9-Q9 -> 1198.3408 | S9: =IF(L9=0,0,R9/L9) -> 0.91553393 | T9: =IF(H9="",'Global Inputs'!$B$15,H9) -> 500 | U9: =IF(I9="",'Global Inputs'!$B$16,I9) -> 149 | V9: =T9+U9 -> 649 | W9: =V9*'Global Inputs'!$B$8 -> 0 | X9: ='Global Inputs'!$B$18 -> 10 | Y9: =U9/(1+'Global Inputs'!$B$17)-W9-X9 -> 139 | Z9: =K9+V9 -> 2193.5 | AA9: =Q9+T9+W9+X9 -> 620.5575 | AB9: =R9+Y9 -> 1337.3408 | AC9: =AB9-R9 -> 139 | AD9: 0.91730733 | AE9: =IF(C9=0,0,R9/C9) -> 239.66816 | AF9: =IF(C9=0,0,AB9/C9) -> 267.46816 | AG9: =L9*'NC Credits'!$B$15 -> 54.0575 | AH9: =IF(OR(ISNUMBER(SEARCH("Overnight",A9)),ISNUMBER(SEARCH("Multi-Day",A9)),ISNUMBER(SEARCH("Medical Tourism",A9))),"MANUAL","AUTO") -> AUTO | AI9: =M9 -> 0 | AJ9: ='Global Inputs'!$B$33 -> 103.5503 | AK9: =C9*F9*AJ9 -> 517.75148 | AL9: =R9+N9-AK9 -> 680.58933 | AM9: =IF(L9=0,0,AL9/L9) -> 0.51997113 | AN9: =AB9+N9-AK9 -> 819.58933 | AO9: =IF((L9+U9/(1+'Global Inputs'!$B$17))=0,0,AN9/(L9+U9/(1+'Global Inputs'!$B$17))) -> 0.56217181 | AP9: =IF(C9*F9=0,0,AL9/(C9*F9)) -> 136.11787 | AQ9: 3 | AR9: Structured preventive-care journey; moderate coordination
A10: Hospital Admission Concierge | B10: Hospital Support | C10: 4 | D10: 1.15 | E10: 0 | F10: 1 | J10: ='MVP1 Pricing & SKU'!$B$7*D10 -> 343.85 | K10: 1574.4 | L10: =K10/(1+'Global Inputs'!$B$7) -> 1334.2373 | M10: =IF(G10="",'Global Inputs'!$B$6,G10) -> 0 | N10: =C10*F10*M10 -> 0 | O10: =K10*'Global Inputs'!$B$8+'Global Inputs'!$B$9 -> 0 | P10: =SUM('Global Inputs'!$B$10:$B$14) -> 56.5 | Q10: =SUM(N10:P10)+AG10 -> 111.604 | R10: =L10-Q10 -> 1222.6333 | S10: =IF(L10=0,0,R10/L10) -> 0.91635371 | T10: =IF(H10="",'Global Inputs'!$B$15,H10) -> 500 | U10: =IF(I10="",'Global Inputs'!$B$16,I10) -> 149 | V10: =T10+U10 -> 649 | W10: =V10*'Global Inputs'!$B$8 -> 0 | X10: ='Global Inputs'!$B$18 -> 10 | Y10: =U10/(1+'Global Inputs'!$B$17)-W10-X10 -> 139 | Z10: =K10+V10 -> 2223.4 | AA10: =Q10+T10+W10+X10 -> 621.604 | AB10: =R10+Y10 -> 1361.6333 | AC10: =AB10-R10 -> 139 | AD10: 0.91801447 | AE10: =IF(C10=0,0,R10/C10) -> 305.65832 | AF10: =IF(C10=0,0,AB10/C10) -> 340.40832 | AG10: =L10*'NC Credits'!$B$15 -> 55.104 | AH10: =IF(OR(ISNUMBER(SEARCH("Overnight",A10)),ISNUMBER(SEARCH("Multi-Day",A10)),ISNUMBER(SEARCH("Medical Tourism",A10))),"MANUAL","AUTO") -> AUTO | AI10: =M10 -> 0 | AJ10: ='Global Inputs'!$B$33 -> 103.5503 | AK10: =C10*F10*AJ10 -> 414.20118 | AL10: =R10+N10-AK10 -> 808.4321 | AM10: =IF(L10=0,0,AL10/L10) -> 0.60591329 | AN10: =AB10+N10-AK10 -> 947.4321 | AO10: =IF((L10+U10/(1+'Global Inputs'!$B$17))=0,0,AN10/(L10+U10/(1+'Global Inputs'!$B$17))) -> 0.63875963 | AP10: =IF(C10*F10=0,0,AL10/(C10*F10)) -> 202.10803 | AQ10: 3 | AR10: Higher coordination, documentation and handoff complexity
A11: Hospital Discharge Concierge | B11: Hospital Support | C11: 4 | D11: 1.1 | E11: 0 | F11: 1 | J11: ='MVP1 Pricing & SKU'!$B$7*D11 -> 328.9 | K11: 1514.6 | L11: =K11/(1+'Global Inputs'!$B$7) -> 1283.5593 | M11: =IF(G11="",'Global Inputs'!$B$6,G11) -> 0 | N11: =C11*F11*M11 -> 0 | O11: =K11*'Global Inputs'!$B$8+'Global Inputs'!$B$9 -> 0 | P11: =SUM('Global Inputs'!$B$10:$B$14) -> 56.5 | Q11: =SUM(N11:P11)+AG11 -> 109.511 | R11: =L11-Q11 -> 1174.0483 | S11: =IF(L11=0,0,R11/L11) -> 0.91468178 | T11: =IF(H11="",'Global Inputs'!$B$15,H11) -> 500 | U11: =IF(I11="",'Global Inputs'!$B$16,I11) -> 149 | V11: =T11+U11 -> 649 | W11: =V11*'Global Inputs'!$B$8 -> 0 | X11: ='Global Inputs'!$B$18 -> 10 | Y11: =U11/(1+'Global Inputs'!$B$17)-W11-X11 -> 139 | Z11: =K11+V11 -> 2163.6 | AA11: =Q11+T11+W11+X11 -> 619.511 | AB11: =R11+Y11 -> 1313.0483 | AC11: =AB11-R11 -> 139 | AD11: 0.91657518 | AE11: =IF(C11=0,0,R11/C11) -> 293.51208 | AF11: =IF(C11=0,0,AB11/C11) -> 328.26208 | AG11: =L11*'NC Credits'!$B$15 -> 53.011 | AH11: =IF(OR(ISNUMBER(SEARCH("Overnight",A11)),ISNUMBER(SEARCH("Multi-Day",A11)),ISNUMBER(SEARCH("Medical Tourism",A11))),"MANUAL","AUTO") -> AUTO | AI11: =M11 -> 0 | AJ11: ='Global Inputs'!$B$33 -> 103.5503 | AK11: =C11*F11*AJ11 -> 414.20118 | AL11: =R11+N11-AK11 -> 759.84714 | AM11: =IF(L11=0,0,AL11/L11) -> 0.59198443 | AN11: =AB11+N11-AK11 -> 898.84714 | AO11: =IF((L11+U11/(1+'Global Inputs'!$B$17))=0,0,AN11/(L11+U11/(1+'Global Inputs'!$B$17))) -> 0.62744148 | AP11: =IF(C11*F11=0,0,AL11/(C11*F11)) -> 189.96178 | AQ11: 3 | AR11: Higher coordination and post-discharge handover responsibility
A12: Overnight Hospital Concierge | B12: Hospital Support | C12: 12 | D12: 0.85 | E12: 299 | F12: 1 | J12: ='MVP1 Pricing & SKU'!$B$7*D12 -> 254.15 | K12: 3547.8 | L12: =K12/(1+'Global Inputs'!$B$7) -> 3006.6102 | M12: =IF(G12="",'Global Inputs'!$B$6,G12) -> 0 | N12: =C12*F12*M12 -> 0 | O12: =K12*'Global Inputs'!$B$8+'Global Inputs'!$B$9 -> 0 | P12: =SUM('Global Inputs'!$B$10:$B$14) -> 56.5 | Q12: =SUM(N12:P12)+AG12 -> 180.673 | R12: =L12-Q12 -> 2825.9372 | S12: =IF(L12=0,0,R12/L12) -> 0.93990807 | T12: =IF(H12="",'Global Inputs'!$B$15,H12) -> 500 | U12: =IF(I12="",'Global Inputs'!$B$16,I12) -> 149 | V12: =T12+U12 -> 649 | W12: =V12*'Global Inputs'!$B$8 -> 0 | X12: ='Global Inputs'!$B$18 -> 10 | Y12: =U12/(1+'Global Inputs'!$B$17)-W12-X12 -> 139 | Z12: =K12+V12 -> 4196.8 | AA12: =Q12+T12+W12+X12 -> 690.673 | AB12: =R12+Y12 -> 2964.9372 | AC12: =AB12-R12 -> 139 | AD12: 0.9395765 | AE12: =IF(C12=0,0,R12/C12) -> 235.49476 | AF12: =IF(C12=0,0,AB12/C12) -> 247.0781 | AG12: =L12*'NC Credits'!$B$15 -> 124.173 | AH12: =IF(OR(ISNUMBER(SEARCH("Overnight",A12)),ISNUMBER(SEARCH("Multi-Day",A12)),ISNUMBER(SEARCH("Medical Tourism",A12))),"MANUAL","AUTO") -> MANUAL | AI12: =M12 -> 0 | AJ12: ='Global Inputs'!$B$33 -> 103.5503 | AK12: =C12*F12*AJ12 -> 1242.6036 | AL12: =R12+N12-AK12 -> 1583.3336 | AM12: =IF(L12=0,0,AL12/L12) -> 0.52661753 | AN12: =AB12+N12-AK12 -> 1722.3336 | AO12: =IF((L12+U12/(1+'Global Inputs'!$B$17))=0,0,AN12/(L12+U12/(1+'Global Inputs'!$B$17))) -> 0.5458005 | AP12: =IF(C12*F12=0,0,AL12/(C12*F12)) -> 131.94447 | AQ12: 2 | AR12: Long-duration service; manual pricing should supersede multiplier
A13: Multi-Day Hospital Concierge (per 12h shift) | B13: Hospital Support | C13: 12 | D13: 0.85 | E13: 299 | F13: 1 | J13: ='MVP1 Pricing & SKU'!$B$7*D13 -> 254.15 | K13: 3547.8 | L13: =K13/(1+'Global Inputs'!$B$7) -> 3006.6102 | M13: =IF(G13="",'Global Inputs'!$B$6,G13) -> 0 | N13: =C13*F13*M13 -> 0 | O13: =K13*'Global Inputs'!$B$8+'Global Inputs'!$B$9 -> 0 | P13: =SUM('Global Inputs'!$B$10:$B$14) -> 56.5 | Q13: =SUM(N13:P13)+AG13 -> 180.673 | R13: =L13-Q13 -> 2825.9372 | S13: =IF(L13=0,0,R13/L13) -> 0.93990807 | T13: =IF(H13="",'Global Inputs'!$B$15,H13) -> 500 | U13: =IF(I13="",'Global Inputs'!$B$16,I13) -> 149 | V13: =T13+U13 -> 649 | W13: =V13*'Global Inputs'!$B$8 -> 0 | X13: ='Global Inputs'!$B$18 -> 10 | Y13: =U13/(1+'Global Inputs'!$B$17)-W13-X13 -> 139 | Z13: =K13+V13 -> 4196.8 | AA13: =Q13+T13+W13+X13 -> 690.673 | AB13: =R13+Y13 -> 2964.9372 | AC13: =AB13-R13 -> 139 | AD13: 0.9395765 | AE13: =IF(C13=0,0,R13/C13) -> 235.49476 | AF13: =IF(C13=0,0,AB13/C13) -> 247.0781 | AG13: =L13*'NC Credits'!$B$15 -> 124.173 | AH13: =IF(OR(ISNUMBER(SEARCH("Overnight",A13)),ISNUMBER(SEARCH("Multi-Day",A13)),ISNUMBER(SEARCH("Medical Tourism",A13))),"MANUAL","AUTO") -> MANUAL | AI13: =M13 -> 0 | AJ13: ='Global Inputs'!$B$33 -> 103.5503 | AK13: =C13*F13*AJ13 -> 1242.6036 | AL13: =R13+N13-AK13 -> 1583.3336 | AM13: =IF(L13=0,0,AL13/L13) -> 0.52661753 | AN13: =AB13+N13-AK13 -> 1722.3336 | AO13: =IF((L13+U13/(1+'Global Inputs'!$B$17))=0,0,AN13/(L13+U13/(1+'Global Inputs'!$B$17))) -> 0.5458005 | AP13: =IF(C13*F13=0,0,AL13/(C13*F13)) -> 131.94447 | AQ13: 2 | AR13: Long-duration service; manual shift pricing
A14: Day Surgery / Procedure Concierge | B14: Procedure & Treatment | C14: 6 | D14: 1.2 | E14: 0 | F14: 1 | J14: ='MVP1 Pricing & SKU'!$B$7*D14 -> 358.8 | K14: 2351.8 | L14: =K14/(1+'Global Inputs'!$B$7) -> 1993.0508 | M14: =IF(G14="",'Global Inputs'!$B$6,G14) -> 0 | N14: =C14*F14*M14 -> 0 | O14: =K14*'Global Inputs'!$B$8+'Global Inputs'!$B$9 -> 0 | P14: =SUM('Global Inputs'!$B$10:$B$14) -> 56.5 | Q14: =SUM(N14:P14)+AG14 -> 138.813 | R14: =L14-Q14 -> 1854.2378 | S14: =IF(L14=0,0,R14/L14) -> 0.9303515 | T14: =IF(H14="",'Global Inputs'!$B$15,H14) -> 500 | U14: =IF(I14="",'Global Inputs'!$B$16,I14) -> 149 | V14: =T14+U14 -> 649 | W14: =V14*'Global Inputs'!$B$8 -> 0 | X14: ='Global Inputs'!$B$18 -> 10 | Y14: =U14/(1+'Global Inputs'!$B$17)-W14-X14 -> 139 | Z14: =K14+V14 -> 3000.8 | AA14: =Q14+T14+W14+X14 -> 648.813 | AB14: =R14+Y14 -> 1993.2378 | AC14: =AB14-R14 -> 139 | AD14: 0.93052779 | AE14: =IF(C14=0,0,R14/C14) -> 309.03964 | AF14: =IF(C14=0,0,AB14/C14) -> 332.20631 | AG14: =L14*'NC Credits'!$B$15 -> 82.313 | AH14: =IF(OR(ISNUMBER(SEARCH("Overnight",A14)),ISNUMBER(SEARCH("Multi-Day",A14)),ISNUMBER(SEARCH("Medical Tourism",A14))),"MANUAL","AUTO") -> AUTO | AI14: =M14 -> 0 | AJ14: ='Global Inputs'!$B$33 -> 103.5503 | AK14: =C14*F14*AJ14 -> 621.30178 | AL14: =R14+N14-AK14 -> 1232.9361 | AM14: =IF(L14=0,0,AL14/L14) -> 0.61861747 | AN14: =AB14+N14-AK14 -> 1371.9361 | AO14: =IF((L14+U14/(1+'Global Inputs'!$B$17))=0,0,AN14/(L14+U14/(1+'Global Inputs'!$B$17))) -> 0.64047783 | AP14: =IF(C14*F14=0,0,AL14/(C14*F14)) -> 205.48935 | AQ14: 3 | AR14: Procedure-day complexity and extended coordination
A15: Pre-Surgery Concierge | B15: Procedure & Treatment | C15: 4 | D15: 1.1 | E15: 0 | F15: 1 | J15: ='MVP1 Pricing & SKU'!$B$7*D15 -> 328.9 | K15: 1514.6 | L15: =K15/(1+'Global Inputs'!$B$7) -> 1283.5593 | M15: =IF(G15="",'Global Inputs'!$B$6,G15) -> 0 | N15: =C15*F15*M15 -> 0 | O15: =K15*'Global Inputs'!$B$8+'Global Inputs'!$B$9 -> 0 | P15: =SUM('Global Inputs'!$B$10:$B$14) -> 56.5 | Q15: =SUM(N15:P15)+AG15 -> 109.511 | R15: =L15-Q15 -> 1174.0483 | S15: =IF(L15=0,0,R15/L15) -> 0.91468178 | T15: =IF(H15="",'Global Inputs'!$B$15,H15) -> 500 | U15: =IF(I15="",'Global Inputs'!$B$16,I15) -> 149 | V15: =T15+U15 -> 649 | W15: =V15*'Global Inputs'!$B$8 -> 0 | X15: ='Global Inputs'!$B$18 -> 10 | Y15: =U15/(1+'Global Inputs'!$B$17)-W15-X15 -> 139 | Z15: =K15+V15 -> 2163.6 | AA15: =Q15+T15+W15+X15 -> 619.511 | AB15: =R15+Y15 -> 1313.0483 | AC15: =AB15-R15 -> 139 | AD15: 0.91657518 | AE15: =IF(C15=0,0,R15/C15) -> 293.51208 | AF15: =IF(C15=0,0,AB15/C15) -> 328.26208 | AG15: =L15*'NC Credits'!$B$15 -> 53.011 | AH15: =IF(OR(ISNUMBER(SEARCH("Overnight",A15)),ISNUMBER(SEARCH("Multi-Day",A15)),ISNUMBER(SEARCH("Medical Tourism",A15))),"MANUAL","AUTO") -> AUTO | AI15: =M15 -> 0 | AJ15: ='Global Inputs'!$B$33 -> 103.5503 | AK15: =C15*F15*AJ15 -> 414.20118 | AL15: =R15+N15-AK15 -> 759.84714 | AM15: =IF(L15=0,0,AL15/L15) -> 0.59198443 | AN15: =AB15+N15-AK15 -> 898.84714 | AO15: =IF((L15+U15/(1+'Global Inputs'!$B$17))=0,0,AN15/(L15+U15/(1+'Global Inputs'!$B$17))) -> 0.62744148 | AP15: =IF(C15*F15=0,0,AL15/(C15*F15)) -> 189.96178 | AQ15: 2 | AR15: Preparation, records and multi-party coordination
A16: Post-Surgery Follow-up | B16: Procedure & Treatment | C16: 3 | D16: 1 | E16: 0 | F16: 1 | J16: ='MVP1 Pricing & SKU'!$B$7*D16 -> 299 | K16: 1096 | L16: =K16/(1+'Global Inputs'!$B$7) -> 928.81356 | M16: =IF(G16="",'Global Inputs'!$B$6,G16) -> 0 | N16: =C16*F16*M16 -> 0 | O16: =K16*'Global Inputs'!$B$8+'Global Inputs'!$B$9 -> 0 | P16: =SUM('Global Inputs'!$B$10:$B$14) -> 56.5 | Q16: =SUM(N16:P16)+AG16 -> 94.86 | R16: =L16-Q16 -> 833.95356 | S16: =IF(L16=0,0,R16/L16) -> 0.89786971 | T16: =IF(H16="",'Global Inputs'!$B$15,H16) -> 500 | U16: =IF(I16="",'Global Inputs'!$B$16,I16) -> 149 | V16: =T16+U16 -> 649 | W16: =V16*'Global Inputs'!$B$8 -> 0 | X16: ='Global Inputs'!$B$18 -> 10 | Y16: =U16/(1+'Global Inputs'!$B$17)-W16-X16 -> 139 | Z16: =K16+V16 -> 1745 | AA16: =Q16+T16+W16+X16 -> 604.86 | AB16: =R16+Y16 -> 972.95356 | AC16: =AB16-R16 -> 139 | AD16: 0.90271045 | AE16: =IF(C16=0,0,R16/C16) -> 277.98452 | AF16: =IF(C16=0,0,AB16/C16) -> 324.31785 | AG16: =L16*'NC Credits'!$B$15 -> 38.36 | AH16: =IF(OR(ISNUMBER(SEARCH("Overnight",A16)),ISNUMBER(SEARCH("Multi-Day",A16)),ISNUMBER(SEARCH("Medical Tourism",A16))),"MANUAL","AUTO") -> AUTO | AI16: =M16 -> 0 | AJ16: ='Global Inputs'!$B$33 -> 103.5503 | AK16: =C16*F16*AJ16 -> 310.65089 | AL16: =R16+N16-AK16 -> 523.30267 | AM16: =IF(L16=0,0,AL16/L16) -> 0.56340981 | AN16: =AB16+N16-AK16 -> 662.30267 | AO16: =IF((L16+U16/(1+'Global Inputs'!$B$17))=0,0,AN16/(L16+U16/(1+'Global Inputs'!$B$17))) -> 0.61448723 | AP16: =IF(C16*F16=0,0,AL16/(C16*F16)) -> 174.43422 | AQ16: 3 | AR16: Standard follow-up journey with moderate coordination
... A34: Family Medical Update Concierge | B34: Continuing Care | C34: 3 | D34: 0.65 | E34: 0 | F34: 1 | J34: ='MVP1 Pricing & SKU'!$B$7*D34 -> 194.35 | K34: 782.05 | L34: =K34/(1+'Global Inputs'!$B$7) -> 662.75424 | M34: =IF(G34="",'Global Inputs'!$B$6,G34) -> 0 | N34: =C34*F34*M34 -> 0 | O34: =K34*'Global Inputs'!$B$8+'Global Inputs'!$B$9 -> 0 | P34: =SUM('Global Inputs'!$B$10:$B$14) -> 56.5 | Q34: =SUM(N34:P34)+AG34 -> 83.87175 | R34: =L34-Q34 -> 578.88249 | S34: =IF(L34=0,0,R34/L34) -> 0.8734497 | T34: =IF(H34="",'Global Inputs'!$B$15,H34) -> 500 | U34: =IF(I34="",'Global Inputs'!$B$16,I34) -> 149 | V34: =T34+U34 -> 649 | W34: =V34*'Global Inputs'!$B$8 -> 0 | X34: ='Global Inputs'!$B$18 -> 10 | Y34: =U34/(1+'Global Inputs'!$B$17)-W34-X34 -> 139 | Z34: =K34+V34 -> 1431.05 | AA34: =Q34+T34+W34+X34 -> 593.87175 | AB34: =R34+Y34 -> 717.88249 | AC34: =AB34-R34 -> 139 | AD34: 0.8843594 | AE34: =IF(C34=0,0,R34/C34) -> 192.96083 | AF34: =IF(C34=0,0,AB34/C34) -> 239.29416 | AG34: =L34*'NC Credits'!$B$15 -> 27.37175 | AH34: =IF(OR(ISNUMBER(SEARCH("Overnight",A34)),ISNUMBER(SEARCH("Multi-Day",A34)),ISNUMBER(SEARCH("Medical Tourism",A34))),"MANUAL","AUTO") -> AUTO | AI34: =M34 -> 0 | AJ34: ='Global Inputs'!$B$33 -> 103.5503 | AK34: =C34*F34*AJ34 -> 310.65089 | AL34: =R34+N34-AK34 -> 268.2316 | AM34: =IF(L34=0,0,AL34/L34) -> 0.40472257 | AN34: =AB34+N34-AK34 -> 407.2316 | AO34: =IF((L34+U34/(1+'Global Inputs'!$B$17))=0,0,AN34/(L34+U34/(1+'Global Inputs'!$B$17))) -> 0.50166859 | AP34: =IF(C34*F34=0,0,AL34/(C34*F34)) -> 89.410533 | AQ34: 5 | AR34: Communication-focused support; no full physical journey

Sheet Service Catalogue
A1: NivrāaCare — Medical Concierge Service Catalogue
A3: Service | B3: Category | C3: Typical Concierge Scope | D3: Clinical Boundary
A4: Hospital Visit | B4: Medical Visit | C4: Accompany patient, navigate registration/queues, coordinate visit, family updates, return handover. | D4: NivrāaCare concierge does not diagnose, prescribe, administer clinical treatment, or replace licensed medical professionals.
A5: Diagnostic Center Visit | B5: Medical Visit | C5: Accompany patient, navigate registration/queues, coordinate visit, family updates, return handover. | D5: NivrāaCare concierge does not diagnose, prescribe, administer clinical treatment, or replace licensed medical professionals.
A6: Clinic Visit | B6: Medical Visit | C6: Accompany patient, navigate registration/queues, coordinate visit, family updates, return handover. | D6: NivrāaCare concierge does not diagnose, prescribe, administer clinical treatment, or replace licensed medical professionals.
A7: Specialist Consultation | B7: Medical Visit | C7: Accompany patient, navigate registration/queues, coordinate visit, family updates, return handover. | D7: NivrāaCare concierge does not diagnose, prescribe, administer clinical treatment, or replace licensed medical professionals.
A8: Health Check-up Concierge | B8: Medical Visit | C8: Accompany patient, navigate registration/queues, coordinate visit, family updates, return handover. | D8: NivrāaCare concierge does not diagnose, prescribe, administer clinical treatment, or replace licensed medical professionals.
A9: Hospital Admission Concierge | B9: Hospital Support | C9: Admission/discharge/overnight non-clinical presence, logistics, documents, family communication. | D9: NivrāaCare concierge does not diagnose, prescribe, administer clinical treatment, or replace licensed medical professionals.
A10: Hospital Discharge Concierge | B10: Hospital Support | C10: Admission/discharge/overnight non-clinical presence, logistics, documents, family communication. | D10: NivrāaCare concierge does not diagnose, prescribe, administer clinical treatment, or replace licensed medical professionals.
A11: Overnight Hospital Concierge | B11: Hospital Support | C11: Admission/discharge/overnight non-clinical presence, logistics, documents, family communication. | D11: NivrāaCare concierge does not diagnose, prescribe, administer clinical treatment, or replace licensed medical professionals.
A12: Multi-Day Hospital Concierge (per 12h shift) | B12: Hospital Support | C12: Admission/discharge/overnight non-clinical presence, logistics, documents, family communication. | D12: NivrāaCare concierge does not diagnose, prescribe, administer clinical treatment, or replace licensed medical professionals.
A13: Day Surgery / Procedure Concierge | B13: Procedure & Treatment | C13: Pre/post procedure logistics, waiting coordination, non-clinical accompaniment and handover. | D13: NivrāaCare concierge does not diagnose, prescribe, administer clinical treatment, or replace licensed medical professionals.
A14: Pre-Surgery Concierge | B14: Procedure & Treatment | C14: Pre/post procedure logistics, waiting coordination, non-clinical accompaniment and handover. | D14: NivrāaCare concierge does not diagnose, prescribe, administer clinical treatment, or replace licensed medical professionals.
... A33: Family Medical Update Concierge | B33: Continuing Care | C33: Ongoing family coordination, scheduled follow-ups, authorised updates and continuity. | D33: NivrāaCare concierge does not diagnose, prescribe, administer clinical treatment, or replace licensed medical professionals.

Sheet Whitefield Monthly Projection
A1: NivrāaCare — Whitefield Monthly Revenue & Profit Projection
A2: Founder model for Whitefield-only launch. Service revenue flows from the MVP-1 hourly pricing engine: ₹299/hour × service-specific multiplier × billable hours + ₹199 fee, 2h minimum. ₹269 is retained only as a legacy reference and is not used in active pricing.
A4: Selected Scenario | B4: Conservative | F4: Scenario Driver | G4: Conservative | H4: Base | I4: Aggressive | J4: Selected | P4: Selected Scenario — Monthly Summary | U4: Variable Cost Breakdown
A5: Operating Input | B5: Value | F5: Active Angels | G5: 4 | H5: 5 | I5: 7 | J5: =IF($B$4="Conservative",G5,IF($B$4="Base",H5,I5)) -> 4 | P5: Demand | Q5: Value | U5: Variable Cost | V5: Monthly ₹ | W5: Driver
A6: Active Angels | B6: =J5 -> 4 | F6: Leads / day | G6: 6 | H6: 10 | I6: 16 | J6: =IF($B$4="Conservative",G6,IF($B$4="Base",H6,I6)) -> 6 | P6: Leads / month | Q6: =$B$11*$B$7 -> 180 | U6: Angel payouts | V6: =SUMPRODUCT(I37:I66,'Service Economics'!N5:N34) -> 0 | W6: Hours × Angel cost
A7: Operating days / month | B7: 30 | F7: Booking conversion | G7: 0.25 | H7: 0.35 | I7: 0.45 | J7: =IF($B$4="Conservative",G7,IF($B$4="Base",H7,I7)) -> 0.25 | P7: Confirmed journeys | Q7: =Q6*$B$12 -> 45 | U7: Payment platform — care service | V7: =SUMPRODUCT(I37:I66,'Service Economics'!O5:O34) -> 0 | W7: Service collections × fee
A8: Max working hours / Angel / day | B8: 8 | F8: Cancellation | G8: 0.12 | H8: 0.08 | I8: 0.06 | J8: =IF($B$4="Conservative",G8,IF($B$4="Base",H8,I8)) -> 0.12 | P8: Cancelled journeys | Q8: =Q7*$B$13 -> 5.4 | U8: Ops / support allocation | V8: =$Q$19*'Global Inputs'!$B$10 -> 376.2 | W8: Per completed journey
A9: Target Angel utilization | B9: 1 | F9: No-show / refund | G9: 0.05 | H9: 0.03 | I9: 0.02 | J9: =IF($B$4="Conservative",G9,IF($B$4="Base",H9,I9)) -> 0.05 | P9: No-show / refund journeys | Q9: =(Q7-Q8)*$B$14 -> 1.98 | U9: Insurance / risk reserve | V9: =$Q$19*'Global Inputs'!$B$11 -> 376.2 | W9: Per completed journey
A10: Avg journeys / Angel / day cap | B10: 1.8 | F10: Target utilization | G10: 0.5 | H10: 0.65 | I10: 0.8 | J10: =IF($B$4="Conservative",G10,IF($B$4="Base",H10,I10)) -> 0.5 | P10: Demand-completed journeys | Q10: =Q7-Q8-Q9 -> 37.62 | U10: WhatsApp / SMS | V10: =$Q$19*'Global Inputs'!$B$12 -> 18.81 | W10: Per completed journey
A11: Customer leads / enquiries per day | B11: =J6 -> 6 | F11: Case 2 transport mix | G11: 0.4 | H11: 0.6 | I11: 0.7 | J11: =IF($B$4="Conservative",G11,IF($B$4="Base",H11,I11)) -> 0.4 | U11: BGV + training allocation | V11: =$Q$19*'Global Inputs'!$B$13 -> 0 | W11: Per completed journey
A12: Booking conversion rate | B12: =J7 -> 0.25 | F12: Repeat journey mix | G12: 0.2 | H12: 0.3 | I12: 0.45 | J12: =IF($B$4="Conservative",G12,IF($B$4="Base",H12,I12)) -> 0.2 | P12: Capacity | Q12: Value | U12: Refund / service recovery reserve | V12: =$Q$19*'Global Inputs'!$B$14 -> 1354.32 | W12: Per completed journey
A13: Cancellation rate | B13: =J8 -> 0.12 | P13: Total Angel hours available | Q13: =$B$6*$B$7*$B$8 -> 960 | U13: Third-party cab actual | V13: =$B$16*SUMPRODUCT(I37:I66,'Service Economics'!T5:T34) -> 7524 | W13: Case 2 journeys
A14: No-show / refund rate | B14: =J9 -> 0.05 | P14: Productive Angel hours | Q14: =Q13*$B$9 -> 960 | U14: Transport payment cost | V14: =$B$16*SUMPRODUCT(I37:I66,'Service Economics'!W5:W34) -> 0 | W14: Case 2 transport collections
A15: Case 1 mix — patient arranges transport | B15: =1-J11 -> 0.6 | P15: Weighted avg service hours | Q15: =S45 -> 4.62 | U15: Transport ops / booking support | V15: =$Q$19*$B$16*'Global Inputs'!$B$18 -> 150.48 | W15: Case 2 journeys
A16: Case 2 mix — NivrāaCare arranges 3P cab | B16: =J11 -> 0.4 | P16: Max journeys by Angel hours | Q16: =IF(Q15=0,0,Q14/Q15) -> 207.79221 | U16: Other service-level variable cost | V16: =SUMPRODUCT(I37:I66,H37:H66) -> 0 | W16: Editable by service
A17: Repeat customer journey mix | B17: =J12 -> 0.2 | P17: Max journeys by daily journey cap | Q17: =$B$6*$B$10*$B$7 -> 216 | U17: NC Credits expected cost | V17: =SUMPRODUCT(I37:I66,'Service Economics'!AG5:AG34) -> 2450.2681 | W17: Expected loyalty redemption cost
A18: New customer journey mix | B18: =1-J12 -> 0.8 | P18: Maximum journeys possible | Q18: =MIN(Q16,Q17) -> 207.79221 | U18: TOTAL VARIABLE COST | V18: =SUM(V6:V17) -> 12250.278 | W18: Should reconcile to Net Revenue − Contribution
A19: Avg journeys / repeat family / month | B19: 2 | P19: Completed journeys (actual) | Q19: =MIN(Q18,Q10) -> 37.62
P20: Unmet demand | Q20: =MAX(Q10-Q19,0) -> 0
A21: Editable Monthly Fixed Costs | P21: Actual Angel utilization | Q21: =IF(Q13=0,0,Q19*Q15/Q13) -> 0.18104625
A22: Fixed Cost | B22: Monthly ₹ | C22: Comment | P22: Capacity surplus / (shortage) hours | Q22: =Q14-Q19*Q15 -> 786.1956
A23: Ops Manager / Care Operations | B23: 45000 | C23: Initial Whitefield operating lead
A24: Customer Support | B24: 10000 | C24: Customer + family support | P24: Revenue & Profitability | Q24: Value | R24: Transport Mix / Contribution | S24: Value
A25: Technology / Cloud / Tools | B25: 8000 | C25: Cloud, monitoring, software | P25: Gross customer service revenue | Q25: =SUM(K37:K66) -> 70007.66 | R25: Case 1 completed journeys | S25: =$Q$19*$B$15 -> 22.572
A26: Marketing | B26: 10000 | C26: Pilot acquisition budget | P26: Transport customer collections | Q26: =SUM(L37:L66) -> 9766.152 | R26: Case 2 completed journeys | S26: =$Q$19*$B$16 -> 15.048
A27: Office / Admin | B27: 10000 | C27: Admin, travel, supplies | P27: Total customer collections | Q27: =Q25+Q26 -> 79773.812 | R27: Case 1 contribution | S27: =$Q$19*$B$15*(S47-S50) -> 32851.636
A28: Legal / CA / Compliance | B28: 4000 | C28: Monthly allocation | P28: Illustrative GST on care service | Q28: =Q25-SUM(Y37:Y66) -> 10679.135 | R28: Case 2 contribution | S28: =$Q$19*$B$16*(S48-S50) -> 23992.763
A29: Fixed Insurance | B29: 5000 | C29: Illustrative fixed component | P29: Illustrative GST on coordination fee | Q29: =SUM(Z37:Z66) -> 0 | R29: Mix check | S29: =$B$15+$B$16 -> 1
A30: Founders / Core Team Salary | B30: 0 | C30: Keep editable for founder discussion | P30: Net operating revenue | Q30: =SUM(M37:M66) -> 69094.677
A31: Miscellaneous | B31: 4000 | C31: Contingency / other fixed costs | P31: Total variable costs | Q31: =Q30-Q32 -> 12250.278
A32: TOTAL FIXED COSTS | B32: =SUM(B23:B31)+'Global Inputs'!$B$30 -> 138000 | C32: Includes payroll Angel salaries from Global Inputs | P32: Monthly contribution before fixed costs | Q32: =SUM(N37:N66) -> 56844.399
A33: Included Angel Payroll (memo) | B33: ='Global Inputs'!$B$30 -> 42000 | C33: Already included in TOTAL FIXED COSTS above | P33: Contribution margin | Q33: =IF(Q30=0,0,Q32/Q30) -> 0.82270301
P34: Contribution / completed journey | Q34: =IF(Q19=0,0,Q32/Q19) -> 1511.0154
A35: Whitefield Service Mix — Editable Demand Mix | N35: Contribution / Angel hour used | P35: Contribution / Angel hour used | Q35: =IF(Q19*Q15=0,0,Q32/(Q19*Q15)) -> 327.05961
A36: Service | B36: Category | C36: Hours | D36: Customer Service Price | E36: Case 1 Contribution/Journey | F36: Case 2 Contribution/Journey | G36: Service Mix % | H36: Other Variable Cost/Journey | I36: Completed Journeys | J36: Required Angel Hours | K36: Gross Service Revenue | L36: Transport Collections | M36: Net Operating Revenue | N36: Monthly Contribution Before Fixed Costs | P36: Monthly fixed costs | Q36: =$B$32 -> 138000 | X36: Transport Helper | Y36: Net Service Rev Helper | Z36: Coord GST Helper
A37: ='Service Economics'!A5 -> Hospital Visit | B37: ='Service Economics'!B5 -> Medical Visit | C37: ='Service Economics'!C5 -> 4 | D37: ='Service Economics'!K5 -> 1395 | E37: ='Service Economics'!R5 -> 1076.8784 | F37: ='Service Economics'!AB5 -> 1215.8784 | G37: 0.23 | H37: 0 | I37: =$Q$19*G37 -> 8.6526 | J37: =I37*C37 -> 34.6104 | K37: =I37*D37 -> 12070.377 | L37: =I37*$B$16*'Service Economics'!V5 -> 2246.215 | M37: =I37*('Service Economics'!L5+$B$16*('Service Economics'!T5+'Service Economics'!U5/(1+'Global Inputs'!$B$17))) -> 12475.348 | N37: =I37*($B$15*E37+$B$16*F37-H37) -> 9798.8825 | P37: Monthly EBITDA / operating profit | Q37: =Q32-Q36 -> -81155.601 | X37: =G37*'Service Economics'!V5 -> 149.27 | Y37: =I37*'Service Economics'!L5 -> 10229.133 | Z37: =I37*$B$16*('Service Economics'!U5-'Service Economics'!U5/(1+'Global Inputs'!$B$17)) -> 0
A38: ='Service Economics'!A6 -> Hospital Visit — Concierge at Hospital | B38: ='Service Economics'!B6 -> Medical Visit | C38: ='Service Economics'!C6 -> 3 | D38: ='Service Economics'!K6 -> 916.6 | E38: ='Service Economics'!R6 -> 688.19866 | F38: ='Service Economics'!AB6 -> 827.19866 | G38: 0.12 | H38: 0 | I38: =$Q$19*G38 -> 4.5144 | J38: =I38*C38 -> 13.5432 | K38: =I38*D38 -> 4137.899 | L38: =I38*$B$16*'Service Economics'!V6 -> 1171.9382 | M38: =I38*('Service Economics'!L6+$B$16*('Service Economics'!T6+'Service Economics'!U6/(1+'Global Inputs'!$B$17))) -> 4678.6323 | N38: =I38*($B$15*E38+$B$16*F38-H38) -> 3357.8047 | P38: Operating margin | Q38: =IF(Q30=0,0,Q37/Q30) -> -1.1745565 | X38: =G38*'Service Economics'!V6 -> 77.88 | Y38: =I38*'Service Economics'!L6 -> 3506.6941 | Z38: =I38*$B$16*('Service Economics'!U6-'Service Economics'!U6/(1+'Global Inputs'!$B$17)) -> 0
A39: ='Service Economics'!A7 -> Clinic Visit | B39: ='Service Economics'!B7 -> Medical Visit | C39: ='Service Economics'!C7 -> 2 | D39: ='Service Economics'!K7 -> 737.2 | E39: ='Service Economics'!R7 -> 542.44376 | F39: ='Service Economics'!AB7 -> 681.44376 | G39: 0.09 | H39: 0 | I39: =$Q$19*G39 -> 3.3858 | J39: =I39*C39 -> 6.7716 | K39: =I39*D39 -> 2496.0118 | L39: =I39*$B$16*'Service Economics'!V7 -> 878.95368 | M39: =I39*('Service Economics'!L7+$B$16*('Service Economics'!T7+'Service Economics'!U7/(1+'Global Inputs'!$B$17))) -> 2994.2179 | N39: =I39*($B$15*E39+$B$16*F39-H39) -> 2024.8566 | P39: Break-even journeys / month | Q39: =IF(S51<=0,0,Q36/S51) -> 91.329314 | X39: =G39*'Service Economics'!V7 -> 58.41 | Y39: =I39*'Service Economics'!L7 -> 2115.2642 | Z39: =I39*$B$16*('Service Economics'!U7-'Service Economics'!U7/(1+'Global Inputs'!$B$17)) -> 0
A40: ='Service Economics'!A8 -> Diagnostic Center Visit | B40: ='Service Economics'!B8 -> Medical Visit | C40: ='Service Economics'!C8 -> 3 | D40: ='Service Economics'!K8 -> 961.45 | E40: ='Service Economics'!R8 -> 724.63739 | F40: ='Service Economics'!AB8 -> 863.63739 | G40: 0.08 | H40: 0 | I40: =$Q$19*G40 -> 3.0096 | J40: =I40*C40 -> 9.0288 | K40: =I40*D40 -> 2893.5799 | L40: =I40*$B$16*'Service Economics'!V8 -> 781.29216 | M40: =I40*('Service Economics'!L8+$B$16*('Service Economics'!T8+'Service Economics'!U8/(1+'Global Inputs'!$B$17))) -> 3233.4785 | N40: =I40*($B$15*E40+$B$16*F40-H40) -> 2348.2024 | P40: Break-even journeys / day | Q40: =IF($B$7=0,0,Q39/$B$7) -> 3.0443105 | X40: =G40*'Service Economics'!V8 -> 51.92 | Y40: =I40*'Service Economics'!L8 -> 2452.1864 | Z40: =I40*$B$16*('Service Economics'!U8-'Service Economics'!U8/(1+'Global Inputs'!$B$17)) -> 0
A41: ='Service Economics'!A9 -> Health Check-up Concierge | B41: ='Service Economics'!B9 -> Medical Visit | C41: ='Service Economics'!C9 -> 5 | D41: ='Service Economics'!K9 -> 1544.5 | E41: ='Service Economics'!R9 -> 1198.3408 | F41: ='Service Economics'!AB9 -> 1337.3408 | G41: 0.05 | H41: 0 | I41: =$Q$19*G41 -> 1.881 | J41: =I41*C41 -> 9.405 | K41: =I41*D41 -> 2905.2045 | L41: =I41*$B$16*'Service Economics'!V9 -> 488.3076 | M41: =I41*('Service Economics'!L9+$B$16*('Service Economics'!T9+'Service Economics'!U9/(1+'Global Inputs'!$B$17))) -> 2950.3453 | N41: =I41*($B$15*E41+$B$16*F41-H41) -> 2358.6627 | P41: Break-even customer collections | Q41: =Q39*S52 -> 193665.27 | X41: =G41*'Service Economics'!V9 -> 32.45 | Y41: =I41*'Service Economics'!L9 -> 2462.0377 | Z41: =I41*$B$16*('Service Economics'!U9-'Service Economics'!U9/(1+'Global Inputs'!$B$17)) -> 0
A42: ='Service Economics'!A10 -> Hospital Admission Concierge | B42: ='Service Economics'!B10 -> Hospital Support | C42: ='Service Economics'!C10 -> 4 | D42: ='Service Economics'!K10 -> 1574.4 | E42: ='Service Economics'!R10 -> 1222.6333 | F42: ='Service Economics'!AB10 -> 1361.6333 | G42: 0.05 | H42: 0 | I42: =$Q$19*G42 -> 1.881 | J42: =I42*C42 -> 7.524 | K42: =I42*D42 -> 2961.4464 | L42: =I42*$B$16*'Service Economics'!V10 -> 488.3076 | M42: =I42*('Service Economics'!L10+$B$16*('Service Economics'!T10+'Service Economics'!U10/(1+'Global Inputs'!$B$17))) -> 2998.0079 | N42: =I42*($B$15*E42+$B$16*F42-H42) -> 2404.3568 | P42: Angels required at break-even | Q42: =IF($B$7*$B$8*$B$9=0,0,Q39*S45/($B$7*$B$8*$B$9)) -> 1.7580893 | X42: =G42*'Service Economics'!V10 -> 32.45 | Y42: =I42*'Service Economics'!L10 -> 2509.7003 | Z42: =I42*$B$16*('Service Economics'!U10-'Service Economics'!U10/(1+'Global Inputs'!$B$17)) -> 0
A43: ='Service Economics'!A11 -> Hospital Discharge Concierge | B43: ='Service Economics'!B11 -> Hospital Support | C43: ='Service Economics'!C11 -> 4 | D43: ='Service Economics'!K11 -> 1514.6 | E43: ='Service Economics'!R11 -> 1174.0483 | F43: ='Service Economics'!AB11 -> 1313.0483 | G43: 0.05 | H43: 0 | I43: =$Q$19*G43 -> 1.881 | J43: =I43*C43 -> 7.524 | K43: =I43*D43 -> 2848.9626 | L43: =I43*$B$16*'Service Economics'!V11 -> 488.3076 | M43: =I43*('Service Economics'!L11+$B$16*('Service Economics'!T11+'Service Economics'!U11/(1+'Global Inputs'!$B$17))) -> 2902.6827 | N43: =I43*($B$15*E43+$B$16*F43-H43) -> 2312.9685 | X43: =G43*'Service Economics'!V11 -> 32.45 | Y43: =I43*'Service Economics'!L11 -> 2414.3751 | Z43: =I43*$B$16*('Service Economics'!U11-'Service Economics'!U11/(1+'Global Inputs'!$B$17)) -> 0
A44: ='Service Economics'!A12 -> Overnight Hospital Concierge | B44: ='Service Economics'!B12 -> Hospital Support | C44: ='Service Economics'!C12 -> 12 | D44: ='Service Economics'!K12 -> 3547.8 | E44: ='Service Economics'!R12 -> 2825.9372 | F44: ='Service Economics'!AB12 -> 2964.9372 | G44: 0.03 | H44: 0 | I44: =$Q$19*G44 -> 1.1286 | J44: =I44*C44 -> 13.5432 | K44: =I44*D44 -> 4004.0471 | L44: =I44*$B$16*'Service Economics'!V12 -> 292.98456 | M44: =I44*('Service Economics'!L12+$B$16*('Service Economics'!T12+'Service Economics'!U12/(1+'Global Inputs'!$B$17))) -> 3686.2448 | N44: =I44*($B$15*E44+$B$16*F44-H44) -> 3252.1028 | R44: Portfolio Averages / Helpers | X44: =G44*'Service Economics'!V12 -> 19.47 | Y44: =I44*'Service Economics'!L12 -> 3393.2602 | Z44: =I44*$B$16*('Service Economics'!U12-'Service Economics'!U12/(1+'Global Inputs'!$B$17)) -> 0
A45: ='Service Economics'!A13 -> Multi-Day Hospital Concierge (per 12h shift) | B45: ='Service Economics'!B13 -> Hospital Support | C45: ='Service Economics'!C13 -> 12 | D45: ='Service Economics'!K13 -> 3547.8 | E45: ='Service Economics'!R13 -> 2825.9372 | F45: ='Service Economics'!AB13 -> 2964.9372 | G45: 0.01 | H45: 0 | I45: =$Q$19*G45 -> 0.3762 | J45: =I45*C45 -> 4.5144 | K45: =I45*D45 -> 1334.6824 | L45: =I45*$B$16*'Service Economics'!V13 -> 97.66152 | M45: =I45*('Service Economics'!L13+$B$16*('Service Economics'!T13+'Service Economics'!U13/(1+'Global Inputs'!$B$17))) -> 1228.7483 | N45: =I45*($B$15*E45+$B$16*F45-H45) -> 1084.0343 | R45: Weighted avg service hours | S45: =SUMPRODUCT(G37:G66,C37:C66) -> 4.62 | X45: =G45*'Service Economics'!V13 -> 6.49 | Y45: =I45*'Service Economics'!L13 -> 1131.0867 | Z45: =I45*$B$16*('Service Economics'!U13-'Service Economics'!U13/(1+'Global Inputs'!$B$17)) -> 0
A46: ='Service Economics'!A14 -> Day Surgery / Procedure Concierge | B46: ='Service Economics'!B14 -> Procedure & Treatment | C46: ='Service Economics'!C14 -> 6 | D46: ='Service Economics'!K14 -> 2351.8 | E46: ='Service Economics'!R14 -> 1854.2378 | F46: ='Service Economics'!AB14 -> 1993.2378 | G46: 0.04 | H46: 0 | I46: =$Q$19*G46 -> 1.5048 | J46: =I46*C46 -> 9.0288 | K46: =I46*D46 -> 3538.9886 | L46: =I46*$B$16*'Service Economics'!V14 -> 390.64608 | M46: =I46*('Service Economics'!L14+$B$16*('Service Economics'!T14+'Service Economics'!U14/(1+'Global Inputs'!$B$17))) -> 3389.789 | N46: =I46*($B$15*E46+$B$16*F46-H46) -> 2873.924 | R46: Weighted avg service price | S46: =SUMPRODUCT(G37:G66,D37:D66) -> 1860.916 | X46: =G46*'Service Economics'!V14 -> 25.96 | Y46: =I46*'Service Economics'!L14 -> 2999.1429 | Z46: =I46*$B$16*('Service Economics'!U14-'Service Economics'!U14/(1+'Global Inputs'!$B$17)) -> 0
A47: ='Service Economics'!A15 -> Pre-Surgery Concierge | B47: ='Service Economics'!B15 -> Procedure & Treatment | C47: ='Service Economics'!C15 -> 4 | D47: ='Service Economics'!K15 -> 1514.6 | E47: ='Service Economics'!R15 -> 1174.0483 | F47: ='Service Economics'!AB15 -> 1313.0483 | G47: 0.02 | H47: 0 | I47: =$Q$19*G47 -> 0.7524 | J47: =I47*C47 -> 3.0096 | K47: =I47*D47 -> 1139.585 | L47: =I47*$B$16*'Service Economics'!V15 -> 195.32304 | M47: =I47*('Service Economics'!L15+$B$16*('Service Economics'!T15+'Service Economics'!U15/(1+'Global Inputs'!$B$17))) -> 1161.0731 | N47: =I47*($B$15*E47+$B$16*F47-H47) -> 925.1874 | R47: Weighted avg Case 1 contribution | S47: =SUMPRODUCT(G37:G66,E37:E66) -> 1455.4154 | X47: =G47*'Service Economics'!V15 -> 12.98 | Y47: =I47*'Service Economics'!L15 -> 965.75003 | Z47: =I47*$B$16*('Service Economics'!U15-'Service Economics'!U15/(1+'Global Inputs'!$B$17)) -> 0
A48: ='Service Economics'!A16 -> Post-Surgery Follow-up | B48: ='Service Economics'!B16 -> Procedure & Treatment | C48: ='Service Economics'!C16 -> 3 | D48: ='Service Economics'!K16 -> 1096 | E48: ='Service Economics'!R16 -> 833.95356 | F48: ='Service Economics'!AB16 -> 972.95356 | G48: 0.03 | H48: 0 | I48: =$Q$19*G48 -> 1.1286 | J48: =I48*C48 -> 3.3858 | K48: =I48*D48 -> 1236.9456 | L48: =I48*$B$16*'Service Economics'!V16 -> 292.98456 | M48: =I48*('Service Economics'!L16+$B$16*('Service Economics'!T16+'Service Economics'!U16/(1+'Global Inputs'!$B$17))) -> 1341.2435 | N48: =I48*($B$15*E48+$B$16*F48-H48) -> 1003.9501 | R48: Weighted avg Case 2 contribution | S48: =SUMPRODUCT(G37:G66,F37:F66) -> 1594.4154 | X48: =G48*'Service Economics'!V16 -> 19.47 | Y48: =I48*'Service Economics'!L16 -> 1048.259 | Z48: =I48*$B$16*('Service Economics'!U16-'Service Economics'!U16/(1+'Global Inputs'!$B$17)) -> 0
A49: ='Service Economics'!A17 -> Dialysis Visit Concierge | B49: ='Service Economics'!B17 -> Recurring Treatment | C49: ='Service Economics'!C17 -> 5 | D49: ='Service Economics'!K17 -> 1544.5 | E49: ='Service Economics'!R17 -> 1198.3408 | F49: ='Service Economics'!AB17 -> 1337.3408 | G49: 0.04 | H49: 0 | I49: =$Q$19*G49 -> 1.5048 | J49: =I49*C49 -> 7.524 | K49: =I49*D49 -> 2324.1636 | L49: =I49*$B$16*'Service Economics'!V17 -> 390.64608 | M49: =I49*('Service Economics'!L17+$B$16*('Service Economics'!T17+'Service Economics'!U17/(1+'Global Inputs'!$B$17))) -> 2360.2762 | N49: =I49*($B$15*E49+$B$16*F49-H49) -> 1886.9301 | R49: Weighted avg transport collection | S49: =SUM(X37:X66) -> 649 | X49: =G49*'Service Economics'!V17 -> 25.96 | Y49: =I49*'Service Economics'!L17 -> 1969.6302 | Z49: =I49*$B$16*('Service Economics'!U17-'Service Economics'!U17/(1+'Global Inputs'!$B$17)) -> 0
A50: ='Service Economics'!A18 -> Chemotherapy Visit Concierge | B50: ='Service Economics'!B18 -> Recurring Treatment | C50: ='Service Economics'!C18 -> 6 | D50: ='Service Economics'!K18 -> 1993 | E50: ='Service Economics'!R18 -> 1562.7281 | F50: ='Service Economics'!AB18 -> 1701.7281 | G50: 0.02 | H50: 0 | I50: =$Q$19*G50 -> 0.7524 | J50: =I50*C50 -> 4.5144 | K50: =I50*D50 -> 1499.5332 | L50: =I50*$B$16*'Service Economics'!V18 -> 195.32304 | M50: =I50*('Service Economics'!L18+$B$16*('Service Economics'!T18+'Service Economics'!U18/(1+'Global Inputs'!$B$17))) -> 1466.1139 | N50: =I50*($B$15*E50+$B$16*F50-H50) -> 1217.63 | R50: Weighted avg other variable cost | S50: =SUMPRODUCT(G37:G66,H37:H66) -> 0 | X50: =G50*'Service Economics'!V18 -> 12.98 | Y50: =I50*'Service Economics'!L18 -> 1270.7908 | Z50: =I50*$B$16*('Service Economics'!U18-'Service Economics'!U18/(1+'Global Inputs'!$B$17)) -> 0
A51: ='Service Economics'!A19 -> Radiation Therapy Concierge | B51: ='Service Economics'!B19 -> Recurring Treatment | C51: ='Service Economics'!C19 -> 3 | D51: ='Service Economics'!K19 -> 1051.15 | E51: ='Service Economics'!R19 -> 797.51483 | F51: ='Service Economics'!AB19 -> 936.51483 | G51: 0.01 | H51: 0 | I51: =$Q$19*G51 -> 0.3762 | J51: =I51*C51 -> 1.1286 | K51: =I51*D51 -> 395.44263 | L51: =I51*$B$16*'Service Economics'!V19 -> 97.66152 | M51: =I51*('Service Economics'!L19+$B$16*('Service Economics'!T19+'Service Economics'!U19/(1+'Global Inputs'!$B$17))) -> 432.78239 | N51: =I51*($B$15*E51+$B$16*F51-H51) -> 320.9418 | R51: Blended contribution / journey | S51: =$B$15*S47+$B$16*S48-S50 -> 1511.0154 | X51: =G51*'Service Economics'!V19 -> 6.49 | Y51: =I51*'Service Economics'!L19 -> 335.12087 | Z51: =I51*$B$16*('Service Economics'!U19-'Service Economics'!U19/(1+'Global Inputs'!$B$17)) -> 0
A52: ='Service Economics'!A20 -> Physiotherapy / Rehab Visit | B52: ='Service Economics'!B20 -> Recurring Treatment | C52: ='Service Economics'!C20 -> 2 | D52: ='Service Economics'!K20 -> 707.3 | E52: ='Service Economics'!R20 -> 518.15128 | F52: ='Service Economics'!AB20 -> 657.15128 | G52: 0.03 | H52: 0 | I52: =$Q$19*G52 -> 1.1286 | J52: =I52*C52 -> 2.2572 | K52: =I52*D52 -> 798.25878 | L52: =I52*$B$16*'Service Economics'!V20 -> 292.98456 | M52: =I52*('Service Economics'!L20+$B$16*('Service Economics'!T20+'Service Economics'!U20/(1+'Global Inputs'!$B$17))) -> 969.47505 | N52: =I52*($B$15*E52+$B$16*F52-H52) -> 647.53569 | R52: Blended customer collection / journey | S52: =S46+$B$16*S49 -> 2120.516 | X52: =G52*'Service Economics'!V20 -> 19.47 | Y52: =I52*'Service Economics'!L20 -> 676.49049 | Z52: =I52*$B$16*('Service Economics'!U20-'Service Economics'!U20/(1+'Global Inputs'!$B$17)) -> 0
A53: ='Service Economics'!A21 -> Chronic Care Follow-up | B53: ='Service Economics'!B21 -> Continuing Care | C53: ='Service Economics'!C21 -> 3 | D53: ='Service Economics'!K21 -> 1006.3 | E53: ='Service Economics'!R21 -> 761.07611 | F53: ='Service Economics'!AB21 -> 900.07611 | G53: 0.02 | H53: 0 | I53: =$Q$19*G53 -> 0.7524 | J53: =I53*C53 -> 2.2572 | K53: =I53*D53 -> 757.14012 | L53: =I53*$B$16*'Service Economics'!V21 -> 195.32304 | M53: =I53*('Service Economics'!L21+$B$16*('Service Economics'!T21+'Service Economics'!U21/(1+'Global Inputs'!$B$17))) -> 836.96721 | N53: =I53*($B$15*E53+$B$16*F53-H53) -> 614.46711 | X53: =G53*'Service Economics'!V21 -> 12.98 | Y53: =I53*'Service Economics'!L21 -> 641.64417 | Z53: =I53*$B$16*('Service Economics'!U21-'Service Economics'!U21/(1+'Global Inputs'!$B$17)) -> 0
A54: ='Service Economics'!A22 -> NRI Parent Medical Concierge | B54: ='Service Economics'!B22 -> Continuing Care | C54: ='Service Economics'!C22 -> 4 | D54: ='Service Economics'!K22 -> 1634.2 | E54: ='Service Economics'!R22 -> 1271.2183 | F54: ='Service Economics'!AB22 -> 1410.2183 | G54: 0.025 | H54: 0 | I54: =$Q$19*G54 -> 0.9405 | J54: =I54*C54 -> 3.762 | K54: =I54*D54 -> 1536.9651 | L54: =I54*$B$16*'Service Economics'!V22 -> 244.1538 | M54: =I54*('Service Economics'!L22+$B$16*('Service Economics'!T22+'Service Economics'!U22/(1+'Global Inputs'!$B$17))) -> 1546.6666 | N54: =I54*($B$15*E54+$B$16*F54-H54) -> 1247.8726 | X54: =G54*'Service Economics'!V22 -> 16.225 | Y54: =I54*'Service Economics'!L22 -> 1302.5128 | Z54: =I54*$B$16*('Service Economics'!U22-'Service Economics'!U22/(1+'Global Inputs'!$B$17)) -> 0
A55: ='Service Economics'!A23 -> Second Opinion Concierge | B55: ='Service Economics'!B23 -> Medical Coordination | C55: ='Service Economics'!C23 -> 2.5 | D55: ='Service Economics'!K23 -> 834.375 | E55: ='Service Economics'!R23 -> 621.39433 | F55: ='Service Economics'!AB23 -> 760.39433 | G55: 0 | H55: 0 | I55: =$Q$19*G55 -> 0 | J55: =I55*C55 -> 0 | K55: =I55*D55 -> 0 | L55: =I55*$B$16*'Service Economics'!V23 -> 0 | M55: =I55*('Service Economics'!L23+$B$16*('Service Economics'!T23+'Service Economics'!U23/(1+'Global Inputs'!$B$17))) -> 0 | N55: =I55*($B$15*E55+$B$16*F55-H55) -> 0 | X55: =G55*'Service Economics'!V23 -> 0 | Y55: =I55*'Service Economics'!L23 -> 0 | Z55: =I55*$B$16*('Service Economics'!U23-'Service Economics'!U23/(1+'Global Inputs'!$B$17)) -> 0
A56: ='Service Economics'!A24 -> Teleconsultation Concierge | B56: ='Service Economics'!B24 -> Medical Coordination | C56: ='Service Economics'!C24 -> 1.5 | D56: ='Service Economics'!K24 -> 587.7 | E56: ='Service Economics'!R24 -> 420.98135 | F56: ='Service Economics'!AB24 -> 559.98135 | G56: 0 | H56: 0 | I56: =$Q$19*G56 -> 0 | J56: =I56*C56 -> 0 | K56: =I56*D56 -> 0 | L56: =I56*$B$16*'Service Economics'!V24 -> 0 | M56: =I56*('Service Economics'!L24+$B$16*('Service Economics'!T24+'Service Economics'!U24/(1+'Global Inputs'!$B$17))) -> 0 | N56: =I56*($B$15*E56+$B$16*F56-H56) -> 0 | X56: =G56*'Service Economics'!V24 -> 0 | Y56: =I56*'Service Economics'!L24 -> 0 | Z56: =I56*$B$16*('Service Economics'!U24-'Service Economics'!U24/(1+'Global Inputs'!$B$17)) -> 0
A57: ='Service Economics'!A25 -> Medical Records Concierge | B57: ='Service Economics'!B25 -> Medical Coordination | C57: ='Service Economics'!C25 -> 2 | D57: ='Service Economics'!K25 -> 557.8 | E57: ='Service Economics'!R25 -> 396.68886 | F57: ='Service Economics'!AB25 -> 535.68886 | G57: 0 | H57: 0 | I57: =$Q$19*G57 -> 0 | J57: =I57*C57 -> 0 | K57: =I57*D57 -> 0 | L57: =I57*$B$16*'Service Economics'!V25 -> 0 | M57: =I57*('Service Economics'!L25+$B$16*('Service Economics'!T25+'Service Economics'!U25/(1+'Global Inputs'!$B$17))) -> 0 | N57: =I57*($B$15*E57+$B$16*F57-H57) -> 0 | X57: =G57*'Service Economics'!V25 -> 0 | Y57: =I57*'Service Economics'!L25 -> 0 | Z57: =I57*$B$16*('Service Economics'!U25-'Service Economics'!U25/(1+'Global Inputs'!$B$17)) -> 0
A58: ='Service Economics'!A26 -> Insurance / TPA Desk Concierge | B58: ='Service Economics'!B26 -> Medical Coordination | C58: ='Service Economics'!C26 -> 3 | D58: ='Service Economics'!K26 -> 871.75 | E58: ='Service Economics'!R26 -> 651.75994 | F58: ='Service Economics'!AB26 -> 790.75994 | G58: 0.01 | H58: 0 | I58: =$Q$19*G58 -> 0.3762 | J58: =I58*C58 -> 1.1286 | K58: =I58*D58 -> 327.95235 | L58: =I58*$B$16*'Service Economics'!V26 -> 97.66152 | M58: =I58*('Service Economics'!L26+$B$16*('Service Economics'!T26+'Service Economics'!U26/(1+'Global Inputs'!$B$17))) -> 375.58724 | N58: =I58*($B$15*E58+$B$16*F58-H58) -> 266.10881 | X58: =G58*'Service Economics'!V26 -> 6.49 | Y58: =I58*'Service Economics'!L26 -> 277.92572 | Z58: =I58*$B$16*('Service Economics'!U26-'Service Economics'!U26/(1+'Global Inputs'!$B$17)) -> 0
A59: ='Service Economics'!A27 -> Hospital Transfer Concierge | B59: ='Service Economics'!B27 -> Medical Coordination | C59: ='Service Economics'!C27 -> 4 | D59: ='Service Economics'!K27 -> 1514.6 | E59: ='Service Economics'!R27 -> 1174.0483 | F59: ='Service Economics'!AB27 -> 1313.0483 | G59: 0.01 | H59: 0 | I59: =$Q$19*G59 -> 0.3762 | J59: =I59*C59 -> 1.5048 | K59: =I59*D59 -> 569.79252 | L59: =I59*$B$16*'Service Economics'!V27 -> 97.66152 | M59: =I59*('Service Economics'!L27+$B$16*('Service Economics'!T27+'Service Economics'!U27/(1+'Global Inputs'!$B$17))) -> 580.53654 | N59: =I59*($B$15*E59+$B$16*F59-H59) -> 462.5937 | X59: =G59*'Service Economics'!V27 -> 6.49 | Y59: =I59*'Service Economics'!L27 -> 482.87502 | Z59: =I59*$B$16*('Service Economics'!U27-'Service Economics'!U27/(1+'Global Inputs'!$B$17)) -> 0
A60: ='Service Economics'!A28 -> Rehab / Nursing Facility Transfer | B60: ='Service Economics'!B28 -> Medical Coordination | C60: ='Service Economics'!C28 -> 4 | D60: ='Service Economics'!K28 -> 1454.8 | E60: ='Service Economics'!R28 -> 1125.4634 | F60: ='Service Economics'!AB28 -> 1264.4634 | G60: 0 | H60: 0 | I60: =$Q$19*G60 -> 0 | J60: =I60*C60 -> 0 | K60: =I60*D60 -> 0 | L60: =I60*$B$16*'Service Economics'!V28 -> 0 | M60: =I60*('Service Economics'!L28+$B$16*('Service Economics'!T28+'Service Economics'!U28/(1+'Global Inputs'!$B$17))) -> 0 | N60: =I60*($B$15*E60+$B$16*F60-H60) -> 0 | X60: =G60*'Service Economics'!V28 -> 0 | Y60: =I60*'Service Economics'!L28 -> 0 | Z60: =I60*$B$16*('Service Economics'!U28-'Service Economics'!U28/(1+'Global Inputs'!$B$17)) -> 0
A61: ='Service Economics'!A29 -> 24×7 Urgent Care Coordination | B61: ='Service Economics'!B29 -> Urgent Coordination | C61: ='Service Economics'!C29 -> 4 | D61: ='Service Economics'!K29 -> 2252.8 | E61: ='Service Economics'!R29 -> 1773.8045 | F61: ='Service Economics'!AB29 -> 1912.8045 | G61: 0.005 | H61: 0 | I61: =$Q$19*G61 -> 0.1881 | J61: =I61*C61 -> 0.7524 | K61: =I61*D61 -> 423.75168 | L61: =I61*$B$16*'Service Economics'!V29 -> 48.83076 | M61: =I61*('Service Economics'!L29+$B$16*('Service Economics'!T29+'Service Economics'!U29/(1+'Global Inputs'!$B$17))) -> 407.94235 | N61: =I61*($B$15*E61+$B$16*F61-H61) -> 344.11099 | X61: =G61*'Service Economics'!V29 -> 3.245 | Y61: =I61*'Service Economics'!L29 -> 359.11159 | Z61: =I61*$B$16*('Service Economics'!U29-'Service Economics'!U29/(1+'Global Inputs'!$B$17)) -> 0
A62: ='Service Economics'!A30 -> Doctor-at-Home Coordination | B62: ='Service Economics'!B30 -> Medical Coordination | C62: ='Service Economics'!C30 -> 2 | D62: ='Service Economics'!K30 -> 707.3 | E62: ='Service Economics'!R30 -> 518.15128 | F62: ='Service Economics'!AB30 -> 657.15128 | G62: 0 | H62: 0 | I62: =$Q$19*G62 -> 0 | J62: =I62*C62 -> 0 | K62: =I62*D62 -> 0 | L62: =I62*$B$16*'Service Economics'!V30 -> 0 | M62: =I62*('Service Economics'!L30+$B$16*('Service Economics'!T30+'Service Economics'!U30/(1+'Global Inputs'!$B$17))) -> 0 | N62: =I62*($B$15*E62+$B$16*F62-H62) -> 0 | X62: =G62*'Service Economics'!V30 -> 0 | Y62: =I62*'Service Economics'!L30 -> 0 | Z62: =I62*$B$16*('Service Economics'!U30-'Service Economics'!U30/(1+'Global Inputs'!$B$17)) -> 0
A63: ='Service Economics'!A31 -> Nurse-at-Home Coordination | B63: ='Service Economics'!B31 -> Medical Coordination | C63: ='Service Economics'!C31 -> 2 | D63: ='Service Economics'!K31 -> 707.3 | E63: ='Service Economics'!R31 -> 518.15128 | F63: ='Service Economics'!AB31 -> 657.15128 | G63: 0 | H63: 0 | I63: =$Q$19*G63 -> 0 | J63: =I63*C63 -> 0 | K63: =I63*D63 -> 0 | L63: =I63*$B$16*'Service Economics'!V31 -> 0 | M63: =I63*('Service Economics'!L31+$B$16*('Service Economics'!T31+'Service Economics'!U31/(1+'Global Inputs'!$B$17))) -> 0 | N63: =I63*($B$15*E63+$B$16*F63-H63) -> 0 | X63: =G63*'Service Economics'!V31 -> 0 | Y63: =I63*'Service Economics'!L31 -> 0 | Z63: =I63*$B$16*('Service Economics'!U31-'Service Economics'!U31/(1+'Global Inputs'!$B$17)) -> 0
A64: ='Service Economics'!A32 -> Medical Tourism — Concierge Package (24 HR Basis) | B64: ='Service Economics'!B32 -> Medical Coordination | C64: ='Service Economics'!C32 -> 24 | D64: ='Service Economics'!K32 -> 17550 | E64: ='Service Economics'!R32 -> 14202.131 | F64: ='Service Economics'!AB32 -> 14341.131 | G64: 0.03 | H64: 0 | I64: =$Q$19*G64 -> 1.1286 | J64: =I64*C64 -> 27.0864 | K64: =I64*D64 -> 19806.93 | L64: =I64*$B$16*'Service Economics'!V32 -> 292.98456 | M64: =I64*('Service Economics'!L32+$B$16*('Service Economics'!T32+'Service Economics'!U32/(1+'Global Inputs'!$B$17))) -> 17078.518 | N64: =I64*($B$15*E64+$B$16*F64-H64) -> 16091.276 | X64: =G64*'Service Economics'!V32 -> 19.47 | Y64: =I64*'Service Economics'!L32 -> 16785.534 | Z64: =I64*$B$16*('Service Economics'!U32-'Service Economics'!U32/(1+'Global Inputs'!$B$17)) -> 0
... A66: ='Service Economics'!A34 -> Family Medical Update Concierge | B66: ='Service Economics'!B34 -> Continuing Care | C66: ='Service Economics'!C34 -> 3 | D66: ='Service Economics'!K34 -> 782.05 | E66: ='Service Economics'!R34 -> 578.88249 | F66: ='Service Economics'!AB34 -> 717.88249 | G66: 0 | H66: 0 | I66: =$Q$19*G66 -> 0 | J66: =I66*C66 -> 0 | K66: =I66*D66 -> 0 | L66: =I66*$B$16*'Service Economics'!V34 -> 0 | M66: =I66*('Service Economics'!L34+$B$16*('Service Economics'!T34+'Service Economics'!U34/(1+'Global Inputs'!$B$17))) -> 0 | N66: =I66*($B$15*E66+$B$16*F66-H66) -> 0 | X66: =G66*'Service Economics'!V34 -> 0 | Y66: =I66*'Service Economics'!L34 -> 0 | Z66: =I66*$B$16*('Service Economics'!U34-'Service Economics'!U34/(1+'Global Inputs'!$B$17)) -> 0
A67: TOTAL / WEIGHTED | G67: =SUM(G37:G66) -> 1 | H67: =SUM(H37:H66) -> 0 | I67: =SUM(I37:I66) -> 37.62 | J67: =SUM(J37:J66) -> 173.8044 | K67: =SUM(K37:K66) -> 70007.66 | L67: =SUM(L37:L66) -> 9766.152 | M67: =SUM(M37:M66) -> 69094.677 | N67: =SUM(N37:N66) -> 56844.399
A70: Scenario Planning — Side-by-Side
A71: Metric | B71: Conservative | C71: Base | D71: Aggressive
A72: Journeys / month | B72: =MIN(($G$6*$B$7*$G$7*(1-$G$8)*(1-$G$9)),($G$5*$B$7*$B$8*$G$10/$S$45),($G$5*$B$10*$B$7)) -> 37.62 | C72: =MIN(($H$6*$B$7*$H$7*(1-$H$8)*(1-$H$9)),($H$5*$B$7*$B$8*$H$10/$S$45),($H$5*$B$10*$B$7)) -> 93.702 | D72: =MIN(($I$6*$B$7*$I$7*(1-$I$8)*(1-$I$9)),($I$5*$B$7*$B$8*$I$10/$S$45),($I$5*$B$10*$B$7)) -> 198.9792
A73: Revenue / customer collections | B73: =MIN(($G$6*$B$7*$G$7*(1-$G$8)*(1-$G$9)),($G$5*$B$7*$B$8*$G$10/$S$45),($G$5*$B$10*$B$7))*($S$46+$G$11*$S$49) -> 79773.812 | C73: =MIN(($H$6*$B$7*$H$7*(1-$H$8)*(1-$H$9)),($H$5*$B$7*$B$8*$H$10/$S$45),($H$5*$B$10*$B$7))*($S$46+$H$11*$S$49) -> 210859.11 | D73: =MIN(($I$6*$B$7*$I$7*(1-$I$8)*(1-$I$9)),($I$5*$B$7*$B$8*$I$10/$S$45),($I$5*$B$10*$B$7))*($S$46+$I$11*$S$49) -> 460679.83
A74: Contribution | B74: =MIN(($G$6*$B$7*$G$7*(1-$G$8)*(1-$G$9)),($G$5*$B$7*$B$8*$G$10/$S$45),($G$5*$B$10*$B$7))*((1-$G$11)*$S$47+$G$11*$S$48-$S$50) -> 56844.399 | C74: =MIN(($H$6*$B$7*$H$7*(1-$H$8)*(1-$H$9)),($H$5*$B$7*$B$8*$H$10/$S$45),($H$5*$B$10*$B$7))*((1-$H$11)*$S$47+$H$11*$S$48-$S$50) -> 144190.08 | D74: =MIN(($I$6*$B$7*$I$7*(1-$I$8)*(1-$I$9)),($I$5*$B$7*$B$8*$I$10/$S$45),($I$5*$B$10*$B$7))*((1-$I$11)*$S$47+$I$11*$S$48-$S$50) -> 308958.07
A75: Fixed Cost | B75: =$B$32 -> 138000 | C75: =$B$32 -> 138000 | D75: =$B$32 -> 138000
A76: Operating Profit | B76: =B74-B75 -> -81155.601 | C76: =C74-C75 -> 6190.0804 | D76: =D74-D75 -> 170958.07
A77: Operating Margin | B77: =IF(B73=0,0,B76/B73) -> -1.0173213 | C77: =IF(C73=0,0,C76/C73) -> 0.029356476 | D77: =IF(D73=0,0,D76/D73) -> 0.37109953
A78: Angels Required for Demand | B78: =($G$6*$B$7*$G$7*(1-$G$8)*(1-$G$9))*$S$45/($B$7*$B$8*$G$10) -> 1.44837 | C78: =($H$6*$B$7*$H$7*(1-$H$8)*(1-$H$9))*$S$45/($B$7*$B$8*$H$10) -> 2.7750208 | D78: =($I$6*$B$7*$I$7*(1-$I$8)*(1-$I$9))*$S$45/($B$7*$B$8*$I$10) -> 4.787937
A82: 12-Month Whitefield Ramp-Up
A83: Month | B83: Demand Growth % | C83: Leads / Day | D83: Active Angels | E83: Estimated Customers | F83: Completed Journeys | G83: Customer Collections | H83: Contribution | I83: Fixed Cost | J83: Profit / (Loss) | K83: Cumulative P/L | L83: Angel Utilization | M83: Angels Required | N83: Break-even? | P83: Ramp KPI | Q83: Value
A84: Month 1 | B84: 0 | C84: =$B$11 -> 6 | D84: 3 | E84: =F84*($B$18+$B$17/$B$19) -> 33.858 | F84: =MIN((C84*$B$7*$B$12*(1-$B$13)*(1-$B$14)),MIN(D84*$B$7*$B$8*$B$9/$S$45,D84*$B$10*$B$7)) -> 37.62 | G84: =F84*$S$52 -> 79773.812 | H84: =F84*$S$51 -> 56844.399 | I84: =$B$32 -> 138000 | J84: =H84-I84 -> -81155.601 | K84: =J84 -> -81155.601 | L84: =IF(D84*$B$7*$B$8=0,0,F84*$S$45/(D84*$B$7*$B$8)) -> 0.241395 | M84: =(C84*$B$7*$B$12*(1-$B$13)*(1-$B$14))*$S$45/($B$7*$B$8*$B$9) -> 0.724185 | N84: =IF(J84>=0,"YES","") | O84: =IF(K84>=0,"YES","") | P84: Operational break-even month | Q84: =IF(COUNTIF(N84:N95,"YES")=0,"Not reached","Month "&MATCH("YES",N84:N95,0)) -> Not reached
A85: Month 2 | B85: 0.15 | C85: =C84*(1+B85) -> 6.9 | D85: 5 | E85: =F85*($B$18+$B$17/$B$19) -> 38.9367 | F85: =MIN((C85*$B$7*$B$12*(1-$B$13)*(1-$B$14)),MIN(D85*$B$7*$B$8*$B$9/$S$45,D85*$B$10*$B$7)) -> 43.263 | G85: =F85*$S$52 -> 91739.884 | H85: =F85*$S$51 -> 65371.059 | I85: =$B$32 -> 138000 | J85: =H85-I85 -> -72628.941 | K85: =K84+J85 -> -153784.54 | L85: =IF(D85*$B$7*$B$8=0,0,F85*$S$45/(D85*$B$7*$B$8)) -> 0.16656255 | M85: =(C85*$B$7*$B$12*(1-$B$13)*(1-$B$14))*$S$45/($B$7*$B$8*$B$9) -> 0.83281275 | N85: =IF(J85>=0,"YES","") | O85: =IF(K85>=0,"YES","") | P85: Cumulative cash break-even month | Q85: =IF(COUNTIF(O84:O95,"YES")=0,"Not reached","Month "&MATCH("YES",O84:O95,0)) -> Not reached
A86: Month 3 | B86: 0.12 | C86: =C85*(1+B86) -> 7.728 | D86: 5 | E86: =F86*($B$18+$B$17/$B$19) -> 43.609104 | F86: =MIN((C86*$B$7*$B$12*(1-$B$13)*(1-$B$14)),MIN(D86*$B$7*$B$8*$B$9/$S$45,D86*$B$10*$B$7)) -> 48.45456 | G86: =F86*$S$52 -> 102748.67 | H86: =F86*$S$51 -> 73215.586 | I86: =$B$32 -> 138000 | J86: =H86-I86 -> -64784.414 | K86: =K85+J86 -> -218568.96 | L86: =IF(D86*$B$7*$B$8=0,0,F86*$S$45/(D86*$B$7*$B$8)) -> 0.18655006 | M86: =(C86*$B$7*$B$12*(1-$B$13)*(1-$B$14))*$S$45/($B$7*$B$8*$B$9) -> 0.93275028 | N86: =IF(J86>=0,"YES","") | O86: =IF(K86>=0,"YES","")
A87: Month 4 | B87: 0.1 | C87: =C86*(1+B87) -> 8.5008 | D87: 6 | E87: =F87*($B$18+$B$17/$B$19) -> 47.970014 | F87: =MIN((C87*$B$7*$B$12*(1-$B$13)*(1-$B$14)),MIN(D87*$B$7*$B$8*$B$9/$S$45,D87*$B$10*$B$7)) -> 53.300016 | G87: =F87*$S$52 -> 113023.54 | H87: =F87*$S$51 -> 80537.145 | I87: =$B$32 -> 138000 | J87: =H87-I87 -> -57462.855 | K87: =K86+J87 -> -276031.81 | L87: =IF(D87*$B$7*$B$8=0,0,F87*$S$45/(D87*$B$7*$B$8)) -> 0.17100422 | M87: =(C87*$B$7*$B$12*(1-$B$13)*(1-$B$14))*$S$45/($B$7*$B$8*$B$9) -> 1.0260253 | N87: =IF(J87>=0,"YES","") | O87: =IF(K87>=0,"YES","")
A88: Month 5 | B88: 0.1 | C88: =C87*(1+B88) -> 9.35088 | D88: 6 | E88: =F88*($B$18+$B$17/$B$19) -> 52.767016 | F88: =MIN((C88*$B$7*$B$12*(1-$B$13)*(1-$B$14)),MIN(D88*$B$7*$B$8*$B$9/$S$45,D88*$B$10*$B$7)) -> 58.630018 | G88: =F88*$S$52 -> 124325.89 | H88: =F88*$S$51 -> 88590.859 | I88: =$B$32 -> 138000 | J88: =H88-I88 -> -49409.141 | K88: =K87+J88 -> -325440.95 | L88: =IF(D88*$B$7*$B$8=0,0,F88*$S$45/(D88*$B$7*$B$8)) -> 0.18810464 | M88: =(C88*$B$7*$B$12*(1-$B$13)*(1-$B$14))*$S$45/($B$7*$B$8*$B$9) -> 1.1286278 | N88: =IF(J88>=0,"YES","") | O88: =IF(K88>=0,"YES","")
A89: Month 6 | B89: 0.08 | C89: =C88*(1+B89) -> 10.09895 | D89: 7 | E89: =F89*($B$18+$B$17/$B$19) -> 56.988377 | F89: =MIN((C89*$B$7*$B$12*(1-$B$13)*(1-$B$14)),MIN(D89*$B$7*$B$8*$B$9/$S$45,D89*$B$10*$B$7)) -> 63.320419 | G89: =F89*$S$52 -> 134271.96 | H89: =F89*$S$51 -> 95678.128 | I89: =$B$32 -> 138000 | J89: =H89-I89 -> -42321.872 | K89: =K88+J89 -> -367762.82 | L89: =IF(D89*$B$7*$B$8=0,0,F89*$S$45/(D89*$B$7*$B$8)) -> 0.17413115 | M89: =(C89*$B$7*$B$12*(1-$B$13)*(1-$B$14))*$S$45/($B$7*$B$8*$B$9) -> 1.2189181 | N89: =IF(J89>=0,"YES","") | O89: =IF(K89>=0,"YES","")
A90: Month 7 | B90: 0.08 | C90: =C89*(1+B90) -> 10.906866 | D90: 7 | E90: =F90*($B$18+$B$17/$B$19) -> 61.547447 | F90: =MIN((C90*$B$7*$B$12*(1-$B$13)*(1-$B$14)),MIN(D90*$B$7*$B$8*$B$9/$S$45,D90*$B$10*$B$7)) -> 68.386053 | G90: =F90*$S$52 -> 145013.72 | H90: =F90*$S$51 -> 103332.38 | I90: =$B$32 -> 138000 | J90: =H90-I90 -> -34667.622 | K90: =K89+J90 -> -402430.44 | L90: =IF(D90*$B$7*$B$8=0,0,F90*$S$45/(D90*$B$7*$B$8)) -> 0.18806164 | M90: =(C90*$B$7*$B$12*(1-$B$13)*(1-$B$14))*$S$45/($B$7*$B$8*$B$9) -> 1.3164315 | N90: =IF(J90>=0,"YES","") | O90: =IF(K90>=0,"YES","")
A91: Month 8 | B91: 0.06 | C91: =C90*(1+B91) -> 11.561278 | D91: 8 | E91: =F91*($B$18+$B$17/$B$19) -> 65.240294 | F91: =MIN((C91*$B$7*$B$12*(1-$B$13)*(1-$B$14)),MIN(D91*$B$7*$B$8*$B$9/$S$45,D91*$B$10*$B$7)) -> 72.489216 | G91: =F91*$S$52 -> 153714.54 | H91: =F91*$S$51 -> 109532.32 | I91: =$B$32 -> 138000 | J91: =H91-I91 -> -28467.679 | K91: =K90+J91 -> -430898.12 | L91: =IF(D91*$B$7*$B$8=0,0,F91*$S$45/(D91*$B$7*$B$8)) -> 0.17442718 | M91: =(C91*$B$7*$B$12*(1-$B$13)*(1-$B$14))*$S$45/($B$7*$B$8*$B$9) -> 1.3954174 | N91: =IF(J91>=0,"YES","") | O91: =IF(K91>=0,"YES","")
A92: Month 9 | B92: 0.06 | C92: =C91*(1+B92) -> 12.254955 | D92: 8 | E92: =F92*($B$18+$B$17/$B$19) -> 69.154712 | F92: =MIN((C92*$B$7*$B$12*(1-$B$13)*(1-$B$14)),MIN(D92*$B$7*$B$8*$B$9/$S$45,D92*$B$10*$B$7)) -> 76.838569 | G92: =F92*$S$52 -> 162937.41 | H92: =F92*$S$51 -> 116104.26 | I92: =$B$32 -> 138000 | J92: =H92-I92 -> -21895.74 | K92: =K91+J92 -> -452793.86 | L92: =IF(D92*$B$7*$B$8=0,0,F92*$S$45/(D92*$B$7*$B$8)) -> 0.18489281 | M92: =(C92*$B$7*$B$12*(1-$B$13)*(1-$B$14))*$S$45/($B$7*$B$8*$B$9) -> 1.4791424 | N92: =IF(J92>=0,"YES","") | O92: =IF(K92>=0,"YES","")
A93: Month 10 | B93: 0.05 | C93: =C92*(1+B93) -> 12.867703 | D93: 9 | E93: =F93*($B$18+$B$17/$B$19) -> 72.612447 | F93: =MIN((C93*$B$7*$B$12*(1-$B$13)*(1-$B$14)),MIN(D93*$B$7*$B$8*$B$9/$S$45,D93*$B$10*$B$7)) -> 80.680497 | G93: =F93*$S$52 -> 171084.28 | H93: =F93*$S$51 -> 121909.47 | I93: =$B$32 -> 138000 | J93: =H93-I93 -> -16090.527 | K93: =K92+J93 -> -468884.39 | L93: =IF(D93*$B$7*$B$8=0,0,F93*$S$45/(D93*$B$7*$B$8)) -> 0.17256662 | M93: =(C93*$B$7*$B$12*(1-$B$13)*(1-$B$14))*$S$45/($B$7*$B$8*$B$9) -> 1.5530996 | N93: =IF(J93>=0,"YES","") | O93: =IF(K93>=0,"YES","")
A94: Month 11 | B94: 0.05 | C94: =C93*(1+B94) -> 13.511088 | D94: 9 | E94: =F94*($B$18+$B$17/$B$19) -> 76.24307 | F94: =MIN((C94*$B$7*$B$12*(1-$B$13)*(1-$B$14)),MIN(D94*$B$7*$B$8*$B$9/$S$45,D94*$B$10*$B$7)) -> 84.714522 | G94: =F94*$S$52 -> 179638.5 | H94: =F94*$S$51 -> 128004.95 | I94: =$B$32 -> 138000 | J94: =H94-I94 -> -9995.053 | K94: =K93+J94 -> -478879.44 | L94: =IF(D94*$B$7*$B$8=0,0,F94*$S$45/(D94*$B$7*$B$8)) -> 0.18119495 | M94: =(C94*$B$7*$B$12*(1-$B$13)*(1-$B$14))*$S$45/($B$7*$B$8*$B$9) -> 1.6307545 | N94: =IF(J94>=0,"YES","") | O94: =IF(K94>=0,"YES","")
A95: Month 12 | B95: 0.05 | C95: =C94*(1+B95) -> 14.186642 | D95: 10 | E95: =F95*($B$18+$B$17/$B$19) -> 80.055223 | F95: =MIN((C95*$B$7*$B$12*(1-$B$13)*(1-$B$14)),MIN(D95*$B$7*$B$8*$B$9/$S$45,D95*$B$10*$B$7)) -> 88.950248 | G95: =F95*$S$52 -> 188620.42 | H95: =F95*$S$51 -> 134405.19 | I95: =$B$32 -> 138000 | J95: =H95-I95 -> -3594.8056 | K95: =K94+J95 -> -482474.25 | L95: =IF(D95*$B$7*$B$8=0,0,F95*$S$45/(D95*$B$7*$B$8)) -> 0.17122923 | M95: =(C95*$B$7*$B$12*(1-$B$13)*(1-$B$14))*$S$45/($B$7*$B$8*$B$9) -> 1.7122923 | N95: =IF(J95>=0,"YES","") | O95: =IF(K95>=0,"YES","")
A97: Model note: Whitefield demand, conversion, utilization, repeat rate and fixed costs are founder assumptions for planning, not verified market data. Transport is modeled as Case 1 (patient-arranged) or Case 2 (NivrāaCare-arranged third-party cab). Accounting/GST treatment of cab pass-through and coordination fee should be validated with the CA.

Sheet Profit Maximizer
A1: NivrāaCare — Profit Maximizer & CFO Decision Support | Fully Loaded View
A2: Ranks modeled economics after payroll allocation while preserving recurring potential and operational complexity. Manual-priced overnight / 24h services are excluded from automatic 'highest' insights.
A4: CFO Insights — Dynamic
A5: Highest modeled eligible contribution / journey | B5: =INDEX($A$15:$A$44,MATCH(MAX($AL$15:$AL$44),$AL$15:$AL$44,0)) -> Medical Tourism — Concierge Package (24 HR Basis) | C5: Fully loaded blended contribution | D5: =MAX($AL$15:$AL$44) -> 11772.524
A6: Highest modeled eligible contribution / Angel hour | B6: =INDEX($A$15:$A$44,MATCH(MAX($AM$15:$AM$44),$AM$15:$AM$44,0)) -> Medical Tourism — Concierge Package (24 HR Basis) | C6: ₹ / Angel hour | D6: =MAX($AM$15:$AM$44) -> 488.20518
A7: Highest recurring strategic potential | B7: =INDEX($A$15:$A$44,MATCH(MAX($AJ$15:$AJ$44),$AJ$15:$AJ$44,0)) -> Hospital Visit | C7: Potential score | D7: =MAX($AJ$15:$AJ$44) -> 5
A8: Lowest fully loaded margin service | B8: =INDEX('Service Economics'!$A$5:$A$34,MATCH(MIN('Service Economics'!$AM$5:$AM$34),'Service Economics'!$AM$5:$AM$34,0)) -> Medical Records Concierge | C8: Fully loaded margin | D8: =MIN('Service Economics'!$AM$5:$AM$34) -> 0.40106519
A9: Recommended transport mix | B9: =IF(AVERAGE($G$15:$G$44)>AVERAGE($F$15:$F$44),"Case 2 primary / Case 1 fallback","Case 1 primary") -> Case 2 primary / Case 1 fallback | C9: Current break-even volume | D9: ='Whitefield Monthly Projection'!$Q$39 -> 91.329314
A10: Biggest profit lever | B10: =INDEX($A$51:$A$63,MATCH(MAX($I$51:$I$63),$I$51:$I$63,0)) -> Customer leads / day | C10: Biggest unit-economics risk | D10: =IF('Whitefield Monthly Projection'!$Q$21<'Whitefield Monthly Projection'!$B$9*0.8,"Low Whitefield demand density / Angel under-utilization",IF('Whitefield Monthly Projection'!$S$45>4,"Long hospital waiting / journey duration","Transport/payment leakage")) -> Low Whitefield demand density / Angel under-utilization
A11: ="Model insight: "&B6&" currently has the highest modeled contribution per Angel hour. Commercial priority must also consider repeat potential, operational complexity and manual-pricing status; do not treat the top modeled service as an automatic launch recommendation." -> Model insight: Medical Tourism — Concierge Package (24 HR Basis) currently has the highest modeled contribution per Angel hour. Commercial priority must also consider repeat potential, operational complexity and manual-pricing status; do not treat the top modeled service as an automatic launch recommendation.
A13: Service Profitability & Capacity Ranking — Incremental + Fully Loaded Views
A14: Service | B14: Category | C14: Hours | D14: Customer Price | E14: Revenue / Angel Hr | F14: Case 1 Contribution | G14: Case 2 Contribution | H14: Blended Contribution / Journey | I14: Contribution Margin | J14: Contribution / Angel Hr | K14: Repeat Potential (1-5) | L14: Operational Complexity (1-5) | M14: Transport Dependency (1-5) | N14: Strategic Weight (0.5-1.5) | O14: Capacity Efficiency Score | P14: Model Score | Q14: Recommended Priority | R14: Current Mix % | S14: Optimization Score | T14: Optimized Mix % | U14: Recurring Service? | V14: Rate Multiplier | W14: Fixed Premium | X14: Recurring Profit/Hr | Y14: Price Sensitivity Weight | Z14: Angel Hr Weight | AA14: Min Booking Test Price | AB14: Addl-Hour Test Price | AC14: Current Collection/Journey | AD14: Optimized Collection Weight | AE14: Optimized Contribution Weight | AF14: Optimized Hours Weight | AG14: Case 1 Fully Loaded Contribution | AH14: Case 2 Fully Loaded Contribution | AI14: Fully Loaded Contribution / Angel Hr | AJ14: Recurring / Strategic Potential | AK14: Portfolio | AL14: Auto-Rank Blended Contribution | AM14: Auto-Rank Contribution / Angel Hr
A15: ='Service Economics'!A5 -> Hospital Visit | B15: ='Service Economics'!B5 -> Medical Visit | C15: ='Service Economics'!C5 -> 4 | D15: ='Service Economics'!K5 -> 1395 | E15: =IF(C15=0,0,D15/C15) -> 348.75 | F15: ='Service Economics'!R5 -> 1076.8784 | G15: ='Service Economics'!AB5 -> 1215.8784 | H15: ='Whitefield Monthly Projection'!$B$15*F15+'Whitefield Monthly Projection'!$B$16*G15-'Whitefield Monthly Projection'!H37 -> 1132.4784 | I15: =IF(('Service Economics'!L5+'Whitefield Monthly Projection'!$B$16*'Service Economics'!U5/(1+'Global Inputs'!$B$17))=0,0,H15/('Service Economics'!L5+'Whitefield Monthly Projection'!$B$16*'Service Economics'!U5/(1+'Global Inputs'!$B$17))) -> 0.91196271 | J15: =IF(C15=0,0,H15/C15) -> 283.1196 | K15: 3 | L15: 3 | M15: 5 | N15: 1.2 | O15: =IF(MAX($J$15:$J$44)=0,0,J15/MAX($J$15:$J$44)*100) -> 47.657444 | P15: =(IF(MAX($J$15:$J$44)=0,0,J15/MAX($J$15:$J$44))*0.45+K15/5*0.2+(6-L15)/5*0.15+(6-M15)/5*0.1+N15/1.5*0.1)*100 -> 52.44585 | Q15: =IF(H15<=0,"REVIEW — Economics need improvement",IF(AND(J15>=AVERAGE($J$15:$J$44)*1.15,K15>=4,L15<=3),"CORE — Push aggressively",IF(J15>=AVERAGE($J$15:$J$44),"GROW — Attractive economics",IF(K15>=4,"STRATEGIC — Important but lower margin","REVIEW — Economics need improvement")))) -> REVIEW — Economics need improvement | R15: ='Whitefield Monthly Projection'!G37 -> 0.23 | S15: =MAX(J15,0)^3*(0.5+K15/10)*(0.5+(6-L15)/10)*N15 -> 17428942 | T15: =IF(SUM($S$15:$S$44)=0,R15,0.2*R15+0.8*S15/SUM($S$15:$S$44)) -> 0.066824069 | U15: No | V15: ='Service Economics'!D5 -> 1 | W15: ='Service Economics'!E5 -> 0 | X15: =IF(U15="Yes",J15,0) -> 0 | Y15: =R15*C15*V15 -> 0.92 | Z15: =R15*C15*'Service Economics'!F5 -> 0.92 | AA15: =MAX(C15,$C$53)*'Global Inputs'!$B$5*V15+W15 -> 1196 | AB15: =MAX(C15,'Global Inputs'!$B$22)*'Global Inputs'!$B$5*V15*$C$54+W15 -> 1076.4 | AC15: =D15+'Whitefield Monthly Projection'!$B$16*'Service Economics'!V5 -> 1654.6 | AD15: =T15*AC15 -> 110.5671 | AE15: =T15*H15 -> 75.676814 | AF15: =T15*C15 -> 0.26729628 | AG15: ='Service Economics'!AL5 -> 662.67721 | AH15: ='Service Economics'!AN5 -> 801.67721 | AI15: ='Service Economics'!AP5 -> 165.6693 | AJ15: ='Service Economics'!AQ5 -> 5 | AK15: ='Service Portfolio'!P5 -> SCALE | AL15: =IF(ISNUMBER(SEARCH("Future",'Service Economics'!AH5)),-1000000000,AG15*(1-'Whitefield Monthly Projection'!$B$16)+AH15*'Whitefield Monthly Projection'!$B$16) -> 718.27721 | AM15: =IF(ISNUMBER(SEARCH("Future",'Service Economics'!AH5)),-1000000000,AI15) -> 165.6693
A16: ='Service Economics'!A6 -> Hospital Visit — Concierge at Hospital | B16: ='Service Economics'!B6 -> Medical Visit | C16: ='Service Economics'!C6 -> 3 | D16: ='Service Economics'!K6 -> 916.6 | E16: =IF(C16=0,0,D16/C16) -> 305.53333 | F16: ='Service Economics'!R6 -> 688.19866 | G16: ='Service Economics'!AB6 -> 827.19866 | H16: ='Whitefield Monthly Projection'!$B$15*F16+'Whitefield Monthly Projection'!$B$16*G16-'Whitefield Monthly Projection'!H38 -> 743.79866 | I16: =IF(('Service Economics'!L6+'Whitefield Monthly Projection'!$B$16*'Service Economics'!U6/(1+'Global Inputs'!$B$17))=0,0,H16/('Service Economics'!L6+'Whitefield Monthly Projection'!$B$16*'Service Economics'!U6/(1+'Global Inputs'!$B$17))) -> 0.88930745 | J16: =IF(C16=0,0,H16/C16) -> 247.93289 | K16: 3 | L16: 2 | M16: 4 | N16: 1 | O16: =IF(MAX($J$15:$J$44)=0,0,J16/MAX($J$15:$J$44)*100) -> 41.734475 | P16: =(IF(MAX($J$15:$J$44)=0,0,J16/MAX($J$15:$J$44))*0.45+K16/5*0.2+(6-L16)/5*0.15+(6-M16)/5*0.1+N16/1.5*0.1)*100 -> 53.44718 | Q16: =IF(H16<=0,"REVIEW — Economics need improvement",IF(AND(J16>=AVERAGE($J$15:$J$44)*1.15,K16>=4,L16<=3),"CORE — Push aggressively",IF(J16>=AVERAGE($J$15:$J$44),"GROW — Attractive economics",IF(K16>=4,"STRATEGIC — Important but lower margin","REVIEW — Economics need improvement")))) -> REVIEW — Economics need improvement | R16: ='Whitefield Monthly Projection'!G38 -> 0.12 | S16: =MAX(J16,0)^3*(0.5+K16/10)*(0.5+(6-L16)/10)*N16 -> 10973241 | T16: =IF(SUM($S$15:$S$44)=0,R16,0.2*R16+0.8*S16/SUM($S$15:$S$44)) -> 0.037110809 | U16: No | V16: ='Service Economics'!D6 -> 0.8 | W16: ='Service Economics'!E6 -> 0 | X16: =IF(U16="Yes",J16,0) -> 0 | Y16: =R16*C16*V16 -> 0.288 | Z16: =R16*C16*'Service Economics'!F6 -> 0.36 | AA16: =MAX(C16,$C$53)*'Global Inputs'!$B$5*V16+W16 -> 717.6 | AB16: =MAX(C16,'Global Inputs'!$B$22)*'Global Inputs'!$B$5*V16*$C$54+W16 -> 645.84 | AC16: =D16+'Whitefield Monthly Projection'!$B$16*'Service Economics'!V6 -> 1176.2 | AD16: =T16*AC16 -> 43.649733 | AE16: =T16*H16 -> 27.60297 | AF16: =T16*C16 -> 0.11133243 | AG16: ='Service Economics'!AL6 -> 377.54777 | AH16: ='Service Economics'!AN6 -> 516.54777 | AI16: ='Service Economics'!AP6 -> 125.84926 | AJ16: ='Service Economics'!AQ6 -> 4 | AK16: ='Service Portfolio'!P6 -> OPTIMIZE | AL16: =IF(ISNUMBER(SEARCH("Future",'Service Economics'!AH6)),-1000000000,AG16*(1-'Whitefield Monthly Projection'!$B$16)+AH16*'Whitefield Monthly Projection'!$B$16) -> 433.14777 | AM16: =IF(ISNUMBER(SEARCH("Future",'Service Economics'!AH6)),-1000000000,AI16) -> 125.84926
A17: ='Service Economics'!A7 -> Clinic Visit | B17: ='Service Economics'!B7 -> Medical Visit | C17: ='Service Economics'!C7 -> 2 | D17: ='Service Economics'!K7 -> 737.2 | E17: =IF(C17=0,0,D17/C17) -> 368.6 | F17: ='Service Economics'!R7 -> 542.44376 | G17: ='Service Economics'!AB7 -> 681.44376 | H17: ='Whitefield Monthly Projection'!$B$15*F17+'Whitefield Monthly Projection'!$B$16*G17-'Whitefield Monthly Projection'!H39 -> 598.04376 | I17: =IF(('Service Economics'!L7+'Whitefield Monthly Projection'!$B$16*'Service Economics'!U7/(1+'Global Inputs'!$B$17))=0,0,H17/('Service Economics'!L7+'Whitefield Monthly Projection'!$B$16*'Service Economics'!U7/(1+'Global Inputs'!$B$17))) -> 0.87389123 | J17: =IF(C17=0,0,H17/C17) -> 299.02188 | K17: 3 | L17: 2 | M17: 4 | N17: 1 | O17: =IF(MAX($J$15:$J$44)=0,0,J17/MAX($J$15:$J$44)*100) -> 50.334271 | P17: =(IF(MAX($J$15:$J$44)=0,0,J17/MAX($J$15:$J$44))*0.45+K17/5*0.2+(6-L17)/5*0.15+(6-M17)/5*0.1+N17/1.5*0.1)*100 -> 57.317089 | Q17: =IF(H17<=0,"REVIEW — Economics need improvement",IF(AND(J17>=AVERAGE($J$15:$J$44)*1.15,K17>=4,L17<=3),"CORE — Push aggressively",IF(J17>=AVERAGE($J$15:$J$44),"GROW — Attractive economics",IF(K17>=4,"STRATEGIC — Important but lower margin","REVIEW — Economics need improvement")))) -> GROW — Attractive economics | R17: ='Whitefield Monthly Projection'!G39 -> 0.09 | S17: =MAX(J17,0)^3*(0.5+K17/10)*(0.5+(6-L17)/10)*N17 -> 19250473 | T17: =IF(SUM($S$15:$S$44)=0,R17,0.2*R17+0.8*S17/SUM($S$15:$S$44)) -> 0.041000431 | U17: No | V17: ='Service Economics'!D7 -> 0.9 | W17: ='Service Economics'!E7 -> 0 | X17: =IF(U17="Yes",J17,0) -> 0 | Y17: =R17*C17*V17 -> 0.162 | Z17: =R17*C17*'Service Economics'!F7 -> 0.18 | AA17: =MAX(C17,$C$53)*'Global Inputs'!$B$5*V17+W17 -> 807.3 | AB17: =MAX(C17,'Global Inputs'!$B$22)*'Global Inputs'!$B$5*V17*$C$54+W17 -> 484.38 | AC17: =D17+'Whitefield Monthly Projection'!$B$16*'Service Economics'!V7 -> 996.8 | AD17: =T17*AC17 -> 40.86923 | AE17: =T17*H17 -> 24.520052 | AF17: =T17*C17 -> 0.082000862 | AG17: ='Service Economics'!AL7 -> 335.34317 | AH17: ='Service Economics'!AN7 -> 474.34317 | AI17: ='Service Economics'!AP7 -> 167.67159 | AJ17: ='Service Economics'!AQ7 -> 4 | AK17: ='Service Portfolio'!P7 -> SCALE | AL17: =IF(ISNUMBER(SEARCH("Future",'Service Economics'!AH7)),-1000000000,AG17*(1-'Whitefield Monthly Projection'!$B$16)+AH17*'Whitefield Monthly Projection'!$B$16) -> 390.94317 | AM17: =IF(ISNUMBER(SEARCH("Future",'Service Economics'!AH7)),-1000000000,AI17) -> 167.67159
A18: ='Service Economics'!A8 -> Diagnostic Center Visit | B18: ='Service Economics'!B8 -> Medical Visit | C18: ='Service Economics'!C8 -> 3 | D18: ='Service Economics'!K8 -> 961.45 | E18: =IF(C18=0,0,D18/C18) -> 320.48333 | F18: ='Service Economics'!R8 -> 724.63739 | G18: ='Service Economics'!AB8 -> 863.63739 | H18: ='Whitefield Monthly Projection'!$B$15*F18+'Whitefield Monthly Projection'!$B$16*G18-'Whitefield Monthly Projection'!H40 -> 780.23739 | I18: =IF(('Service Economics'!L8+'Whitefield Monthly Projection'!$B$16*'Service Economics'!U8/(1+'Global Inputs'!$B$17))=0,0,H18/('Service Economics'!L8+'Whitefield Monthly Projection'!$B$16*'Service Economics'!U8/(1+'Global Inputs'!$B$17))) -> 0.89232385 | J18: =IF(C18=0,0,H18/C18) -> 260.07913 | K18: 3 | L18: 2 | M18: 4 | N18: 1 | O18: =IF(MAX($J$15:$J$44)=0,0,J18/MAX($J$15:$J$44)*100) -> 43.779048 | P18: =(IF(MAX($J$15:$J$44)=0,0,J18/MAX($J$15:$J$44))*0.45+K18/5*0.2+(6-L18)/5*0.15+(6-M18)/5*0.1+N18/1.5*0.1)*100 -> 54.367238 | Q18: =IF(H18<=0,"REVIEW — Economics need improvement",IF(AND(J18>=AVERAGE($J$15:$J$44)*1.15,K18>=4,L18<=3),"CORE — Push aggressively",IF(J18>=AVERAGE($J$15:$J$44),"GROW — Attractive economics",IF(K18>=4,"STRATEGIC — Important but lower margin","REVIEW — Economics need improvement")))) -> REVIEW — Economics need improvement | R18: ='Whitefield Monthly Projection'!G40 -> 0.08 | S18: =MAX(J18,0)^3*(0.5+K18/10)*(0.5+(6-L18)/10)*N18 -> 12666278 | T18: =IF(SUM($S$15:$S$44)=0,R18,0.2*R18+0.8*S18/SUM($S$15:$S$44)) -> 0.031133646 | U18: No | V18: ='Service Economics'!D8 -> 0.85 | W18: ='Service Economics'!E8 -> 0 | X18: =IF(U18="Yes",J18,0) -> 0 | Y18: =R18*C18*V18 -> 0.204 | Z18: =R18*C18*'Service Economics'!F8 -> 0.24 | AA18: =MAX(C18,$C$53)*'Global Inputs'!$B$5*V18+W18 -> 762.45 | AB18: =MAX(C18,'Global Inputs'!$B$22)*'Global Inputs'!$B$5*V18*$C$54+W18 -> 686.205 | AC18: =D18+'Whitefield Monthly Projection'!$B$16*'Service Economics'!V8 -> 1221.05 | AD18: =T18*AC18 -> 38.015739 | AE18: =T18*H18 -> 24.291635 | AF18: =T18*C18 -> 0.093400938 | AG18: ='Service Economics'!AL8 -> 413.9865 | AH18: ='Service Economics'!AN8 -> 552.9865 | AI18: ='Service Economics'!AP8 -> 137.9955 | AJ18: ='Service Economics'!AQ8 -> 4 | AK18: ='Service Portfolio'!P8 -> OPTIMIZE | AL18: =IF(ISNUMBER(SEARCH("Future",'Service Economics'!AH8)),-1000000000,AG18*(1-'Whitefield Monthly Projection'!$B$16)+AH18*'Whitefield Monthly Projection'!$B$16) -> 469.5865 | AM18: =IF(ISNUMBER(SEARCH("Future",'Service Economics'!AH8)),-1000000000,AI18) -> 137.9955
A19: ='Service Economics'!A9 -> Health Check-up Concierge | B19: ='Service Economics'!B9 -> Medical Visit | C19: ='Service Economics'!C9 -> 5 | D19: ='Service Economics'!K9 -> 1544.5 | E19: =IF(C19=0,0,D19/C19) -> 308.9 | F19: ='Service Economics'!R9 -> 1198.3408 | G19: ='Service Economics'!AB9 -> 1337.3408 | H19: ='Whitefield Monthly Projection'!$B$15*F19+'Whitefield Monthly Projection'!$B$16*G19-'Whitefield Monthly Projection'!H41 -> 1253.9408 | I19: =IF(('Service Economics'!L9+'Whitefield Monthly Projection'!$B$16*'Service Economics'!U9/(1+'Global Inputs'!$B$17))=0,0,H19/('Service Economics'!L9+'Whitefield Monthly Projection'!$B$16*'Service Economics'!U9/(1+'Global Inputs'!$B$17))) -> 0.91628963 | J19: =IF(C19=0,0,H19/C19) -> 250.78816 | K19: 2 | L19: 3 | M19: 4 | N19: 0.9 | O19: =IF(MAX($J$15:$J$44)=0,0,J19/MAX($J$15:$J$44)*100) -> 42.215102 | P19: =(IF(MAX($J$15:$J$44)=0,0,J19/MAX($J$15:$J$44))*0.45+K19/5*0.2+(6-L19)/5*0.15+(6-M19)/5*0.1+N19/1.5*0.1)*100 -> 45.996796 | Q19: =IF(H19<=0,"REVIEW — Economics need improvement",IF(AND(J19>=AVERAGE($J$15:$J$44)*1.15,K19>=4,L19<=3),"CORE — Push aggressively",IF(J19>=AVERAGE($J$15:$J$44),"GROW — Attractive economics",IF(K19>=4,"STRATEGIC — Important but lower margin","REVIEW — Economics need improvement")))) -> REVIEW — Economics need improvement | R19: ='Whitefield Monthly Projection'!G41 -> 0.05 | S19: =MAX(J19,0)^3*(0.5+K19/10)*(0.5+(6-L19)/10)*N19 -> 7949716.3 | T19: =IF(SUM($S$15:$S$44)=0,R19,0.2*R19+0.8*S19/SUM($S$15:$S$44)) -> 0.019498307 | U19: No | V19: ='Service Economics'!D9 -> 0.9 | W19: ='Service Economics'!E9 -> 0 | X19: =IF(U19="Yes",J19,0) -> 0 | Y19: =R19*C19*V19 -> 0.225 | Z19: =R19*C19*'Service Economics'!F9 -> 0.25 | AA19: =MAX(C19,$C$53)*'Global Inputs'!$B$5*V19+W19 -> 1345.5 | AB19: =MAX(C19,'Global Inputs'!$B$22)*'Global Inputs'!$B$5*V19*$C$54+W19 -> 1210.95 | AC19: =D19+'Whitefield Monthly Projection'!$B$16*'Service Economics'!V9 -> 1804.1 | AD19: =T19*AC19 -> 35.176896 | AE19: =T19*H19 -> 24.449723 | AF19: =T19*C19 -> 0.097491535 | AG19: ='Service Economics'!AL9 -> 680.58933 | AH19: ='Service Economics'!AN9 -> 819.58933 | AI19: ='Service Economics'!AP9 -> 136.11787 | AJ19: ='Service Economics'!AQ9 -> 3 | AK19: ='Service Portfolio'!P9 -> REVIEW | AL19: =IF(ISNUMBER(SEARCH("Future",'Service Economics'!AH9)),-1000000000,AG19*(1-'Whitefield Monthly Projection'!$B$16)+AH19*'Whitefield Monthly Projection'!$B$16) -> 736.18933 | AM19: =IF(ISNUMBER(SEARCH("Future",'Service Economics'!AH9)),-1000000000,AI19) -> 136.11787
A20: ='Service Economics'!A10 -> Hospital Admission Concierge | B20: ='Service Economics'!B10 -> Hospital Support | C20: ='Service Economics'!C10 -> 4 | D20: ='Service Economics'!K10 -> 1574.4 | E20: =IF(C20=0,0,D20/C20) -> 393.6 | F20: ='Service Economics'!R10 -> 1222.6333 | G20: ='Service Economics'!AB10 -> 1361.6333 | H20: ='Whitefield Monthly Projection'!$B$15*F20+'Whitefield Monthly Projection'!$B$16*G20-'Whitefield Monthly Projection'!H42 -> 1278.2333 | I20: =IF(('Service Economics'!L10+'Whitefield Monthly Projection'!$B$16*'Service Economics'!U10/(1+'Global Inputs'!$B$17))=0,0,H20/('Service Economics'!L10+'Whitefield Monthly Projection'!$B$16*'Service Economics'!U10/(1+'Global Inputs'!$B$17))) -> 0.91706062 | J20: =IF(C20=0,0,H20/C20) -> 319.55832 | K20: 2 | L20: 4 | M20: 4 | N20: 1.1 | O20: =IF(MAX($J$15:$J$44)=0,0,J20/MAX($J$15:$J$44)*100) -> 53.791165 | P20: =(IF(MAX($J$15:$J$44)=0,0,J20/MAX($J$15:$J$44))*0.45+K20/5*0.2+(6-L20)/5*0.15+(6-M20)/5*0.1+N20/1.5*0.1)*100 -> 49.539357 | Q20: =IF(H20<=0,"REVIEW — Economics need improvement",IF(AND(J20>=AVERAGE($J$15:$J$44)*1.15,K20>=4,L20<=3),"CORE — Push aggressively",IF(J20>=AVERAGE($J$15:$J$44),"GROW — Attractive economics",IF(K20>=4,"STRATEGIC — Important but lower margin","REVIEW — Economics need improvement")))) -> GROW — Attractive economics | R20: ='Whitefield Monthly Projection'!G42 -> 0.05 | S20: =MAX(J20,0)^3*(0.5+K20/10)*(0.5+(6-L20)/10)*N20 -> 17588920 | T20: =IF(SUM($S$15:$S$44)=0,R20,0.2*R20+0.8*S20/SUM($S$15:$S$44)) -> 0.03101521 | U20: No | V20: ='Service Economics'!D10 -> 1.15 | W20: ='Service Economics'!E10 -> 0 | X20: =IF(U20="Yes",J20,0) -> 0 | Y20: =R20*C20*V20 -> 0.23 | Z20: =R20*C20*'Service Economics'!F10 -> 0.2 | AA20: =MAX(C20,$C$53)*'Global Inputs'!$B$5*V20+W20 -> 1375.4 | AB20: =MAX(C20,'Global Inputs'!$B$22)*'Global Inputs'!$B$5*V20*$C$54+W20 -> 1237.86 | AC20: =D20+'Whitefield Monthly Projection'!$B$16*'Service Economics'!V10 -> 1834 | AD20: =T20*AC20 -> 56.881895 | AE20: =T20*H20 -> 39.644674 | AF20: =T20*C20 -> 0.12406084 | AG20: ='Service Economics'!AL10 -> 808.4321 | AH20: ='Service Economics'!AN10 -> 947.4321 | AI20: ='Service Economics'!AP10 -> 202.10803 | AJ20: ='Service Economics'!AQ10 -> 3 | AK20: ='Service Portfolio'!P10 -> RETAIN | AL20: =IF(ISNUMBER(SEARCH("Future",'Service Economics'!AH10)),-1000000000,AG20*(1-'Whitefield Monthly Projection'!$B$16)+AH20*'Whitefield Monthly Projection'!$B$16) -> 864.0321 | AM20: =IF(ISNUMBER(SEARCH("Future",'Service Economics'!AH10)),-1000000000,AI20) -> 202.10803
A21: ='Service Economics'!A11 -> Hospital Discharge Concierge | B21: ='Service Economics'!B11 -> Hospital Support | C21: ='Service Economics'!C11 -> 4 | D21: ='Service Economics'!K11 -> 1514.6 | E21: =IF(C21=0,0,D21/C21) -> 378.65 | F21: ='Service Economics'!R11 -> 1174.0483 | G21: ='Service Economics'!AB11 -> 1313.0483 | H21: ='Whitefield Monthly Projection'!$B$15*F21+'Whitefield Monthly Projection'!$B$16*G21-'Whitefield Monthly Projection'!H43 -> 1229.6483 | I21: =IF(('Service Economics'!L11+'Whitefield Monthly Projection'!$B$16*'Service Economics'!U11/(1+'Global Inputs'!$B$17))=0,0,H21/('Service Economics'!L11+'Whitefield Monthly Projection'!$B$16*'Service Economics'!U11/(1+'Global Inputs'!$B$17))) -> 0.91548955 | J21: =IF(C21=0,0,H21/C21) -> 307.41208 | K21: 2 | L21: 4 | M21: 4 | N21: 1.1 | O21: =IF(MAX($J$15:$J$44)=0,0,J21/MAX($J$15:$J$44)*100) -> 51.746591 | P21: =(IF(MAX($J$15:$J$44)=0,0,J21/MAX($J$15:$J$44))*0.45+K21/5*0.2+(6-L21)/5*0.15+(6-M21)/5*0.1+N21/1.5*0.1)*100 -> 48.619299 | Q21: =IF(H21<=0,"REVIEW — Economics need improvement",IF(AND(J21>=AVERAGE($J$15:$J$44)*1.15,K21>=4,L21<=3),"CORE — Push aggressively",IF(J21>=AVERAGE($J$15:$J$44),"GROW — Attractive economics",IF(K21>=4,"STRATEGIC — Important but lower margin","REVIEW — Economics need improvement")))) -> GROW — Attractive economics | R21: ='Whitefield Monthly Projection'!G43 -> 0.05 | S21: =MAX(J21,0)^3*(0.5+K21/10)*(0.5+(6-L21)/10)*N21 -> 15658550 | T21: =IF(SUM($S$15:$S$44)=0,R21,0.2*R21+0.8*S21/SUM($S$15:$S$44)) -> 0.028708808 | U21: No | V21: ='Service Economics'!D11 -> 1.1 | W21: ='Service Economics'!E11 -> 0 | X21: =IF(U21="Yes",J21,0) -> 0 | Y21: =R21*C21*V21 -> 0.22 | Z21: =R21*C21*'Service Economics'!F11 -> 0.2 | AA21: =MAX(C21,$C$53)*'Global Inputs'!$B$5*V21+W21 -> 1315.6 | AB21: =MAX(C21,'Global Inputs'!$B$22)*'Global Inputs'!$B$5*V21*$C$54+W21 -> 1184.04 | AC21: =D21+'Whitefield Monthly Projection'!$B$16*'Service Economics'!V11 -> 1774.2 | AD21: =T21*AC21 -> 50.935168 | AE21: =T21*H21 -> 35.301738 | AF21: =T21*C21 -> 0.11483523 | AG21: ='Service Economics'!AL11 -> 759.84714 | AH21: ='Service Economics'!AN11 -> 898.84714 | AI21: ='Service Economics'!AP11 -> 189.96178 | AJ21: ='Service Economics'!AQ11 -> 3 | AK21: ='Service Portfolio'!P11 -> RETAIN | AL21: =IF(ISNUMBER(SEARCH("Future",'Service Economics'!AH11)),-1000000000,AG21*(1-'Whitefield Monthly Projection'!$B$16)+AH21*'Whitefield Monthly Projection'!$B$16) -> 815.44714 | AM21: =IF(ISNUMBER(SEARCH("Future",'Service Economics'!AH11)),-1000000000,AI21) -> 189.96178
A22: ='Service Economics'!A12 -> Overnight Hospital Concierge | B22: ='Service Economics'!B12 -> Hospital Support | C22: ='Service Economics'!C12 -> 12 | D22: ='Service Economics'!K12 -> 3547.8 | E22: =IF(C22=0,0,D22/C22) -> 295.65 | F22: ='Service Economics'!R12 -> 2825.9372 | G22: ='Service Economics'!AB12 -> 2964.9372 | H22: ='Whitefield Monthly Projection'!$B$15*F22+'Whitefield Monthly Projection'!$B$16*G22-'Whitefield Monthly Projection'!H44 -> 2881.5372 | I22: =IF(('Service Economics'!L12+'Whitefield Monthly Projection'!$B$16*'Service Economics'!U12/(1+'Global Inputs'!$B$17))=0,0,H22/('Service Economics'!L12+'Whitefield Monthly Projection'!$B$16*'Service Economics'!U12/(1+'Global Inputs'!$B$17))) -> 0.93977158 | J22: =IF(C22=0,0,H22/C22) -> 240.1281 | K22: 2 | L22: 4 | M22: 2 | N22: 0.9 | O22: =IF(MAX($J$15:$J$44)=0,0,J22/MAX($J$15:$J$44)*100) -> 40.420697 | P22: =(IF(MAX($J$15:$J$44)=0,0,J22/MAX($J$15:$J$44))*0.45+K22/5*0.2+(6-L22)/5*0.15+(6-M22)/5*0.1+N22/1.5*0.1)*100 -> 46.189313 | Q22: =IF(H22<=0,"REVIEW — Economics need improvement",IF(AND(J22>=AVERAGE($J$15:$J$44)*1.15,K22>=4,L22<=3),"CORE — Push aggressively",IF(J22>=AVERAGE($J$15:$J$44),"GROW — Attractive economics",IF(K22>=4,"STRATEGIC — Important but lower margin","REVIEW — Economics need improvement")))) -> REVIEW — Economics need improvement | R22: ='Whitefield Monthly Projection'!G44 -> 0.03 | S22: =MAX(J22,0)^3*(0.5+K22/10)*(0.5+(6-L22)/10)*N22 -> 6106150.9 | T22: =IF(SUM($S$15:$S$44)=0,R22,0.2*R22+0.8*S22/SUM($S$15:$S$44)) -> 0.013295618 | U22: No | V22: ='Service Economics'!D12 -> 0.85 | W22: ='Service Economics'!E12 -> 299 | X22: =IF(U22="Yes",J22,0) -> 0 | Y22: =R22*C22*V22 -> 0.306 | Z22: =R22*C22*'Service Economics'!F12 -> 0.36 | AA22: =MAX(C22,$C$53)*'Global Inputs'!$B$5*V22+W22 -> 3348.8 | AB22: =MAX(C22,'Global Inputs'!$B$22)*'Global Inputs'!$B$5*V22*$C$54+W22 -> 3043.82 | AC22: =D22+'Whitefield Monthly Projection'!$B$16*'Service Economics'!V12 -> 3807.4 | AD22: =T22*AC22 -> 50.621737 | AE22: =T22*H22 -> 38.311818 | AF22: =T22*C22 -> 0.15954742 | AG22: ='Service Economics'!AL12 -> 1583.3336 | AH22: ='Service Economics'!AN12 -> 1722.3336 | AI22: ='Service Economics'!AP12 -> 131.94447 | AJ22: ='Service Economics'!AQ12 -> 2 | AK22: ='Service Portfolio'!P12 -> REVIEW | AL22: =IF(ISNUMBER(SEARCH("Future",'Service Economics'!AH12)),-1000000000,AG22*(1-'Whitefield Monthly Projection'!$B$16)+AH22*'Whitefield Monthly Projection'!$B$16) -> 1638.9336 | AM22: =IF(ISNUMBER(SEARCH("Future",'Service Economics'!AH12)),-1000000000,AI22) -> 131.94447
A23: ='Service Economics'!A13 -> Multi-Day Hospital Concierge (per 12h shift) | B23: ='Service Economics'!B13 -> Hospital Support | C23: ='Service Economics'!C13 -> 12 | D23: ='Service Economics'!K13 -> 3547.8 | E23: =IF(C23=0,0,D23/C23) -> 295.65 | F23: ='Service Economics'!R13 -> 2825.9372 | G23: ='Service Economics'!AB13 -> 2964.9372 | H23: ='Whitefield Monthly Projection'!$B$15*F23+'Whitefield Monthly Projection'!$B$16*G23-'Whitefield Monthly Projection'!H45 -> 2881.5372 | I23: =IF(('Service Economics'!L13+'Whitefield Monthly Projection'!$B$16*'Service Economics'!U13/(1+'Global Inputs'!$B$17))=0,0,H23/('Service Economics'!L13+'Whitefield Monthly Projection'!$B$16*'Service Economics'!U13/(1+'Global Inputs'!$B$17))) -> 0.93977158 | J23: =IF(C23=0,0,H23/C23) -> 240.1281 | K23: 3 | L23: 5 | M23: 1 | N23: 0.8 | O23: =IF(MAX($J$15:$J$44)=0,0,J23/MAX($J$15:$J$44)*100) -> 40.420697 | P23: =(IF(MAX($J$15:$J$44)=0,0,J23/MAX($J$15:$J$44))*0.45+K23/5*0.2+(6-L23)/5*0.15+(6-M23)/5*0.1+N23/1.5*0.1)*100 -> 48.522647 | Q23: =IF(H23<=0,"REVIEW — Economics need improvement",IF(AND(J23>=AVERAGE($J$15:$J$44)*1.15,K23>=4,L23<=3),"CORE — Push aggressively",IF(J23>=AVERAGE($J$15:$J$44),"GROW — Attractive economics",IF(K23>=4,"STRATEGIC — Important but lower margin","REVIEW — Economics need improvement")))) -> REVIEW — Economics need improvement | R23: ='Whitefield Monthly Projection'!G45 -> 0.01 | S23: =MAX(J23,0)^3*(0.5+K23/10)*(0.5+(6-L23)/10)*N23 -> 5316920.5 | T23: =IF(SUM($S$15:$S$44)=0,R23,0.2*R23+0.8*S23/SUM($S$15:$S$44)) -> 0.0083526472 | U23: Yes | V23: ='Service Economics'!D13 -> 0.85 | W23: ='Service Economics'!E13 -> 299 | X23: =IF(U23="Yes",J23,0) -> 240.1281 | Y23: =R23*C23*V23 -> 0.102 | Z23: =R23*C23*'Service Economics'!F13 -> 0.12 | AA23: =MAX(C23,$C$53)*'Global Inputs'!$B$5*V23+W23 -> 3348.8 | AB23: =MAX(C23,'Global Inputs'!$B$22)*'Global Inputs'!$B$5*V23*$C$54+W23 -> 3043.82 | AC23: =D23+'Whitefield Monthly Projection'!$B$16*'Service Economics'!V13 -> 3807.4 | AD23: =T23*AC23 -> 31.801869 | AE23: =T23*H23 -> 24.068463 | AF23: =T23*C23 -> 0.10023177 | AG23: ='Service Economics'!AL13 -> 1583.3336 | AH23: ='Service Economics'!AN13 -> 1722.3336 | AI23: ='Service Economics'!AP13 -> 131.94447 | AJ23: ='Service Economics'!AQ13 -> 2 | AK23: ='Service Portfolio'!P13 -> REVIEW | AL23: =IF(ISNUMBER(SEARCH("Future",'Service Economics'!AH13)),-1000000000,AG23*(1-'Whitefield Monthly Projection'!$B$16)+AH23*'Whitefield Monthly Projection'!$B$16) -> 1638.9336 | AM23: =IF(ISNUMBER(SEARCH("Future",'Service Economics'!AH13)),-1000000000,AI23) -> 131.94447
A24: ='Service Economics'!A14 -> Day Surgery / Procedure Concierge | B24: ='Service Economics'!B14 -> Procedure & Treatment | C24: ='Service Economics'!C14 -> 6 | D24: ='Service Economics'!K14 -> 2351.8 | E24: =IF(C24=0,0,D24/C24) -> 391.96667 | F24: ='Service Economics'!R14 -> 1854.2378 | G24: ='Service Economics'!AB14 -> 1993.2378 | H24: ='Whitefield Monthly Projection'!$B$15*F24+'Whitefield Monthly Projection'!$B$16*G24-'Whitefield Monthly Projection'!H46 -> 1909.8378 | I24: =IF(('Service Economics'!L14+'Whitefield Monthly Projection'!$B$16*'Service Economics'!U14/(1+'Global Inputs'!$B$17))=0,0,H24/('Service Economics'!L14+'Whitefield Monthly Projection'!$B$16*'Service Economics'!U14/(1+'Global Inputs'!$B$17))) -> 0.93042509 | J24: =IF(C24=0,0,H24/C24) -> 318.30631 | K24: 2 | L24: 4 | M24: 4 | N24: 1.1 | O24: =IF(MAX($J$15:$J$44)=0,0,J24/MAX($J$15:$J$44)*100) -> 53.580413 | P24: =(IF(MAX($J$15:$J$44)=0,0,J24/MAX($J$15:$J$44))*0.45+K24/5*0.2+(6-L24)/5*0.15+(6-M24)/5*0.1+N24/1.5*0.1)*100 -> 49.444519 | Q24: =IF(H24<=0,"REVIEW — Economics need improvement",IF(AND(J24>=AVERAGE($J$15:$J$44)*1.15,K24>=4,L24<=3),"CORE — Push aggressively",IF(J24>=AVERAGE($J$15:$J$44),"GROW — Attractive economics",IF(K24>=4,"STRATEGIC — Important but lower margin","REVIEW — Economics need improvement")))) -> GROW — Attractive economics | R24: ='Whitefield Monthly Projection'!G46 -> 0.04 | S24: =MAX(J24,0)^3*(0.5+K24/10)*(0.5+(6-L24)/10)*N24 -> 17382991 | T24: =IF(SUM($S$15:$S$44)=0,R24,0.2*R24+0.8*S24/SUM($S$15:$S$44)) -> 0.028769167 | U24: No | V24: ='Service Economics'!D14 -> 1.2 | W24: ='Service Economics'!E14 -> 0 | X24: =IF(U24="Yes",J24,0) -> 0 | Y24: =R24*C24*V24 -> 0.288 | Z24: =R24*C24*'Service Economics'!F14 -> 0.24 | AA24: =MAX(C24,$C$53)*'Global Inputs'!$B$5*V24+W24 -> 2152.8 | AB24: =MAX(C24,'Global Inputs'!$B$22)*'Global Inputs'!$B$5*V24*$C$54+W24 -> 1937.52 | AC24: =D24+'Whitefield Monthly Projection'!$B$16*'Service Economics'!V14 -> 2611.4 | AD24: =T24*AC24 -> 75.127802 | AE24: =T24*H24 -> 54.944444 | AF24: =T24*C24 -> 0.172615 | AG24: ='Service Economics'!AL14 -> 1232.9361 | AH24: ='Service Economics'!AN14 -> 1371.9361 | AI24: ='Service Economics'!AP14 -> 205.48935 | AJ24: ='Service Economics'!AQ14 -> 3 | AK24: ='Service Portfolio'!P14 -> RETAIN | AL24: =IF(ISNUMBER(SEARCH("Future",'Service Economics'!AH14)),-1000000000,AG24*(1-'Whitefield Monthly Projection'!$B$16)+AH24*'Whitefield Monthly Projection'!$B$16) -> 1288.5361 | AM24: =IF(ISNUMBER(SEARCH("Future",'Service Economics'!AH14)),-1000000000,AI24) -> 205.48935
A25: ='Service Economics'!A15 -> Pre-Surgery Concierge | B25: ='Service Economics'!B15 -> Procedure & Treatment | C25: ='Service Economics'!C15 -> 4 | D25: ='Service Economics'!K15 -> 1514.6 | E25: =IF(C25=0,0,D25/C25) -> 378.65 | F25: ='Service Economics'!R15 -> 1174.0483 | G25: ='Service Economics'!AB15 -> 1313.0483 | H25: ='Whitefield Monthly Projection'!$B$15*F25+'Whitefield Monthly Projection'!$B$16*G25-'Whitefield Monthly Projection'!H47 -> 1229.6483 | I25: =IF(('Service Economics'!L15+'Whitefield Monthly Projection'!$B$16*'Service Economics'!U15/(1+'Global Inputs'!$B$17))=0,0,H25/('Service Economics'!L15+'Whitefield Monthly Projection'!$B$16*'Service Economics'!U15/(1+'Global Inputs'!$B$17))) -> 0.91548955 | J25: =IF(C25=0,0,H25/C25) -> 307.41208 | K25: 2 | L25: 3 | M25: 4 | N25: 1 | O25: =IF(MAX($J$15:$J$44)=0,0,J25/MAX($J$15:$J$44)*100) -> 51.746591 | P25: =(IF(MAX($J$15:$J$44)=0,0,J25/MAX($J$15:$J$44))*0.45+K25/5*0.2+(6-L25)/5*0.15+(6-M25)/5*0.1+N25/1.5*0.1)*100 -> 50.952633 | Q25: =IF(H25<=0,"REVIEW — Economics need improvement",IF(AND(J25>=AVERAGE($J$15:$J$44)*1.15,K25>=4,L25<=3),"CORE — Push aggressively",IF(J25>=AVERAGE($J$15:$J$44),"GROW — Attractive economics",IF(K25>=4,"STRATEGIC — Important but lower margin","REVIEW — Economics need improvement")))) -> GROW — Attractive economics | R25: ='Whitefield Monthly Projection'!G47 -> 0.02 | S25: =MAX(J25,0)^3*(0.5+K25/10)*(0.5+(6-L25)/10)*N25 -> 16268624 | T25: =IF(SUM($S$15:$S$44)=0,R25,0.2*R25+0.8*S25/SUM($S$15:$S$44)) -> 0.023437723 | U25: No | V25: ='Service Economics'!D15 -> 1.1 | W25: ='Service Economics'!E15 -> 0 | X25: =IF(U25="Yes",J25,0) -> 0 | Y25: =R25*C25*V25 -> 0.088 | Z25: =R25*C25*'Service Economics'!F15 -> 0.08 | AA25: =MAX(C25,$C$53)*'Global Inputs'!$B$5*V25+W25 -> 1315.6 | AB25: =MAX(C25,'Global Inputs'!$B$22)*'Global Inputs'!$B$5*V25*$C$54+W25 -> 1184.04 | AC25: =D25+'Whitefield Monthly Projection'!$B$16*'Service Economics'!V15 -> 1774.2 | AD25: =T25*AC25 -> 41.583208 | AE25: =T25*H25 -> 28.820157 | AF25: =T25*C25 -> 0.093750892 | AG25: ='Service Economics'!AL15 -> 759.84714 | AH25: ='Service Economics'!AN15 -> 898.84714 | AI25: ='Service Economics'!AP15 -> 189.96178 | AJ25: ='Service Economics'!AQ15 -> 2 | AK25: ='Service Portfolio'!P15 -> RETAIN | AL25: =IF(ISNUMBER(SEARCH("Future",'Service Economics'!AH15)),-1000000000,AG25*(1-'Whitefield Monthly Projection'!$B$16)+AH25*'Whitefield Monthly Projection'!$B$16) -> 815.44714 | AM25: =IF(ISNUMBER(SEARCH("Future",'Service Economics'!AH15)),-1000000000,AI25) -> 189.96178
A26: ='Service Economics'!A16 -> Post-Surgery Follow-up | B26: ='Service Economics'!B16 -> Procedure & Treatment | C26: ='Service Economics'!C16 -> 3 | D26: ='Service Economics'!K16 -> 1096 | E26: =IF(C26=0,0,D26/C26) -> 365.33333 | F26: ='Service Economics'!R16 -> 833.95356 | G26: ='Service Economics'!AB16 -> 972.95356 | H26: ='Whitefield Monthly Projection'!$B$15*F26+'Whitefield Monthly Projection'!$B$16*G26-'Whitefield Monthly Projection'!H48 -> 889.55356 | I26: =IF(('Service Economics'!L16+'Whitefield Monthly Projection'!$B$16*'Service Economics'!U16/(1+'Global Inputs'!$B$17))=0,0,H26/('Service Economics'!L16+'Whitefield Monthly Projection'!$B$16*'Service Economics'!U16/(1+'Global Inputs'!$B$17))) -> 0.89998114 | J26: =IF(C26=0,0,H26/C26) -> 296.51785 | K26: 3 | L26: 3 | M26: 4 | N26: 1 | O26: =IF(MAX($J$15:$J$44)=0,0,J26/MAX($J$15:$J$44)*100) -> 49.912769 | P26: =(IF(MAX($J$15:$J$44)=0,0,J26/MAX($J$15:$J$44))*0.45+K26/5*0.2+(6-L26)/5*0.15+(6-M26)/5*0.1+N26/1.5*0.1)*100 -> 54.127413 | Q26: =IF(H26<=0,"REVIEW — Economics need improvement",IF(AND(J26>=AVERAGE($J$15:$J$44)*1.15,K26>=4,L26<=3),"CORE — Push aggressively",IF(J26>=AVERAGE($J$15:$J$44),"GROW — Attractive economics",IF(K26>=4,"STRATEGIC — Important but lower margin","REVIEW — Economics need improvement")))) -> GROW — Attractive economics | R26: ='Whitefield Monthly Projection'!G48 -> 0.03 | S26: =MAX(J26,0)^3*(0.5+K26/10)*(0.5+(6-L26)/10)*N26 -> 16685242 | T26: =IF(SUM($S$15:$S$44)=0,R26,0.2*R26+0.8*S26/SUM($S$15:$S$44)) -> 0.025935498 | U26: Yes | V26: ='Service Economics'!D16 -> 1 | W26: ='Service Economics'!E16 -> 0 | X26: =IF(U26="Yes",J26,0) -> 296.51785 | Y26: =R26*C26*V26 -> 0.09 | Z26: =R26*C26*'Service Economics'!F16 -> 0.09 | AA26: =MAX(C26,$C$53)*'Global Inputs'!$B$5*V26+W26 -> 897 | AB26: =MAX(C26,'Global Inputs'!$B$22)*'Global Inputs'!$B$5*V26*$C$54+W26 -> 807.3 | AC26: =D26+'Whitefield Monthly Projection'!$B$16*'Service Economics'!V16 -> 1355.6 | AD26: =T26*AC26 -> 35.158161 | AE26: =T26*H26 -> 23.071015 | AF26: =T26*C26 -> 0.077806494 | AG26: ='Service Economics'!AL16 -> 523.30267 | AH26: ='Service Economics'!AN16 -> 662.30267 | AI26: ='Service Economics'!AP16 -> 174.43422 | AJ26: ='Service Economics'!AQ16 -> 3 | AK26: ='Service Portfolio'!P16 -> RETAIN | AL26: =IF(ISNUMBER(SEARCH("Future",'Service Economics'!AH16)),-1000000000,AG26*(1-'Whitefield Monthly Projection'!$B$16)+AH26*'Whitefield Monthly Projection'!$B$16) -> 578.90267 | AM26: =IF(ISNUMBER(SEARCH("Future",'Service Economics'!AH16)),-1000000000,AI26) -> 174.43422
... A44: ='Service Economics'!A34 -> Family Medical Update Concierge | B44: ='Service Economics'!B34 -> Continuing Care | C44: ='Service Economics'!C34 -> 3 | D44: ='Service Economics'!K34 -> 782.05 | E44: =IF(C44=0,0,D44/C44) -> 260.68333 | F44: ='Service Economics'!R34 -> 578.88249 | G44: ='Service Economics'!AB34 -> 717.88249 | H44: ='Whitefield Monthly Projection'!$B$15*F44+'Whitefield Monthly Projection'!$B$16*G44-'Whitefield Monthly Projection'!H66 -> 634.48249 | I44: =IF(('Service Economics'!L34+'Whitefield Monthly Projection'!$B$16*'Service Economics'!U34/(1+'Global Inputs'!$B$17))=0,0,H44/('Service Economics'!L34+'Whitefield Monthly Projection'!$B$16*'Service Economics'!U34/(1+'Global Inputs'!$B$17))) -> 0.87835366 | J44: =IF(C44=0,0,H44/C44) -> 211.49416 | K44: 5 | L44: 1 | M44: 1 | N44: 1.2 | O44: =IF(MAX($J$15:$J$44)=0,0,J44/MAX($J$15:$J$44)*100) -> 35.600754 | P44: =(IF(MAX($J$15:$J$44)=0,0,J44/MAX($J$15:$J$44))*0.45+K44/5*0.2+(6-L44)/5*0.15+(6-M44)/5*0.1+N44/1.5*0.1)*100 -> 69.020339 | Q44: =IF(H44<=0,"REVIEW — Economics need improvement",IF(AND(J44>=AVERAGE($J$15:$J$44)*1.15,K44>=4,L44<=3),"CORE — Push aggressively",IF(J44>=AVERAGE($J$15:$J$44),"GROW — Attractive economics",IF(K44>=4,"STRATEGIC — Important but lower margin","REVIEW — Economics need improvement")))) -> STRATEGIC — Important but lower margin | R44: ='Whitefield Monthly Projection'!G66 -> 0 | S44: =MAX(J44,0)^3*(0.5+K44/10)*(0.5+(6-L44)/10)*N44 -> 11352105 | T44: =IF(SUM($S$15:$S$44)=0,R44,0.2*R44+0.8*S44/SUM($S$15:$S$44)) -> 0.013563475 | U44: Yes | V44: ='Service Economics'!D34 -> 0.65 | W44: ='Service Economics'!E34 -> 0 | X44: =IF(U44="Yes",J44,0) -> 211.49416 | Y44: =R44*C44*V44 -> 0 | Z44: =R44*C44*'Service Economics'!F34 -> 0 | AA44: =MAX(C44,$C$53)*'Global Inputs'!$B$5*V44+W44 -> 583.05 | AB44: =MAX(C44,'Global Inputs'!$B$22)*'Global Inputs'!$B$5*V44*$C$54+W44 -> 524.745 | AC44: =D44+'Whitefield Monthly Projection'!$B$16*'Service Economics'!V34 -> 1041.65 | AD44: =T44*AC44 -> 14.128394 | AE44: =T44*H44 -> 8.6057874 | AF44: =T44*C44 -> 0.040690425 | AG44: ='Service Economics'!AL34 -> 268.2316 | AH44: ='Service Economics'!AN34 -> 407.2316 | AI44: ='Service Economics'!AP34 -> 89.410533 | AJ44: ='Service Economics'!AQ34 -> 5 | AK44: ='Service Portfolio'!P34 -> OPTIMIZE | AL44: =IF(ISNUMBER(SEARCH("Future",'Service Economics'!AH34)),-1000000000,AG44*(1-'Whitefield Monthly Projection'!$B$16)+AH44*'Whitefield Monthly Projection'!$B$16) -> 323.8316 | AM44: =IF(ISNUMBER(SEARCH("Future",'Service Economics'!AH34)),-1000000000,AI44) -> 89.410533
A49: Profit Optimization Levers — One-Variable Sensitivity (All Else Equal)
A50: Lever | B50: Current Value | C50: Test Value | D50: Monthly Revenue | E50: Contribution | F50: Operating Profit | G50: Profit / Angel | H50: Break-even Journeys | I50: Δ Operating Profit
A51: Base price / hour | B51: ='Global Inputs'!$B$5 -> 299 | C51: 499 | D51: ='Whitefield Monthly Projection'!$Q$27+'Whitefield Monthly Projection'!$Q$19*(SUM($Y$15:$Y$44)*(C51-B51)) -> 118966.33 | E51: ='Whitefield Monthly Projection'!$Q$32+'Whitefield Monthly Projection'!$Q$19*((SUM($Y$15:$Y$44)*(C51-B51))/(1+'Global Inputs'!$B$7)*(1-'NC Credits'!$B$15)-(SUM($Y$15:$Y$44)*(C51-B51))*'Global Inputs'!$B$8) -> 88686.658 | F51: ='Whitefield Monthly Projection'!$Q$37+'Whitefield Monthly Projection'!$Q$19*((SUM($Y$15:$Y$44)*(C51-B51))/(1+'Global Inputs'!$B$7)*(1-'NC Credits'!$B$15)-(SUM($Y$15:$Y$44)*(C51-B51))*'Global Inputs'!$B$8) -> -49313.342 | G51: =IF('Whitefield Monthly Projection'!$B$6=0,0,F51/'Whitefield Monthly Projection'!$B$6) -> -12328.336 | H51: =IF(E51/'Whitefield Monthly Projection'!$Q$19<=0,0,'Whitefield Monthly Projection'!$B$32/(E51/'Whitefield Monthly Projection'!$Q$19)) -> 58.53823 | I51: =F51-'Whitefield Monthly Projection'!$Q$37 -> 31842.259
A52: Angel cost / hour | B52: ='Global Inputs'!$B$6 -> 0 | C52: 160 | D52: ='Whitefield Monthly Projection'!$Q$27 -> 79773.812 | E52: ='Whitefield Monthly Projection'!$Q$32-'Whitefield Monthly Projection'!$Q$19*(SUM($Z$15:$Z$44)*(C52-B52)) -> 29035.695 | F52: ='Whitefield Monthly Projection'!$Q$37-'Whitefield Monthly Projection'!$Q$19*(SUM($Z$15:$Z$44)*(C52-B52)) -> -108964.3 | G52: =IF('Whitefield Monthly Projection'!$B$6=0,0,F52/'Whitefield Monthly Projection'!$B$6) -> -27241.076 | H52: =IF(E52/'Whitefield Monthly Projection'!$Q$19<=0,0,'Whitefield Monthly Projection'!$B$32/(E52/'Whitefield Monthly Projection'!$Q$19)) -> 178.79923 | I52: =F52-'Whitefield Monthly Projection'!$Q$37 -> -27808.704
A53: Minimum booking hours | B53: ='Global Inputs'!$B$22 -> 2 | C53: 3 | D53: ='Whitefield Monthly Projection'!$Q$27+'Whitefield Monthly Projection'!$Q$19*(SUMPRODUCT($R$15:$R$44,$AA$15:$AA$44-$D$15:$D$44)) -> 73485.384 | E53: ='Whitefield Monthly Projection'!$Q$32+'Whitefield Monthly Projection'!$Q$19*((SUMPRODUCT($R$15:$R$44,$AA$15:$AA$44-$D$15:$D$44))/(1+'Global Inputs'!$B$7)*(1-'NC Credits'!$B$15)-(SUMPRODUCT($R$15:$R$44,$AA$15:$AA$44-$D$15:$D$44))*'Global Inputs'!$B$8) -> 51735.318 | F53: ='Whitefield Monthly Projection'!$Q$37+'Whitefield Monthly Projection'!$Q$19*((SUMPRODUCT($R$15:$R$44,$AA$15:$AA$44-$D$15:$D$44))/(1+'Global Inputs'!$B$7)*(1-'NC Credits'!$B$15)-(SUMPRODUCT($R$15:$R$44,$AA$15:$AA$44-$D$15:$D$44))*'Global Inputs'!$B$8) -> -86264.682 | G53: =IF('Whitefield Monthly Projection'!$B$6=0,0,F53/'Whitefield Monthly Projection'!$B$6) -> -21566.17 | H53: =IF(E53/'Whitefield Monthly Projection'!$Q$19<=0,0,'Whitefield Monthly Projection'!$B$32/(E53/'Whitefield Monthly Projection'!$Q$19)) -> 100.34847 | I53: =F53-'Whitefield Monthly Projection'!$Q$37 -> -5109.0809
A54: Portfolio multiplier factor | B54: 1 | C54: 0.9 | D54: ='Whitefield Monthly Projection'!$Q$27+'Whitefield Monthly Projection'!$Q$19*(SUMPRODUCT($R$15:$R$44,$AB$15:$AB$44-$D$15:$D$44)) -> 66428.151 | E54: ='Whitefield Monthly Projection'!$Q$32+'Whitefield Monthly Projection'!$Q$19*((SUMPRODUCT($R$15:$R$44,$AB$15:$AB$44-$D$15:$D$44))/(1+'Global Inputs'!$B$7)*(1-'NC Credits'!$B$15)-(SUMPRODUCT($R$15:$R$44,$AB$15:$AB$44-$D$15:$D$44))*'Global Inputs'!$B$8) -> 46001.615 | F54: ='Whitefield Monthly Projection'!$Q$37+'Whitefield Monthly Projection'!$Q$19*((SUMPRODUCT($R$15:$R$44,$AB$15:$AB$44-$D$15:$D$44))/(1+'Global Inputs'!$B$7)*(1-'NC Credits'!$B$15)-(SUMPRODUCT($R$15:$R$44,$AB$15:$AB$44-$D$15:$D$44))*'Global Inputs'!$B$8) -> -91998.385 | G54: =IF('Whitefield Monthly Projection'!$B$6=0,0,F54/'Whitefield Monthly Projection'!$B$6) -> -22999.596 | H54: =IF(E54/'Whitefield Monthly Projection'!$Q$19<=0,0,'Whitefield Monthly Projection'!$B$32/(E54/'Whitefield Monthly Projection'!$Q$19)) -> 112.85604 | I54: =F54-'Whitefield Monthly Projection'!$Q$37 -> -10842.784
A55: Transport coordination fee | B55: ='Global Inputs'!$B$16 -> 149 | C55: 199 | D55: ='Whitefield Monthly Projection'!$Q$27+'Whitefield Monthly Projection'!$Q$19*'Whitefield Monthly Projection'!$B$16*(C55-B55) -> 80526.212 | E55: ='Whitefield Monthly Projection'!$Q$32+'Whitefield Monthly Projection'!$Q$19*('Whitefield Monthly Projection'!$B$16*((C55-B55)/(1+'Global Inputs'!$B$17)-(C55-B55)*'Global Inputs'!$B$8)) -> 57596.799 | F55: ='Whitefield Monthly Projection'!$Q$37+'Whitefield Monthly Projection'!$Q$19*('Whitefield Monthly Projection'!$B$16*((C55-B55)/(1+'Global Inputs'!$B$17)-(C55-B55)*'Global Inputs'!$B$8)) -> -80403.201 | G55: =IF('Whitefield Monthly Projection'!$B$6=0,0,F55/'Whitefield Monthly Projection'!$B$6) -> -20100.8 | H55: =IF(E55/'Whitefield Monthly Projection'!$Q$19<=0,0,'Whitefield Monthly Projection'!$B$32/(E55/'Whitefield Monthly Projection'!$Q$19)) -> 90.136259 | I55: =F55-'Whitefield Monthly Projection'!$Q$37 -> 752.4
A56: Cab cost | B56: ='Global Inputs'!$B$15 -> 500 | C56: 450 | D56: ='Whitefield Monthly Projection'!$Q$27+'Whitefield Monthly Projection'!$Q$19*'Whitefield Monthly Projection'!$B$16*(C56-B56) -> 79021.412 | E56: ='Whitefield Monthly Projection'!$Q$32+'Whitefield Monthly Projection'!$Q$19*(-'Whitefield Monthly Projection'!$B$16*(C56-B56)*'Global Inputs'!$B$8) -> 56844.399 | F56: ='Whitefield Monthly Projection'!$Q$37+'Whitefield Monthly Projection'!$Q$19*(-'Whitefield Monthly Projection'!$B$16*(C56-B56)*'Global Inputs'!$B$8) -> -81155.601 | G56: =IF('Whitefield Monthly Projection'!$B$6=0,0,F56/'Whitefield Monthly Projection'!$B$6) -> -20288.9 | H56: =IF(E56/'Whitefield Monthly Projection'!$Q$19<=0,0,'Whitefield Monthly Projection'!$B$32/(E56/'Whitefield Monthly Projection'!$Q$19)) -> 91.329314 | I56: =F56-'Whitefield Monthly Projection'!$Q$37 -> 0
A57: Payment platform fee | B57: ='Global Inputs'!$B$8 -> 0 | C57: 0.015 | D57: ='Whitefield Monthly Projection'!$Q$27 -> 79773.812 | E57: ='Whitefield Monthly Projection'!$Q$32-('Whitefield Monthly Projection'!$Q$27*(C57-B57)) -> 55647.792 | F57: ='Whitefield Monthly Projection'!$Q$37-('Whitefield Monthly Projection'!$Q$27*(C57-B57)) -> -82352.208 | G57: =IF('Whitefield Monthly Projection'!$B$6=0,0,F57/'Whitefield Monthly Projection'!$B$6) -> -20588.052 | H57: =IF(E57/'Whitefield Monthly Projection'!$Q$19<=0,0,'Whitefield Monthly Projection'!$B$32/(E57/'Whitefield Monthly Projection'!$Q$19)) -> 93.293189 | I57: =F57-'Whitefield Monthly Projection'!$Q$37 -> -1196.6072
A58: Angel utilization | B58: ='Whitefield Monthly Projection'!$B$9 -> 1 | C58: 0.75 | D58: =MIN('Whitefield Monthly Projection'!$Q$10,'Whitefield Monthly Projection'!$B$6*'Whitefield Monthly Projection'!$B$7*'Whitefield Monthly Projection'!$B$8*C58/'Whitefield Monthly Projection'!$S$45,'Whitefield Monthly Projection'!$B$6*'Whitefield Monthly Projection'!$B$10*'Whitefield Monthly Projection'!$B$7)*'Whitefield Monthly Projection'!$S$52 -> 79773.812 | E58: =MIN('Whitefield Monthly Projection'!$Q$10,'Whitefield Monthly Projection'!$B$6*'Whitefield Monthly Projection'!$B$7*'Whitefield Monthly Projection'!$B$8*C58/'Whitefield Monthly Projection'!$S$45,'Whitefield Monthly Projection'!$B$6*'Whitefield Monthly Projection'!$B$10*'Whitefield Monthly Projection'!$B$7)*'Whitefield Monthly Projection'!$S$51 -> 56844.399 | F58: =E58-'Whitefield Monthly Projection'!$B$32 -> -81155.601 | G58: =IF('Whitefield Monthly Projection'!$B$6=0,0,F58/'Whitefield Monthly Projection'!$B$6) -> -20288.9 | H58: =IF(E58/'Whitefield Monthly Projection'!$Q$19<=0,0,'Whitefield Monthly Projection'!$B$32/(E58/'Whitefield Monthly Projection'!$Q$19)) -> 91.329314 | I58: =F58-'Whitefield Monthly Projection'!$Q$37 -> 0
A59: Service mix | B59: Current Mix | C59: Optimized Mix | D59: =MIN('Whitefield Monthly Projection'!$Q$10,'Whitefield Monthly Projection'!$B$6*'Whitefield Monthly Projection'!$B$7*'Whitefield Monthly Projection'!$B$8*'Whitefield Monthly Projection'!$B$9/SUM($AF$15:$AF$44),'Whitefield Monthly Projection'!$B$6*'Whitefield Monthly Projection'!$B$10*'Whitefield Monthly Projection'!$B$7)*SUM($AD$15:$AD$44) -> 162653.82 | E59: =MIN('Whitefield Monthly Projection'!$Q$10,'Whitefield Monthly Projection'!$B$6*'Whitefield Monthly Projection'!$B$7*'Whitefield Monthly Projection'!$B$8*'Whitefield Monthly Projection'!$B$9/SUM($AF$15:$AF$44),'Whitefield Monthly Projection'!$B$6*'Whitefield Monthly Projection'!$B$10*'Whitefield Monthly Projection'!$B$7)*SUM($AE$15:$AE$44) -> 124180.9 | F59: =E59-'Whitefield Monthly Projection'!$B$32 -> -13819.102 | G59: =IF('Whitefield Monthly Projection'!$B$6=0,0,F59/'Whitefield Monthly Projection'!$B$6) -> -3454.7756 | H59: =IF(E59/'Whitefield Monthly Projection'!$Q$19<=0,0,'Whitefield Monthly Projection'!$B$32/(E59/'Whitefield Monthly Projection'!$Q$19)) -> 41.80643 | I59: =F59-'Whitefield Monthly Projection'!$Q$37 -> 67336.499
A60: Repeat booking rate | B60: ='Whitefield Monthly Projection'!$B$17 -> 0.2 | C60: 0.4 | D60: ='Whitefield Monthly Projection'!$Q$27 -> 79773.812 | E60: ='Whitefield Monthly Projection'!$Q$32+('Whitefield Monthly Projection'!$Q$19*(C60-B60)*'Global Inputs'!$B$20) -> 59094.075 | F60: ='Whitefield Monthly Projection'!$Q$37+('Whitefield Monthly Projection'!$Q$19*(C60-B60)*'Global Inputs'!$B$20) -> -78905.925 | G60: =IF('Whitefield Monthly Projection'!$B$6=0,0,F60/'Whitefield Monthly Projection'!$B$6) -> -19726.481 | H60: =IF(E60/'Whitefield Monthly Projection'!$Q$19<=0,0,'Whitefield Monthly Projection'!$B$32/(E60/'Whitefield Monthly Projection'!$Q$19)) -> 87.852462 | I60: =F60-'Whitefield Monthly Projection'!$Q$37 -> 2249.676
A61: Cancellation rate | B61: ='Whitefield Monthly Projection'!$B$13 -> 0.12 | C61: 0.05 | D61: =MIN(('Whitefield Monthly Projection'!$Q$7*(1-C61)*(1-'Whitefield Monthly Projection'!$B$14)),'Whitefield Monthly Projection'!$B$6*'Whitefield Monthly Projection'!$B$7*'Whitefield Monthly Projection'!$B$8*'Whitefield Monthly Projection'!$B$9/'Whitefield Monthly Projection'!$S$45,'Whitefield Monthly Projection'!$B$6*'Whitefield Monthly Projection'!$B$10*'Whitefield Monthly Projection'!$B$7)*'Whitefield Monthly Projection'!$S$52 -> 86119.456 | E61: =MIN(('Whitefield Monthly Projection'!$Q$7*(1-C61)*(1-'Whitefield Monthly Projection'!$B$14)),'Whitefield Monthly Projection'!$B$6*'Whitefield Monthly Projection'!$B$7*'Whitefield Monthly Projection'!$B$8*'Whitefield Monthly Projection'!$B$9/'Whitefield Monthly Projection'!$S$45,'Whitefield Monthly Projection'!$B$6*'Whitefield Monthly Projection'!$B$10*'Whitefield Monthly Projection'!$B$7)*'Whitefield Monthly Projection'!$S$51 -> 61366.113 | F61: =E61-'Whitefield Monthly Projection'!$B$32 -> -76633.887 | G61: =IF('Whitefield Monthly Projection'!$B$6=0,0,F61/'Whitefield Monthly Projection'!$B$6) -> -19158.472 | H61: =IF(E61/'Whitefield Monthly Projection'!$Q$19<=0,0,'Whitefield Monthly Projection'!$B$32/(E61/'Whitefield Monthly Projection'!$Q$19)) -> 84.599786 | I61: =F61-'Whitefield Monthly Projection'!$Q$37 -> 4521.7136
A62: Customer leads / day | B62: ='Whitefield Monthly Projection'!$B$11 -> 6 | C62: 20 | D62: =MIN((C62*'Whitefield Monthly Projection'!$B$7*'Whitefield Monthly Projection'!$B$12*(1-'Whitefield Monthly Projection'!$B$13)*(1-'Whitefield Monthly Projection'!$B$14)),'Whitefield Monthly Projection'!$B$6*'Whitefield Monthly Projection'!$B$7*'Whitefield Monthly Projection'!$B$8*'Whitefield Monthly Projection'!$B$9/'Whitefield Monthly Projection'!$S$45,'Whitefield Monthly Projection'!$B$6*'Whitefield Monthly Projection'!$B$10*'Whitefield Monthly Projection'!$B$7)*'Whitefield Monthly Projection'!$S$52 -> 265912.71 | E62: =MIN((C62*'Whitefield Monthly Projection'!$B$7*'Whitefield Monthly Projection'!$B$12*(1-'Whitefield Monthly Projection'!$B$13)*(1-'Whitefield Monthly Projection'!$B$14)),'Whitefield Monthly Projection'!$B$6*'Whitefield Monthly Projection'!$B$7*'Whitefield Monthly Projection'!$B$8*'Whitefield Monthly Projection'!$B$9/'Whitefield Monthly Projection'!$S$45,'Whitefield Monthly Projection'!$B$6*'Whitefield Monthly Projection'!$B$10*'Whitefield Monthly Projection'!$B$7)*'Whitefield Monthly Projection'!$S$51 -> 189481.33 | F62: =E62-'Whitefield Monthly Projection'!$B$32 -> 51481.331 | G62: =F62/'Whitefield Monthly Projection'!$B$6 -> 12870.333 | H62: ='Whitefield Monthly Projection'!$B$32/'Whitefield Monthly Projection'!$S$51 -> 91.329314 | I62: =F62-'Whitefield Monthly Projection'!$Q$37 -> 132636.93
A63: Fixed monthly cost | B63: ='Whitefield Monthly Projection'!$B$32 -> 138000 | C63: 150000 | D63: ='Whitefield Monthly Projection'!$Q$27 -> 79773.812 | E63: ='Whitefield Monthly Projection'!$Q$32 -> 56844.399 | F63: =E63-C63 -> -93155.601 | G63: =F63/'Whitefield Monthly Projection'!$B$6 -> -23288.9 | H63: =C63/'Whitefield Monthly Projection'!$S$51 -> 99.270994 | I63: =F63-'Whitefield Monthly Projection'!$Q$37 -> -12000
A67: Whitefield Portfolio — Current Mix vs Profit-Optimized Mix
A68: Metric | B68: Current / Default Mix | C68: Profit-Optimized Mix | D68: Improvement
A69: Weighted avg service hours | B69: =SUMPRODUCT($R$15:$R$44,$C$15:$C$44) -> 4.62 | C69: =SUM($AF$15:$AF$44) -> 7.0468398 | D69: =C69-B69 -> 2.4268398
A70: Monthly journeys | B70: ='Whitefield Monthly Projection'!$Q$19 -> 37.62 | C70: =MIN('Whitefield Monthly Projection'!$Q$10,'Whitefield Monthly Projection'!$B$6*'Whitefield Monthly Projection'!$B$7*'Whitefield Monthly Projection'!$B$8*'Whitefield Monthly Projection'!$B$9/SUM($AF$15:$AF$44),'Whitefield Monthly Projection'!$B$6*'Whitefield Monthly Projection'!$B$10*'Whitefield Monthly Projection'!$B$7) -> 37.62 | D70: =C70-B70 -> 0
A71: Customer collections | B71: ='Whitefield Monthly Projection'!$Q$27 -> 79773.812 | C71: =MIN('Whitefield Monthly Projection'!$Q$10,'Whitefield Monthly Projection'!$B$6*'Whitefield Monthly Projection'!$B$7*'Whitefield Monthly Projection'!$B$8*'Whitefield Monthly Projection'!$B$9/SUM($AF$15:$AF$44),'Whitefield Monthly Projection'!$B$6*'Whitefield Monthly Projection'!$B$10*'Whitefield Monthly Projection'!$B$7)*SUM($AD$15:$AD$44) -> 162653.82 | D71: =C71-B71 -> 82880.013
A72: Monthly contribution | B72: ='Whitefield Monthly Projection'!$Q$32 -> 56844.399 | C72: =MIN('Whitefield Monthly Projection'!$Q$10,'Whitefield Monthly Projection'!$B$6*'Whitefield Monthly Projection'!$B$7*'Whitefield Monthly Projection'!$B$8*'Whitefield Monthly Projection'!$B$9/SUM($AF$15:$AF$44),'Whitefield Monthly Projection'!$B$6*'Whitefield Monthly Projection'!$B$10*'Whitefield Monthly Projection'!$B$7)*SUM($AE$15:$AE$44) -> 124180.9 | D72: =C72-B72 -> 67336.499
A73: Contribution / Angel hour | B73: ='Whitefield Monthly Projection'!$Q$35 -> 327.05961 | C73: =IF(C70*C69=0,0,C72/(C70*C69)) -> 468.42666 | D73: =C73-B73 -> 141.36705
A74: Monthly operating profit | B74: ='Whitefield Monthly Projection'!$Q$37 -> -81155.601 | C74: =C72-'Whitefield Monthly Projection'!$B$32 -> -13819.102 | D74: =C74-B74 -> 67336.499
A76: Profit Maximizer note: the optimized mix is intentionally weighted heavily toward contribution per Angel hour, while retaining 20% of the current portfolio mix so the model does not collapse into a single service. Founder judgement inputs remain editable.

Sheet Path to Profitability
A1: NivrāaCare — Path to Profitability | Whitefield CFO Model
A2: Purpose: show the path from validation → fully loaded break-even → operating profit using base hourly pricing, service multipliers, NivrāaCredits and payroll Angel economics.
A4: Target Monthly Operating Profit | B4: 0 | D4: Profitability Status | E4: =IF('Whitefield Monthly Projection'!$Q$34<=0,"RED — Negative unit economics",IF('Whitefield Monthly Projection'!$Q$37>=0,"GREEN — Operating profit positive","AMBER — Unit economics positive; volume / overhead gap")) -> AMBER — Unit economics positive; volume / overhead gap | G4: Recommended Operating Model | H4: =IF('Whitefield Monthly Projection'!$Q$19<=$H$8,"Ultra-Lean Pilot",IF('Whitefield Monthly Projection'!$Q$19<=$I$8,"Lean MVP","Full Team")) -> Ultra-Lean Pilot
A6: 1. Current Business Position — Whitefield Base Case | G6: 2. Lean MVP vs Full Team — Profitability Engine
A7: Metric | B7: Current | D7: Profit Target Math | E7: Value | G7: Editable Thresholds | H7: Ultra-Lean max | I7: Lean MVP max | J7: Source / Note | L7: Auto-Recommendation | M7: Value
A8: Completed journeys / month | B8: ='Whitefield Monthly Projection'!$Q$19 -> 37.62 | D8: Current profitability gap | E8: =MAX('Whitefield Monthly Projection'!$Q$36-'Whitefield Monthly Projection'!$Q$32,0) -> 81155.601 | G8: Monthly journey thresholds | H8: 50 | I8: 150 | J8: Founder planning assumptions; editable | L8: Current monthly journeys | M8: ='Whitefield Monthly Projection'!$Q$19 -> 37.62
A9: Journeys / day | B9: ='Whitefield Monthly Projection'!$Q$19/'Whitefield Monthly Projection'!$B$7 -> 1.254 | D9: Required monthly contribution | E9: ='Whitefield Monthly Projection'!$Q$36+$B$4 -> 138000 | L9: Recommended operating model | M9: =$H$4 -> Ultra-Lean Pilot
A10: Active Angels | B10: ='Whitefield Monthly Projection'!$B$6 -> 4 | D10: Additional contribution required | E10: =MAX(E9-'Whitefield Monthly Projection'!$Q$32,0) -> 81155.601 | G10: Monthly Fixed Cost Component | H10: Ultra-Lean Pilot | I10: Lean MVP | J10: Full Team | K10: Note | L10: Current fixed costs | M10: ='Whitefield Monthly Projection'!$Q$36 -> 138000
A11: Angel utilization | B11: ='Whitefield Monthly Projection'!$Q$21 -> 0.18104625 | D11: Current contribution / journey | E11: ='Whitefield Monthly Projection'!$Q$34 -> 1511.0154 | G11: Ops / Care Operations | H11: 20000 | I11: 45000 | J11: 60000 | K11: Founder-led → coordinator → full ops | L11: Recommended fixed-cost ceiling | M11: =IF($H$4="Ultra-Lean Pilot",$H$20,IF($H$4="Lean MVP",$I$20,$J$20)) -> 110000
A12: Customer collections | B12: ='Whitefield Monthly Projection'!$Q$27 -> 79773.812 | D12: Required journeys / month at current unit economics | E12: =IF(E11<=0,0,E9/E11) -> 91.329314 | G12: Customer Support | H12: 0 | I12: 15000 | J12: 35000 | K12: Shared / part-time initially | L12: Potential monthly saving | M12: =MAX(M10-M11,0) -> 28000
A13: Net operating revenue | B13: ='Whitefield Monthly Projection'!$Q$30 -> 69094.677 | D13: Required journeys / day | E13: =IF('Whitefield Monthly Projection'!$B$7=0,0,E12/'Whitefield Monthly Projection'!$B$7) -> 3.0443105 | G13: Technology / Cloud / Tools | H13: 8000 | I13: 12000 | J13: 20000 | K13: Lean SaaS stack | L13: Profit after restructuring | M13: ='Whitefield Monthly Projection'!$Q$32-M11 -> -53155.601
A14: Contribution / journey | B14: ='Whitefield Monthly Projection'!$Q$34 -> 1511.0154 | D14: Current journeys / day | E14: =B9 -> 1.254 | G14: Marketing | H14: 25000 | I14: 40000 | J14: 75000 | K14: Whitefield-focused acquisition | L14: Sustainable fixed cost at break-even | M14: ='Whitefield Monthly Projection'!$Q$32 -> 56844.399
A15: Contribution / Angel hour | B15: ='Whitefield Monthly Projection'!$Q$35 -> 327.05961 | D15: Journey gap / day | E15: =MAX(E13-E14,0) -> 1.7903105 | G15: Office / Admin | H15: 0 | I15: 5000 | J15: 15000 | K15: No office in pilot | L15: Sustainable fixed cost at selected target | M15: ='Whitefield Monthly Projection'!$Q$32-$B$4 -> 56844.399
A16: Monthly contribution | B16: ='Whitefield Monthly Projection'!$Q$32 -> 56844.399 | G16: Legal / CA / Compliance | H16: 5000 | I16: 8000 | J16: 10000 | K16: Required compliance only | L16: Required fixed-cost reduction for target | M16: =MAX(M10-M14,0) -> 81155.601
A17: Fixed monthly cost | B17: ='Whitefield Monthly Projection'!$Q$36 -> 138000 | G17: Fixed Insurance | H17: 5000 | I17: 7000 | J17: 10000 | K17: Illustrative planning allocation
A18: Monthly operating profit | B18: ='Whitefield Monthly Projection'!$Q$37 -> -81155.601 | G18: Founders / Core Team Salary | H18: 0 | I18: 0 | J18: 0 | K18: Editable; initially zero | L18: =IF(M13>=M10,"GREEN — Current contribution covers the operating structure.",IF(M13>=M10*0.75,"AMBER — Close to fixed-cost coverage; avoid premature hiring.","RED — Fixed costs are materially ahead of Whitefield journey density. Do not add permanent payroll yet.")) -> RED — Fixed costs are materially ahead of Whitefield journey density. Do not add permanent payroll yet.
A19: Current monthly loss | B19: =MAX(-B18,0) -> 81155.601 | G19: Miscellaneous | H19: 5000 | I19: 8000 | J19: 15000 | K19: Contingency
A20: Break-even journeys / month | B20: ='Whitefield Monthly Projection'!$Q$39 -> 91.329314 | G20: TOTAL FIXED COST | H20: =SUM(H11:H19)+'Global Inputs'!$B$30 -> 110000 | I20: =SUM(I11:I19)+'Global Inputs'!$B$30 -> 182000 | J20: =SUM(J11:J19)+'Global Inputs'!$B$30 -> 282000 | K20: Includes ₹240k full-team overhead + payroll Angel salaries from Global Inputs
A21: Break-even journeys / day | B21: ='Whitefield Monthly Projection'!$Q$40 -> 3.0443105
G23: Operating Model Comparison
A24: 3. CFO Action Plan — What Must Change First | G24: Metric | H24: Ultra-Lean Pilot | I24: Lean MVP | J24: Full Team
A25: Priority | B25: Dynamic Action | C25: Current | D25: Target / Recommendation | E25: Why | G25: Fixed monthly cost | H25: =$H20 -> 110000 | I25: =$I20 -> 182000 | J25: =$J20 -> 282000
A26: 1 | B26: Keep fixed costs aligned to current demand | C26: ='Whitefield Monthly Projection'!$Q$36 -> 138000 | D26: =M11 -> 110000 | E26: At ~current journey density, the full-team cost base absorbs too much contribution. | G26: Contribution / journey | H26: ='Whitefield Monthly Projection'!$Q$34 -> 1511.0154 | I26: ='Whitefield Monthly Projection'!$Q$34 -> 1511.0154 | J26: ='Whitefield Monthly Projection'!$Q$34 -> 1511.0154
A27: 2 | B27: Increase completed journeys / day | C27: =B9 -> 1.254 | D27: =E13 -> 3.0443105 | E27: Fixed costs need more contribution volume unless the cost base is reduced. | G27: Break-even journeys / month | H27: =IF(H26<=0,0,H25/H26) -> 72.798729 | I27: =IF(I26<=0,0,I25/I26) -> 120.44881 | J27: =IF(J26<=0,0,J25/J26) -> 186.62947
A28: 3 | B28: Increase blended contribution / journey | C28: ='Whitefield Monthly Projection'!$Q$34 -> 1511.0154 | D28: =MAX('Whitefield Monthly Projection'!$Q$34,'Profit Maximizer'!$C$72/'Profit Maximizer'!$C$70) -> 3300.9276 | E28: Higher contribution per Angel hour reduces the journey volume needed to break even. | G28: Break-even journeys / day | H28: =IF('Whitefield Monthly Projection'!$B$7=0,0,H27/'Whitefield Monthly Projection'!$B$7) -> 2.4266243 | I28: =IF('Whitefield Monthly Projection'!$B$7=0,0,I27/'Whitefield Monthly Projection'!$B$7) -> 4.0149602 | J28: =IF('Whitefield Monthly Projection'!$B$7=0,0,J27/'Whitefield Monthly Projection'!$B$7) -> 6.2209823
A29: 4 | B29: Increase repeat / recurring journey share | C29: ='Whitefield Monthly Projection'!$B$17 -> 0.2 | D29: 0.45 | E29: Recurring medical journeys reduce dependence on one-time acquisition. | G29: Break-even customer collections | H29: =H27*'Whitefield Monthly Projection'!$S$52 -> 154370.87 | I29: =I27*'Whitefield Monthly Projection'!$S$52 -> 255413.62 | J29: =J27*'Whitefield Monthly Projection'!$S$52 -> 395750.77
A30: 5 | B30: Hold MVP-1 pricing stable until actual cohort data exists | C30: ='Whitefield Monthly Projection'!$Q$21 -> 0.18104625 | D30: Review after 50–100 completed journeys | E30: Avoid changing price based only on modeled sensitivity; conversion and repeat behavior must validate the move. | G30: Angels required at break-even | H30: =IF('Whitefield Monthly Projection'!$B$7*'Whitefield Monthly Projection'!$B$8*'Whitefield Monthly Projection'!$B$9=0,0,H27*'Whitefield Monthly Projection'!$S$45/('Whitefield Monthly Projection'!$B$7*'Whitefield Monthly Projection'!$B$8*'Whitefield Monthly Projection'!$B$9)) -> 1.4013755 | I30: =IF('Whitefield Monthly Projection'!$B$7*'Whitefield Monthly Projection'!$B$8*'Whitefield Monthly Projection'!$B$9=0,0,I27*'Whitefield Monthly Projection'!$S$45/('Whitefield Monthly Projection'!$B$7*'Whitefield Monthly Projection'!$B$8*'Whitefield Monthly Projection'!$B$9)) -> 2.3186395 | J30: =IF('Whitefield Monthly Projection'!$B$7*'Whitefield Monthly Projection'!$B$8*'Whitefield Monthly Projection'!$B$9=0,0,J27*'Whitefield Monthly Projection'!$S$45/('Whitefield Monthly Projection'!$B$7*'Whitefield Monthly Projection'!$B$8*'Whitefield Monthly Projection'!$B$9)) -> 3.5926173
A31: 6 | B31: Raise price carefully where value is strongest | C31: ='Global Inputs'!$B$5 -> 299 | D31: 499 | E31: A moderate rate increase can improve contribution without requiring a full demand reset. | G31: Monthly profit at 3 journeys/day | H31: =3*'Whitefield Monthly Projection'!$B$7*'Whitefield Monthly Projection'!$Q$34-H$25 -> 25991.386 | I31: =3*'Whitefield Monthly Projection'!$B$7*'Whitefield Monthly Projection'!$Q$34-I$25 -> -46008.614 | J31: =3*'Whitefield Monthly Projection'!$B$7*'Whitefield Monthly Projection'!$Q$34-J$25 -> -146008.61
A32: 7 | B32: Keep transport asset-light | C32: ='Whitefield Monthly Projection'!$B$16 -> 0.4 | D32: 0.6 | E32: Use third-party transport coordination; do not carry vehicle depreciation in MVP. | G32: Monthly profit at 5 journeys/day | H32: =5*'Whitefield Monthly Projection'!$B$7*'Whitefield Monthly Projection'!$Q$34-H$25 -> 116652.31 | I32: =5*'Whitefield Monthly Projection'!$B$7*'Whitefield Monthly Projection'!$Q$34-I$25 -> 44652.31 | J32: =5*'Whitefield Monthly Projection'!$B$7*'Whitefield Monthly Projection'!$Q$34-J$25 -> -55347.69
G33: Monthly profit at 8 journeys/day | H33: =8*'Whitefield Monthly Projection'!$B$7*'Whitefield Monthly Projection'!$Q$34-H$25 -> 252643.7 | I33: =8*'Whitefield Monthly Projection'!$B$7*'Whitefield Monthly Projection'!$Q$34-I$25 -> 180643.7 | J33: =8*'Whitefield Monthly Projection'!$B$7*'Whitefield Monthly Projection'!$Q$34-J$25 -> 80643.695
G34: Monthly profit at 10 journeys/day | H34: =10*'Whitefield Monthly Projection'!$B$7*'Whitefield Monthly Projection'!$Q$34-H$25 -> 343304.62 | I34: =10*'Whitefield Monthly Projection'!$B$7*'Whitefield Monthly Projection'!$Q$34-I$25 -> 271304.62 | J34: =10*'Whitefield Monthly Projection'!$B$7*'Whitefield Monthly Projection'!$Q$34-J$25 -> 171304.62
A35: 4. Profit Bridge — Major Levers | G35: Monthly profit at 15 journeys/day | H35: =15*'Whitefield Monthly Projection'!$B$7*'Whitefield Monthly Projection'!$Q$34-H$25 -> 569956.93 | I35: =15*'Whitefield Monthly Projection'!$B$7*'Whitefield Monthly Projection'!$Q$34-I$25 -> 497956.93 | J35: =15*'Whitefield Monthly Projection'!$B$7*'Whitefield Monthly Projection'!$Q$34-J$25 -> 397956.93
A36: Lever | B36: ='MVP1 Pricing & SKU'!$B$7 -> 299 | C36: 349 | D36: Incremental Monthly Profit | E36: New Monthly Operating Profit | F36: Difficulty | G36: Test only after real conversion data; this is a sensitivity, not an MVP launch recommendation.
A37: ='Profit Maximizer'!A51 -> Base price / hour | B37: ='Profit Maximizer'!B51 -> 299 | C37: ='Profit Maximizer'!C51 -> 499 | D37: ='Profit Maximizer'!I51 -> 31842.259 | E37: ='Profit Maximizer'!F51 -> -49313.342 | F37: Medium | G37: Test ₹499/hour on new customers / premium services.
A38: ='Profit Maximizer'!A52 -> Angel cost / hour | B38: ='Profit Maximizer'!B52 -> 0 | C38: ='Profit Maximizer'!C52 -> 160 | D38: ='Profit Maximizer'!I52 -> -27808.704 | E38: ='Profit Maximizer'!F52 -> -108964.3 | F38: Medium | G38: Negotiate gig payout bands without compromising Angel quality.
A39: Portfolio multiplier factor sensitivity | B39: 1 | C39: 0.9 | D39: ='Profit Maximizer'!I54 -> -10842.784 | E39: ='Profit Maximizer'!F54 -> -91998.385 | F39: Medium | G39: Test after 50–100 journeys; do not add extra pricing tiers in MVP-1.
A40: ='Profit Maximizer'!A54 -> Portfolio multiplier factor | B40: ='Profit Maximizer'!B54 -> 1 | C40: ='Profit Maximizer'!C54 -> 0.9 | D40: ='Profit Maximizer'!I54 -> -10842.784 | E40: ='Profit Maximizer'!F54 -> -91998.385 | F40: Low | G40: Charge long hospital waits appropriately.
A41: ='Profit Maximizer'!A55 -> Transport coordination fee | B41: ='Profit Maximizer'!B55 -> 149 | C41: ='Profit Maximizer'!C55 -> 199 | D41: ='Profit Maximizer'!I55 -> 752.4 | E41: ='Profit Maximizer'!F55 -> -80403.201 | F41: Low | G41: Keep transport coordination fee transparent.
A42: ='Profit Maximizer'!A56 -> Cab cost | B42: ='Profit Maximizer'!B56 -> 500 | C42: ='Profit Maximizer'!C56 -> 450 | D42: ='Profit Maximizer'!I56 -> 0 | E42: ='Profit Maximizer'!F56 -> -81155.601 | F42: Medium | G42: Negotiate preferred cab / mobility rates; avoid owning vehicles.
A43: ='Profit Maximizer'!A57 -> Payment platform fee | B43: ='Profit Maximizer'!B57 -> 0 | C43: ='Profit Maximizer'!C57 -> 0.015 | D43: ='Profit Maximizer'!I57 -> -1196.6072 | E43: ='Profit Maximizer'!F57 -> -82352.208 | F43: Low | G43: Reduce payment leakage with better gateway pricing / payment mix.
A44: ='Profit Maximizer'!A58 -> Angel utilization | B44: ='Profit Maximizer'!B58 -> 1 | C44: ='Profit Maximizer'!C58 -> 0.75 | D44: ='Profit Maximizer'!I58 -> 0 | E44: ='Profit Maximizer'!F58 -> -81155.601 | F44: Medium | G44: Do not add Angels until demand fills available hours.
A45: ='Profit Maximizer'!A59 -> Service mix | B45: ='Profit Maximizer'!B59 -> Current Mix | C45: ='Profit Maximizer'!C59 -> Optimized Mix | D45: ='Profit Maximizer'!I59 -> 67336.499 | E45: ='Profit Maximizer'!F59 -> -13819.102 | F45: Medium | G45: Push services with higher contribution per Angel hour.
A46: ='Profit Maximizer'!A60 -> Repeat booking rate | B46: ='Profit Maximizer'!B60 -> 0.2 | C46: ='Profit Maximizer'!C60 -> 0.4 | D46: ='Profit Maximizer'!I60 -> 2249.676 | E46: ='Profit Maximizer'!F60 -> -78905.925 | F46: Medium | G46: Build subscription / recurring-parent journey behavior.
A47: ='Profit Maximizer'!A61 -> Cancellation rate | B47: ='Profit Maximizer'!B61 -> 0.12 | C47: ='Profit Maximizer'!C61 -> 0.05 | D47: ='Profit Maximizer'!I61 -> 4521.7136 | E47: ='Profit Maximizer'!F61 -> -76633.887 | F47: Low | G47: Reduce avoidable cancellations with reminders and confirmation.
A48: ='Profit Maximizer'!A62 -> Customer leads / day | B48: ='Profit Maximizer'!B62 -> 6 | C48: ='Profit Maximizer'!C62 -> 20 | D48: ='Profit Maximizer'!I62 -> 132636.93 | E48: ='Profit Maximizer'!F62 -> 51481.331 | F48: Medium | G48: Concentrate GTM inside Whitefield to increase journey density.
A49: ='Profit Maximizer'!A63 -> Fixed monthly cost | B49: ='Profit Maximizer'!B63 -> 138000 | C49: ='Profit Maximizer'!C63 -> 150000 | D49: ='Profit Maximizer'!I63 -> -12000 | E49: ='Profit Maximizer'!F63 -> -93155.601 | F49: High | G49: Keep MVP cost base lean until journey density proves itself.
A50: Urgent request premium | B50: 0 | C50: 300 | D50: ='Whitefield Monthly Projection'!$Q$19*SUMIF('Whitefield Monthly Projection'!$A$37:$A$66,"24×7 Urgent Care Coordination",'Whitefield Monthly Projection'!$G$37:$G$66)*($C50/(1+'Global Inputs'!$B$7)-$C50*'Global Inputs'!$B$8) -> 47.822034 | E50: ='Whitefield Monthly Projection'!$Q$37+D50 -> -81107.779 | F50: Low | G50: Use a transparent urgent coordination premium.
A51: Overnight premium | B51: 0 | C51: 500 | D51: ='Whitefield Monthly Projection'!$Q$19*SUMIF('Whitefield Monthly Projection'!$A$37:$A$66,"Overnight Hospital Concierge",'Whitefield Monthly Projection'!$G$37:$G$66)*($C51/(1+'Global Inputs'!$B$7)-$C51*'Global Inputs'!$B$8) -> 478.22034 | E51: ='Whitefield Monthly Projection'!$Q$37+D51 -> -80677.38 | F51: Low | G51: Price overnight inconvenience and late-hour staffing separately.
A52: NRI Parent premium | B52: 0 | C52: 300 | D52: ='Whitefield Monthly Projection'!$Q$19*SUMIF('Whitefield Monthly Projection'!$A$37:$A$66,"NRI Parent Medical Concierge",'Whitefield Monthly Projection'!$G$37:$G$66)*($C52/(1+'Global Inputs'!$B$7)-$C52*'Global Inputs'!$B$8) -> 239.11017 | E52: ='Whitefield Monthly Projection'!$Q$37+D52 -> -80916.491 | F52: Low | G52: Charge for higher-touch family communication and coordination.
A53: Weekend / holiday premium | B53: 0 | C53: 0.1 | D53: ='Whitefield Monthly Projection'!$Q$19*25%*'Whitefield Monthly Projection'!$S$46*$C53*(1/(1+'Global Inputs'!$B$7)-'Global Inputs'!$B$8) -> 1483.2131 | E53: ='Whitefield Monthly Projection'!$Q$37+D53 -> -79672.388 | F53: Medium | G53: Apply only during defined premium windows; keep transparent.
A56: 5. Fastest Path to Profitability — Strategy Comparison
A57: Strategy | B57: Journeys / Day | C57: Avg Service Price | D57: Contribution / Journey | E57: Fixed Cost | F57: Monthly Profit | G57: Angels Needed | H57: Difficulty | I57: What Changes
A58: A — Lean MVP | B58: ='Whitefield Monthly Projection'!$Q$19/'Whitefield Monthly Projection'!$B$7 -> 1.254 | C58: ='Whitefield Monthly Projection'!$S$46 -> 1860.916 | D58: ='Whitefield Monthly Projection'!$Q$34 -> 1511.0154 | E58: =$I$20 -> 182000 | F58: ='Whitefield Monthly Projection'!$Q$32-E58 -> -125155.6 | G58: ='Whitefield Monthly Projection'!$Q$19*'Whitefield Monthly Projection'!$S$45/('Whitefield Monthly Projection'!$B$7*'Whitefield Monthly Projection'!$B$8*'Whitefield Monthly Projection'!$B$9) -> 0.724185 | H58: Low | I58: Current demand; cut fixed cost | K58: Repeat Engine Helper | L58: Value
A59: B — Volume Growth | B59: =(E59+$B$4)/D59/'Whitefield Monthly Projection'!$B$7 -> 3.0443105 | C59: ='Whitefield Monthly Projection'!$S$46 -> 1860.916 | D59: ='Whitefield Monthly Projection'!$Q$34 -> 1511.0154 | E59: ='Whitefield Monthly Projection'!$Q$36 -> 138000 | F59: =B59*'Whitefield Monthly Projection'!$B$7*D59-E59 -> 0 | G59: =B59*'Whitefield Monthly Projection'!$B$7*'Whitefield Monthly Projection'!$S$45/('Whitefield Monthly Projection'!$B$7*'Whitefield Monthly Projection'!$B$8*'Whitefield Monthly Projection'!$B$9) -> 1.7580893 | H59: High | I59: Keep economics; grow to target | K59: Current repeat share | L59: ='Whitefield Monthly Projection'!$B$17 -> 0.2
A60: C — Pricing Improvement | B60: =(E60+$B$4)/D60/'Whitefield Monthly Projection'!$B$7 -> 2.6445037 | C60: ='Whitefield Monthly Projection'!$S$46+('Whitefield Monthly Projection'!$S$45*($L$67-'Global Inputs'!$B$5)) -> 2784.916 | D60: ='Whitefield Monthly Projection'!$Q$34+('Whitefield Monthly Projection'!$S$45*($L$67-'Global Inputs'!$B$5))/(1+'Global Inputs'!$B$7)-('Whitefield Monthly Projection'!$S$45*($L$67-'Global Inputs'!$B$5))*'Global Inputs'!$B$8 -> 2294.0662 | E60: =$I$20 -> 182000 | F60: =B60*'Whitefield Monthly Projection'!$B$7*D60-E60 -> 0 | G60: =B60*'Whitefield Monthly Projection'!$S$45/('Whitefield Monthly Projection'!$B$8*'Whitefield Monthly Projection'!$B$9) -> 1.5272009 | H60: Medium | I60: Increase base rate to ₹499/hour | K60: Target repeat share | L60: 0.5
A61: D — Better Service Mix | B61: =(E61+$B$4)/D61/'Whitefield Monthly Projection'!$B$7 -> 1.8378672 | C61: ='Profit Maximizer'!$C$71/'Profit Maximizer'!$C$70 -> 4323.5998 | D61: ='Profit Maximizer'!$C$72/'Profit Maximizer'!$C$70 -> 3300.9276 | E61: =$I$20 -> 182000 | F61: =B61*'Whitefield Monthly Projection'!$B$7*D61-E61 -> 0 | G61: =B61*'Whitefield Monthly Projection'!$B$7*'Profit Maximizer'!$C$69/('Whitefield Monthly Projection'!$B$7*'Whitefield Monthly Projection'!$B$8*'Whitefield Monthly Projection'!$B$9) -> 1.6188945 | H61: Medium | I61: Push high contribution / Angel-hour services | K61: Recurring avg contrib / journey | L61: =SUMIF('Profit Maximizer'!$U$15:$U$44,"Yes",'Profit Maximizer'!$H$15:$H$44)/COUNTIF('Profit Maximizer'!$U$15:$U$44,"Yes") -> 1843.9259
A62: E — Repeat Customer Engine | B62: =(E62+$B$4)/D62/'Whitefield Monthly Projection'!$B$7 -> 3.708556 | C62: ='Whitefield Monthly Projection'!$S$46 -> 1860.916 | D62: =$L$63 -> 1635.8568 | E62: =$I$20 -> 182000 | F62: =B62*'Whitefield Monthly Projection'!$B$7*D62-E62 -> 0 | G62: =B62*'Whitefield Monthly Projection'!$S$45/('Whitefield Monthly Projection'!$B$8*'Whitefield Monthly Projection'!$B$9) -> 2.1416911 | H62: Medium | I62: Raise recurring / repeat journey share | K62: Implied non-recurring contrib / journey | L62: =IF(1-L59=0,0,('Whitefield Monthly Projection'!$Q$34-L59*L61)/(1-L59)) -> 1427.7878
A63: F — Hybrid | B63: =MIN($L$68*'Whitefield Monthly Projection'!$B$7*$L$69*(1-$L$70)*(1-$L$71)/'Whitefield Monthly Projection'!$B$7,'Whitefield Monthly Projection'!$B$6*'Whitefield Monthly Projection'!$B$8*$L$72/((1-$L$73)*'Whitefield Monthly Projection'!$S$45+$L$73*'Profit Maximizer'!$C$69)) -> 3.839943 | C63: ='Whitefield Monthly Projection'!$S$46+('Whitefield Monthly Projection'!$S$45*($L$67-'Global Inputs'!$B$5)) -> 2784.916 | D63: =((1-$L$73)*('Whitefield Monthly Projection'!$Q$34+('Whitefield Monthly Projection'!$S$45*($L$67-'Global Inputs'!$B$5))/(1+'Global Inputs'!$B$7)-('Whitefield Monthly Projection'!$S$45*($L$67-'Global Inputs'!$B$5))*'Global Inputs'!$B$8)+$L$73*('Profit Maximizer'!$C$72/'Profit Maximizer'!$C$70)) -> 2797.4969 | E63: =$I$20 -> 182000 | F63: =B63*'Whitefield Monthly Projection'!$B$7*D63-E63 -> 140266.87 | G63: =B63*'Whitefield Monthly Projection'!$B$7*((1-$L$73)*'Whitefield Monthly Projection'!$S$45+$L$73*'Profit Maximizer'!$C$69)/('Whitefield Monthly Projection'!$B$7*'Whitefield Monthly Projection'!$B$8*$L$72) -> 4 | H63: Medium | I63: Lean cost + better price + better mix + denser demand | K63: Target blended contrib / journey | L63: =L60*L61+(1-L60)*L62 -> 1635.8568
A65: Recommended Path | B65: =IF(F58>=$B$4,"A — Lean MVP",IF(F63>=$B$4,"F — Hybrid",IF(F61>=$B$4,"D — Better Service Mix",IF(F60>=$B$4,"C — Pricing Improvement","B — Volume Growth")))) -> F — Hybrid
K66: Hybrid Assumption | L66: Value
K67: Base price / hour | L67: 499
K68: Leads / day | L68: 15
K69: Booking conversion | L69: 0.4
K70: Cancellation | L70: 0.05
K71: No-show / refund | L71: 0.02
K72: Target utilization | L72: 0.7
K73: Optimized-mix blend | L73: 0.5
A76: 6. Break-even Journey Calculator — By Medical Concierge Service | I76: 7. Price vs Volume — Monthly Operating Profit | U76: Journeys / Day | V76: Monthly Operating Profit
A77: Service | B77: Hours | C77: Blended Contribution / Journey | D77: Contribution / Angel Hr | E77: Break-even Journeys / Month | F77: Break-even Journeys / Day | G77: Priority | I77: Avg Service Price / Journeys per Day | J77: 3 | K77: 5 | L77: 8 | M77: 10 | N77: 12 | O77: 15 | P77: 20 | Q77: 25 | U77: 3 | V77: =U77*'Whitefield Monthly Projection'!$B$7*'Whitefield Monthly Projection'!$Q$34-$M$11 -> 25991.386
A78: ='Profit Maximizer'!A15 -> Hospital Visit | B78: ='Profit Maximizer'!C15 -> 4 | C78: ='Profit Maximizer'!H15 -> 1132.4784 | D78: ='Profit Maximizer'!J15 -> 283.1196 | E78: =IF(C78<=0,0,$M$11/C78) -> 97.132096 | F78: =IF('Whitefield Monthly Projection'!$B$7=0,0,E78/'Whitefield Monthly Projection'!$B$7) -> 3.2377365 | G78: ='Profit Maximizer'!Q15 -> REVIEW — Economics need improvement | I78: 1499 | J78: =3*'Whitefield Monthly Projection'!$B$7*('Whitefield Monthly Projection'!$Q$34+($I78-'Whitefield Monthly Projection'!$S$46)/(1+'Global Inputs'!$B$7)-($I78-'Whitefield Monthly Projection'!$S$46)*'Global Inputs'!$B$8)-$M$11 -> -1612.3769 | K78: =5*'Whitefield Monthly Projection'!$B$7*('Whitefield Monthly Projection'!$Q$34+($I78-'Whitefield Monthly Projection'!$S$46)/(1+'Global Inputs'!$B$7)-($I78-'Whitefield Monthly Projection'!$S$46)*'Global Inputs'!$B$8)-$M$11 -> 70646.038 | L78: =8*'Whitefield Monthly Projection'!$B$7*('Whitefield Monthly Projection'!$Q$34+($I78-'Whitefield Monthly Projection'!$S$46)/(1+'Global Inputs'!$B$7)-($I78-'Whitefield Monthly Projection'!$S$46)*'Global Inputs'!$B$8)-$M$11 -> 179033.66 | M78: =10*'Whitefield Monthly Projection'!$B$7*('Whitefield Monthly Projection'!$Q$34+($I78-'Whitefield Monthly Projection'!$S$46)/(1+'Global Inputs'!$B$7)-($I78-'Whitefield Monthly Projection'!$S$46)*'Global Inputs'!$B$8)-$M$11 -> 251292.08 | N78: =12*'Whitefield Monthly Projection'!$B$7*('Whitefield Monthly Projection'!$Q$34+($I78-'Whitefield Monthly Projection'!$S$46)/(1+'Global Inputs'!$B$7)-($I78-'Whitefield Monthly Projection'!$S$46)*'Global Inputs'!$B$8)-$M$11 -> 323550.49 | O78: =15*'Whitefield Monthly Projection'!$B$7*('Whitefield Monthly Projection'!$Q$34+($I78-'Whitefield Monthly Projection'!$S$46)/(1+'Global Inputs'!$B$7)-($I78-'Whitefield Monthly Projection'!$S$46)*'Global Inputs'!$B$8)-$M$11 -> 431938.12 | P78: =20*'Whitefield Monthly Projection'!$B$7*('Whitefield Monthly Projection'!$Q$34+($I78-'Whitefield Monthly Projection'!$S$46)/(1+'Global Inputs'!$B$7)-($I78-'Whitefield Monthly Projection'!$S$46)*'Global Inputs'!$B$8)-$M$11 -> 612584.15 | Q78: =25*'Whitefield Monthly Projection'!$B$7*('Whitefield Monthly Projection'!$Q$34+($I78-'Whitefield Monthly Projection'!$S$46)/(1+'Global Inputs'!$B$7)-($I78-'Whitefield Monthly Projection'!$S$46)*'Global Inputs'!$B$8)-$M$11 -> 793230.19 | U78: 5 | V78: =U78*'Whitefield Monthly Projection'!$B$7*'Whitefield Monthly Projection'!$Q$34-$M$11 -> 116652.31
A79: ='Profit Maximizer'!A16 -> Hospital Visit — Concierge at Hospital | B79: ='Profit Maximizer'!C16 -> 3 | C79: ='Profit Maximizer'!H16 -> 743.79866 | D79: ='Profit Maximizer'!J16 -> 247.93289 | E79: =IF(C79<=0,0,$M$11/C79) -> 147.88948 | F79: =IF('Whitefield Monthly Projection'!$B$7=0,0,E79/'Whitefield Monthly Projection'!$B$7) -> 4.9296495 | G79: ='Profit Maximizer'!Q16 -> REVIEW — Economics need improvement | I79: 1699 | J79: =3*'Whitefield Monthly Projection'!$B$7*('Whitefield Monthly Projection'!$Q$34+($I79-'Whitefield Monthly Projection'!$S$46)/(1+'Global Inputs'!$B$7)-($I79-'Whitefield Monthly Projection'!$S$46)*'Global Inputs'!$B$8)-$M$11 -> 13641.86 | K79: =5*'Whitefield Monthly Projection'!$B$7*('Whitefield Monthly Projection'!$Q$34+($I79-'Whitefield Monthly Projection'!$S$46)/(1+'Global Inputs'!$B$7)-($I79-'Whitefield Monthly Projection'!$S$46)*'Global Inputs'!$B$8)-$M$11 -> 96069.767 | L79: =8*'Whitefield Monthly Projection'!$B$7*('Whitefield Monthly Projection'!$Q$34+($I79-'Whitefield Monthly Projection'!$S$46)/(1+'Global Inputs'!$B$7)-($I79-'Whitefield Monthly Projection'!$S$46)*'Global Inputs'!$B$8)-$M$11 -> 219711.63 | M79: =10*'Whitefield Monthly Projection'!$B$7*('Whitefield Monthly Projection'!$Q$34+($I79-'Whitefield Monthly Projection'!$S$46)/(1+'Global Inputs'!$B$7)-($I79-'Whitefield Monthly Projection'!$S$46)*'Global Inputs'!$B$8)-$M$11 -> 302139.53 | N79: =12*'Whitefield Monthly Projection'!$B$7*('Whitefield Monthly Projection'!$Q$34+($I79-'Whitefield Monthly Projection'!$S$46)/(1+'Global Inputs'!$B$7)-($I79-'Whitefield Monthly Projection'!$S$46)*'Global Inputs'!$B$8)-$M$11 -> 384567.44 | O79: =15*'Whitefield Monthly Projection'!$B$7*('Whitefield Monthly Projection'!$Q$34+($I79-'Whitefield Monthly Projection'!$S$46)/(1+'Global Inputs'!$B$7)-($I79-'Whitefield Monthly Projection'!$S$46)*'Global Inputs'!$B$8)-$M$11 -> 508209.3 | P79: =20*'Whitefield Monthly Projection'!$B$7*('Whitefield Monthly Projection'!$Q$34+($I79-'Whitefield Monthly Projection'!$S$46)/(1+'Global Inputs'!$B$7)-($I79-'Whitefield Monthly Projection'!$S$46)*'Global Inputs'!$B$8)-$M$11 -> 714279.07 | Q79: =25*'Whitefield Monthly Projection'!$B$7*('Whitefield Monthly Projection'!$Q$34+($I79-'Whitefield Monthly Projection'!$S$46)/(1+'Global Inputs'!$B$7)-($I79-'Whitefield Monthly Projection'!$S$46)*'Global Inputs'!$B$8)-$M$11 -> 920348.84 | U79: 8 | V79: =U79*'Whitefield Monthly Projection'!$B$7*'Whitefield Monthly Projection'!$Q$34-$M$11 -> 252643.7
A80: ='Profit Maximizer'!A17 -> Clinic Visit | B80: ='Profit Maximizer'!C17 -> 2 | C80: ='Profit Maximizer'!H17 -> 598.04376 | D80: ='Profit Maximizer'!J17 -> 299.02188 | E80: =IF(C80<=0,0,$M$11/C80) -> 183.93303 | F80: =IF('Whitefield Monthly Projection'!$B$7=0,0,E80/'Whitefield Monthly Projection'!$B$7) -> 6.1311009 | G80: ='Profit Maximizer'!Q17 -> GROW — Attractive economics | I80: 1799 | J80: =3*'Whitefield Monthly Projection'!$B$7*('Whitefield Monthly Projection'!$Q$34+($I80-'Whitefield Monthly Projection'!$S$46)/(1+'Global Inputs'!$B$7)-($I80-'Whitefield Monthly Projection'!$S$46)*'Global Inputs'!$B$8)-$M$11 -> 21268.979 | K80: =5*'Whitefield Monthly Projection'!$B$7*('Whitefield Monthly Projection'!$Q$34+($I80-'Whitefield Monthly Projection'!$S$46)/(1+'Global Inputs'!$B$7)-($I80-'Whitefield Monthly Projection'!$S$46)*'Global Inputs'!$B$8)-$M$11 -> 108781.63 | L80: =8*'Whitefield Monthly Projection'!$B$7*('Whitefield Monthly Projection'!$Q$34+($I80-'Whitefield Monthly Projection'!$S$46)/(1+'Global Inputs'!$B$7)-($I80-'Whitefield Monthly Projection'!$S$46)*'Global Inputs'!$B$8)-$M$11 -> 240050.61 | M80: =10*'Whitefield Monthly Projection'!$B$7*('Whitefield Monthly Projection'!$Q$34+($I80-'Whitefield Monthly Projection'!$S$46)/(1+'Global Inputs'!$B$7)-($I80-'Whitefield Monthly Projection'!$S$46)*'Global Inputs'!$B$8)-$M$11 -> 327563.26 | N80: =12*'Whitefield Monthly Projection'!$B$7*('Whitefield Monthly Projection'!$Q$34+($I80-'Whitefield Monthly Projection'!$S$46)/(1+'Global Inputs'!$B$7)-($I80-'Whitefield Monthly Projection'!$S$46)*'Global Inputs'!$B$8)-$M$11 -> 415075.92 | O80: =15*'Whitefield Monthly Projection'!$B$7*('Whitefield Monthly Projection'!$Q$34+($I80-'Whitefield Monthly Projection'!$S$46)/(1+'Global Inputs'!$B$7)-($I80-'Whitefield Monthly Projection'!$S$46)*'Global Inputs'!$B$8)-$M$11 -> 546344.9 | P80: =20*'Whitefield Monthly Projection'!$B$7*('Whitefield Monthly Projection'!$Q$34+($I80-'Whitefield Monthly Projection'!$S$46)/(1+'Global Inputs'!$B$7)-($I80-'Whitefield Monthly Projection'!$S$46)*'Global Inputs'!$B$8)-$M$11 -> 765126.53 | Q80: =25*'Whitefield Monthly Projection'!$B$7*('Whitefield Monthly Projection'!$Q$34+($I80-'Whitefield Monthly Projection'!$S$46)/(1+'Global Inputs'!$B$7)-($I80-'Whitefield Monthly Projection'!$S$46)*'Global Inputs'!$B$8)-$M$11 -> 983908.16 | U80: 10 | V80: =U80*'Whitefield Monthly Projection'!$B$7*'Whitefield Monthly Projection'!$Q$34-$M$11 -> 343304.62
A81: ='Profit Maximizer'!A18 -> Diagnostic Center Visit | B81: ='Profit Maximizer'!C18 -> 3 | C81: ='Profit Maximizer'!H18 -> 780.23739 | D81: ='Profit Maximizer'!J18 -> 260.07913 | E81: =IF(C81<=0,0,$M$11/C81) -> 140.98273 | F81: =IF('Whitefield Monthly Projection'!$B$7=0,0,E81/'Whitefield Monthly Projection'!$B$7) -> 4.6994245 | G81: ='Profit Maximizer'!Q18 -> REVIEW — Economics need improvement | I81: 1999 | J81: =3*'Whitefield Monthly Projection'!$B$7*('Whitefield Monthly Projection'!$Q$34+($I81-'Whitefield Monthly Projection'!$S$46)/(1+'Global Inputs'!$B$7)-($I81-'Whitefield Monthly Projection'!$S$46)*'Global Inputs'!$B$8)-$M$11 -> 36523.216 | K81: =5*'Whitefield Monthly Projection'!$B$7*('Whitefield Monthly Projection'!$Q$34+($I81-'Whitefield Monthly Projection'!$S$46)/(1+'Global Inputs'!$B$7)-($I81-'Whitefield Monthly Projection'!$S$46)*'Global Inputs'!$B$8)-$M$11 -> 134205.36 | L81: =8*'Whitefield Monthly Projection'!$B$7*('Whitefield Monthly Projection'!$Q$34+($I81-'Whitefield Monthly Projection'!$S$46)/(1+'Global Inputs'!$B$7)-($I81-'Whitefield Monthly Projection'!$S$46)*'Global Inputs'!$B$8)-$M$11 -> 280728.58 | M81: =10*'Whitefield Monthly Projection'!$B$7*('Whitefield Monthly Projection'!$Q$34+($I81-'Whitefield Monthly Projection'!$S$46)/(1+'Global Inputs'!$B$7)-($I81-'Whitefield Monthly Projection'!$S$46)*'Global Inputs'!$B$8)-$M$11 -> 378410.72 | N81: =12*'Whitefield Monthly Projection'!$B$7*('Whitefield Monthly Projection'!$Q$34+($I81-'Whitefield Monthly Projection'!$S$46)/(1+'Global Inputs'!$B$7)-($I81-'Whitefield Monthly Projection'!$S$46)*'Global Inputs'!$B$8)-$M$11 -> 476092.87 | O81: =15*'Whitefield Monthly Projection'!$B$7*('Whitefield Monthly Projection'!$Q$34+($I81-'Whitefield Monthly Projection'!$S$46)/(1+'Global Inputs'!$B$7)-($I81-'Whitefield Monthly Projection'!$S$46)*'Global Inputs'!$B$8)-$M$11 -> 622616.08 | P81: =20*'Whitefield Monthly Projection'!$B$7*('Whitefield Monthly Projection'!$Q$34+($I81-'Whitefield Monthly Projection'!$S$46)/(1+'Global Inputs'!$B$7)-($I81-'Whitefield Monthly Projection'!$S$46)*'Global Inputs'!$B$8)-$M$11 -> 866821.44 | Q81: =25*'Whitefield Monthly Projection'!$B$7*('Whitefield Monthly Projection'!$Q$34+($I81-'Whitefield Monthly Projection'!$S$46)/(1+'Global Inputs'!$B$7)-($I81-'Whitefield Monthly Projection'!$S$46)*'Global Inputs'!$B$8)-$M$11 -> 1111026.8 | U81: 12 | V81: =U81*'Whitefield Monthly Projection'!$B$7*'Whitefield Monthly Projection'!$Q$34-$M$11 -> 433965.54
A82: ='Profit Maximizer'!A19 -> Health Check-up Concierge | B82: ='Profit Maximizer'!C19 -> 5 | C82: ='Profit Maximizer'!H19 -> 1253.9408 | D82: ='Profit Maximizer'!J19 -> 250.78816 | E82: =IF(C82<=0,0,$M$11/C82) -> 87.723439 | F82: =IF('Whitefield Monthly Projection'!$B$7=0,0,E82/'Whitefield Monthly Projection'!$B$7) -> 2.9241146 | G82: ='Profit Maximizer'!Q19 -> REVIEW — Economics need improvement | I82: 2199 | J82: =3*'Whitefield Monthly Projection'!$B$7*('Whitefield Monthly Projection'!$Q$34+($I82-'Whitefield Monthly Projection'!$S$46)/(1+'Global Inputs'!$B$7)-($I82-'Whitefield Monthly Projection'!$S$46)*'Global Inputs'!$B$8)-$M$11 -> 51777.454 | K82: =5*'Whitefield Monthly Projection'!$B$7*('Whitefield Monthly Projection'!$Q$34+($I82-'Whitefield Monthly Projection'!$S$46)/(1+'Global Inputs'!$B$7)-($I82-'Whitefield Monthly Projection'!$S$46)*'Global Inputs'!$B$8)-$M$11 -> 159629.09 | L82: =8*'Whitefield Monthly Projection'!$B$7*('Whitefield Monthly Projection'!$Q$34+($I82-'Whitefield Monthly Projection'!$S$46)/(1+'Global Inputs'!$B$7)-($I82-'Whitefield Monthly Projection'!$S$46)*'Global Inputs'!$B$8)-$M$11 -> 321406.54 | M82: =10*'Whitefield Monthly Projection'!$B$7*('Whitefield Monthly Projection'!$Q$34+($I82-'Whitefield Monthly Projection'!$S$46)/(1+'Global Inputs'!$B$7)-($I82-'Whitefield Monthly Projection'!$S$46)*'Global Inputs'!$B$8)-$M$11 -> 429258.18 | N82: =12*'Whitefield Monthly Projection'!$B$7*('Whitefield Monthly Projection'!$Q$34+($I82-'Whitefield Monthly Projection'!$S$46)/(1+'Global Inputs'!$B$7)-($I82-'Whitefield Monthly Projection'!$S$46)*'Global Inputs'!$B$8)-$M$11 -> 537109.81 | O82: =15*'Whitefield Monthly Projection'!$B$7*('Whitefield Monthly Projection'!$Q$34+($I82-'Whitefield Monthly Projection'!$S$46)/(1+'Global Inputs'!$B$7)-($I82-'Whitefield Monthly Projection'!$S$46)*'Global Inputs'!$B$8)-$M$11 -> 698887.27 | P82: =20*'Whitefield Monthly Projection'!$B$7*('Whitefield Monthly Projection'!$Q$34+($I82-'Whitefield Monthly Projection'!$S$46)/(1+'Global Inputs'!$B$7)-($I82-'Whitefield Monthly Projection'!$S$46)*'Global Inputs'!$B$8)-$M$11 -> 968516.36 | Q82: =25*'Whitefield Monthly Projection'!$B$7*('Whitefield Monthly Projection'!$Q$34+($I82-'Whitefield Monthly Projection'!$S$46)/(1+'Global Inputs'!$B$7)-($I82-'Whitefield Monthly Projection'!$S$46)*'Global Inputs'!$B$8)-$M$11 -> 1238145.4 | U82: 15 | V82: =U82*'Whitefield Monthly Projection'!$B$7*'Whitefield Monthly Projection'!$Q$34-$M$11 -> 569956.93
A83: ='Profit Maximizer'!A20 -> Hospital Admission Concierge | B83: ='Profit Maximizer'!C20 -> 4 | C83: ='Profit Maximizer'!H20 -> 1278.2333 | D83: ='Profit Maximizer'!J20 -> 319.55832 | E83: =IF(C83<=0,0,$M$11/C83) -> 86.056279 | F83: =IF('Whitefield Monthly Projection'!$B$7=0,0,E83/'Whitefield Monthly Projection'!$B$7) -> 2.8685426 | G83: ='Profit Maximizer'!Q20 -> GROW — Attractive economics | I83: 2499 | J83: =3*'Whitefield Monthly Projection'!$B$7*('Whitefield Monthly Projection'!$Q$34+($I83-'Whitefield Monthly Projection'!$S$46)/(1+'Global Inputs'!$B$7)-($I83-'Whitefield Monthly Projection'!$S$46)*'Global Inputs'!$B$8)-$M$11 -> 74658.81 | K83: =5*'Whitefield Monthly Projection'!$B$7*('Whitefield Monthly Projection'!$Q$34+($I83-'Whitefield Monthly Projection'!$S$46)/(1+'Global Inputs'!$B$7)-($I83-'Whitefield Monthly Projection'!$S$46)*'Global Inputs'!$B$8)-$M$11 -> 197764.68 | L83: =8*'Whitefield Monthly Projection'!$B$7*('Whitefield Monthly Projection'!$Q$34+($I83-'Whitefield Monthly Projection'!$S$46)/(1+'Global Inputs'!$B$7)-($I83-'Whitefield Monthly Projection'!$S$46)*'Global Inputs'!$B$8)-$M$11 -> 382423.49 | M83: =10*'Whitefield Monthly Projection'!$B$7*('Whitefield Monthly Projection'!$Q$34+($I83-'Whitefield Monthly Projection'!$S$46)/(1+'Global Inputs'!$B$7)-($I83-'Whitefield Monthly Projection'!$S$46)*'Global Inputs'!$B$8)-$M$11 -> 505529.37 | N83: =12*'Whitefield Monthly Projection'!$B$7*('Whitefield Monthly Projection'!$Q$34+($I83-'Whitefield Monthly Projection'!$S$46)/(1+'Global Inputs'!$B$7)-($I83-'Whitefield Monthly Projection'!$S$46)*'Global Inputs'!$B$8)-$M$11 -> 628635.24 | O83: =15*'Whitefield Monthly Projection'!$B$7*('Whitefield Monthly Projection'!$Q$34+($I83-'Whitefield Monthly Projection'!$S$46)/(1+'Global Inputs'!$B$7)-($I83-'Whitefield Monthly Projection'!$S$46)*'Global Inputs'!$B$8)-$M$11 -> 813294.05 | P83: =20*'Whitefield Monthly Projection'!$B$7*('Whitefield Monthly Projection'!$Q$34+($I83-'Whitefield Monthly Projection'!$S$46)/(1+'Global Inputs'!$B$7)-($I83-'Whitefield Monthly Projection'!$S$46)*'Global Inputs'!$B$8)-$M$11 -> 1121058.7 | Q83: =25*'Whitefield Monthly Projection'!$B$7*('Whitefield Monthly Projection'!$Q$34+($I83-'Whitefield Monthly Projection'!$S$46)/(1+'Global Inputs'!$B$7)-($I83-'Whitefield Monthly Projection'!$S$46)*'Global Inputs'!$B$8)-$M$11 -> 1428823.4 | U83: 20 | V83: =U83*'Whitefield Monthly Projection'!$B$7*'Whitefield Monthly Projection'!$Q$34-$M$11 -> 796609.24
A84: ='Profit Maximizer'!A21 -> Hospital Discharge Concierge | B84: ='Profit Maximizer'!C21 -> 4 | C84: ='Profit Maximizer'!H21 -> 1229.6483 | D84: ='Profit Maximizer'!J21 -> 307.41208 | E84: =IF(C84<=0,0,$M$11/C84) -> 89.456471 | F84: =IF('Whitefield Monthly Projection'!$B$7=0,0,E84/'Whitefield Monthly Projection'!$B$7) -> 2.9818824 | G84: ='Profit Maximizer'!Q21 -> GROW — Attractive economics | U84: 25 | V84: =U84*'Whitefield Monthly Projection'!$B$7*'Whitefield Monthly Projection'!$Q$34-$M$11 -> 1023261.5
A85: ='Profit Maximizer'!A22 -> Overnight Hospital Concierge | B85: ='Profit Maximizer'!C22 -> 12 | C85: ='Profit Maximizer'!H22 -> 2881.5372 | D85: ='Profit Maximizer'!J22 -> 240.1281 | E85: =IF(C85<=0,0,$M$11/C85) -> 38.174069 | F85: =IF('Whitefield Monthly Projection'!$B$7=0,0,E85/'Whitefield Monthly Projection'!$B$7) -> 1.272469 | G85: ='Profit Maximizer'!Q22 -> REVIEW — Economics need improvement
A86: ='Profit Maximizer'!A23 -> Multi-Day Hospital Concierge (per 12h shift) | B86: ='Profit Maximizer'!C23 -> 12 | C86: ='Profit Maximizer'!H23 -> 2881.5372 | D86: ='Profit Maximizer'!J23 -> 240.1281 | E86: =IF(C86<=0,0,$M$11/C86) -> 38.174069 | F86: =IF('Whitefield Monthly Projection'!$B$7=0,0,E86/'Whitefield Monthly Projection'!$B$7) -> 1.272469 | G86: ='Profit Maximizer'!Q23 -> REVIEW — Economics need improvement | I86: 8. Fixed Cost vs Journey Density — Monthly Operating Profit | U86: Avg Service Price | V86: Monthly Operating Profit
A87: ='Profit Maximizer'!A24 -> Day Surgery / Procedure Concierge | B87: ='Profit Maximizer'!C24 -> 6 | C87: ='Profit Maximizer'!H24 -> 1909.8378 | D87: ='Profit Maximizer'!J24 -> 318.30631 | E87: =IF(C87<=0,0,$M$11/C87) -> 57.596513 | F87: =IF('Whitefield Monthly Projection'!$B$7=0,0,E87/'Whitefield Monthly Projection'!$B$7) -> 1.9198838 | G87: ='Profit Maximizer'!Q24 -> GROW — Attractive economics | I87: Monthly Fixed Cost / Journeys per Day | J87: 3 | K87: 5 | L87: 8 | M87: 10 | N87: 12 | O87: 15 | P87: 20 | U87: 1499 | V87: ='Whitefield Monthly Projection'!$Q$19*('Whitefield Monthly Projection'!$Q$34+(U87-'Whitefield Monthly Projection'!$S$46)/(1+'Global Inputs'!$B$7)-(U87-'Whitefield Monthly Projection'!$S$46)*'Global Inputs'!$B$8)-$M$11 -> -64693.974
A88: ='Profit Maximizer'!A25 -> Pre-Surgery Concierge | B88: ='Profit Maximizer'!C25 -> 4 | C88: ='Profit Maximizer'!H25 -> 1229.6483 | D88: ='Profit Maximizer'!J25 -> 307.41208 | E88: =IF(C88<=0,0,$M$11/C88) -> 89.456471 | F88: =IF('Whitefield Monthly Projection'!$B$7=0,0,E88/'Whitefield Monthly Projection'!$B$7) -> 2.9818824 | G88: ='Profit Maximizer'!Q25 -> GROW — Attractive economics | I88: 75000 | J88: =3*'Whitefield Monthly Projection'!$B$7*'Whitefield Monthly Projection'!$Q$34-$I88 -> 60991.386 | K88: =5*'Whitefield Monthly Projection'!$B$7*'Whitefield Monthly Projection'!$Q$34-$I88 -> 151652.31 | L88: =8*'Whitefield Monthly Projection'!$B$7*'Whitefield Monthly Projection'!$Q$34-$I88 -> 287643.7 | M88: =10*'Whitefield Monthly Projection'!$B$7*'Whitefield Monthly Projection'!$Q$34-$I88 -> 378304.62 | N88: =12*'Whitefield Monthly Projection'!$B$7*'Whitefield Monthly Projection'!$Q$34-$I88 -> 468965.54 | O88: =15*'Whitefield Monthly Projection'!$B$7*'Whitefield Monthly Projection'!$Q$34-$I88 -> 604956.93 | P88: =20*'Whitefield Monthly Projection'!$B$7*'Whitefield Monthly Projection'!$Q$34-$I88 -> 831609.24 | U88: 1699 | V88: ='Whitefield Monthly Projection'!$Q$19*('Whitefield Monthly Projection'!$Q$34+(U88-'Whitefield Monthly Projection'!$S$46)/(1+'Global Inputs'!$B$7)-(U88-'Whitefield Monthly Projection'!$S$46)*'Global Inputs'!$B$8)-$M$11 -> -58317.702
A89: ='Profit Maximizer'!A26 -> Post-Surgery Follow-up | B89: ='Profit Maximizer'!C26 -> 3 | C89: ='Profit Maximizer'!H26 -> 889.55356 | D89: ='Profit Maximizer'!J26 -> 296.51785 | E89: =IF(C89<=0,0,$M$11/C89) -> 123.65753 | F89: =IF('Whitefield Monthly Projection'!$B$7=0,0,E89/'Whitefield Monthly Projection'!$B$7) -> 4.1219178 | G89: ='Profit Maximizer'!Q26 -> GROW — Attractive economics | I89: 100000 | J89: =3*'Whitefield Monthly Projection'!$B$7*'Whitefield Monthly Projection'!$Q$34-$I89 -> 35991.386 | K89: =5*'Whitefield Monthly Projection'!$B$7*'Whitefield Monthly Projection'!$Q$34-$I89 -> 126652.31 | L89: =8*'Whitefield Monthly Projection'!$B$7*'Whitefield Monthly Projection'!$Q$34-$I89 -> 262643.7 | M89: =10*'Whitefield Monthly Projection'!$B$7*'Whitefield Monthly Projection'!$Q$34-$I89 -> 353304.62 | N89: =12*'Whitefield Monthly Projection'!$B$7*'Whitefield Monthly Projection'!$Q$34-$I89 -> 443965.54 | O89: =15*'Whitefield Monthly Projection'!$B$7*'Whitefield Monthly Projection'!$Q$34-$I89 -> 579956.93 | P89: =20*'Whitefield Monthly Projection'!$B$7*'Whitefield Monthly Projection'!$Q$34-$I89 -> 806609.24 | U89: 1799 | V89: ='Whitefield Monthly Projection'!$Q$19*('Whitefield Monthly Projection'!$Q$34+(U89-'Whitefield Monthly Projection'!$S$46)/(1+'Global Inputs'!$B$7)-(U89-'Whitefield Monthly Projection'!$S$46)*'Global Inputs'!$B$8)-$M$11 -> -55129.567
A90: ='Profit Maximizer'!A27 -> Dialysis Visit Concierge | B90: ='Profit Maximizer'!C27 -> 5 | C90: ='Profit Maximizer'!H27 -> 1253.9408 | D90: ='Profit Maximizer'!J27 -> 250.78816 | E90: =IF(C90<=0,0,$M$11/C90) -> 87.723439 | F90: =IF('Whitefield Monthly Projection'!$B$7=0,0,E90/'Whitefield Monthly Projection'!$B$7) -> 2.9241146 | G90: ='Profit Maximizer'!Q27 -> STRATEGIC — Important but lower margin | I90: 125000 | J90: =3*'Whitefield Monthly Projection'!$B$7*'Whitefield Monthly Projection'!$Q$34-$I90 -> 10991.386 | K90: =5*'Whitefield Monthly Projection'!$B$7*'Whitefield Monthly Projection'!$Q$34-$I90 -> 101652.31 | L90: =8*'Whitefield Monthly Projection'!$B$7*'Whitefield Monthly Projection'!$Q$34-$I90 -> 237643.7 | M90: =10*'Whitefield Monthly Projection'!$B$7*'Whitefield Monthly Projection'!$Q$34-$I90 -> 328304.62 | N90: =12*'Whitefield Monthly Projection'!$B$7*'Whitefield Monthly Projection'!$Q$34-$I90 -> 418965.54 | O90: =15*'Whitefield Monthly Projection'!$B$7*'Whitefield Monthly Projection'!$Q$34-$I90 -> 554956.93 | P90: =20*'Whitefield Monthly Projection'!$B$7*'Whitefield Monthly Projection'!$Q$34-$I90 -> 781609.24 | U90: 1999 | V90: ='Whitefield Monthly Projection'!$Q$19*('Whitefield Monthly Projection'!$Q$34+(U90-'Whitefield Monthly Projection'!$S$46)/(1+'Global Inputs'!$B$7)-(U90-'Whitefield Monthly Projection'!$S$46)*'Global Inputs'!$B$8)-$M$11 -> -48753.296
A91: ='Profit Maximizer'!A28 -> Chemotherapy Visit Concierge | B91: ='Profit Maximizer'!C28 -> 6 | C91: ='Profit Maximizer'!H28 -> 1618.3281 | D91: ='Profit Maximizer'!J28 -> 269.72134 | E91: =IF(C91<=0,0,$M$11/C91) -> 67.971386 | F91: =IF('Whitefield Monthly Projection'!$B$7=0,0,E91/'Whitefield Monthly Projection'!$B$7) -> 2.2657129 | G91: ='Profit Maximizer'!Q28 -> STRATEGIC — Important but lower margin | I91: 150000 | J91: =3*'Whitefield Monthly Projection'!$B$7*'Whitefield Monthly Projection'!$Q$34-$I91 -> -14008.614 | K91: =5*'Whitefield Monthly Projection'!$B$7*'Whitefield Monthly Projection'!$Q$34-$I91 -> 76652.31 | L91: =8*'Whitefield Monthly Projection'!$B$7*'Whitefield Monthly Projection'!$Q$34-$I91 -> 212643.7 | M91: =10*'Whitefield Monthly Projection'!$B$7*'Whitefield Monthly Projection'!$Q$34-$I91 -> 303304.62 | N91: =12*'Whitefield Monthly Projection'!$B$7*'Whitefield Monthly Projection'!$Q$34-$I91 -> 393965.54 | O91: =15*'Whitefield Monthly Projection'!$B$7*'Whitefield Monthly Projection'!$Q$34-$I91 -> 529956.93 | P91: =20*'Whitefield Monthly Projection'!$B$7*'Whitefield Monthly Projection'!$Q$34-$I91 -> 756609.24 | U91: 2199 | V91: ='Whitefield Monthly Projection'!$Q$19*('Whitefield Monthly Projection'!$Q$34+(U91-'Whitefield Monthly Projection'!$S$46)/(1+'Global Inputs'!$B$7)-(U91-'Whitefield Monthly Projection'!$S$46)*'Global Inputs'!$B$8)-$M$11 -> -42377.024
A92: ='Profit Maximizer'!A29 -> Radiation Therapy Concierge | B92: ='Profit Maximizer'!C29 -> 3 | C92: ='Profit Maximizer'!H29 -> 853.11483 | D92: ='Profit Maximizer'!J29 -> 284.37161 | E92: =IF(C92<=0,0,$M$11/C92) -> 128.93927 | F92: =IF('Whitefield Monthly Projection'!$B$7=0,0,E92/'Whitefield Monthly Projection'!$B$7) -> 4.2979755 | G92: ='Profit Maximizer'!Q29 -> STRATEGIC — Important but lower margin | I92: 200000 | J92: =3*'Whitefield Monthly Projection'!$B$7*'Whitefield Monthly Projection'!$Q$34-$I92 -> -64008.614 | K92: =5*'Whitefield Monthly Projection'!$B$7*'Whitefield Monthly Projection'!$Q$34-$I92 -> 26652.31 | L92: =8*'Whitefield Monthly Projection'!$B$7*'Whitefield Monthly Projection'!$Q$34-$I92 -> 162643.7 | M92: =10*'Whitefield Monthly Projection'!$B$7*'Whitefield Monthly Projection'!$Q$34-$I92 -> 253304.62 | N92: =12*'Whitefield Monthly Projection'!$B$7*'Whitefield Monthly Projection'!$Q$34-$I92 -> 343965.54 | O92: =15*'Whitefield Monthly Projection'!$B$7*'Whitefield Monthly Projection'!$Q$34-$I92 -> 479956.93 | P92: =20*'Whitefield Monthly Projection'!$B$7*'Whitefield Monthly Projection'!$Q$34-$I92 -> 706609.24 | U92: 2499 | V92: ='Whitefield Monthly Projection'!$Q$19*('Whitefield Monthly Projection'!$Q$34+(U92-'Whitefield Monthly Projection'!$S$46)/(1+'Global Inputs'!$B$7)-(U92-'Whitefield Monthly Projection'!$S$46)*'Global Inputs'!$B$8)-$M$11 -> -32812.618
A93: ='Profit Maximizer'!A30 -> Physiotherapy / Rehab Visit | B93: ='Profit Maximizer'!C30 -> 2 | C93: ='Profit Maximizer'!H30 -> 573.75128 | D93: ='Profit Maximizer'!J30 -> 286.87564 | E93: =IF(C93<=0,0,$M$11/C93) -> 191.72071 | F93: =IF('Whitefield Monthly Projection'!$B$7=0,0,E93/'Whitefield Monthly Projection'!$B$7) -> 6.3906902 | G93: ='Profit Maximizer'!Q30 -> STRATEGIC — Important but lower margin | I93: 240000 | J93: =3*'Whitefield Monthly Projection'!$B$7*'Whitefield Monthly Projection'!$Q$34-$I93 -> -104008.61 | K93: =5*'Whitefield Monthly Projection'!$B$7*'Whitefield Monthly Projection'!$Q$34-$I93 -> -13347.69 | L93: =8*'Whitefield Monthly Projection'!$B$7*'Whitefield Monthly Projection'!$Q$34-$I93 -> 122643.7 | M93: =10*'Whitefield Monthly Projection'!$B$7*'Whitefield Monthly Projection'!$Q$34-$I93 -> 213304.62 | N93: =12*'Whitefield Monthly Projection'!$B$7*'Whitefield Monthly Projection'!$Q$34-$I93 -> 303965.54 | O93: =15*'Whitefield Monthly Projection'!$B$7*'Whitefield Monthly Projection'!$Q$34-$I93 -> 439956.93 | P93: =20*'Whitefield Monthly Projection'!$B$7*'Whitefield Monthly Projection'!$Q$34-$I93 -> 666609.24
A94: ='Profit Maximizer'!A31 -> Chronic Care Follow-up | B94: ='Profit Maximizer'!C31 -> 3 | C94: ='Profit Maximizer'!H31 -> 816.67611 | D94: ='Profit Maximizer'!J31 -> 272.22537 | E94: =IF(C94<=0,0,$M$11/C94) -> 134.69232 | F94: =IF('Whitefield Monthly Projection'!$B$7=0,0,E94/'Whitefield Monthly Projection'!$B$7) -> 4.489744 | G94: ='Profit Maximizer'!Q31 -> STRATEGIC — Important but lower margin | I94: 300000 | J94: =3*'Whitefield Monthly Projection'!$B$7*'Whitefield Monthly Projection'!$Q$34-$I94 -> -164008.61 | K94: =5*'Whitefield Monthly Projection'!$B$7*'Whitefield Monthly Projection'!$Q$34-$I94 -> -73347.69 | L94: =8*'Whitefield Monthly Projection'!$B$7*'Whitefield Monthly Projection'!$Q$34-$I94 -> 62643.695 | M94: =10*'Whitefield Monthly Projection'!$B$7*'Whitefield Monthly Projection'!$Q$34-$I94 -> 153304.62 | N94: =12*'Whitefield Monthly Projection'!$B$7*'Whitefield Monthly Projection'!$Q$34-$I94 -> 243965.54 | O94: =15*'Whitefield Monthly Projection'!$B$7*'Whitefield Monthly Projection'!$Q$34-$I94 -> 379956.93 | P94: =20*'Whitefield Monthly Projection'!$B$7*'Whitefield Monthly Projection'!$Q$34-$I94 -> 606609.24 | U94: Monthly Fixed Cost | V94: Monthly Operating Profit
A95: ='Profit Maximizer'!A32 -> NRI Parent Medical Concierge | B95: ='Profit Maximizer'!C32 -> 4 | C95: ='Profit Maximizer'!H32 -> 1326.8183 | D95: ='Profit Maximizer'!J32 -> 331.70456 | E95: =IF(C95<=0,0,$M$11/C95) -> 82.9051 | F95: =IF('Whitefield Monthly Projection'!$B$7=0,0,E95/'Whitefield Monthly Projection'!$B$7) -> 2.7635033 | G95: ='Profit Maximizer'!Q32 -> GROW — Attractive economics | U95: 75000 | V95: ='Whitefield Monthly Projection'!$Q$32-U95 -> -18155.601
A96: ='Profit Maximizer'!A33 -> Second Opinion Concierge | B96: ='Profit Maximizer'!C33 -> 2.5 | C96: ='Profit Maximizer'!H33 -> 676.99433 | D96: ='Profit Maximizer'!J33 -> 270.79773 | E96: =IF(C96<=0,0,$M$11/C96) -> 162.4829 | F96: =IF('Whitefield Monthly Projection'!$B$7=0,0,E96/'Whitefield Monthly Projection'!$B$7) -> 5.4160965 | G96: ='Profit Maximizer'!Q33 -> REVIEW — Economics need improvement | U96: 100000 | V96: ='Whitefield Monthly Projection'!$Q$32-U96 -> -43155.601
A97: ='Profit Maximizer'!A34 -> Teleconsultation Concierge | B97: ='Profit Maximizer'!C34 -> 1.5 | C97: ='Profit Maximizer'!H34 -> 476.58135 | D97: ='Profit Maximizer'!J34 -> 317.7209 | E97: =IF(C97<=0,0,$M$11/C97) -> 230.81054 | F97: =IF('Whitefield Monthly Projection'!$B$7=0,0,E97/'Whitefield Monthly Projection'!$B$7) -> 7.6936848 | G97: ='Profit Maximizer'!Q34 -> GROW — Attractive economics | U97: 125000 | V97: ='Whitefield Monthly Projection'!$Q$32-U97 -> -68155.601
A98: ='Profit Maximizer'!A35 -> Medical Records Concierge | B98: ='Profit Maximizer'!C35 -> 2 | C98: ='Profit Maximizer'!H35 -> 452.28886 | D98: ='Profit Maximizer'!J35 -> 226.14443 | E98: =IF(C98<=0,0,$M$11/C98) -> 243.2074 | F98: =IF('Whitefield Monthly Projection'!$B$7=0,0,E98/'Whitefield Monthly Projection'!$B$7) -> 8.1069134 | G98: ='Profit Maximizer'!Q35 -> REVIEW — Economics need improvement | U98: 150000 | V98: ='Whitefield Monthly Projection'!$Q$32-U98 -> -93155.601
A99: ='Profit Maximizer'!A36 -> Insurance / TPA Desk Concierge | B99: ='Profit Maximizer'!C36 -> 3 | C99: ='Profit Maximizer'!H36 -> 707.35994 | D99: ='Profit Maximizer'!J36 -> 235.78665 | E99: =IF(C99<=0,0,$M$11/C99) -> 155.50782 | F99: =IF('Whitefield Monthly Projection'!$B$7=0,0,E99/'Whitefield Monthly Projection'!$B$7) -> 5.1835939 | G99: ='Profit Maximizer'!Q36 -> REVIEW — Economics need improvement | U99: 200000 | V99: ='Whitefield Monthly Projection'!$Q$32-U99 -> -143155.6
A100: ='Profit Maximizer'!A37 -> Hospital Transfer Concierge | B100: ='Profit Maximizer'!C37 -> 4 | C100: ='Profit Maximizer'!H37 -> 1229.6483 | D100: ='Profit Maximizer'!J37 -> 307.41208 | E100: =IF(C100<=0,0,$M$11/C100) -> 89.456471 | F100: =IF('Whitefield Monthly Projection'!$B$7=0,0,E100/'Whitefield Monthly Projection'!$B$7) -> 2.9818824 | G100: ='Profit Maximizer'!Q37 -> GROW — Attractive economics | U100: 240000 | V100: ='Whitefield Monthly Projection'!$Q$32-U100 -> -183155.6
A101: ='Profit Maximizer'!A38 -> Rehab / Nursing Facility Transfer | B101: ='Profit Maximizer'!C38 -> 4 | C101: ='Profit Maximizer'!H38 -> 1181.0634 | D101: ='Profit Maximizer'!J38 -> 295.26584 | E101: =IF(C101<=0,0,$M$11/C101) -> 93.136409 | F101: =IF('Whitefield Monthly Projection'!$B$7=0,0,E101/'Whitefield Monthly Projection'!$B$7) -> 3.104547 | G101: ='Profit Maximizer'!Q38 -> REVIEW — Economics need improvement | U101: 300000 | V101: ='Whitefield Monthly Projection'!$Q$32-U101 -> -243155.6
A102: ='Profit Maximizer'!A39 -> 24×7 Urgent Care Coordination | B102: ='Profit Maximizer'!C39 -> 4 | C102: ='Profit Maximizer'!H39 -> 1829.4045 | D102: ='Profit Maximizer'!J39 -> 457.35114 | E102: =IF(C102<=0,0,$M$11/C102) -> 60.128855 | F102: =IF('Whitefield Monthly Projection'!$B$7=0,0,E102/'Whitefield Monthly Projection'!$B$7) -> 2.0042952 | G102: ='Profit Maximizer'!Q39 -> GROW — Attractive economics
A103: ='Profit Maximizer'!A40 -> Doctor-at-Home Coordination | B103: ='Profit Maximizer'!C40 -> 2 | C103: ='Profit Maximizer'!H40 -> 573.75128 | D103: ='Profit Maximizer'!J40 -> 286.87564 | E103: =IF(C103<=0,0,$M$11/C103) -> 191.72071 | F103: =IF('Whitefield Monthly Projection'!$B$7=0,0,E103/'Whitefield Monthly Projection'!$B$7) -> 6.3906902 | G103: ='Profit Maximizer'!Q40 -> REVIEW — Economics need improvement | U103: Angel Utilization | V103: Operating Profit
A104: ='Profit Maximizer'!A41 -> Nurse-at-Home Coordination | B104: ='Profit Maximizer'!C41 -> 2 | C104: ='Profit Maximizer'!H41 -> 573.75128 | D104: ='Profit Maximizer'!J41 -> 286.87564 | E104: =IF(C104<=0,0,$M$11/C104) -> 191.72071 | F104: =IF('Whitefield Monthly Projection'!$B$7=0,0,E104/'Whitefield Monthly Projection'!$B$7) -> 6.3906902 | G104: ='Profit Maximizer'!Q41 -> STRATEGIC — Important but lower margin | U104: 0.3 | V104: =G113 -> -125155.6
A105: ='Profit Maximizer'!A42 -> Medical Tourism — Concierge Package (24 HR Basis) | B105: ='Profit Maximizer'!C42 -> 24 | C105: ='Profit Maximizer'!H42 -> 14257.731 | D105: ='Profit Maximizer'!J42 -> 594.07214 | E105: =IF(C105<=0,0,$M$11/C105) -> 7.7151124 | F105: =IF('Whitefield Monthly Projection'!$B$7=0,0,E105/'Whitefield Monthly Projection'!$B$7) -> 0.25717041 | G105: ='Profit Maximizer'!Q42 -> GROW — Attractive economics | U105: 0.4 | V105: =G114 -> -125155.6
A106: ='Profit Maximizer'!A43 -> Pharmacy / Prescription Coordination | B106: ='Profit Maximizer'!C43 -> 1.5 | C106: ='Profit Maximizer'!H43 -> 476.58135 | D106: ='Profit Maximizer'!J43 -> 317.7209 | E106: =IF(C106<=0,0,$M$11/C106) -> 230.81054 | F106: =IF('Whitefield Monthly Projection'!$B$7=0,0,E106/'Whitefield Monthly Projection'!$B$7) -> 7.6936848 | G106: ='Profit Maximizer'!Q43 -> GROW — Attractive economics | U106: 0.5 | V106: =G115 -> -125155.6
A107: ='Profit Maximizer'!A44 -> Family Medical Update Concierge | B107: ='Profit Maximizer'!C44 -> 3 | C107: ='Profit Maximizer'!H44 -> 634.48249 | D107: ='Profit Maximizer'!J44 -> 211.49416 | E107: =IF(C107<=0,0,$M$11/C107) -> 173.36964 | F107: =IF('Whitefield Monthly Projection'!$B$7=0,0,E107/'Whitefield Monthly Projection'!$B$7) -> 5.778988 | G107: ='Profit Maximizer'!Q44 -> STRATEGIC — Important but lower margin | U107: 0.6 | V107: =G116 -> -125155.6
U108: 0.7 | V108: =G117 -> -125155.6
...

Sheet Growth & Pricing Strategy
A1: NivrāaCare — Growth, Pricing & Profitability Strategy | Founder CFO Decision Engine
A2: Objective: optimize Price → Conversion → Customers → Repeat Usage → Monthly Journeys → Angel Utilization → Contribution → Fixed-Cost Coverage → EBITDA → Cash Runway. | AO2: Hourly Price | AP2: Monthly Profit | AR2: Hourly Price | AS2: Conversion | AU2: Journeys / Day | AV2: Monthly Profit | AX2: Angel Utilization | AY2: Monthly Profit
AO3: 249 | AP3: =H64 -> -17650.928 | AR3: 249 | AS3: =B64 -> 0.5 | AU3: 3 | AV3: =AU3*$B$7*$AB$11-$B$27 -> -79750.441 | AX3: 0.3 | AY3: =H95 -> -93472.243
A4: FOUNDER INPUT / SELECTOR | B4: VALUE | C4: NOTE | E4: FOUNDER DASHBOARD — CURRENT SELECTED GROWTH STRATEGY | AA4: SELECTED PRICING HELPER | AB4: VALUE | AO4: 299 | AP4: =H65 -> -4067.3621 | AR4: 299 | AS4: =B65 -> 0.45 | AU4: 5 | AV4: =AU4*$B$7*$AB$11-$B$27 -> -11584.068 | AX4: 0.4 | AY4: =H96 -> -63962.991
A5: Target monthly operating profit | B5: 0 | C5: Select break-even through ₹1Cr/month | E5: Selected base hourly rate | F5: =$B$16 -> 299 | H5: TARGET-PROFIT REQUIREMENT | I5: VALUE | AA5: Avg care bill | AB5: =$B$17+MAX($B$11,$B$18)*$B$16+$B$20 -> 1580.38 | AO5: 349 | AP5: =H66 -> -1193.8738 | AR5: 349 | AS5: =B66 -> 0.4 | AU5: 8 | AV5: =AU5*$B$7*$AB$11-$B$27 -> 90665.491 | AX5: 0.5 | AY5: =H97 -> -34453.739
A6: Leads per day | B6: 10 | C6: Founder planning assumption | E6: Legacy extended-hour price (inactive) | F6: =$B$19 -> 269 | H6: Target operating profit | I6: =$B$5 -> 0 | AA6: Net care revenue | AB6: =AB5/(1+$B$23) -> 1339.3051 | AO6: 399 | AP6: =H67 -> 6191.1645 | AR6: 399 | AS6: =B67 -> 0.37 | AU6: 10 | AV6: =AU6*$B$7*$AB$11-$B$27 -> 158831.86 | AX6: 0.6 | AY6: =H98 -> -4944.4862
A7: Operating days / month | B7: 26 | C7: Whitefield operating assumption | E7: Minimum booking hours | F7: =$B$18 -> 2 | H7: Required monthly contribution | I7: =$B$27+$B$5 -> 182000 | AA7: Angel cost / journey | AB7: =$B$11*$B$21 -> 0 | AO7: 449 | AP7: =H68 -> 15831.978 | AR7: 449 | AS7: =B68 -> 0.35 | AU7: 12 | AV7: =AU7*$B$7*$AB$11-$B$27 -> 226998.24 | AX7: 0.7 | AY7: =H99 -> -4067.3621
A8: Active Angels | B8: 5 | C8: Current planning assumption | E8: Journey / coordination fee | F8: =$B$17 -> 199 | H8: Required journeys / month | I8: =IF($AB$11<=0,0,I7/$AB$11) -> 138.83678 | AA8: Other variable cost / journey | AB8: =$B$22+AB5*$B$24+AB6*'NC Credits'!$B$15 -> 111.8133 | AU8: 15 | AV8: =AU8*$B$7*$AB$11-$B$27 -> 329247.8 | AX8: 0.8 | AY8: =H100 -> -4067.3621
A9: Working hours / Angel / day | B9: 8 | C9: Capacity assumption | E9: Average customer bill | F9: =$AB$23 -> 1969.78 | H9: Required journeys / day | I9: =I8/$B$7 -> 5.3398763 | AA9: Care contribution / journey | AB9: =AB6-AB7-AB8 -> 1227.4918 | AU9: 20 | AV9: =AU9*$B$7*$AB$11-$B$27 -> 499663.73 | AX9: 0.9 | AY9: =H101 -> -4067.3621
A10: Target Angel utilization | B10: 0.65 | C10: Productive service + required journey capacity | E10: Contribution / journey | F10: =$AB$11 -> 1310.8918 | H10: Required Angels | I10: =I8*$B$11/($B$7*$B$9*$B$10) -> 4.7442747 | AA10: Blended transport contribution | AB10: =$B$25*$B$26 -> 83.4
A11: Average actual journey duration | B11: ='Whitefield Monthly Projection'!$S$45 -> 4.62 | C11: Linked to current Whitefield service mix | E11: Contribution / Angel hour | F11: =$AB$12 -> 283.74281 | H11: Required leads / day | I11: =IF($AB$13*$B$14*(1-$B$12)*(1-$B$13)=0,0,I8/($B$7*$AB$13*$B$14*(1-$B$12)*(1-$B$13))) -> 10.22859 | AA11: Total blended contribution / journey | AB11: =AB9+AB10 -> 1310.8918
A12: Cancellation rate | B12: 0.08 | C12: Founder planning assumption | E12: True CAC | F12: =$AB$22 -> 300 | H12: Sustainable fixed-cost ceiling | I12: =$AB$18-$B$5 -> 177932.64 | AA12: Contribution / Angel hour | AB12: =IF($B$11=0,0,AB11/$B$11) -> 283.74281 | AO12: Monthly Fixed Cost | AP12: Monthly Profit | AR12: Lifetime Journeys | AS12: Safe CAC | AT12: Cumulative Contribution | AU12: Recurring Service | AV12: Monthly Revenue | AX12: Service | AY12: Contribution / Journey
A13: No-show / refund rate | B13: 0.03 | C13: Founder planning assumption | E13: Repeat journey share | F13: =$B$15 -> 0.3 | H13: Profit gap at current selected pricing | I13: =MAX($B$5-$AB$19,0) -> 4067.3621 | AA13: Current selected conversion | AB13: =INDEX($B$64:$B$68,MATCH($B$16,$A$64:$A$68,0)) -> 0.45 | AO13: 68000 | AP13: =$AB$18-AO13 -> 109932.64 | AR13: 1 | AS13: =D125 -> 393.26754 | AT13: =B125 -> 1310.8918 | AU13: Dialysis Visit Concierge | AV13: =H144 -> 23416 | AX13: =A177 -> Hospital Visit | AY13: =E177 -> 1111.5309
